Workbook

Sheet README
A1: The V — Album Atlas
A2: An album-level atlas of indie twang, slacker rock, and everything that fed them. Companion to V_Map.docx and to the Slacker Rock & Alt-Country Field Guide (whose Region and Style vocabulary it reuses).
A4: THE SHAPE. Picture a V. The bottom point is the modern indie-twang and slacker scene (2014–now). Climbing the V goes back in time through the genres that fed it; the V widens with each era.
A5: LAYER (vertical, from the original release year): L1 Now 2014–2026 · L2 Bridge 1998–2013 · L3 Nineties 1987–1997 · L4 Underground 1978–1986 · L5 Classic 1965–1977 · L6 Roots before 1965 (the R1 roots lane is always L6).
A6: ZONE (horizontal, from the primary lane): Core = the scenes happening now (completionist) · V = direct ancestors and close siblings (deep) · Context = popular branches whose main line leads elsewhere (landmarks only). Row colour: orange = Core, blue = V, grey = Context.
A8: SHEETS. Albums — one row per album (Layer and Zone are formulas). Artists — one row per artist with key album IDs. Lanes — the 54 lanes with parents/children and a live album count. Scenes, Labels — gazetteer. Tags — the controlled descriptor vocabulary. Paths — the listening paths from V_Map.docx. Borderline Log — every judgment call. Needs Verification — candidates that could not be verified (never in Albums). QA Log — every error-correction run. Stats — live counts by layer × zone, lane, year and priority.
A10: HOW TO USE. Filter Albums by Zone/Lane/Priority, or search a descriptor (e.g. 'pedal steel'). 'Start here' marks one or two entry points per lane. The Terry column links Josh Terry's No Expectations coverage. Lineage basis: Documented = established by interview, cover, credit, shared member or critic; Inferred = resemblance only.
A11: YOUR COLUMNS. Heard (Y/N), Rating (1–5) and My notes are blank for you; they have dropdowns. Example: Heard = Y, Rating = 4, My notes = 'side two is the one'.
A13: CONFIDENCE. High = two independent sources agree on artist, title, original year and original label; Medium = one reliable source. Sources lists the verification URLs.
A14: Active years on the Artists sheet are the span of that artist's releases in this atlas, not a full career span.

Sheet Albums
A1: ID | B1: Artist | C1: Album | D1: Year | E1: Type | F1: Label | G1: Layer | H1: Zone | I1: Primary lane | J1: Secondary lanes | K1: Style | L1: Region | M1: Base | N1: Scene | O1: Descriptors | P1: Description | Q1: Lineage | R1: Lineage basis | S1: Key tracks | T1: Priority | U1: Start here | V1: Terry | W1: In field guide | X1: Sources | Y1: Confidence | Z1: Heard | AA1: Rating | AB1: My notes
A2: A0001 | B2: The Carter Family | C2: The Essential Carter Family | D2: 2013 | E2: Compilation | F2: Columbia/Legacy | G2: =IF(LEFT(I2,3)="R1 ","L6",IF(D2>=2014,"L1",IF(D2>=1998,"L2",IF(D2>=1987,"L3",IF(D2>=1978,"L4",IF(D2>=1965,"L5","L6")))))) -> L6 | H2: =IFERROR(INDEX(Lanes!$C$2:$C$60,MATCH(LEFT(I2,FIND(" ",I2)-1),Lanes!$A$2:$A$60,0)),"?") -> V | I2: R1 Roots | K2: Country folk | L2: The South | M2: Maces Spring, VA | O2: close harmonies; fingerpicked acoustic; storytelling; spiritual or gospel; drawl | P2: A.P., Sara and Maybelle Carter cut hundreds of sides for Victor, ARC and Decca between 1927 and 1941, turning Appalachian hymns, ballads and parlor songs into the bedrock repertoire of country music. Maybelle's thumb-brush guitar style became a standard technique for generations of pickers, and Sara and Maybelle's plain, close harmonies set the template for duet singing in both country and folk. This 40-track set is the standard single-disc entry point to that catalog. | Q2: The founding act of recorded country and folk music; directly covered and cited by Woody Guthrie, Johnny Cash (who married into the family via June Carter), Bob Dylan, and the entire folk revival, and an explicit touchstone for Gillian Welch and the modern indie-folk line. | R2: Documented | S2: Wildwood Flower; Keep on the Sunny Side; Can the Circle Be Unbroken | T2: Essential | X2: https://en.wikipedia.org/wiki/Carter_Family_discography https://www.discogs.com/release/16074438-The-Carter-Family-The-Essential-Carter-Family | Y2: High
A3: A0002 | B3: Jimmie Rodgers | C3: The Essential Jimmie Rodgers | D3: 1997 | E3: Compilation | F3: RCA | G3: =IF(LEFT(I3,3)="R1 ","L6",IF(D3>=2014,"L1",IF(D3>=1998,"L2",IF(D3>=1987,"L3",IF(D3>=1978,"L4",IF(D3>=1965,"L5","L6")))))) -> L6 | H3: =IFERROR(INDEX(Lanes!$C$2:$C$60,MATCH(LEFT(I3,FIND(" ",I3)-1),Lanes!$A$2:$A$60,0)),"?") -> V | I3: R1 Roots | K3: Country folk | L3: The South | M3: Meridian, MS | O3: fingerpicked acoustic; storytelling; road songs; drawl; heartbreak | P3: The 'Father of Country Music' fused blues, hobo-song sentimentality and his trademark blue yodel into records that sold in the hundreds of thousands during the Depression, cut mostly with just his own guitar for producer Ralph Peer. His rambling, train- and jailhouse-themed songwriting set the storytelling mold that country and folk singers kept returning to for decades. This 20-track RCA set covers his key 1927-1931 Victor sides. | Q3: Established the singing-brakeman persona and blue-yodel sound that shaped Bob Wills, Hank Snow, Merle Haggard and Lefty Frizzell, and fed the train-and-drifter songwriting strain that runs through Woody Guthrie into the outlaw and Americana lines. | R3: Documented | S3: Blue Yodel No. 1 (T for Texas); Waiting for a Train; In the Jailhouse Now | T3: Essential | X3: https://www.discogs.com/release/6163197-Jimmie-Rodgers-The-Essential-Jimmie-Rodgers https://en.wikipedia.org/wiki/Jimmie_Rodgers_discography | Y3: High
A4: A0003 | B4: Hank Williams | C4: 40 Greatest Hits | D4: 1978 | E4: Compilation | F4: Mercury | G4: =IF(LEFT(I4,3)="R1 ","L6",IF(D4>=2014,"L1",IF(D4>=1998,"L2",IF(D4>=1987,"L3",IF(D4>=1978,"L4",IF(D4>=1965,"L5","L6")))))) -> L6 | H4: =IFERROR(INDEX(Lanes!$C$2:$C$60,MATCH(LEFT(I4,FIND(" ",I4)-1),Lanes!$A$2:$A$60,0)),"?") -> V | I4: R1 Roots | K4: Honky-tonk | L4: The South | M4: Montgomery, AL | O4: Telecaster twang; drawl; heartbreak; drinking songs; storytelling | P4: Williams and his band the Drifting Cowboys cut these sides for MGM between 1947 and 1952, distilling honky-tonk into plainspoken, three-minute songs about drinking, cheating and loneliness delivered in his high, aching voice. He died at 29, but this two-record set of his MGM singles is still the standard way listeners meet him, left unedited and unoverdubbed unlike some earlier reissues. It is the single most-cited record in the lane's whole family tree. | Q4: The core honky-tonk songbook that country music keeps rewriting; a direct model for Lefty Frizzell, Patsy Cline, George Jones, the outlaw country of Waylon Jennings and Willie Nelson, and every plainspoken heartbreak songwriter downstream through John Prine to today's alt-country. | R4: Documented | S4: Your Cheatin' Heart; I'm So Lonesome I Could Cry; Hey, Good Lookin' | T4: Essential | U4: Y | X4: https://en.wikipedia.org/wiki/40_Greatest_Hits_(Hank_Williams_album) | Y4: Medium
A5: A0004 | B5: Various Artists | C5: Anthology of American Folk Music | D5: 1952 | E5: Compilation | F5: Folkways Records | G5: =IF(LEFT(I5,3)="R1 ","L6",IF(D5>=2014,"L1",IF(D5>=1998,"L2",IF(D5>=1987,"L3",IF(D5>=1978,"L4",IF(D5>=1965,"L5","L6")))))) -> L6 | H5: =IFERROR(INDEX(Lanes!$C$2:$C$60,MATCH(LEFT(I5,FIND(" ",I5)-1),Lanes!$A$2:$A$60,0)),"?") -> V | I5: R1 Roots | K5: Country folk | L5: The South | M5: Various, USA | O5: banjo; fiddle; storytelling; spiritual or gospel; Southern gothic | P5: Collector Harry Smith assembled 84 commercial 78-rpm sides from 1926-1933 - Appalachian ballads, Cajun two-steps, gospel, blues and string-band music from Dock Boggs, Mississippi John Hurt, the Carter Family, Clarence Ashley and dozens of others - into six LPs split across Ballads, Social Music and Songs. It sold poorly on release but became the shared songbook of the 1950s-60s folk revival, sending researchers out to find still-living performers like Boggs and Hurt. Its strange, plainspoken mix of the sacred and the murderous defined how a whole generation understood 'old, weird America.' | Q5: The single most important source text for the folk revival: it directly shaped Bob Dylan, the New Lost City Ramblers, Joan Baez and Jerry Garcia, and its rediscovered artists fed the American Primitive guitar line and, further downstream, Gillian Welch and the 2010s indie-folk revival. | R5: Documented | S5: Henry Lee; John the Revelator; Acadian One Step | T5: Essential | U5: Y | X5: https://en.wikipedia.org/wiki/Anthology_of_American_Folk_Music | Y5: Medium
A6: A0005 | B6: Woody Guthrie | C6: Dust Bowl Ballads | D6: 1940 | E6: LP | F6: Victor | G6: =IF(LEFT(I6,3)="R1 ","L6",IF(D6>=2014,"L1",IF(D6>=1998,"L2",IF(D6>=1987,"L3",IF(D6>=1978,"L4",IF(D6>=1965,"L5","L6")))))) -> L6 | H6: =IFERROR(INDEX(Lanes!$C$2:$C$60,MATCH(LEFT(I6,FIND(" ",I6)-1),Lanes!$A$2:$A$60,0)),"?") -> V | I6: R1 Roots | K6: Country folk | L6: Texas and Oklahoma | M6: Okemah, OK | O6: storytelling; political; harmonica; drawl; road songs | P6: Recorded for RCA Victor as a themed set of his own songs about Dust Bowl migration and Depression-era poverty, this is one of the first true concept albums, built around the multi-part talking blues 'Tom Joad' (a compression of Steinbeck's Grapes of Wrath) and dry, plainspoken narratives like 'Do Re Mi.' Guthrie sings in a flat, conversational drawl over simple guitar and harmonica, treating hard times as material for storytelling rather than lament. It was Guthrie's first and most commercially successful record. | Q6: The template for the topical, talking-blues singer-songwriter tradition that runs through Pete Seeger and Bob Dylan (who called Guthrie his primary influence) into the whole folk-songwriting trunk line that reaches Townes Van Zandt and, eventually, Big Thief. | R6: Documented | S6: Tom Joad; Do Re Mi; Talkin' Dust Bowl Blues | T6: Essential | X6: https://en.wikipedia.org/wiki/Dust_Bowl_Ballads | Y6: Medium
A7: A0006 | B7: Woody Guthrie | C7: This Land Is Your Land: The Asch Recordings, Vol. 1 | D7: 1997 | E7: Compilation | F7: Smithsonian Folkways | G7: =IF(LEFT(I7,3)="R1 ","L6",IF(D7>=2014,"L1",IF(D7>=1998,"L2",IF(D7>=1987,"L3",IF(D7>=1978,"L4",IF(D7>=1965,"L5","L6")))))) -> L6 | H7: =IFERROR(INDEX(Lanes!$C$2:$C$60,MATCH(LEFT(I7,FIND(" ",I7)-1),Lanes!$A$2:$A$60,0)),"?") -> V | I7: R1 Roots | K7: Country folk | L7: Texas and Oklahoma | M7: Okemah, OK | O7: storytelling; political; harmonica; spiritual or gospel; road songs | P7: Drawn from the hundreds of songs Guthrie cut for Moses Asch's Folkways label through the 1940s, this is the standard modern entry point to that catalog, opening with the title anthem and moving through migrant, labor and children's songs, several cut alongside Cisco Houston and Sonny Terry. It shows the looser, more collaborative side of Guthrie next to the tighter Dust Bowl Ballads concept record. Smithsonian Folkways issued it as the first in a multi-volume series drawing on Asch's vault. | Q7: Preserves the bulk of Guthrie's Asch-era songwriting, the direct source for Pete Seeger, the Almanac Singers' topical-song lineage, and the folk-revival singer-songwriters who followed him into the 1960s. | R7: Documented | S7: This Land Is Your Land; Pastures of Plenty; Grand Coulee Dam | T7: Recommended | X7: https://www.discogs.com/release/2190465-Woody-Guthrie-This-Land-Is-Your-Land-The-Asch-Recordings-Vol-1 | Y7: Medium
A8: A0007 | B8: The Louvin Brothers | C8: Tragic Songs of Life | D8: 1956 | E8: LP | F8: Capitol | G8: =IF(LEFT(I8,3)="R1 ","L6",IF(D8>=2014,"L1",IF(D8>=1998,"L2",IF(D8>=1987,"L3",IF(D8>=1978,"L4",IF(D8>=1965,"L5","L6")))))) -> L6 | H8: =IFERROR(INDEX(Lanes!$C$2:$C$60,MATCH(LEFT(I8,FIND(" ",I8)-1),Lanes!$A$2:$A$60,0)),"?") -> V | I8: R1 Roots | K8: Classic country | L8: The South | M8: Henagar, AL | O8: mandolin; close harmonies; storytelling; heartbreak; Southern gothic | P8: Ira Louvin's high, keening tenor and Charlie's lead vocal wrap tight, shape-note-schooled harmony around murder ballads and orphan songs like 'Knoxville Girl' and 'In the Pines,' with Ira's mandolin the only real lead instrument against spare guitar and bass. It is bleaker and more traditional than their gospel records, closer to the Anthology of American Folk Music's old ballads than to Nashville pop-country. Producer Ken Nelson kept the sound close and unadorned, letting the brothers' blend carry the record. | Q8: The close-harmony duo singing here is a direct model for the Everly Brothers, Gram Parsons and Emmylou Harris, and its stock of tragic-ballad narratives feeds the Southern gothic strain of storytelling that runs down through Southern rock into Drive-By Truckers. | R8: Documented | S8: Knoxville Girl; In the Pines; Kentucky | T8: Essential | X8: https://en.wikipedia.org/wiki/Tragic_Songs_of_Life | Y8: Medium
A9: A0008 | B9: The Louvin Brothers | C9: Satan Is Real | D9: 1959 | E9: LP | F9: Capitol | G9: =IF(LEFT(I9,3)="R1 ","L6",IF(D9>=2014,"L1",IF(D9>=1998,"L2",IF(D9>=1987,"L3",IF(D9>=1978,"L4",IF(D9>=1965,"L5","L6")))))) -> L6 | H9: =IFERROR(INDEX(Lanes!$C$2:$C$60,MATCH(LEFT(I9,FIND(" ",I9)-1),Lanes!$A$2:$A$60,0)),"?") -> V | I9: R1 Roots | K9: Classic country | L9: The South | M9: Henagar, AL | O9: mandolin; close harmonies; spiritual or gospel; Southern gothic; baritone | P9: A full gospel concept record from two Baptist-raised brothers who genuinely believed the fire-and-brimstone warnings in these songs, built around the title track's spoken sermon over a wall of vocal harmony and capped by the infamous cover photo of the brothers before a plywood devil. Ira's mandolin and the pair's close, high harmonies carry material that ranges from stark warnings ('Satan's Jeweled Crown') to tender hymns. It is widely considered their most fully realized record. | Q9: Its gospel fervor and Southern-gothic imagery directly influenced the Byrds (who covered 'The Christian Life' on Sweetheart of the Rodeo) and Emmylou Harris, and it stands as a touchstone for later alt-country and indie artists drawn to sacred-and-profane country songwriting. | R9: Documented | S9: Satan Is Real; The Christian Life; Satan's Jeweled Crown | T9: Essential | X9: https://en.wikipedia.org/wiki/Satan_Is_Real | Y9: Medium
A10: A0009 | B10: The Everly Brothers | C10: Songs Our Daddy Taught Us | D10: 1958 | E10: LP | F10: Cadence | G10: =IF(LEFT(I10,3)="R1 ","L6",IF(D10>=2014,"L1",IF(D10>=1998,"L2",IF(D10>=1987,"L3",IF(D10>=1978,"L4",IF(D10>=1965,"L5","L6")))))) -> L6 | H10: =IFERROR(INDEX(Lanes!$C$2:$C$60,MATCH(LEFT(I10,FIND(" ",I10)-1),Lanes!$A$2:$A$60,0)),"?") -> V | I10: R1 Roots | K10: Country folk | L10: The South | M10: Nashville, TN | O10: close harmonies; fingerpicked acoustic; storytelling; drawl; heartbreak | P10: At the peak of their teen-pop fame, Don and Phil Everly set aside the rock and roll singles to cut old Appalachian ballads and parlor songs their father Ike had taught them growing up, backed by spare acoustic guitar instead of a rock band. Songs like 'Barbara Allen' and 'Down in the Willow Garden' show the same brother-harmony blend that powered their hits applied to genuinely old material, years ahead of the folk boom that would make such repertoire fashionable. Critics at the time mostly ignored it; it is now seen as a quietly radical move for a teen idol act. | Q10: A direct bridge between old-time Appalachian duet singing and the brother-harmony sound that Simon & Garfunkel, the Byrds and Gram Parsons and Emmylou Harris's duets all drew on. | R10: Documented | S10: Barbara Allen; Down in the Willow Garden; Roving Gambler | T10: Essential | X10: https://en.wikipedia.org/wiki/Songs_Our_Daddy_Taught_Us | Y10: Medium
A11: A0010 | B11: The Everly Brothers | C11: The Best of The Everly Brothers | D11: 1959 | E11: Compilation | F11: Cadence | G11: =IF(LEFT(I11,3)="R1 ","L6",IF(D11>=2014,"L1",IF(D11>=1998,"L2",IF(D11>=1987,"L3",IF(D11>=1978,"L4",IF(D11>=1965,"L5","L6")))))) -> L6 | H11: =IFERROR(INDEX(Lanes!$C$2:$C$60,MATCH(LEFT(I11,FIND(" ",I11)-1),Lanes!$A$2:$A$60,0)),"?") -> V | I11: R1 Roots | K11: Country folk | L11: The South | M11: Nashville, TN | O11: close harmonies; duets; heartbreak; breezy; drawl | P11: An era-original hits set on the brothers' own Cadence label, gathering the run of singles - 'Bye Bye Love,' 'Wake Up Little Susie,' 'All I Have to Do Is Dream' - that made their tight, two-part sibling harmony one of the defining sounds of late-1950s pop and country radio alike. Chet Atkins' clean guitar work and the brothers' close blend gave the songs a country foundation under otherwise teen-pop arrangements. It is the standard way to hear the hit-single side of a duo whose sound sits right at the country/pop border. | Q11: Their harmony-singing template runs forward into the Beatles, the Byrds' vocal blend, and the duet tradition Gram Parsons and Emmylou Harris carried into country rock. | R11: Documented | S11: Bye Bye Love; Wake Up Little Susie; All I Have to Do Is Dream | T11: Recommended | X11: https://en.wikipedia.org/wiki/The_Everly_Brothers_discography | Y11: Medium
A12: A0011 | B12: Lefty Frizzell | C12: Look What Thoughts Will Do | D12: 1997 | E12: Compilation | F12: Columbia/Legacy | G12: =IF(LEFT(I12,3)="R1 ","L6",IF(D12>=2014,"L1",IF(D12>=1998,"L2",IF(D12>=1987,"L3",IF(D12>=1978,"L4",IF(D12>=1965,"L5","L6")))))) -> L6 | H12: =IFERROR(INDEX(Lanes!$C$2:$C$60,MATCH(LEFT(I12,FIND(" ",I12)-1),Lanes!$A$2:$A$60,0)),"?") -> V | I12: R1 Roots | K12: Honky-tonk | L12: Texas and Oklahoma | M12: Corsicana, TX | O12: Telecaster twang; drawl; heartbreak; storytelling; drinking songs | P12: Frizzell sang honky-tonk with a loose, sliding phrasing - drawing out and bending syllables in ways no one had before him - that became one of the two or three most imitated vocal styles in country music, heard later in Merle Haggard and George Strait alike. This 2-disc, 34-track Columbia/Legacy set gathers his defining 1950s sides, from the double-sided 1950 breakthrough 'If You've Got the Money (I've Got the Time)' b/w 'I Love You a Thousand Ways' through 1959's 'Long Black Veil.' The band stays spare and clean behind him, keeping the focus on that elastic phrasing. | Q12: His vocal phrasing is a direct, oft-cited influence on Merle Haggard, George Strait and Randy Travis, keeping the honky-tonk singing style alive as a technique that later alt-country and Americana singers study. | R12: Documented | S12: If You've Got the Money (I've Got the Time); Long Black Veil; I Love You a Thousand Ways | T12: Essential | X12: https://www.discogs.com/release/1508292-Lefty-Frizzell-Look-What-Thoughts-Will-Do https://en.wikipedia.org/wiki/Lefty_Frizzell_discography | Y12: High
A13: A0012 | B13: Bob Wills & His Texas Playboys | C13: The Essential Bob Wills (1935-1947) | D13: 1992 | E13: Compilation | F13: Columbia | G13: =IF(LEFT(I13,3)="R1 ","L6",IF(D13>=2014,"L1",IF(D13>=1998,"L2",IF(D13>=1987,"L3",IF(D13>=1978,"L4",IF(D13>=1965,"L5","L6")))))) -> L6 | H13: =IFERROR(INDEX(Lanes!$C$2:$C$60,MATCH(LEFT(I13,FIND(" ",I13)-1),Lanes!$A$2:$A$60,0)),"?") -> V | I13: R1 Roots | K13: Classic country | L13: Texas and Oklahoma | M13: Tulsa, OK | O13: fiddle; horns; storytelling; road songs; breezy | P13: Wills led a big, horn-and-fiddle Western swing band broadcasting daily from Cain's Ballroom in Tulsa, blending string-band fiddling with jazz and blues horn charts into a loose, danceable sound built for a live room full of dancers. 'New San Antonio Rose' became a national hit and 'Steel Guitar Rag' helped establish the pedal steel as a lead country instrument. This Columbia/Legacy set gathers his most influential 1935-1947 sides for the label. | Q13: Western swing's blend of jazz-informed horns and string-band instruments fed directly into Merle Haggard (who recorded a full Wills tribute album) and the Bakersfield sound, and its steel-guitar lead lines are a direct ancestor of the pedal steel vocabulary the whole V draws on. | R13: Documented | S13: New San Antonio Rose; Steel Guitar Rag; Take Me Back to Tulsa | T13: Essential | X13: https://www.discogs.com/master/1260552-Bob-Wills-The-Essential-Bob-Wills-1935-1947 https://en.wikipedia.org/wiki/Bob_Wills | Y13: High
A14: A0013 | B14: Johnny Cash | C14: Johnny Cash with His Hot and Blue Guitar! | D14: 1957 | E14: LP | F14: Sun Records | G14: =IF(LEFT(I14,3)="R1 ","L6",IF(D14>=2014,"L1",IF(D14>=1998,"L2",IF(D14>=1987,"L3",IF(D14>=1978,"L4",IF(D14>=1965,"L5","L6")))))) -> L6 | H14: =IFERROR(INDEX(Lanes!$C$2:$C$60,MATCH(LEFT(I14,FIND(" ",I14)-1),Lanes!$A$2:$A$60,0)),"?") -> V | I14: R1 Roots | K14: Classic country | L14: The South | M14: Memphis, TN | N14: Memphis, Sun Records | O14: baritone; drawl; storytelling; drinking songs; road songs | P14: Cash's debut album, cut with just guitarist Luther Perkins and bassist Marshall Grant (the Tennessee Two) behind his low, dry baritone, sets the boom-chicka-boom train-rhythm sound that defined his whole career, built around hits like 'I Walk the Line' and 'Folsom Prison Blues.' The arrangements are stripped to almost nothing, letting Cash's flat delivery and Sun Records' slapback echo carry the songs. It is the founding document of the Cash persona: plain, direct and a little dangerous. | Q14: Set the minimal, rhythm-forward Sun sound and the plainspoken outlaw-adjacent persona that Cash carried into the Outlaw country movement and that Southern storytelling songwriters from Steve Earle to Jason Isbell still cite directly. | R14: Documented | S14: Folsom Prison Blues; I Walk the Line; Cry! Cry! Cry! | T14: Essential | X14: https://en.wikipedia.org/wiki/Johnny_Cash_with_His_Hot_and_Blue_Guitar! https://en.wikipedia.org/wiki/Johnny_Cash | Y14: High
A15: A0014 | B15: Johnny Cash | C15: Johnny Cash Sings the Songs That Made Him Famous | D15: 1958 | E15: Compilation | F15: Sun Records | G15: =IF(LEFT(I15,3)="R1 ","L6",IF(D15>=2014,"L1",IF(D15>=1998,"L2",IF(D15>=1987,"L3",IF(D15>=1978,"L4",IF(D15>=1965,"L5","L6")))))) -> L6 | H15: =IFERROR(INDEX(Lanes!$C$2:$C$60,MATCH(LEFT(I15,FIND(" ",I15)-1),Lanes!$A$2:$A$60,0)),"?") -> V | I15: R1 Roots | K15: Classic country | L15: The South | M15: Memphis, TN | N15: Memphis, Sun Records | O15: baritone; drawl; storytelling; heartbreak; road songs | P15: Assembled from Cash's Sun singles after he had already left for Columbia, this collects the run of 1956-58 45s - 'There You Go,' 'Ballad of a Teenage Queen,' 'Guess Things Happen That Way' - that built his early fame, again with the spare Tennessee Two arrangements and slapback echo. It functions as Sun's own closing statement on the Cash catalog before Columbia became the story. The song selection is stronger and more pop-leaning than the debut, showing Cash's range widening. | Q15: Closes out the Sun era that established Cash's train-rhythm sound before his Columbia years broadened him into the Outlaw and Americana movements' patron saint. | R15: Documented | S15: Ballad of a Teenage Queen; Guess Things Happen That Way; There You Go | T15: Recommended | X15: https://en.wikipedia.org/wiki/Sings_the_Songs_That_Made_Him_Famous | Y15: Medium
A16: A0015 | B16: Johnny Cash | C16: The Fabulous Johnny Cash | D16: 1958 | E16: LP | F16: Columbia | G16: =IF(LEFT(I16,3)="R1 ","L6",IF(D16>=2014,"L1",IF(D16>=1998,"L2",IF(D16>=1987,"L3",IF(D16>=1978,"L4",IF(D16>=1965,"L5","L6")))))) -> L6 | H16: =IFERROR(INDEX(Lanes!$C$2:$C$60,MATCH(LEFT(I16,FIND(" ",I16)-1),Lanes!$A$2:$A$60,0)),"?") -> V | I16: R1 Roots | K16: Classic country | L16: The South | M16: Memphis, TN | O16: baritone; drawl; storytelling; spiritual or gospel; heartbreak | P16: Cash's first Columbia album, cut right after leaving Sun, keeps the same Tennessee Two lineup and boom-chicka-boom pulse but adds fuller Nashville production and reaches toward the storytelling ballads ('Don't Take Your Guns to Town,' 'I Still Miss Someone') that would define his mature songwriting. It is a transitional record, still recognizably Sun-era Cash but pointed at the bigger stages Columbia would give him. 'Don't Take Your Guns to Town' became his first Columbia number-one. | Q16: Bridges Cash's Sun-era minimalism and his Columbia-era ballad writing, carrying his plainspoken storytelling forward into the Outlaw country and Americana songwriters who followed. | R16: Documented | S16: Don't Take Your Guns to Town; I Still Miss Someone; Frankie's Man, Johnny | T16: Recommended | X16: https://en.wikipedia.org/wiki/The_Fabulous_Johnny_Cash | Y16: Medium
A17: A0016 | B17: Patsy Cline | C17: Showcase | D17: 1961 | E17: LP | F17: Decca | G17: =IF(LEFT(I17,3)="R1 ","L6",IF(D17>=2014,"L1",IF(D17>=1998,"L2",IF(D17>=1987,"L3",IF(D17>=1978,"L4",IF(D17>=1965,"L5","L6")))))) -> L6 | H17: =IFERROR(INDEX(Lanes!$C$2:$C$60,MATCH(LEFT(I17,FIND(" ",I17)-1),Lanes!$A$2:$A$60,0)),"?") -> V | I17: R1 Roots | K17: Mainstream country | L17: The South | M17: Winchester, VA | O17: strings; close harmonies; heartbreak; baritone; polished | P17: Produced by Owen Bradley with the Jordanaires' background vocals and lush string arrangements, Showcase is the record where the 'Nashville Sound' fully crystallizes: Cline's huge, aching voice bending pop and torch-song phrasing into country radio via 'I Fall to Pieces' and 'Crazy.' It softened the fiddle-and-steel honky-tonk that came before it in favor of orchestral polish, opening the door for countrypolitan production. Cline died two years later, making this and Sentimentally Yours the twin pillars of her studio catalog. | Q17: Owen Bradley's countrypolitan production model here shaped the Nashville Sound mainstream for the next decade and gave later women in country (Loretta Lynn, k.d. lang, and eventually alt-country singers like Neko Case) a vocal-forward, string-laden template to work against or embrace. | R17: Documented | S17: Crazy; I Fall to Pieces; She's Got You | T17: Essential | X17: https://en.wikipedia.org/wiki/Patsy_Cline | Y17: Medium
A18: A0017 | B18: Flatt & Scruggs | C18: Foggy Mountain Jamboree | D18: 1957 | E18: LP | F18: Columbia | G18: =IF(LEFT(I18,3)="R1 ","L6",IF(D18>=2014,"L1",IF(D18>=1998,"L2",IF(D18>=1987,"L3",IF(D18>=1978,"L4",IF(D18>=1965,"L5","L6")))))) -> L6 | H18: =IFERROR(INDEX(Lanes!$C$2:$C$60,MATCH(LEFT(I18,FIND(" ",I18)-1),Lanes!$A$2:$A$60,0)),"?") -> V | I18: R1 Roots | K18: Bluegrass | L18: The South | M18: Nashville, TN | O18: banjo; mandolin; fiddle; close harmonies; storytelling | P18: Earl Scruggs' three-finger banjo picking is the whole show here, driving instrumentals like 'Flint Hill Special' and 'Foggy Mountain Chimes' at breakneck speed while Lester Flatt's easy lead vocals anchor the sung numbers. It is widely treated as the definitive Flatt & Scruggs studio album, tighter and more purely instrumental-focused than their later, more pop-crossover work. The Grammy Hall of Fame inducted it in 2012 as a foundational bluegrass document. | Q18: Scruggs' banjo style became the default vocabulary for bluegrass banjo playing and fed directly into the American Primitive and newgrass lines, and the duo's clean, fast picking is a constant reference point for indie and alt-country bands that add banjo to their sound. | R18: Documented | S18: Flint Hill Special; Foggy Mountain Chimes; Blue Ridge Cabin Home | T18: Essential | X18: https://en.wikipedia.org/wiki/Foggy_Mountain_Jamboree | Y18: Medium
A19: A0018 | B19: Bill Monroe | C19: The Essential Bill Monroe (1945-1949) | D19: 1992 | E19: Compilation | F19: Columbia | G19: =IF(LEFT(I19,3)="R1 ","L6",IF(D19>=2014,"L1",IF(D19>=1998,"L2",IF(D19>=1987,"L3",IF(D19>=1978,"L4",IF(D19>=1965,"L5","L6")))))) -> L6 | H19: =IFERROR(INDEX(Lanes!$C$2:$C$60,MATCH(LEFT(I19,FIND(" ",I19)-1),Lanes!$A$2:$A$60,0)),"?") -> V | I19: R1 Roots | K19: Bluegrass | L19: The South | M19: Rosine, KY | O19: mandolin; fiddle; banjo; close harmonies; storytelling | P19: This is the classic 1945-1948 Blue Grass Boys lineup - Monroe on mandolin, Lester Flatt on guitar, Earl Scruggs on banjo, Chubby Wise on fiddle - cutting the sides that invented bluegrass as a named genre: fast, hard-driven string-band music with Monroe's keening 'high lonesome' tenor on top. Songs like 'Blue Moon of Kentucky' and 'Uncle Pen' became bluegrass standards covered by nearly everyone who followed. This Columbia/Legacy set is the standard way to hear that founding lineup. | Q19: The direct source of the entire bluegrass genre; its high-lonesome vocal style and hard-driven picking fed Flatt & Scruggs, the Stanley Brothers, and, much later, the American Primitive and newgrass lines and the 2010s bluegrass-inflected wing of indie folk. | R19: Documented | S19: Blue Moon of Kentucky; Uncle Pen; Can't You Hear Me Callin' | T19: Essential | X19: https://en.wikipedia.org/wiki/Bill_Monroe_discography https://en.wikipedia.org/wiki/Bill_Monroe | Y19: High
A20: A0019 | B20: The Stanley Brothers | C20: Country Pickin' and Singin' | D20: 1958 | E20: LP | F20: Mercury | G20: =IF(LEFT(I20,3)="R1 ","L6",IF(D20>=2014,"L1",IF(D20>=1998,"L2",IF(D20>=1987,"L3",IF(D20>=1978,"L4",IF(D20>=1965,"L5","L6")))))) -> L6 | H20: =IFERROR(INDEX(Lanes!$C$2:$C$60,MATCH(LEFT(I20,FIND(" ",I20)-1),Lanes!$A$2:$A$60,0)),"?") -> V | I20: R1 Roots | K20: Bluegrass | L20: The South | M20: Dickenson County, VA | O20: banjo; mandolin; close harmonies; drawl; storytelling | P20: Carter and Ralph Stanley's high, hard mountain harmonies sit closer to the old ballad tradition than Bill Monroe's more polished bluegrass, with Ralph's clawhammer-descended banjo and the brothers' tight blood-harmony vocals carrying songs rooted directly in their native southwest Virginia. This Mercury LP is one of their earliest full studio albums as a working bluegrass band rather than a singles act. It shows the rawer, more old-time-inflected wing of bluegrass next to Monroe's and Flatt & Scruggs's smoother sound. | Q20: The Stanleys' raw mountain harmony style is a direct reference point for Ralph Stanley's later solo career (via O Brother, Where Art Thou?) and for the old-time-leaning wing of the 2010s bluegrass and indie-folk revival. | R20: Documented | S20: Angel Band; White Dove; The Fields Have Turned Brown | T20: Recommended | X20: https://en.wikipedia.org/wiki/Stanley_Brothers | Y20: Medium
A21: A0020 | B21: Marty Robbins | C21: Gunfighter Ballads and Trail Songs | D21: 1959 | E21: LP | F21: Columbia | G21: =IF(LEFT(I21,3)="R1 ","L6",IF(D21>=2014,"L1",IF(D21>=1998,"L2",IF(D21>=1987,"L3",IF(D21>=1978,"L4",IF(D21>=1965,"L5","L6")))))) -> L6 | H21: =IFERROR(INDEX(Lanes!$C$2:$C$60,MATCH(LEFT(I21,FIND(" ",I21)-1),Lanes!$A$2:$A$60,0)),"?") -> V | I21: R1 Roots | K21: Classic country | L21: Elsewhere | M21: Glendale, AZ | O21: Telecaster twang; storytelling; road songs; baritone; drawl | P21: A concept record of Western narrative ballads, built around the galloping Spanish-guitar riff and murder-ballad plot of 'El Paso,' which crossed over to number one on both country and pop charts. Robbins sings these cowboy-outlaw stories with a clean, theatrical baritone over spare Nashville session backing, treating each song as a short story with a beginning, middle and violent end. AllMusic has called it the most influential Western-ballads album of the postwar era. | Q21: Its story-song format and Western imagery fed directly into the outlaw-country movement's cowboy mythology and into narrative country songwriting generally, an explicit reference point for storytelling-heavy Southern rock and alt-country writers who followed. | R21: Documented | S21: El Paso; Big Iron; Cool Water | T21: Essential | X21: https://en.wikipedia.org/wiki/Gunfighter_Ballads_and_Trail_Songs | Y21: Medium
A22: A0021 | B22: Buck Owens | C22: Buck Owens | D22: 1961 | E22: LP | F22: Capitol | G22: =IF(LEFT(I22,3)="R1 ","L6",IF(D22>=2014,"L1",IF(D22>=1998,"L2",IF(D22>=1987,"L3",IF(D22>=1978,"L4",IF(D22>=1965,"L5","L6")))))) -> L6 | H22: =IFERROR(INDEX(Lanes!$C$2:$C$60,MATCH(LEFT(I22,FIND(" ",I22)-1),Lanes!$A$2:$A$60,0)),"?") -> V | I22: R1 Roots | K22: Honky-tonk | L22: Elsewhere | M22: Bakersfield, CA | N22: Bakersfield sound | O22: Telecaster twang; drawl; close harmonies; heartbreak; rowdy | P22: Owens' debut album for Capitol, cut in Nashville-averse Bakersfield with producer Ken Nelson, is an early statement of what became known as the Bakersfield sound: bright, biting double-Telecaster twang, a hard backbeat, and none of the strings and choruses Nashville was adding to records at the time. It is rawer and more rock-and-roll-adjacent than the Nashville Sound records being made in the same years, closer to a bar band than a countrypolitan session. It set up the run of hits Owens and Don Rich would cut through the decade. | Q22: The Bakersfield sound this record establishes is a direct model for Dwight Yoakam's 1980s revival of the style and for the Telecaster-driven honky-tonk that runs through the whole hard-country wing of the V, cited constantly by Gram Parsons and later alt-country guitarists. | R22: Documented | S22: Under Your Spell Again; Above and Beyond; Excuse Me (I Think I've Got a Heartache) | T22: Essential | X22: https://en.wikipedia.org/wiki/Buck_Owens_(1961_album) | Y22: Medium
A23: A0022 | B23: Ray Charles | C23: Modern Sounds in Country and Western Music | D23: 1962 | E23: LP | F23: ABC-Paramount | G23: =IF(LEFT(I23,3)="R1 ","L6",IF(D23>=2014,"L1",IF(D23>=1998,"L2",IF(D23>=1987,"L3",IF(D23>=1978,"L4",IF(D23>=1965,"L5","L6")))))) -> L6 | H23: =IFERROR(INDEX(Lanes!$C$2:$C$60,MATCH(LEFT(I23,FIND(" ",I23)-1),Lanes!$A$2:$A$60,0)),"?") -> V | I23: R1 Roots | K23: Crossover | L23: The South | M23: Albany, GA | O23: strings; horns; piano; close harmonies; heartbreak | P23: Charles took a stack of Nashville publisher demos and ran them through his own R&B and soul arranging sensibility - strings, horns, gospel-inflected backing vocals - turning Hank Williams and Eddy Arnold songs like 'You Don't Know Me' into pop-soul records. 'I Can't Stop Loving You' went to number one and the album itself topped the pop chart, an unprecedented commercial crossing for a Black R&B artist covering country songs during segregation. It is the record that proved country songwriting could carry any genre's arrangement. | Q23: Its genre-blurring template is a direct ancestor of every later crossover between soul, pop and country songwriting, and its success helped keep country standards like Hank Williams's catalog in wide circulation outside Nashville. | R23: Documented | S23: I Can't Stop Loving You; You Don't Know Me; Born to Lose | T23: Essential | X23: https://en.wikipedia.org/wiki/Modern_Sounds_in_Country_and_Western_Music | Y23: Medium
A24: A0023 | B24: Doc Watson | C24: Doc Watson | D24: 1964 | E24: LP | F24: Vanguard | G24: =IF(LEFT(I24,3)="R1 ","L6",IF(D24>=2014,"L1",IF(D24>=1998,"L2",IF(D24>=1987,"L3",IF(D24>=1978,"L4",IF(D24>=1965,"L5","L6")))))) -> L6 | H24: =IFERROR(INDEX(Lanes!$C$2:$C$60,MATCH(LEFT(I24,FIND(" ",I24)-1),Lanes!$A$2:$A$60,0)),"?") -> V | I24: R1 Roots | K24: Country folk | L24: The South | M24: Deep Gap, NC | O24: fingerpicked acoustic; banjo; storytelling; drawl; harmonica | P24: Watson's debut solo album, supervised by folk revivalist Ralph Rinzler, introduced his flatpicked-fiddle-tune guitar style to a national folk-revival audience: dazzlingly fast, note-perfect runs on tunes like 'Black Mountain Rag' next to plain, unadorned old ballads and blues. Blind since infancy, he plays guitar, banjo and harmonica across the record, moving comfortably between Appalachian traditional material and older blues songs. It made flatpicking a technique other guitarists specifically tried to learn. | Q24: Watson's flatpicking vocabulary is foundational to the whole acoustic-guitar wing of American folk and bluegrass playing, a direct technical ancestor of the fingerstyle American Primitive guitarists and the 2010s indie-folk pickers who came after him. | R24: Documented | S24: Black Mountain Rag; Tom Dooley; Deep River Blues | T24: Essential | X24: https://en.wikipedia.org/wiki/Doc_Watson_(album) | Y24: Medium
A25: A0024 | B25: Lead Belly | C25: Where Did You Sleep Last Night: Lead Belly Legacy, Vol. 1 | D25: 1996 | E25: Compilation | F25: Smithsonian Folkways | G25: =IF(LEFT(I25,3)="R1 ","L6",IF(D25>=2014,"L1",IF(D25>=1998,"L2",IF(D25>=1987,"L3",IF(D25>=1978,"L4",IF(D25>=1965,"L5","L6")))))) -> L6 | H25: =IFERROR(INDEX(Lanes!$C$2:$C$60,MATCH(LEFT(I25,FIND(" ",I25)-1),Lanes!$A$2:$A$60,0)),"?") -> V | I25: R1 Roots | K25: Country folk | L25: The South | M25: Shreveport, LA | O25: fingerpicked acoustic; storytelling; spiritual or gospel; political; drawl | P25: Huddie Ledbetter played a booming twelve-string guitar and carried an enormous songster's repertoire of blues, work songs, prison songs and children's rhymes, first brought to wide attention by folklorists John and Alan Lomax recording him in Louisiana's Angola prison. This first volume of Smithsonian Folkways' posthumous retrospective gathers his best-known versions of songs like the title track (also known as 'In the Pines') alongside staples such as 'Goodnight, Irene' and 'Rock Island Line.' His plain, forceful delivery and songster's range across genres made him one of the folk revival's most-covered sources. | Q25: Directly covered by the folk revival (the Weavers took 'Goodnight, Irene' to number one) and by Lonnie Donegan's skiffle version of 'Rock Island Line,' which helped spark the UK skiffle boom that fed into the Beatles and, further downstream, the whole folk-into-rock trunk line. | R25: Documented | S25: Where Did You Sleep Last Night (In the Pines); Goodnight, Irene; Rock Island Line | T25: Essential | X25: https://en.wikipedia.org/wiki/Lead_Belly | Y25: Medium
A26: A0025 | B26: Mississippi John Hurt | C26: Avalon Blues: The Complete 1928 Okeh Recordings | D26: 1996 | E26: Compilation | F26: Columbia | G26: =IF(LEFT(I26,3)="R1 ","L6",IF(D26>=2014,"L1",IF(D26>=1998,"L2",IF(D26>=1987,"L3",IF(D26>=1978,"L4",IF(D26>=1965,"L5","L6")))))) -> L6 | H26: =IFERROR(INDEX(Lanes!$C$2:$C$60,MATCH(LEFT(I26,FIND(" ",I26)-1),Lanes!$A$2:$A$60,0)),"?") -> V | I26: R1 Roots | K26: Country folk | L26: The South | M26: Avalon, MS | O26: fingerpicked acoustic; storytelling; hushed; drawl; heartbreak | P26: Hurt's two 1928 OKeh sessions produced a gentle, syncopated fingerpicking style and a warm, unhurried singing voice utterly unlike the harder Delta blues of his contemporaries, on songs like 'Frankie' and 'Candy Man Blues.' The records sold poorly and Hurt returned to farming in Avalon, Mississippi for over three decades until a blues researcher traced him there in 1963 using clues from one of these very songs. This Columbia/Legacy set gathers the complete, foundational sessions that made his later rediscovery possible. | Q26: His gentle fingerstyle approach became a direct model for the American Primitive guitarists (John Fahey specifically cited him) and for 1960s folk-revival guitarists like Doc Watson and Dave Van Ronk. | R26: Documented | S26: Frankie; Candy Man Blues; Avalon Blues | T26: Essential | X26: https://en.wikipedia.org/wiki/Mississippi_John_Hurt | Y26: Medium
A27: A0026 | B27: Elizabeth Cotten | C27: Folksongs and Instrumentals with Guitar | D27: 1958 | E27: LP | F27: Folkways | G27: =IF(LEFT(I27,3)="R1 ","L6",IF(D27>=2014,"L1",IF(D27>=1998,"L2",IF(D27>=1987,"L3",IF(D27>=1978,"L4",IF(D27>=1965,"L5","L6")))))) -> L6 | H27: =IFERROR(INDEX(Lanes!$C$2:$C$60,MATCH(LEFT(I27,FIND(" ",I27)-1),Lanes!$A$2:$A$60,0)),"?") -> V | I27: R1 Roots | K27: Country folk | L27: The South | M27: Chapel Hill, NC | O27: fingerpicked acoustic; storytelling; hushed; lullaby; drawl | P27: Cotten, a self-taught left-handed guitarist who played a right-handed guitar upside down, developed a distinctive alternating-bass fingerpicking approach now simply called 'Cotten picking,' recorded here at around 65 years old after folklorist-collector Mike Seeger's family (she worked as their housekeeper) discovered her playing. The record includes her own composition 'Freight Train,' written as a child, alongside old-time instrumentals and rags played with a quiet, unhurried touch. It introduced an entirely new guitar vocabulary to the folk revival. | Q27: Her fingerpicking technique is a foundational influence on the American Primitive guitar line (John Fahey, Jack Rose) and on generations of folk and indie fingerstyle guitarists who learned 'Freight Train' as a standard. | R27: Documented | S27: Freight Train; Vastopol; Wilson Rag | T27: Essential | X27: https://en.wikipedia.org/wiki/Elizabeth_Cotten | Y27: Medium
A28: A0027 | B28: Jean Ritchie | C28: Singing the Traditional Songs of Her Kentucky Mountain Family | D28: 1952 | E28: LP | F28: Elektra | G28: =IF(LEFT(I28,3)="R1 ","L6",IF(D28>=2014,"L1",IF(D28>=1998,"L2",IF(D28>=1987,"L3",IF(D28>=1978,"L4",IF(D28>=1965,"L5","L6")))))) -> L6 | H28: =IFERROR(INDEX(Lanes!$C$2:$C$60,MATCH(LEFT(I28,FIND(" ",I28)-1),Lanes!$A$2:$A$60,0)),"?") -> V | I28: R1 Roots | K28: Country folk | L28: The South | M28: Viper, KY | O28: storytelling; hushed; spiritual or gospel; drawl; lullaby | P28: Ritchie sang the ballads, lullabies and play-party songs passed down through her large Appalachian family in Viper, Kentucky, often accompanying herself on the mountain dulcimer she helped popularize far beyond its home region. This early Elektra LP (one of the label's first releases) presents the songs plainly, without folk-revival polish, as direct family tradition rather than performance repertoire. Songs like 'Nottamun Town' and 'Shady Grove' from her family's collection went on to become folk-revival standards covered widely. | Q28: Her repertoire and dulcimer playing fed directly into the 1960s folk revival - Bob Dylan and Fairport Convention both drew on 'Nottamun Town' - and helped establish the dulcimer as a folk-revival instrument that indie folk artists still reach for. | R28: Documented | S28: Nottamun Town; Shady Grove; The Cuckoo | T28: Recommended | X28: https://en.wikipedia.org/wiki/Jean_Ritchie | Y28: Medium
A29: A0028 | B29: Odetta | C29: Odetta Sings Ballads and Blues | D29: 1956 | E29: LP | F29: Tradition Records | G29: =IF(LEFT(I29,3)="R1 ","L6",IF(D29>=2014,"L1",IF(D29>=1998,"L2",IF(D29>=1987,"L3",IF(D29>=1978,"L4",IF(D29>=1965,"L5","L6")))))) -> L6 | H29: =IFERROR(INDEX(Lanes!$C$2:$C$60,MATCH(LEFT(I29,FIND(" ",I29)-1),Lanes!$A$2:$A$60,0)),"?") -> V | I29: R1 Roots | K29: Country folk | L29: The South | M29: Birmingham, AL | O29: storytelling; spiritual or gospel; political; baritone; hushed | P29: Odetta's debut solo album pairs a trained, classically resonant contralto with simple guitar accompaniment on spirituals, blues and folk ballads like 'Muleskinner Blues' and a spiritual trilogy of 'Oh, Freedom,' 'Come and Go With Me' and 'I'm on My Way.' Her powerful, deliberate delivery treated traditional Black American song as concert repertoire, directly inspiring the generation of singer-songwriters who followed her into coffeehouses and onto festival stages. The Library of Congress added it to the National Recording Registry in 2021. | Q29: A direct and often-cited influence on Bob Dylan, Joan Baez and Janis Joplin, and a key figure in bringing spirituals and blues into the folk-revival concert repertoire that the whole folk-songwriting trunk line draws on. | R29: Documented | S29: Muleskinner Blues; Oh, Freedom; Santy Anno | T29: Essential | X29: https://en.wikipedia.org/wiki/Odetta_Sings_Ballads_and_Blues | Y29: Medium
A30: A0029 | B30: Bob Dylan | C30: Bob Dylan | D30: 1962 | E30: LP | F30: Columbia | G30: =IF(LEFT(I30,3)="R1 ","L6",IF(D30>=2014,"L1",IF(D30>=1998,"L2",IF(D30>=1987,"L3",IF(D30>=1978,"L4",IF(D30>=1965,"L5","L6")))))) -> L6 | H30: =IFERROR(INDEX(Lanes!$C$2:$C$60,MATCH(LEFT(I30,FIND(" ",I30)-1),Lanes!$A$2:$A$60,0)),"?") -> V | I30: R1 Roots | J30: V22 | K30: Country folk | L30: Elsewhere | M30: New York, NY | N30: Greenwich Village | O30: fingerpicked acoustic; storytelling; harmonica; drawl; heartbreak | P30: Cut cheaply and quickly for producer John Hammond, Dylan's debut is almost entirely other people's material - blues and folk standards like 'House of the Rising Sun' and 'Man of Constant Sorrow' - sung in a nasal, Guthrie-indebted rasp over his own guitar and harmonica, with only two originals ('Talkin' New York' and 'Song to Woody') hinting at what was coming. It sold poorly and got him nicknamed 'Hammond's Folly' inside Columbia. Heard now, it is the clearest document of Dylan as a Greenwich Village folk interpreter before he became a songwriter. | Q30: The starting point of Dylan's catalog, which this lane logs here by release year before his songwriting and 1965 electric turn move him into the Dylan and The Band lane (V22); 'Song to Woody' is an explicit tribute naming Woody Guthrie as his direct source. | R30: Documented | S30: Song to Woody; Talkin' New York; House of the Rising Sun | T30: Essential | X30: https://en.wikipedia.org/wiki/Bob_Dylan_(album) | Y30: Medium
A31: A0030 | B31: Bob Dylan | C31: The Freewheelin' Bob Dylan | D31: 1963 | E31: LP | F31: Columbia | G31: =IF(LEFT(I31,3)="R1 ","L6",IF(D31>=2014,"L1",IF(D31>=1998,"L2",IF(D31>=1987,"L3",IF(D31>=1978,"L4",IF(D31>=1965,"L5","L6")))))) -> L6 | H31: =IFERROR(INDEX(Lanes!$C$2:$C$60,MATCH(LEFT(I31,FIND(" ",I31)-1),Lanes!$A$2:$A$60,0)),"?") -> V | I31: R1 Roots | J31: V22 | K31: Country folk | L31: Elsewhere | M31: New York, NY | N31: Greenwich Village | O31: fingerpicked acoustic; storytelling; harmonica; political; heartbreak | P31: Where the debut leaned on covers, this is almost entirely Dylan's own songs, and it is the record that made him the folk revival's defining songwriter: 'Blowin' in the Wind' and 'A Hard Rain's a-Gonna Fall' as topical anthems, 'Don't Think Twice, It's All Right' as a plainspoken breakup song, all carried by just his guitar, harmonica and increasingly assured voice. It set the template - solo acoustic performer as serious songwriter - that the entire folk-songwriting trunk line keeps returning to. | Q31: Established Dylan as a songwriter rather than an interpreter, directly shaping Townes Van Zandt, John Prine and the plainspoken folk-songwriting line that runs through Gillian Welch to Big Thief; logged here by year before his 1965 electric turn carries him into V22. | R31: Documented | S31: Blowin' in the Wind; Don't Think Twice, It's All Right; A Hard Rain's a-Gonna Fall | T31: Essential | X31: https://en.wikipedia.org/wiki/The_Freewheelin%27_Bob_Dylan | Y31: Medium
A32: A0031 | B32: Kitty Wells | C32: Kitty Wells' Country Hit Parade | D32: 1956 | E32: Compilation | F32: Decca | G32: =IF(LEFT(I32,3)="R1 ","L6",IF(D32>=2014,"L1",IF(D32>=1998,"L2",IF(D32>=1987,"L3",IF(D32>=1978,"L4",IF(D32>=1965,"L5","L6")))))) -> L6 | H32: =IFERROR(INDEX(Lanes!$C$2:$C$60,MATCH(LEFT(I32,FIND(" ",I32)-1),Lanes!$A$2:$A$60,0)),"?") -> V | I32: R1 Roots | K32: Honky-tonk | L32: The South | M32: Nashville, TN | O32: Telecaster twang; drawl; heartbreak; close harmonies; storytelling | P32: Wells' first LP gathers the hit singles that made her the first major female star of honky-tonk, anchored by 1952's 'It Wasn't God Who Made Honky Tonk Angels,' a direct sung answer to Hank Thompson's 'Wild Side of Life' that argued men, not women, caused honky-tonk heartbreak. Her plain, unadorned vocal delivery over spare steel-and-fiddle backing gave woman's-eye-view songwriting a mainstream country audience for the first time. It opened the door commercially for every woman who sang hard country after her. | Q32: Directly cleared the commercial path for Patsy Cline, Loretta Lynn, Tammy Wynette and Dolly Parton to sing frankly about women's experience in country music, a lineage alt-country and Americana women songwriters still trace back to her. | R32: Documented | S32: It Wasn't God Who Made Honky Tonk Angels; Release Me; Cheatin's a Sin | T32: Essential | X32: https://en.wikipedia.org/wiki/Kitty_Wells%27_Country_Hit_Parade | Y32: Medium
A33: A0032 | B33: Ernest Tubb | C33: The Ernest Tubb Story | D33: 1959 | E33: Compilation | F33: Decca | G33: =IF(LEFT(I33,3)="R1 ","L6",IF(D33>=2014,"L1",IF(D33>=1998,"L2",IF(D33>=1987,"L3",IF(D33>=1978,"L4",IF(D33>=1965,"L5","L6")))))) -> L6 | H33: =IFERROR(INDEX(Lanes!$C$2:$C$60,MATCH(LEFT(I33,FIND(" ",I33)-1),Lanes!$A$2:$A$60,0)),"?") -> V | I33: R1 Roots | K33: Honky-tonk | L33: Texas and Oklahoma | M33: San Antonio, TX | O33: Telecaster twang; drawl; heartbreak; drinking songs; road songs | P33: Tubb's loose, talk-singing baritone and his band's clean electric guitar (played early on by Fay 'Smitty' Smith and later a procession of Texas pickers) pushed country music off the front porch and into the honky-tonk, led by 1941's 'Walking the Floor Over You,' one of the style's founding hits. This 24-track Decca retrospective, issued while Tubb was still a touring star, spans his biggest sides from the 1940s and 50s. He also helped popularize the electric lead guitar as a country lead instrument years before it was standard. | Q33: As one of honky-tonk's founding artists, Tubb is a direct ancestor of Lefty Frizzell, George Jones and Buck Owens, and his electric-guitar-led band set the instrumental template hard country and later alt-country bands still use. | R33: Documented | S33: Walking the Floor Over You; Filipino Baby; Rainbow at Midnight | T33: Recommended | X33: https://en.wikipedia.org/wiki/The_Ernest_Tubb_Story | Y33: Medium
A34: A0033 | B34: Songs: Ohia | C34: Songs: Ohia | D34: 1997 | E34: LP | F34: Secretly Canadian | G34: =IF(LEFT(I34,3)="R1 ","L6",IF(D34>=2014,"L1",IF(D34>=1998,"L2",IF(D34>=1987,"L3",IF(D34>=1978,"L4",IF(D34>=1965,"L5","L6")))))) -> L3 | H34: =IFERROR(INDEX(Lanes!$C$2:$C$60,MATCH(LEFT(I34,FIND(" ",I34)-1),Lanes!$A$2:$A$60,0)),"?") -> V | I34: V1 Molina and the Magnolia circle | K34: Lo-fi | L34: Chicago and the Midwest | M34: Chicago, IL | N34: Chicago | O34: lo-fi; hushed; bleak; Midwestern; storytelling | P34: Jason Molina's debut as Songs: Ohia, nicknamed 'the Black Album' for its plain dark sleeve, is little more than his reverb-soaked tenor voice and a spare electric or tenor guitar, cut fast and self-distributed before Secretly Canadian picked it up. Song titles like 'Vanquisher' and 'Fortunate Man' sit over almost no percussion, just repeated, incantatory phrases about ghosts and Midwestern dark. It set the stark, haunted template Molina returned to for the rest of his career. | Q34: Grew out of the same lo-fi, DIY folk underground that produced Will Oldham's Palace records, and established the voice-and-guitar minimalism that every later Songs: Ohia and Magnolia Electric Co. record built from or reacted against. | R34: Documented | S34: Vanquisher; Fortunate Man; Hayfoot | T34: Essential | U34: Y | W34: Y | X34: https://en.wikipedia.org/wiki/Songs:_Ohia_(album) | Y34: Medium
A35: A0034 | B35: Songs: Ohia | C35: Impala | D35: 1998 | E35: LP | F35: Happy Go Lucky | G35: =IF(LEFT(I35,3)="R1 ","L6",IF(D35>=2014,"L1",IF(D35>=1998,"L2",IF(D35>=1987,"L3",IF(D35>=1978,"L4",IF(D35>=1965,"L5","L6")))))) -> L2 | H35: =IFERROR(INDEX(Lanes!$C$2:$C$60,MATCH(LEFT(I35,FIND(" ",I35)-1),Lanes!$A$2:$A$60,0)),"?") -> V | I35: V1 Molina and the Magnolia circle | K35: Lo-fi | L35: Chicago and the Midwest | M35: Chicago, IL | N35: Chicago | O35: lo-fi; cracked or yelping; bleak; storytelling; Midwestern | P35: Molina's second Songs: Ohia LP keeps the four-track hiss of the debut but adds a full, ramshackle band clattering behind him, giving songs like 'An Ace Unable to Change' a looser, more chaotic pulse. Parenthetical titles like '(Gambling Song)' and '(Trans Am)' hint at a private mythology that runs through the whole record. It is rougher and more obscure than the albums that followed, a transitional record between bedroom tape and full-band songwriter. | Q35: Bridges the stripped-down debut and the fuller-band Axxess & Ace, part of Molina's rapid early run of Secretly Canadian-adjacent releases out of the Bloomington/Chicago underground. | R35: Documented | S35: An Ace Unable to Change; This Time Anything Finite at All; Just What Can Last | T35: Recommended | W35: Y | X35: https://en.wikipedia.org/wiki/Impala_(album) | Y35: Medium
A36: A0035 | B36: Songs: Ohia | C36: Axxess & Ace | D36: 1999 | E36: LP | F36: Secretly Canadian | G36: =IF(LEFT(I36,3)="R1 ","L6",IF(D36>=2014,"L1",IF(D36>=1998,"L2",IF(D36>=1987,"L3",IF(D36>=1978,"L4",IF(D36>=1965,"L5","L6")))))) -> L2 | H36: =IFERROR(INDEX(Lanes!$C$2:$C$60,MATCH(LEFT(I36,FIND(" ",I36)-1),Lanes!$A$2:$A$60,0)),"?") -> V | I36: V1 Molina and the Magnolia circle | K36: Alt-country | L36: Chicago and the Midwest | M36: Chicago, IL | N36: Chicago | O36: drawl; hushed; storytelling; heartbreak; Midwestern | P36: Axxess & Ace tightens Molina's songwriting into something closer to conventional verse-chorus structure while keeping the hushed, echo-drenched production of his earliest work. 'Captain Badass' stretches out past seven minutes as a slow-burning centerpiece, while 'Love & Work' and 'Redhead' show a plainer, more direct kind of heartbreak song. It is often cited as the record where Molina's songwriting caught up with his atmosphere. | Q36: Continues the Secretly Canadian run that runs from Songs: Ohia's debut through The Lioness, tightening the songwriting that would fully bloom on Didn't It Rain and Magnolia Electric Co. | R36: Documented | S36: Captain Badass; Love & Work; Redhead | T36: Recommended | W36: Y | X36: https://en.wikipedia.org/wiki/Axxess_%26_Ace | Y36: Medium
A37: A0036 | B37: Songs: Ohia | C37: The Lioness | D37: 2000 | E37: LP | F37: Secretly Canadian | G37: =IF(LEFT(I37,3)="R1 ","L6",IF(D37>=2014,"L1",IF(D37>=1998,"L2",IF(D37>=1987,"L3",IF(D37>=1978,"L4",IF(D37>=1965,"L5","L6")))))) -> L2 | H37: =IFERROR(INDEX(Lanes!$C$2:$C$60,MATCH(LEFT(I37,FIND(" ",I37)-1),Lanes!$A$2:$A$60,0)),"?") -> V | I37: V1 Molina and the Magnolia circle | J37: V2 | K37: Country folk | L37: Chicago and the Midwest | M37: Chicago, IL | N37: Chicago | O37: hushed; drawl; fingerpicked acoustic; bleak; storytelling | P37: Recorded near Glasgow with producer Andy Miller, Alasdair Roberts, and members of Arab Strap, The Lioness pairs Molina's voice with a chillier, more atmospheric backing than his American records, opening on the seven-minute drone of 'The Black Crow'. Songs like 'Lioness' and 'Tigress' move at a near-funereal pace, closer to Scottish folk-noir than to Americana. It is one of the clearest points of contact between the Songs: Ohia catalog and the Drag City/Will Oldham circle, via Roberts. | Q37: Made with Alasdair Roberts and Arab Strap's rhythm section in Scotland, linking the Songs: Ohia catalog directly to the UK folk underground that also produced Roberts's own records. | R37: Documented | S37: The Black Crow; Lioness; Tigress | T37: Essential | W37: Y | X37: https://en.wikipedia.org/wiki/The_Lioness_(album) | Y37: Medium
A38: A0037 | B38: Songs: Ohia | C38: Ghost Tropic | D38: 2000 | E38: LP | F38: Secretly Canadian | G38: =IF(LEFT(I38,3)="R1 ","L6",IF(D38>=2014,"L1",IF(D38>=1998,"L2",IF(D38>=1987,"L3",IF(D38>=1978,"L4",IF(D38>=1965,"L5","L6")))))) -> L2 | H38: =IFERROR(INDEX(Lanes!$C$2:$C$60,MATCH(LEFT(I38,FIND(" ",I38)-1),Lanes!$A$2:$A$60,0)),"?") -> V | I38: V1 Molina and the Magnolia circle | J38: V12 | K38: Slowcore | L38: Chicago and the Midwest | M38: Chicago, IL | N38: Chicago | O38: hushed; glacial; long songs (7+ minutes); bleak; drawl | P38: Recorded by Mike Mogis, Ghost Tropic is the slowest and most drone-like Songs: Ohia record, built from long, barely-moving pieces like the twelve-minute 'Not Just a Ghost's Heart' and the eleven-minute 'Incantation'. Molina's guitar and voice sit in wide, reverberant space rather than pushing toward a chorus, closer to American slowcore than to a folk or country record. It is the Songs: Ohia album most often cited as a bridge to the Low/Codeine slowcore lineage. | Q38: The most slowcore-indebted Songs: Ohia record, sitting between the folk-noir of The Lioness and the gospel-country turn of Didn't It Rain the following year. | R38: Inferred | S38: Ghost Tropic; Not Just a Ghost's Heart; Incantation | T38: Recommended | W38: Y | X38: https://en.wikipedia.org/wiki/Ghost_Tropic | Y38: Medium
A39: A0038 | B39: Songs: Ohia | C39: Mi Sei Apparso Come Un Fantasma | D39: 2001 | E39: Live | F39: Paper Cup | G39: =IF(LEFT(I39,3)="R1 ","L6",IF(D39>=2014,"L1",IF(D39>=1998,"L2",IF(D39>=1987,"L3",IF(D39>=1978,"L4",IF(D39>=1965,"L5","L6")))))) -> L2 | H39: =IFERROR(INDEX(Lanes!$C$2:$C$60,MATCH(LEFT(I39,FIND(" ",I39)-1),Lanes!$A$2:$A$60,0)),"?") -> V | I39: V1 Molina and the Magnolia circle | K39: Alt-country | L39: Chicago and the Midwest | M39: Chicago, IL | N39: Chicago | O39: live in the room; drawl; hushed; storytelling; Midwestern | P39: Recorded near Modena, Italy in 2000 with Molina's touring band of the Sullivan brothers, Jeff Panall and Jim Grabowski and released locally the following year, this live set captures the full-band version of Songs: Ohia mid-tour, reworking songs like 'Tigress' and 'Being in Love' from The Lioness alongside then-new, otherwise-untitled pieces. It is looser and more electric than the studio records of the same period, a document of the road band rather than a studio statement. | Q39: A snapshot of the touring band that also cut Ghost Tropic and Didn't It Rain, showing how the Songs: Ohia sound opened up once Molina had a full electric group behind him. | R39: Documented | S39: Tigress; Being in Love; Cabwaylingo | T39: Deep cut | W39: Y | X39: https://en.wikipedia.org/wiki/Mi_Sei_Apparso_Come_Un_Fantasma | Y39: Medium
A40: A0039 | B40: Songs: Ohia | C40: Protection Spells | D40: 2000 | E40: LP | F40: Secretly Canadian | G40: =IF(LEFT(I40,3)="R1 ","L6",IF(D40>=2014,"L1",IF(D40>=1998,"L2",IF(D40>=1987,"L3",IF(D40>=1978,"L4",IF(D40>=1965,"L5","L6")))))) -> L2 | H40: =IFERROR(INDEX(Lanes!$C$2:$C$60,MATCH(LEFT(I40,FIND(" ",I40)-1),Lanes!$A$2:$A$60,0)),"?") -> V | I40: V1 Molina and the Magnolia circle | K40: Lo-fi | L40: Chicago and the Midwest | M40: Chicago, IL | N40: Chicago | O40: lo-fi; hushed; bleak; drawl; storytelling | P40: A solo, mostly acoustic album sold at live shows in 2000 and long out of print, Protection Spells is one of Molina's least-heard records, closer in spirit to the stark debut than to the full-band records surrounding it. Songs like 'Trouble Will Find You' and 'The Moon Undoes It All' are recorded plainly, voice and guitar with little else. It survives mainly as a tour artifact rather than a widely distributed release, but its titles and mood run through Molina's later, more famous work. | Q40: A between-albums tour-only release from the same 2000 stretch that produced The Lioness and Ghost Tropic, showing the stripped-down solo mode Molina kept returning to between full-band records. | R40: Documented | S40: Trouble Will Find You; The Moon Undoes It All; Darkness That Strong | T40: Deep cut | W40: Y | X40: https://en.wikipedia.org/wiki/Protection_Spells | Y40: Medium
A41: A0040 | B41: Songs: Ohia | C41: Hecla & Griper | D41: 1997 | E41: EP | F41: Secretly Canadian | G41: =IF(LEFT(I41,3)="R1 ","L6",IF(D41>=2014,"L1",IF(D41>=1998,"L2",IF(D41>=1987,"L3",IF(D41>=1978,"L4",IF(D41>=1965,"L5","L6")))))) -> L3 | H41: =IFERROR(INDEX(Lanes!$C$2:$C$60,MATCH(LEFT(I41,FIND(" ",I41)-1),Lanes!$A$2:$A$60,0)),"?") -> V | I41: V1 Molina and the Magnolia circle | K41: Lo-fi | L41: Chicago and the Midwest | M41: Chicago, IL | N41: Chicago | O41: lo-fi; hushed; bleak; drawl; short songs (under 2 minutes) | P41: Released the same year as the Songs: Ohia debut, this early EP is spare, plainly recorded songs like 'Pass' and 'Defenders' that run only a minute or two apiece, closer to sketches than finished songs. It shares the debut's stark voice-and-guitar sound and dark, allusive titles. It is a minor, early document more than a destination record, useful mainly for hearing how quickly Molina was already writing and releasing material. | Q41: A same-year companion to the Songs: Ohia debut LP, part of the flood of early Secretly Canadian releases that established Molina's stark solo sound before the full band arrived. | R41: Documented | S41: Pass; Defenders; Declarer | T41: Deep cut | W41: Y | X41: https://en.wikipedia.org/wiki/Jason_Molina | Y41: Medium
A42: A0041 | B42: Songs: Ohia | C42: Didn't It Rain | D42: 2002 | E42: LP | F42: Secretly Canadian | G42: =IF(LEFT(I42,3)="R1 ","L6",IF(D42>=2014,"L1",IF(D42>=1998,"L2",IF(D42>=1987,"L3",IF(D42>=1978,"L4",IF(D42>=1965,"L5","L6")))))) -> L2 | H42: =IFERROR(INDEX(Lanes!$C$2:$C$60,MATCH(LEFT(I42,FIND(" ",I42)-1),Lanes!$A$2:$A$60,0)),"?") -> V | I42: V1 Molina and the Magnolia circle | K42: Alt-country | L42: Chicago and the Midwest | M42: Chicago, IL | N42: Chicago | O42: drawl; hushed; spiritual or gospel; storytelling; long songs (7+ minutes) | P42: Recorded in Philadelphia with members of the bluegrass band Jim & Jennie & the Pinetops and named for a Mahalia Jackson song, Didn't It Rain trades Ghost Tropic's dense drone for a warmer, near-gospel small-group sound. The title track and 'Blue Factory Flame' stretch past seven and eight minutes on repeated, mantra-like phrases, while 'Two Blue Lights' offers a rare moment of brevity. Many fans and critics treat this as the true beginning of the Magnolia Electric Co. sound, one year before the name change. | Q42: The field guide's other suggested starting point alongside Magnolia Electric Co.; its gospel-tinged small-band sound is the direct bridge from the earlier solo Songs: Ohia records to the full-band Crazy Horse-scale group that followed. | R42: Documented | S42: Didn't It Rain; Blue Factory Flame; Two Blue Lights | T42: Essential | U42: Y | W42: Y | X42: https://en.wikipedia.org/wiki/Didn%27t_It_Rain_(Songs:_Ohia_album) | Y42: Medium
A43: A0042 | B43: Songs: Ohia | C43: The Magnolia Electric Co. | D43: 2003 | E43: LP | F43: Secretly Canadian | G43: =IF(LEFT(I43,3)="R1 ","L6",IF(D43>=2014,"L1",IF(D43>=1998,"L2",IF(D43>=1987,"L3",IF(D43>=1978,"L4",IF(D43>=1965,"L5","L6")))))) -> L2 | H43: =IFERROR(INDEX(Lanes!$C$2:$C$60,MATCH(LEFT(I43,FIND(" ",I43)-1),Lanes!$A$2:$A$60,0)),"?") -> V | I43: V1 Molina and the Magnolia circle | J43: V20 | K43: Country rock | L43: Chicago and the Midwest | M43: Chicago, IL | N43: Chicago | O43: Crazy Horse fuzz; drawl; long solos; storytelling; anthemic | P43: Cut live in the studio with a full touring band, The Magnolia Electric Co. opens with the seven-minute 'Farewell Transmission' and never really lets up, trading Molina's earlier hushed folk for Crazy Horse-scale electric guitar, organ and drums. 'I've Been Riding with the Ghost' and 'Just Be Simple' pair big, ragged choruses with Molina's still-bleak lyrics about ghosts and highways. It is the record that gave the band its next name and its widest audience, and remains the most-cited entry point into the whole catalog. | Q43: Draws directly on Neil Young and Crazy Horse's guitar-heavy heartland rock and Molina's own heavy-metal roots, and gave its name to Magnolia Electric Co., the band Molina led for the next decade. | R43: Documented | S43: Farewell Transmission; I've Been Riding with the Ghost; Just Be Simple | T43: Essential | W43: Y | X43: https://en.wikipedia.org/wiki/The_Magnolia_Electric_Co. | Y43: Medium
A44: A0043 | B44: Jason Molina | C44: Pyramid Electric Co. | D44: 2004 | E44: LP | F44: Secretly Canadian | G44: =IF(LEFT(I44,3)="R1 ","L6",IF(D44>=2014,"L1",IF(D44>=1998,"L2",IF(D44>=1987,"L3",IF(D44>=1978,"L4",IF(D44>=1965,"L5","L6")))))) -> L2 | H44: =IFERROR(INDEX(Lanes!$C$2:$C$60,MATCH(LEFT(I44,FIND(" ",I44)-1),Lanes!$A$2:$A$60,0)),"?") -> V | I44: V1 Molina and the Magnolia circle | K44: Lo-fi | L44: Chicago and the Midwest | M44: Chicago, IL | N44: Chicago | O44: hushed; piano; bleak; lullaby; drawl | P44: Engineered by Mike Mogis, Pyramid Electric Co. strips everything back to Molina alone with voice, guitar and piano, the quietest record he made under his own name. The title track runs nearly nine minutes as a slow piano meditation, while 'Long Desert Train' closes the record on a similarly patient note. It is a deliberate come-down from the full-band Magnolia Electric Co. album released the year before, a private, unhurried companion piece. | Q44: A solo counterpart released the year after The Magnolia Electric Co., returning to the hushed, voice-and-instrument minimalism of the earliest Songs: Ohia records. | R44: Documented | S44: Pyramid Electric Co.; Long Desert Train; Division St. Girl | T44: Recommended | X44: https://en.wikipedia.org/wiki/Pyramid_Electric_Co. | Y44: Medium
A45: A0044 | B45: Jason Molina | C45: Let Me Go, Let Me Go, Let Me Go | D45: 2006 | E45: LP | F45: Secretly Canadian | G45: =IF(LEFT(I45,3)="R1 ","L6",IF(D45>=2014,"L1",IF(D45>=1998,"L2",IF(D45>=1987,"L3",IF(D45>=1978,"L4",IF(D45>=1965,"L5","L6")))))) -> L2 | H45: =IFERROR(INDEX(Lanes!$C$2:$C$60,MATCH(LEFT(I45,FIND(" ",I45)-1),Lanes!$A$2:$A$60,0)),"?") -> V | I45: V1 Molina and the Magnolia circle | K45: Indie folk | L45: Chicago and the Midwest | M45: Chicago, IL | N45: Chicago | O45: hushed; fingerpicked acoustic; bleak; drawl; spiritual or gospel | P45: Released the same year as Magnolia Electric Co.'s full-band Fading Trails, this sparse solo record leans on plain acoustic guitar and Molina's voice, with the title track closing things out at nearly seven minutes. Songs like 'It's Easier Now' and 'Alone With the Owl' keep the arrangements minimal so the lyrics about isolation and endurance carry the weight. It is one of the most purely singer-songwriter entries in Molina's catalog, closer to the folk end of his sound than to the band's rock side. | Q45: Continues the solo, stripped-down thread running from Pyramid Electric Co. through Molina's later work, released as a quiet counterweight to the same year's full-band Fading Trails. | R45: Documented | S45: It's Easier Now; Alone With the Owl; Let Me Go Let Me Go Let Me Go | T45: Recommended | X45: https://en.wikipedia.org/wiki/Let_Me_Go,_Let_Me_Go,_Let_Me_Go | Y45: Medium
A46: A0045 | B46: Jason Molina | C46: Autumn Bird Songs | D46: 2012 | E46: EP | F46: Graveface Records | G46: =IF(LEFT(I46,3)="R1 ","L6",IF(D46>=2014,"L1",IF(D46>=1998,"L2",IF(D46>=1987,"L3",IF(D46>=1978,"L4",IF(D46>=1965,"L5","L6")))))) -> L2 | H46: =IFERROR(INDEX(Lanes!$C$2:$C$60,MATCH(LEFT(I46,FIND(" ",I46)-1),Lanes!$A$2:$A$60,0)),"?") -> V | I46: V1 Molina and the Magnolia circle | K46: Indie folk | L46: Chicago and the Midwest | M46: Chicago, IL | O46: hushed; fingerpicked acoustic; short songs (under 2 minutes); bleak; lullaby | P46: An eight-song, twenty-two-minute set released during Molina's illness, Autumn Bird Songs is brief, plainly recorded songs like 'Heart My Heart' and 'The Harvest Law' that feel closer to sketches than to a full statement. It is quieter and more fragile than his earlier work, released on Graveface rather than his usual home at Secretly Canadian. For a small, committed audience it is one of the last pieces of new music Molina put out in his lifetime. | Q46: One of Molina's final releases before his 2013 death, extending the hushed solo-acoustic mode of Pyramid Electric Co. and Let Me Go, Let Me Go, Let Me Go into a briefer, more fragile form. | R46: Documented | S46: Heart My Heart; The Harvest Law; Enough of a Stranger | T46: Deep cut | X46: https://graveface.bandcamp.com/album/autumn-bird-songs https://en.wikipedia.org/wiki/Jason_Molina | Y46: High
A47: A0046 | B47: Jason Molina | C47: Eight Gates | D47: 2020 | E47: LP | F47: Secretly Canadian | G47: =IF(LEFT(I47,3)="R1 ","L6",IF(D47>=2014,"L1",IF(D47>=1998,"L2",IF(D47>=1987,"L3",IF(D47>=1978,"L4",IF(D47>=1965,"L5","L6")))))) -> L1 | H47: =IFERROR(INDEX(Lanes!$C$2:$C$60,MATCH(LEFT(I47,FIND(" ",I47)-1),Lanes!$A$2:$A$60,0)),"?") -> V | I47: V1 Molina and the Magnolia circle | K47: Indie folk | L47: Chicago and the Midwest | M47: Chicago, IL | O47: hushed; piano; bleak; spiritual or gospel; drawl | P47: Recorded in the 2000s but shelved until after Molina's 2013 death, Eight Gates was assembled and released by Secretly Canadian in 2020 as a posthumous studio album. Opener 'Whisper Away' and 'Shadow Answers the Wall' sit in the same hushed, piano-and-guitar territory as Pyramid Electric Co., by turns unfinished-sounding and quietly devastating. It gave fans a final, previously unheard chapter of Molina's writing, released under his own name seven years after he died. | Q47: A posthumous release of 2000s-era Molina recordings, closing out the catalog begun with Songs: Ohia's 1997 debut and continued through his solo and Magnolia Electric Co. work. | R47: Documented | S47: Whisper Away; Shadow Answers the Wall; The Mission's End | T47: Essential | X47: https://jasonmolina.bandcamp.com/album/eight-gates https://en.wikipedia.org/wiki/Jason_Molina | Y47: High
A48: A0047 | B48: Pavement | C48: Slanted and Enchanted | D48: 1992 | E48: LP | F48: Matador Records | G48: =IF(LEFT(I48,3)="R1 ","L6",IF(D48>=2014,"L1",IF(D48>=1998,"L2",IF(D48>=1987,"L3",IF(D48>=1978,"L4",IF(D48>=1965,"L5","L6")))))) -> L3 | H48: =IFERROR(INDEX(Lanes!$C$2:$C$60,MATCH(LEFT(I48,FIND(" ",I48)-1),Lanes!$A$2:$A$60,0)),"?") -> V | I48: V10 Slacker and '90s indie rock | K48: Slacker | L48: The West | M48: Stockton, CA | O48: lo-fi; deadpan; jangle; feedback; funny-sad | P48: Stephen Malkmus and Scott Kannberg's debut buries hooky, Fall-indebted guitar pop under tape hiss and wobbly, half-mixed production, with Malkmus's flat, ironic drawl floating over songs that keep threatening to fall apart. It set the template for the whole slacker-rock movement: smart, allusive lyrics delivered like they don't matter, played by a band that sounds like it barely rehearsed. Tracks like 'Summer Babe' and 'Trigger Cut' turned deliberate sloppiness into a new kind of hook. | Q48: Grew out of Malkmus and Kannberg's Stockton four-track experiments and the Fall's off-kilter post-punk; became the foundational text for Matador's 1990s indie-rock roster and every slacker band after it. | R48: Documented | S48: Summer Babe; Trigger Cut; In the Mouth a Desert | T48: Essential | W48: Y | X48: https://en.wikipedia.org/wiki/Pavement_(band) | Y48: Medium
A49: A0048 | B49: Pavement | C49: Westing (By Musket and Sextant) | D49: 1993 | E49: Compilation | F49: Drag City | G49: =IF(LEFT(I49,3)="R1 ","L6",IF(D49>=2014,"L1",IF(D49>=1998,"L2",IF(D49>=1987,"L3",IF(D49>=1978,"L4",IF(D49>=1965,"L5","L6")))))) -> L3 | H49: =IFERROR(INDEX(Lanes!$C$2:$C$60,MATCH(LEFT(I49,FIND(" ",I49)-1),Lanes!$A$2:$A$60,0)),"?") -> V | I49: V10 Slacker and '90s indie rock | K49: Lo-fi | L49: The West | M49: Stockton, CA | O49: lo-fi; noise wall; feedback; deadpan; short songs (under 2 minutes) | P49: This compilation gathers Pavement's first three EPs (Slay Tracks, Demolition Plot J-7, Perfect Sound Forever) plus the 'Summer Babe' single and stray compilation tracks, capturing the band before they cleaned up any of their four-track hiss. It is rawer and more purely noisy than the albums that followed, closer to Sonic Youth skronk than to the melodic slacker-pop Pavement became. Songs like 'Box Elder' show the pop instincts were there from the start, just buried under distortion. | Q49: Documents Pavement's earliest Drag City/Treble Kicker singles before they signed properly to Matador, tracing the band's move from pure noise experiment toward song. | R49: Documented | S49: Box Elder; Debris Slide; Summer Babe (Winter Version) | T49: Recommended | W49: Y | X49: https://en.wikipedia.org/wiki/Westing_(By_Musket_and_Sextant) https://en.wikipedia.org/wiki/Pavement_(band) | Y49: High
A50: A0049 | B50: Pavement | C50: Crooked Rain, Crooked Rain | D50: 1994 | E50: LP | F50: Matador Records | G50: =IF(LEFT(I50,3)="R1 ","L6",IF(D50>=2014,"L1",IF(D50>=1998,"L2",IF(D50>=1987,"L3",IF(D50>=1978,"L4",IF(D50>=1965,"L5","L6")))))) -> L3 | H50: =IFERROR(INDEX(Lanes!$C$2:$C$60,MATCH(LEFT(I50,FIND(" ",I50)-1),Lanes!$A$2:$A$60,0)),"?") -> V | I50: V10 Slacker and '90s indie rock | K50: Slacker | L50: The West | M50: Stockton, CA | O50: jangle; deadpan; funny-sad; pop-culture references; breezy | P50: Pavement's second album trades some of the debut's hiss for actual hooks, stretching out into loose California classic-rock shapes on 'Range Life' while keeping Malkmus's sing-song sarcasm intact on 'Cut Your Hair.' It is the record where the band's private jokes and non sequiturs start to sound like genuine songwriting rather than noise-pop experiments. 'Gold Soundz' became the closest thing indie rock had to a canonical singalong in 1994. | Q50: Built directly on Slanted and Enchanted's lo-fi template but points toward the more song-focused American indie rock of the later 1990s, influencing everyone from Silver Jews to the Strokes. | R50: Documented | S50: Gold Soundz; Cut Your Hair; Range Life | T50: Essential | U50: Y | W50: Y | X50: https://en.wikipedia.org/wiki/Pavement_(band) | Y50: Medium
A51: A0050 | B51: Pavement | C51: Wowee Zowee | D51: 1995 | E51: LP | F51: Matador Records | G51: =IF(LEFT(I51,3)="R1 ","L6",IF(D51>=2014,"L1",IF(D51>=1998,"L2",IF(D51>=1987,"L3",IF(D51>=1978,"L4",IF(D51>=1965,"L5","L6")))))) -> L3 | H51: =IFERROR(INDEX(Lanes!$C$2:$C$60,MATCH(LEFT(I51,FIND(" ",I51)-1),Lanes!$A$2:$A$60,0)),"?") -> V | I51: V10 Slacker and '90s indie rock | K51: Lo-fi | L51: The West | M51: Stockton, CA | O51: lo-fi; deadpan; funny-sad; breezy; feedback | P51: Deliberately shapeless where Crooked Rain had hooks, Wowee Zowee sprawls across eighteen tracks that swing from country pastiche to hardcore blasts to hazy, half-finished sketches. It confused listeners expecting a follow-up single but has since become a cult favorite for exactly that restlessness, a band actively resisting its own commercial momentum. 'Father to a Sister of Thought' and 'Rattled by the Rush' show the songwriting still holding together under all the sprawl. | Q51: A deliberate swerve away from the college-rock accessibility of Crooked Rain, Crooked Rain, closer in spirit to the era's lo-fi underground (Sebadoh, Guided by Voices) than to Pavement's own prior record. | R51: Documented | S51: Rattled by the Rush; Father to a Sister of Thought; AT&T | T51: Recommended | W51: Y | X51: https://en.wikipedia.org/wiki/Pavement_(band) | Y51: Medium
A52: A0051 | B52: Pavement | C52: Brighten the Corners | D52: 1997 | E52: LP | F52: Matador Records | G52: =IF(LEFT(I52,3)="R1 ","L6",IF(D52>=2014,"L1",IF(D52>=1998,"L2",IF(D52>=1987,"L3",IF(D52>=1978,"L4",IF(D52>=1965,"L5","L6")))))) -> L3 | H52: =IFERROR(INDEX(Lanes!$C$2:$C$60,MATCH(LEFT(I52,FIND(" ",I52)-1),Lanes!$A$2:$A$60,0)),"?") -> V | I52: V10 Slacker and '90s indie rock | K52: Jangle | L52: The West | M52: Stockton, CA | O52: jangle; deadpan; breezy; pop-culture references; funny-sad | P52: The most straightforwardly melodic Pavement album, Brighten the Corners trims the sprawl of Wowee Zowee back into tight, guitar-pop songs without losing Malkmus's deadpan non sequiturs. 'Stereo' and 'Shady Lane' are as close as the band got to conventional radio songs, though the lyrics remain as slippery as ever. It reads as the sound of a band settling into confident midcareer craft rather than chasing a breakthrough. | Q52: A return to song-length discipline after Wowee Zowee's sprawl, closer in feel to Crooked Rain, Crooked Rain and pointing toward Malkmus's more polished solo work after the band's split. | R52: Documented | S52: Stereo; Shady Lane; Type Slowly | T52: Recommended | W52: Y | X52: https://en.wikipedia.org/wiki/Pavement_(band) | Y52: Medium
A53: A0052 | B53: Pavement | C53: Terror Twilight | D53: 1999 | E53: LP | F53: Matador Records | G53: =IF(LEFT(I53,3)="R1 ","L6",IF(D53>=2014,"L1",IF(D53>=1998,"L2",IF(D53>=1987,"L3",IF(D53>=1978,"L4",IF(D53>=1965,"L5","L6")))))) -> L2 | H53: =IFERROR(INDEX(Lanes!$C$2:$C$60,MATCH(LEFT(I53,FIND(" ",I53)-1),Lanes!$A$2:$A$60,0)),"?") -> V | I53: V10 Slacker and '90s indie rock | K53: Jangle | L53: The West | M53: Stockton, CA | O53: jangle; breezy; deadpan; funny-sad; polished | P53: Produced by Nigel Godrich fresh off OK Computer, Pavement's final album is their most polished and, in spots, most melancholy, with 'Spit on a Stranger' and 'Major Leagues' sounding almost wistful compared to the band's earlier smirk. Internal tension between Malkmus and drummer Bob Nastanovich was already pulling the band apart during the sessions, and the record's more measured, less collaborative feel reflects that. It closed out the band's original run on a note of unexpected tenderness. | Q53: Pavement's last studio album before their 1999 breakup, produced outside the band's usual DIY circle and pointing directly toward the more song-crafted, less chaotic sound of Malkmus's subsequent solo records. | R53: Documented | S53: Spit on a Stranger; Major Leagues; Carrot Rope | T53: Recommended | W53: Y | X53: https://en.wikipedia.org/wiki/Pavement_(band) | Y53: Medium
A54: A0053 | B54: Archers of Loaf | C54: Icky Mettle | D54: 1993 | E54: LP | F54: Alias Records | G54: =IF(LEFT(I54,3)="R1 ","L6",IF(D54>=2014,"L1",IF(D54>=1998,"L2",IF(D54>=1987,"L3",IF(D54>=1978,"L4",IF(D54>=1965,"L5","L6")))))) -> L3 | H54: =IFERROR(INDEX(Lanes!$C$2:$C$60,MATCH(LEFT(I54,FIND(" ",I54)-1),Lanes!$A$2:$A$60,0)),"?") -> V | I54: V10 Slacker and '90s indie rock | K54: Slacker | L54: The Carolinas | M54: Chapel Hill, NC | N54: Durham and Chapel Hill | O54: feedback; shouted; jangle; deadpan; short songs (under 2 minutes) | P54: Eric Bachmann's Chapel Hill band debuts with tangled, feedback-streaked guitar interplay and a yelped, half-sardonic vocal delivery that made them instant peers of Pavement without sounding like an imitation. 'Web in Front' and 'Wrong' pair genuinely catchy melodies with production that stays scrappy and unresolved. It is one of the definitive documents of the early-1990s Chapel Hill scene that also produced Superchunk and Polvo. | Q54: A cornerstone of Chapel Hill's Merge/Alias-adjacent indie rock boom, sharing DNA with Pavement's noisy melodicism while helping put North Carolina on the same map as Matador's New York roster. | R54: Documented | S54: Web in Front; Wrong | T54: Essential | U54: Y | W54: Y | X54: https://en.wikipedia.org/wiki/Archers_of_Loaf | Y54: Medium
A55: A0054 | B55: Archers of Loaf | C55: Vee Vee | D55: 1995 | E55: LP | F55: Alias Records | G55: =IF(LEFT(I55,3)="R1 ","L6",IF(D55>=2014,"L1",IF(D55>=1998,"L2",IF(D55>=1987,"L3",IF(D55>=1978,"L4",IF(D55>=1965,"L5","L6")))))) -> L3 | H55: =IFERROR(INDEX(Lanes!$C$2:$C$60,MATCH(LEFT(I55,FIND(" ",I55)-1),Lanes!$A$2:$A$60,0)),"?") -> V | I55: V10 Slacker and '90s indie rock | K55: Noise | L55: The Carolinas | M55: Chapel Hill, NC | N55: Durham and Chapel Hill | O55: feedback; noise wall; shouted; deadpan; storytelling | P55: The Archers' second album tightens the songwriting while turning up the guitar noise, with Eric Johnson and Eric Bachmann's twin-guitar clatter pushed further toward abrasion on tracks like 'Harnessed in Slums.' Bachmann's vocals grow more strained and urgent, matching lyrics that read as more directly bitter than the debut's shaggier jokes. It is generally regarded as the band's most abrasive and structurally ambitious record. | Q55: Pushes the noisy melodicism of Icky Mettle toward harder-edged post-hardcore and noise rock, a move that anticipated the heavier turn of other Southern indie bands later in the decade. | R55: Documented | S55: Harnessed in Slums; Underdogs of Nipomo | T55: Recommended | W55: Y | X55: https://en.wikipedia.org/wiki/Archers_of_Loaf | Y55: Medium
A56: A0055 | B56: Archers of Loaf | C56: All the Nation's Airports | D56: 1996 | E56: LP | F56: Alias Records | G56: =IF(LEFT(I56,3)="R1 ","L6",IF(D56>=2014,"L1",IF(D56>=1998,"L2",IF(D56>=1987,"L3",IF(D56>=1978,"L4",IF(D56>=1965,"L5","L6")))))) -> L3 | H56: =IFERROR(INDEX(Lanes!$C$2:$C$60,MATCH(LEFT(I56,FIND(" ",I56)-1),Lanes!$A$2:$A$60,0)),"?") -> V | I56: V10 Slacker and '90s indie rock | K56: Slacker | L56: The Carolinas | M56: Chapel Hill, NC | N56: Durham and Chapel Hill | O56: jangle; deadpan; pop-culture references; breezy; feedback | P56: A deliberate step toward cleaner production and more accessible songwriting, All the Nation's Airports keeps the tangled guitar lines of earlier records but gives them more room to breathe, especially on the single 'Chumming the Ocean.' Critics at the time were divided on the polish, but the record holds up as the band's most tuneful outing without losing its off-kilter character. It shows a band trying to grow without abandoning what made them odd in the first place. | Q56: Follows Vee Vee's noise-rock turn with a more melodic, radio-conscious record, part of a wider mid-1990s move by Matador- and Alias-adjacent bands toward cleaner studio sound. | R56: Documented | S56: Chumming the Ocean; Scenic Pastures | T56: Recommended | W56: Y | X56: https://en.wikipedia.org/wiki/Archers_of_Loaf | Y56: Medium
A57: A0056 | B57: Archers of Loaf | C57: White Trash Heroes | D57: 1998 | E57: LP | F57: Alias Records | G57: =IF(LEFT(I57,3)="R1 ","L6",IF(D57>=2014,"L1",IF(D57>=1998,"L2",IF(D57>=1987,"L3",IF(D57>=1978,"L4",IF(D57>=1965,"L5","L6")))))) -> L2 | H57: =IFERROR(INDEX(Lanes!$C$2:$C$60,MATCH(LEFT(I57,FIND(" ",I57)-1),Lanes!$A$2:$A$60,0)),"?") -> V | I57: V10 Slacker and '90s indie rock | K57: Noise | L57: The Carolinas | M57: Chapel Hill, NC | N57: Durham and Chapel Hill | O57: noise wall; deadpan; bleak; feedback; storytelling | P57: The Archers' final studio album before their initial breakup is their strangest, trading straightforward guitar pop for murkier, more processed arrangements and a bleaker lyrical tone on songs like 'Fashion Bleeds.' It divided longtime fans expecting another Icky Mettle but has been reassessed since as a genuine left turn rather than a decline. The record's unease in hindsight reads as the sound of a band pulling itself apart. | Q57: A late, more experimental swerve from a band that had already helped define 1990s Chapel Hill indie rock, closer in mood to the era's noisier post-hardcore than to the band's earlier slacker-pop. | R57: Documented | S57: Fashion Bleeds | T57: Deep cut | W57: Y | X57: https://en.wikipedia.org/wiki/Archers_of_Loaf | Y57: Medium
A58: A0057 | B58: Superchunk | C58: Superchunk | D58: 1990 | E58: LP | F58: Matador Records | G58: =IF(LEFT(I58,3)="R1 ","L6",IF(D58>=2014,"L1",IF(D58>=1998,"L2",IF(D58>=1987,"L3",IF(D58>=1978,"L4",IF(D58>=1965,"L5","L6")))))) -> L3 | H58: =IFERROR(INDEX(Lanes!$C$2:$C$60,MATCH(LEFT(I58,FIND(" ",I58)-1),Lanes!$A$2:$A$60,0)),"?") -> V | I58: V10 Slacker and '90s indie rock | K58: Punk | L58: The Carolinas | M58: Chapel Hill, NC | N58: Durham and Chapel Hill | O58: shouted; short songs (under 2 minutes); feedback; rowdy; noise wall | P58: Superchunk's self-titled debut is fast, blunt hardcore-pop, all buzzsaw guitars and Mac McCaughan's yelped, barely-melodic vocals, closer to Buzzcocks-via-Hüsker-Dü than to the more tuneful band they'd become. It captures a Chapel Hill house-party band before the songwriting caught up to the energy. Still, the raw speed and DIY snottiness set the tone for everything the band and their soon-to-be-founded label Merge represented. | Q58: Superchunk's earliest recordings, made before Mac McCaughan and Laura Ballance founded Merge Records, drawing on Hüsker Dü and Buzzcocks-style hardcore-pop that the band would soon refine into their signature sound. | R58: Documented | S58: Slack Motherfucker; Cast Iron | T58: Recommended | W58: Y | X58: https://en.wikipedia.org/wiki/Superchunk | Y58: Medium
A59: A0058 | B59: Superchunk | C59: No Pocky for Kitty | D59: 1991 | E59: LP | F59: Matador Records | G59: =IF(LEFT(I59,3)="R1 ","L6",IF(D59>=2014,"L1",IF(D59>=1998,"L2",IF(D59>=1987,"L3",IF(D59>=1978,"L4",IF(D59>=1965,"L5","L6")))))) -> L3 | H59: =IFERROR(INDEX(Lanes!$C$2:$C$60,MATCH(LEFT(I59,FIND(" ",I59)-1),Lanes!$A$2:$A$60,0)),"?") -> V | I59: V10 Slacker and '90s indie rock | K59: Punk | L59: The Carolinas | M59: Chapel Hill, NC | N59: Durham and Chapel Hill | O59: shouted; rowdy; noise wall; short songs (under 2 minutes); anthemic | P59: Recorded with Steve Albini, No Pocky for Kitty is louder and more focused than the debut, with 'Skip Steps 1 & 3' and 'Seed Toss' turning Superchunk's hardcore energy into genuine anthems. McCaughan's vocals are still shouted but the hooks are sharper, and the rhythm section of Ballance and Jon Wurster (soon to join) locks in tighter. It remains a favorite among fans who prize the band's rawest, most physically exciting era. | Q59: An Albini-recorded leap in power and focus from the scrappier debut, part of the same early-1990s Matador roster as Pavement and Liz Phair before Superchunk struck out on their own label, Merge. | R59: Documented | S59: Skip Steps 1 & 3; Seed Toss | T59: Recommended | W59: Y | X59: https://en.wikipedia.org/wiki/Superchunk | Y59: Medium
A60: A0059 | B60: Superchunk | C60: On the Mouth | D60: 1993 | E60: LP | F60: Matador Records | G60: =IF(LEFT(I60,3)="R1 ","L6",IF(D60>=2014,"L1",IF(D60>=1998,"L2",IF(D60>=1987,"L3",IF(D60>=1978,"L4",IF(D60>=1965,"L5","L6")))))) -> L3 | H60: =IFERROR(INDEX(Lanes!$C$2:$C$60,MATCH(LEFT(I60,FIND(" ",I60)-1),Lanes!$A$2:$A$60,0)),"?") -> V | I60: V10 Slacker and '90s indie rock | K60: Punk | L60: The Carolinas | M60: Chapel Hill, NC | N60: Durham and Chapel Hill | O60: shouted; anthemic; rowdy; jangle; short songs (under 2 minutes) | P60: On the Mouth keeps the tempo high but starts letting real hooks and cleaner production through, with 'Precision Auto' and 'For Tension' showing a band tightening its craft without losing its punk urgency. It was Superchunk's last album for Matador before the band committed fully to their own label. The record sits right at the hinge between the group's hardcore-pop origins and the more melodic indie rock of Foolish. | Q60: The final Matador-era Superchunk album before the band moved entirely to their own Merge Records, bridging their raw early sound and the more melodic songwriting of the mid-1990s run. | R60: Documented | S60: Precision Auto; For Tension | T60: Recommended | W60: Y | X60: https://en.wikipedia.org/wiki/Superchunk | Y60: Medium
A61: A0060 | B61: Superchunk | C61: Foolish | D61: 1994 | E61: LP | F61: Merge Records | G61: =IF(LEFT(I61,3)="R1 ","L6",IF(D61>=2014,"L1",IF(D61>=1998,"L2",IF(D61>=1987,"L3",IF(D61>=1978,"L4",IF(D61>=1965,"L5","L6")))))) -> L3 | H61: =IFERROR(INDEX(Lanes!$C$2:$C$60,MATCH(LEFT(I61,FIND(" ",I61)-1),Lanes!$A$2:$A$60,0)),"?") -> V | I61: V10 Slacker and '90s indie rock | K61: Slacker | L61: The Carolinas | M61: Chapel Hill, NC | N61: Durham and Chapel Hill | O61: heartbreak; jangle; deadpan; funny-sad; breezy | P61: Written largely about Mac McCaughan and Laura Ballance's breakup while they continued running Merge Records together, Foolish slows the tempos down and lets real vulnerability into songs like 'Like a Fool' and 'The First Part.' It is the record where Superchunk stopped being just a fast hardcore-pop band and became genuine songwriters, without losing the tension and drive underneath. The unusual real-life backstory gives the whole album an unresolved, quietly aching quality. | Q61: Superchunk's first album fully self-released on their own Merge Records, marking a deliberate slowdown from the hardcore-pop of On the Mouth toward the more emotionally direct songwriting that defined their mid-1990s work. | R61: Documented | S61: Like a Fool; The First Part | T61: Essential | W61: Y | X61: https://en.wikipedia.org/wiki/Superchunk | Y61: Medium
A62: A0061 | B62: Superchunk | C62: Here's Where the Strings Come In | D62: 1995 | E62: LP | F62: Merge Records | G62: =IF(LEFT(I62,3)="R1 ","L6",IF(D62>=2014,"L1",IF(D62>=1998,"L2",IF(D62>=1987,"L3",IF(D62>=1978,"L4",IF(D62>=1965,"L5","L6")))))) -> L3 | H62: =IFERROR(INDEX(Lanes!$C$2:$C$60,MATCH(LEFT(I62,FIND(" ",I62)-1),Lanes!$A$2:$A$60,0)),"?") -> V | I62: V10 Slacker and '90s indie rock | K62: Jangle | L62: The Carolinas | M62: Chapel Hill, NC | N62: Durham and Chapel Hill | O62: jangle; anthemic; breezy; deadpan; short songs (under 2 minutes) | P62: Here's Where the Strings Come In balances Foolish's melodic turn with a return to punchier tempos, producing some of the band's most enduring singalongs in 'Hyper Enough' and 'Detroit Has a Skyline.' Jim Wilbur's guitar interplay with McCaughan gets more melodic without sacrificing the band's momentum, and the record is often cited as the clearest distillation of the 1990s Superchunk sound. It remains a fan-favorite entry point to the band's catalog. | Q62: Consolidates the melodic songwriting Foolish introduced into Superchunk's fastest, most durable album, cementing Merge Records' identity alongside labelmates like Polvo and the Magnetic Fields. | R62: Documented | S62: Hyper Enough; Detroit Has a Skyline | T62: Essential | W62: Y | X62: https://en.wikipedia.org/wiki/Superchunk | Y62: Medium
A63: A0062 | B63: Superchunk | C63: Indoor Living | D63: 1997 | E63: LP | F63: Merge Records | G63: =IF(LEFT(I63,3)="R1 ","L6",IF(D63>=2014,"L1",IF(D63>=1998,"L2",IF(D63>=1987,"L3",IF(D63>=1978,"L4",IF(D63>=1965,"L5","L6")))))) -> L3 | H63: =IFERROR(INDEX(Lanes!$C$2:$C$60,MATCH(LEFT(I63,FIND(" ",I63)-1),Lanes!$A$2:$A$60,0)),"?") -> V | I63: V10 Slacker and '90s indie rock | K63: Jangle | L63: The Carolinas | M63: Chapel Hill, NC | N63: Durham and Chapel Hill | O63: breezy; jangle; hushed; funny-sad; polished | P63: Indoor Living is Superchunk's most deliberately restrained record to date, adding keyboards and slower tempos and letting McCaughan's voice sit further forward in a calmer mix on songs like 'Watery Hands.' It reflects a band settling into its thirties without losing its melodic instincts, trading raw velocity for warmth and space. Longtime fans were split on the shift, but it opened the door to the even more textured Come Pick Me Up. | Q63: A deliberate slowdown and studio expansion from the punchy mid-1990s run, setting up the more orchestrated, Jim O'Rourke-produced sound of Come Pick Me Up two years later. | R63: Documented | S63: Watery Hands; Song for Marion Brown | T63: Recommended | W63: Y | X63: https://en.wikipedia.org/wiki/Superchunk | Y63: Medium
A64: A0063 | B64: Superchunk | C64: Come Pick Me Up | D64: 1999 | E64: LP | F64: Merge Records | G64: =IF(LEFT(I64,3)="R1 ","L6",IF(D64>=2014,"L1",IF(D64>=1998,"L2",IF(D64>=1987,"L3",IF(D64>=1978,"L4",IF(D64>=1965,"L5","L6")))))) -> L2 | H64: =IFERROR(INDEX(Lanes!$C$2:$C$60,MATCH(LEFT(I64,FIND(" ",I64)-1),Lanes!$A$2:$A$60,0)),"?") -> V | I64: V10 Slacker and '90s indie rock | K64: Indie folk | L64: The Carolinas | M64: Chapel Hill, NC | N64: Durham and Chapel Hill | O64: horns; strings; hushed; breezy; funny-sad | P64: Produced by Jim O'Rourke, Come Pick Me Up dresses Superchunk's songs in horns and strings for the first time, pulling the band furthest from its hardcore-pop roots toward orchestrated indie pop on tracks like 'Hello Hawk.' It is a warmer, more patient record than anything the band had made before, trading urgency for arrangement. The album closed out the band's most productive decade on an unexpectedly lush note. | Q64: The most orchestrated Superchunk record of the 1990s, produced by Jim O'Rourke fresh from his Chicago post-rock and Wilco work, pointing the band toward the long hiatus that preceded their 2010 return. | R64: Documented | S64: Hello Hawk; So Convinced | T64: Recommended | W64: Y | X64: https://en.wikipedia.org/wiki/Superchunk | Y64: Medium
A65: A0064 | B65: Superchunk | C65: Majesty Shredding | D65: 2010 | E65: LP | F65: Merge Records | G65: =IF(LEFT(I65,3)="R1 ","L6",IF(D65>=2014,"L1",IF(D65>=1998,"L2",IF(D65>=1987,"L3",IF(D65>=1978,"L4",IF(D65>=1965,"L5","L6")))))) -> L2 | H65: =IFERROR(INDEX(Lanes!$C$2:$C$60,MATCH(LEFT(I65,FIND(" ",I65)-1),Lanes!$A$2:$A$60,0)),"?") -> V | I65: V10 Slacker and '90s indie rock | K65: Punk | L65: The Carolinas | M65: Chapel Hill, NC | N65: Durham and Chapel Hill | O65: anthemic; rowdy; jangle; breezy; short songs (under 2 minutes) | P65: After a nine-year album hiatus, Superchunk returned with Majesty Shredding, reconnecting with the speed and hooks of their mid-1990s peak on songs like 'Digging for Something' and 'Crossed Wires.' It sounds like a band picking up exactly where its best records left off rather than chasing a new sound, proof the original chemistry of McCaughan, Ballance, Wilbur, and Wurster had barely aged. The record was widely received as a genuine comeback rather than a nostalgia exercise. | Q65: Superchunk's 2000s-into-2010s return to the fast, hook-driven sound of their Merge Records prime, carrying the Chapel Hill scene they helped build into a new decade. | R65: Documented | S65: Digging for Something; Crossed Wires | T65: Recommended | W65: Y | X65: https://en.wikipedia.org/wiki/Superchunk | Y65: Medium
A66: A0065 | B66: Built to Spill | C66: Ultimate Alternative Wavers | D66: 1993 | E66: LP | F66: C/Z Records | G66: =IF(LEFT(I66,3)="R1 ","L6",IF(D66>=2014,"L1",IF(D66>=1998,"L2",IF(D66>=1987,"L3",IF(D66>=1978,"L4",IF(D66>=1965,"L5","L6")))))) -> L3 | H66: =IFERROR(INDEX(Lanes!$C$2:$C$60,MATCH(LEFT(I66,FIND(" ",I66)-1),Lanes!$A$2:$A$60,0)),"?") -> V | I66: V10 Slacker and '90s indie rock | K66: Slacker | L66: The West | M66: Boise, ID | N66: Boise | O66: lo-fi; long solos; deadpan; feedback; breezy | P66: Doug Martsch's first Built to Spill album, made with a rotating early lineup, is scrappier and more meandering than the band's later work, stretching songs out into loose, unhurried guitar jams over lo-fi production. It already carries the unhurried, Neil Young-indebted guitar tone that would define the band, just without the sharper songwriting of what followed. It stands as an early document of Boise's unlikely indie-rock scene. | Q66: Built to Spill's debut, recorded before Martsch settled the band into a more consistent lineup, drawing on Dinosaur Jr.'s guitar sprawl and setting the stage for the more focused songwriting of There's Nothing Wrong with Love. | R66: Documented | S66: Get a Life; Built Too Long | T66: Deep cut | W66: Y | X66: https://en.wikipedia.org/wiki/Ultimate_Alternative_Wavers https://en.wikipedia.org/wiki/Built_to_Spill | Y66: High
... A71: A0070 | B71: Built to Spill | C71: You in Reverse | D71: 2006 | E71: LP | F71: Warner Bros. Records | G71: =IF(LEFT(I71,3)="R1 ","L6",IF(D71>=2014,"L1",IF(D71>=1998,"L2",IF(D71>=1987,"L3",IF(D71>=1978,"L4",IF(D71>=1965,"L5","L6")))))) -> L2 | H71: =IFERROR(INDEX(Lanes!$C$2:$C$60,MATCH(LEFT(I71,FIND(" ",I71)-1),Lanes!$A$2:$A$60,0)),"?") -> V | I71: V10 Slacker and '90s indie rock | K71: Slacker | L71: The West | M71: Boise, ID | N71: Boise | O71: long solos; long songs (7+ minutes); cosmic; breezy; deadpan | P71: After a five-year gap, Built to Spill returned with a heavier emphasis on extended jamming, opening with the eight-minute 'Goin' Against Your Mind' and leaning further into the Crazy Horse-scale guitar interplay hinted at on Perfect from Now On. It is a looser, more improvisational record than its immediate predecessors, reflecting a band comfortable stretching out live. Doug Martsch's guitar tone remains the clear center of gravity throughout. | Q71: A return to the extended, jam-oriented structures of Perfect from Now On after two more concise records, continuing Built to Spill's 2000s life as Boise's most enduring indie-rock export. | R71: Documented | S71: Goin' Against Your Mind; Conventional Wisdom | T71: Recommended | W71: Y | X71: https://en.wikipedia.org/wiki/You_in_Reverse https://en.wikipedia.org/wiki/Built_to_Spill | Y71: High
A72: A0071 | B72: The Halo Benders | C72: God Don't Make No Junk | D72: 1994 | E72: LP | F72: K Records | G72: =IF(LEFT(I72,3)="R1 ","L6",IF(D72>=2014,"L1",IF(D72>=1998,"L2",IF(D72>=1987,"L3",IF(D72>=1978,"L4",IF(D72>=1965,"L5","L6")))))) -> L3 | H72: =IFERROR(INDEX(Lanes!$C$2:$C$60,MATCH(LEFT(I72,FIND(" ",I72)-1),Lanes!$A$2:$A$60,0)),"?") -> V | I72: V10 Slacker and '90s indie rock | K72: Lo-fi | L72: The West | M72: Boise, ID / Olympia, WA | N72: Olympia | O72: lo-fi; baritone; deadpan; funny-sad; small-town | P72: A side project pairing Built to Spill's Doug Martsch with K Records founder Calvin Johnson, the Halo Benders' debut sets Johnson's deep, deadpan baritone against Martsch's higher, more melodic voice, often within the same song. The arrangements are homemade and unpolished, closer to K Records' lo-fi pop tradition than to Built to Spill's guitar sprawl. It plays like two very different songwriters trading verses in the same room. | Q72: Connects Boise's Built to Spill directly to Olympia's K Records lo-fi scene through Doug Martsch and Calvin Johnson's shared project, linking two of the decade's key regional indie hubs. | R72: Documented | S72: Country Fair; Canned Oxygen | T72: Deep cut | X72: https://en.wikipedia.org/wiki/The_Halo_Benders | Y72: Medium
A73: A0072 | B73: The Halo Benders | C73: The Rebels Not In | D73: 1998 | E73: LP | F73: K Records | G73: =IF(LEFT(I73,3)="R1 ","L6",IF(D73>=2014,"L1",IF(D73>=1998,"L2",IF(D73>=1987,"L3",IF(D73>=1978,"L4",IF(D73>=1965,"L5","L6")))))) -> L2 | H73: =IFERROR(INDEX(Lanes!$C$2:$C$60,MATCH(LEFT(I73,FIND(" ",I73)-1),Lanes!$A$2:$A$60,0)),"?") -> V | I73: V10 Slacker and '90s indie rock | K73: Lo-fi | L73: The West | M73: Boise, ID / Olympia, WA | N73: Olympia | O73: lo-fi; baritone; deadpan; small-town; breezy | P73: The third and final Halo Benders record keeps the Martsch/Johnson vocal contrast intact while the songs lean slightly more toward pop structure than the murkier debut. It remains a minor, clearly side-project affair next to either songwriter's main band, but that low-stakes looseness is part of its appeal. Fans of both Built to Spill and K Records' Beat Happening lineage tend to find something to like here. | Q73: Closes out the Martsch/Johnson collaboration that had run alongside both Built to Spill's and Beat Happening's main careers through the 1990s. | R73: Documented | S73: Boy's Best Friend | T73: Deep cut | X73: https://en.wikipedia.org/wiki/The_Halo_Benders | Y73: Medium
A74: A0073 | B74: Silkworm | C74: Firewater | D74: 1996 | E74: LP | F74: Matador Records | G74: =IF(LEFT(I74,3)="R1 ","L6",IF(D74>=2014,"L1",IF(D74>=1998,"L2",IF(D74>=1987,"L3",IF(D74>=1978,"L4",IF(D74>=1965,"L5","L6")))))) -> L3 | H74: =IFERROR(INDEX(Lanes!$C$2:$C$60,MATCH(LEFT(I74,FIND(" ",I74)-1),Lanes!$A$2:$A$60,0)),"?") -> V | I74: V10 Slacker and '90s indie rock | K74: Post-punk | L74: The West | M74: Seattle, WA | O74: baritone; deadpan; drawl; storytelling; noise wall | P74: Silkworm's Matador debut pairs Tim Midyett and Andy Cohen's dual songwriting and dry, conversational baritones with lean, muscular guitar interplay, closer to a smarter, more literate Superchunk than to their noise-rock peers. The songs are direct and unshowy, built around riffs rather than hooks, with lyrics that read like short stories. It marked the band's arrival on the national indie stage after years as a Pacific Northwest cult act. | Q74: Formed from the band's Missoula-to-Seattle relocation, Firewater is Silkworm's step up to Matador Records alongside labelmates Pavement and Yo La Tengo, cementing their move from regional to national indie profile. | R74: Documented | S74: Insomnia; The Bones | T74: Recommended | X74: https://en.wikipedia.org/wiki/Silkworm_(band) | Y74: Medium
A75: A0074 | B75: Silkworm | C75: Developer | D75: 1997 | E75: LP | F75: Matador Records | G75: =IF(LEFT(I75,3)="R1 ","L6",IF(D75>=2014,"L1",IF(D75>=1998,"L2",IF(D75>=1987,"L3",IF(D75>=1978,"L4",IF(D75>=1965,"L5","L6")))))) -> L3 | H75: =IFERROR(INDEX(Lanes!$C$2:$C$60,MATCH(LEFT(I75,FIND(" ",I75)-1),Lanes!$A$2:$A$60,0)),"?") -> V | I75: V10 Slacker and '90s indie rock | K75: Post-punk | L75: The West | M75: Seattle, WA | O75: baritone; drawl; storytelling; deadpan; noise wall | P75: Developer keeps Silkworm's twin-vocalist, riff-driven approach intact while tightening the songwriting further, with Andy Cohen and Tim Midyett's contrasting voices trading off across terse, unsentimental rock songs. It is a transitional record between the band's Matador years and their subsequent move to Touch and Go, still carrying the dry Montana-bred wit that ran through all their work. Critics of the era praised its economy and lack of indulgence. | Q75: The last Silkworm album on Matador before the band's move to Touch and Go Records for Blueblood, continuing the lean, literate guitar-rock style the band built out of Missoula and Seattle's underground scenes. | R75: Documented | S75: Wet Firecracker | T75: Deep cut | X75: https://en.wikipedia.org/wiki/Developer_(album) https://en.wikipedia.org/wiki/Silkworm_(band) | Y75: High
A76: A0075 | B76: Silkworm | C76: Blueblood | D76: 1998 | E76: LP | F76: Touch and Go Records | G76: =IF(LEFT(I76,3)="R1 ","L6",IF(D76>=2014,"L1",IF(D76>=1998,"L2",IF(D76>=1987,"L3",IF(D76>=1978,"L4",IF(D76>=1965,"L5","L6")))))) -> L2 | H76: =IFERROR(INDEX(Lanes!$C$2:$C$60,MATCH(LEFT(I76,FIND(" ",I76)-1),Lanes!$A$2:$A$60,0)),"?") -> V | I76: V10 Slacker and '90s indie rock | K76: Post-punk | L76: The West | M76: Chicago, IL | O76: baritone; drawl; deadpan; storytelling; noise wall | P76: Silkworm's Touch and Go debut, made after the band relocated to Chicago, sharpens their riff-first approach with producer Steve Albini's characteristically dry, live-sounding engineering. Tim Midyett and Andy Cohen's songwriting stays plainspoken and unsentimental, closer to a bar-band version of Silver Jews than to anything flashy. It is often cited by fans as the point where the band's Chicago-era identity solidified. | Q76: Marks Silkworm's move from Matador to Touch and Go Records and from Seattle to Chicago, aligning the band with the Albini-adjacent Midwest noise-rock and indie-rock underground of the late 1990s. | R76: Documented | S76: Slave Wages | T76: Recommended | X76: https://en.wikipedia.org/wiki/Silkworm_(band) | Y76: Medium
A77: A0076 | B77: Silkworm | C77: Lifestyle | D77: 2000 | E77: LP | F77: Touch and Go Records | G77: =IF(LEFT(I77,3)="R1 ","L6",IF(D77>=2014,"L1",IF(D77>=1998,"L2",IF(D77>=1987,"L3",IF(D77>=1978,"L4",IF(D77>=1965,"L5","L6")))))) -> L2 | H77: =IFERROR(INDEX(Lanes!$C$2:$C$60,MATCH(LEFT(I77,FIND(" ",I77)-1),Lanes!$A$2:$A$60,0)),"?") -> V | I77: V10 Slacker and '90s indie rock | K77: Post-punk | L77: The West | M77: Chicago, IL | O77: baritone; drawl; storytelling; deadpan; bleak | P77: Lifestyle sharpens Silkworm's Chicago-era sound into some of the band's most direct and emotionally clear-eyed songwriting, with Midyett and Cohen's dry vocal delivery carrying lyrics about domestic disappointment and adult compromise. The guitar interplay stays lean and riff-driven, avoiding any of the era's more fashionable noise-rock excess. It is frequently cited by longtime fans as a high point of the band's Touch and Go run. | Q77: Continues Silkworm's Touch and Go, Albini-adjacent Chicago period, extending the band's 1990s Matador-era sound into the new decade without significant change in approach. | R77: Documented | S77: Not Tomorrow; Plan of the Man | T77: Recommended | X77: https://en.wikipedia.org/wiki/Silkworm_(band) | Y77: Medium
A78: A0077 | B78: Silkworm | C78: Italian Platinum | D78: 2002 | E78: LP | F78: Touch and Go Records | G78: =IF(LEFT(I78,3)="R1 ","L6",IF(D78>=2014,"L1",IF(D78>=1998,"L2",IF(D78>=1987,"L3",IF(D78>=1978,"L4",IF(D78>=1965,"L5","L6")))))) -> L2 | H78: =IFERROR(INDEX(Lanes!$C$2:$C$60,MATCH(LEFT(I78,FIND(" ",I78)-1),Lanes!$A$2:$A$60,0)),"?") -> V | I78: V10 Slacker and '90s indie rock | K78: Post-punk | L78: The West | M78: Chicago, IL | O78: baritone; drawl; storytelling; deadpan; anthemic | P78: Italian Platinum keeps Silkworm's dual-vocalist songwriting formula while opening up slightly more melodic space on tracks like 'Young Cannons.' It is a confident, road-tested record from a band deep into its second decade together, still built on riffs and plainspoken storytelling rather than studio polish. The album continued the critical respect the band had built without ever translating into wider commercial recognition. | Q78: A later, confident entry in Silkworm's Touch and Go catalog, carrying the Missoula-bred band's lean guitar-rock sound into the early 2000s alongside labelmates like Braid and the Jesus Lizard. | R78: Documented | S78: Young Cannons | T78: Deep cut | X78: https://en.wikipedia.org/wiki/Silkworm_(band) | Y78: Medium
A79: A0078 | B79: Polvo | C79: Cor-Crane Secret | D79: 1992 | E79: LP | F79: Merge Records | G79: =IF(LEFT(I79,3)="R1 ","L6",IF(D79>=2014,"L1",IF(D79>=1998,"L2",IF(D79>=1987,"L3",IF(D79>=1978,"L4",IF(D79>=1965,"L5","L6")))))) -> L3 | H79: =IFERROR(INDEX(Lanes!$C$2:$C$60,MATCH(LEFT(I79,FIND(" ",I79)-1),Lanes!$A$2:$A$60,0)),"?") -> V | I79: V10 Slacker and '90s indie rock | K79: Post-punk | L79: The Carolinas | M79: Chapel Hill, NC | N79: Durham and Chapel Hill | O79: feedback; noise wall; harmonized guitars; storytelling; shouted | P79: Polvo's debut tangles two guitars into dissonant, oddly-tuned patterns that would later get them lumped in with math rock, though the songs still carry the loose, off-kilter energy of the Chapel Hill scene around them. Ash Bowie and Dave Brylawski's interlocking riffs sound genuinely disorienting compared to the more straightforward noise-pop of labelmates like Superchunk. It is a strange, exploratory record that set the band apart even among an already adventurous local scene. | Q79: Emerged from the same Chapel Hill scene as Superchunk and Archers of Loaf but pushed further into dissonant, non-standard-tuning guitar interplay, prefiguring the American math-rock underground of the mid-1990s. | R79: Documented | S79: Vibracobra; Tilebreaker | T79: Recommended | X79: https://en.wikipedia.org/wiki/Polvo | Y79: Medium
A80: A0079 | B80: Polvo | C80: Today's Active Lifestyles | D80: 1993 | E80: LP | F80: Merge Records | G80: =IF(LEFT(I80,3)="R1 ","L6",IF(D80>=2014,"L1",IF(D80>=1998,"L2",IF(D80>=1987,"L3",IF(D80>=1978,"L4",IF(D80>=1965,"L5","L6")))))) -> L3 | H80: =IFERROR(INDEX(Lanes!$C$2:$C$60,MATCH(LEFT(I80,FIND(" ",I80)-1),Lanes!$A$2:$A$60,0)),"?") -> V | I80: V10 Slacker and '90s indie rock | K80: Post-punk | L80: The Carolinas | M80: Chapel Hill, NC | N80: Durham and Chapel Hill | O80: feedback; noise wall; harmonized guitars; storytelling; bleak | P80: Polvo's second album pushes their alternate-tuned, dissonant guitar interplay even further, with longer, more unresolved song structures than the debut. It is a denser, harder listen than Cor-Crane Secret, trading some of that record's immediacy for genuine strangeness. The band's Eastern-influenced drones and jagged riffs make it a key document of Chapel Hill's noisier, more experimental fringe. | Q80: A deeper dive into the dissonant, drone-influenced guitar language Polvo introduced on Cor-Crane Secret, part of Merge Records' broader 1990s roster alongside Superchunk and Butterglory. | R80: Documented | S80: Thermal Cradle; My Kimono | T80: Deep cut | X80: https://en.wikipedia.org/wiki/Polvo | Y80: Medium
A81: A0080 | B81: Polvo | C81: Exploded Drawing | D81: 1996 | E81: LP | F81: Touch and Go Records | G81: =IF(LEFT(I81,3)="R1 ","L6",IF(D81>=2014,"L1",IF(D81>=1998,"L2",IF(D81>=1987,"L3",IF(D81>=1978,"L4",IF(D81>=1965,"L5","L6")))))) -> L3 | H81: =IFERROR(INDEX(Lanes!$C$2:$C$60,MATCH(LEFT(I81,FIND(" ",I81)-1),Lanes!$A$2:$A$60,0)),"?") -> V | I81: V10 Slacker and '90s indie rock | K81: Post-punk | L81: The Carolinas | M81: Chapel Hill, NC | N81: Durham and Chapel Hill | O81: harmonized guitars; feedback; storytelling; cosmic; noise wall | P81: Moving to Touch and Go, Polvo pushed their sound toward more overtly psychedelic and Eastern-tinged textures on Exploded Drawing, incorporating sitar-like drones alongside their usual tangled guitar interplay. It is a more expansive, less purely aggressive record than the band's Merge-era work, reflecting a group actively broadening its palette. The record stands as a bridge between the band's noisier early records and their later, more progressive-leaning work. | Q81: Polvo's move from Merge to Touch and Go coincided with a more psychedelic, drone-influenced direction, aligning them with the label's other angular, adventurous 1990s bands like Silkworm and the Jesus Lizard. | R81: Documented | S81: Time Isn't on My Side; Everything Isn't Right | T81: Recommended | X81: https://en.wikipedia.org/wiki/Polvo | Y81: Medium
A82: A0081 | B82: Modest Mouse | C82: This Is a Long Drive for Someone with Nothing to Think About | D82: 1996 | E82: LP | F82: Up Records | G82: =IF(LEFT(I82,3)="R1 ","L6",IF(D82>=2014,"L1",IF(D82>=1998,"L2",IF(D82>=1987,"L3",IF(D82>=1978,"L4",IF(D82>=1965,"L5","L6")))))) -> L3 | H82: =IFERROR(INDEX(Lanes!$C$2:$C$60,MATCH(LEFT(I82,FIND(" ",I82)-1),Lanes!$A$2:$A$60,0)),"?") -> V | I82: V10 Slacker and '90s indie rock | K82: Slacker | L82: The West | M82: Issaquah, WA | O82: cracked or yelping; road songs; small-town; feedback; deadpan | P82: Modest Mouse's debut full-length pairs Isaac Brock's cracked, half-shouted vocals with jittery, start-stop guitar figures and long, meandering song structures built around road-trip imagery and small-town alienation. It is rawer and more overtly punk than the band's later work, closer to a nervous, rural cousin of Pavement's sprawl. The record established the trio's reputation as one of the odder, more promising bands to come out of Up Records' Pacific Northwest roster. | Q82: Modest Mouse's debut on Seattle's Up Records, drawing on the same Pacific Northwest indie underground as Built to Spill and Modest Mouse's own later major-label work. | R82: Documented | S82: Dramamine; Novocain Stain | T82: Recommended | X82: https://en.wikipedia.org/wiki/Modest_Mouse | Y82: Medium
A83: A0082 | B83: Modest Mouse | C83: The Lonesome Crowded West | D83: 1997 | E83: LP | F83: Up Records | G83: =IF(LEFT(I83,3)="R1 ","L6",IF(D83>=2014,"L1",IF(D83>=1998,"L2",IF(D83>=1987,"L3",IF(D83>=1978,"L4",IF(D83>=1965,"L5","L6")))))) -> L3 | H83: =IFERROR(INDEX(Lanes!$C$2:$C$60,MATCH(LEFT(I83,FIND(" ",I83)-1),Lanes!$A$2:$A$60,0)),"?") -> V | I83: V10 Slacker and '90s indie rock | K83: Slacker | L83: The West | M83: Issaquah, WA | O83: cracked or yelping; road songs; small-town; political; storytelling | P83: A sprawling double-length statement about suburban sprawl eating the rural West, The Lonesome Crowded West pairs Isaac Brock's yelped, half-sung vocals with dynamic shifts from quiet, twangy passages to full-throttle noise on songs like 'Trucker's Atlas' and 'Cowboy Dan.' It remains the definitive Modest Mouse album for many fans, capturing the band's regional preoccupations before they signed to a major label. Its loose, road-worn structure mirrors its subject matter directly. | Q83: The high point of Modest Mouse's Up Records period, widely regarded as the clearest statement of the Pacific Northwest strain of 1990s slacker rock before the band's jump to Epic for The Moon & Antarctica. | R83: Documented | S83: Trucker's Atlas; Cowboy Dan; Doin' the Cockroach | T83: Essential | X83: https://en.wikipedia.org/wiki/Modest_Mouse | Y83: Medium
A84: A0083 | B84: Modest Mouse | C84: The Moon & Antarctica | D84: 2000 | E84: LP | F84: Epic Records | G84: =IF(LEFT(I84,3)="R1 ","L6",IF(D84>=2014,"L1",IF(D84>=1998,"L2",IF(D84>=1987,"L3",IF(D84>=1978,"L4",IF(D84>=1965,"L5","L6")))))) -> L2 | H84: =IFERROR(INDEX(Lanes!$C$2:$C$60,MATCH(LEFT(I84,FIND(" ",I84)-1),Lanes!$A$2:$A$60,0)),"?") -> V | I84: V10 Slacker and '90s indie rock | K84: Slacker | L84: The West | M84: Issaquah, WA | O84: cosmic; cracked or yelping; storytelling; bleak; political | P84: Modest Mouse's major-label debut trades some of the earlier records' rawness for more spacious, atmospheric production, with Isaac Brock's lyrics turning toward existential and cosmic themes on '3rd Planet' and 'The Stars Are Projectors.' It is a more deliberately composed, less sprawling record than The Lonesome Crowded West, but keeps the same unsettled, cracked-voice intensity. The album is widely considered the band's artistic peak and the bridge into their 2000s mainstream breakthrough. | Q84: Modest Mouse's first album for Epic Records after building a following on Up Records, carrying the band's 1990s Pacific Northwest indie-rock sound into a more polished, widescreen 2000s register. | R84: Documented | S84: 3rd Planet; The Stars Are Projectors; Gravity Rides Everything | T84: Essential | X84: https://en.wikipedia.org/wiki/Modest_Mouse | Y84: Medium
A85: A0084 | B85: Liz Phair | C85: Exile in Guyville | D85: 1993 | E85: LP | F85: Matador Records | G85: =IF(LEFT(I85,3)="R1 ","L6",IF(D85>=2014,"L1",IF(D85>=1998,"L2",IF(D85>=1987,"L3",IF(D85>=1978,"L4",IF(D85>=1965,"L5","L6")))))) -> L3 | H85: =IFERROR(INDEX(Lanes!$C$2:$C$60,MATCH(LEFT(I85,FIND(" ",I85)-1),Lanes!$A$2:$A$60,0)),"?") -> V | I85: V10 Slacker and '90s indie rock | K85: Slacker | L85: Chicago and the Midwest | M85: Chicago, IL | O85: deadpan; heartbreak; lo-fi; funny-sad; storytelling | P85: Conceived as a song-by-song response to the Rolling Stones' Exile on Main St., Liz Phair's debut pairs blunt, sexually frank lyrics with a flat, deadpan vocal delivery and deliberately unpolished home-recorded guitar. It emerged from Chicago's Girly-Sound cassette scene into one of the most acclaimed indie records of the decade, direct in a way few of her peers matched. Songs like 'Fuck and Run' and 'Divorce Song' made bluntness itself the point. | Q85: Grew out of Phair's Girly-Sound home cassettes and the Chicago indie scene around Urge Overkill and Material Issue, becoming a Matador Records landmark that widened the lane for candid, unglamorous female singer-songwriters in indie rock. | R85: Documented | S85: Never Said; Fuck and Run; Divorce Song | T85: Essential | X85: https://en.wikipedia.org/wiki/Liz_Phair | Y85: Medium
A86: A0085 | B86: Liz Phair | C86: Whip-Smart | D86: 1994 | E86: LP | F86: Matador Records | G86: =IF(LEFT(I86,3)="R1 ","L6",IF(D86>=2014,"L1",IF(D86>=1998,"L2",IF(D86>=1987,"L3",IF(D86>=1978,"L4",IF(D86>=1965,"L5","L6")))))) -> L3 | H86: =IFERROR(INDEX(Lanes!$C$2:$C$60,MATCH(LEFT(I86,FIND(" ",I86)-1),Lanes!$A$2:$A$60,0)),"?") -> V | I86: V10 Slacker and '90s indie rock | K86: Slacker | L86: Chicago and the Midwest | M86: Chicago, IL | O86: deadpan; heartbreak; breezy; storytelling; pop-culture references | P86: Whip-Smart pulls Liz Phair's songwriting toward slightly more polished, radio-conscious arrangements without losing the blunt, deadpan candor of Exile in Guyville, most visibly on the single 'Supernova.' It sold well and drew inevitable comparisons to its predecessor, though it stands on its own as a more outward-facing, less confessional record. The contrast between the two albums traces the tension of an indie artist absorbing sudden mainstream attention. | Q86: Liz Phair's second album, following up the acclaimed Exile in Guyville with a more commercially aimed but still Matador-rooted record from the same Chicago indie scene. | R86: Documented | S86: Supernova; Whip-Smart | T86: Recommended | X86: https://en.wikipedia.org/wiki/Liz_Phair | Y86: Medium
A87: A0086 | B87: Helium | C87: The Dirt of Luck | D87: 1995 | E87: LP | F87: Matador Records | G87: =IF(LEFT(I87,3)="R1 ","L6",IF(D87>=2014,"L1",IF(D87>=1998,"L2",IF(D87>=1987,"L3",IF(D87>=1978,"L4",IF(D87>=1965,"L5","L6")))))) -> L3 | H87: =IFERROR(INDEX(Lanes!$C$2:$C$60,MATCH(LEFT(I87,FIND(" ",I87)-1),Lanes!$A$2:$A$60,0)),"?") -> V | I87: V10 Slacker and '90s indie rock | K87: Noise | L87: The Northeast | M87: Boston, MA | O87: deadpan; feedback; baritone; storytelling; noise wall | P87: Mary Timony's Helium debuts on Matador with fuzzed-out, noise-pop guitars under her husky, vibrato-less vocal delivery, sitting somewhere between Boston's noisier indie underground and the more melodic side of 1990s alt-rock. Songs like 'Superball' and 'Pat's Trick' balance genuine pop hooks against squalls of guitar noise. It established Timony as one of the era's more distinctive singer-guitarists. | Q87: Emerged from Boston's early-1990s indie underground (Timony had been in Autoclave), part of Matador's mid-decade wave of women-led noise-pop bands alongside Liz Phair and Versus. | R87: Documented | S87: Superball; Pat's Trick | T87: Recommended | X87: https://en.wikipedia.org/wiki/Helium_(band) | Y87: Medium
A88: A0087 | B88: Helium | C88: The Magic City | D88: 1997 | E88: LP | F88: Matador Records | G88: =IF(LEFT(I88,3)="R1 ","L6",IF(D88>=2014,"L1",IF(D88>=1998,"L2",IF(D88>=1987,"L3",IF(D88>=1978,"L4",IF(D88>=1965,"L5","L6")))))) -> L3 | H88: =IFERROR(INDEX(Lanes!$C$2:$C$60,MATCH(LEFT(I88,FIND(" ",I88)-1),Lanes!$A$2:$A$60,0)),"?") -> V | I88: V10 Slacker and '90s indie rock | K88: Noise | L88: The Northeast | M88: Boston, MA | O88: synths; drum machine; deadpan; cosmic; storytelling | P88: Helium's second album swaps out much of the guitar noise of the debut for analog synths and drum machines, building a stranger, more fantastical song-cycle around fairy-tale and science-fiction imagery. Mary Timony's songwriting grows more ambitious and less garage-rock in scope, closer to a lo-fi prog record than to the band's noisier early singles. It remains a cult favorite for listeners drawn to its unusual, hermetic atmosphere. | Q88: A deliberate stylistic swerve from The Dirt of Luck's noise-pop toward synth-driven art rock, prefiguring Mary Timony's later solo and Wild Flag work. | R88: Documented | S88: Medieval People; Leon's Space Song | T88: Deep cut | X88: https://en.wikipedia.org/wiki/Helium_(band) | Y88: Medium
A89: A0088 | B89: Versus | C89: The Stars Are Insane | D89: 1994 | E89: LP | F89: TeenBeat Records | G89: =IF(LEFT(I89,3)="R1 ","L6",IF(D89>=2014,"L1",IF(D89>=1998,"L2",IF(D89>=1987,"L3",IF(D89>=1978,"L4",IF(D89>=1965,"L5","L6")))))) -> L3 | H89: =IFERROR(INDEX(Lanes!$C$2:$C$60,MATCH(LEFT(I89,FIND(" ",I89)-1),Lanes!$A$2:$A$60,0)),"?") -> V | I89: V10 Slacker and '90s indie rock | K89: Jangle | L89: The Northeast | M89: New York, NY | O89: jangle; close harmonies; heartbreak; breezy; storytelling | P89: Versus's debut pairs Richard Baluyut and Fontaine Toups's dual vocals with loud-soft dynamics borrowed from grunge but filtered through a distinctly melodic, indie-pop sensibility. The songs are disciplined and tightly played compared to much of the era's shambling slacker rock, closer to a New York answer to Superchunk. It set the template for the band's decade-long run on the city's DIY indie scene. | Q89: Emerged from the same early-1990s New York indie-pop underground as Unrest's TeenBeat label roster, blending grunge dynamics with jangle-pop melody ahead of the band's later Caroline Records albums. | R89: Documented | S89: Wired; Let It Ride | T89: Recommended | X89: https://en.wikipedia.org/wiki/Versus_(band) | Y89: Medium
A90: A0089 | B90: Versus | C90: Secret Swingers | D90: 1996 | E90: LP | F90: Caroline Records | G90: =IF(LEFT(I90,3)="R1 ","L6",IF(D90>=2014,"L1",IF(D90>=1998,"L2",IF(D90>=1987,"L3",IF(D90>=1978,"L4",IF(D90>=1965,"L5","L6")))))) -> L3 | H90: =IFERROR(INDEX(Lanes!$C$2:$C$60,MATCH(LEFT(I90,FIND(" ",I90)-1),Lanes!$A$2:$A$60,0)),"?") -> V | I90: V10 Slacker and '90s indie rock | K90: Jangle | L90: The Northeast | M90: New York, NY | O90: jangle; close harmonies; breezy; storytelling; anthemic | P90: Versus's second full-length sharpens the loud-soft dynamics of the debut into tighter, more confident songwriting, with James Baluyut's addition on second guitar thickening the band's sound. It keeps the disciplined, almost muscular musicianship that set the band apart from looser slacker contemporaries. The record is often cited by fans as the strongest entry in the band's catalog. | Q90: Continues Versus's move from the DIY TeenBeat scene to the larger Caroline Records roster, part of New York's mid-1990s indie-rock underground alongside Chavez and Cell. | R90: Documented | S90: Miss Out; Air | T90: Recommended | X90: https://en.wikipedia.org/wiki/Versus_(band) | Y90: Medium
A91: A0090 | B91: Versus | C91: Two Cents Plus Tax | D91: 1998 | E91: LP | F91: Caroline Records | G91: =IF(LEFT(I91,3)="R1 ","L6",IF(D91>=2014,"L1",IF(D91>=1998,"L2",IF(D91>=1987,"L3",IF(D91>=1978,"L4",IF(D91>=1965,"L5","L6")))))) -> L2 | H91: =IFERROR(INDEX(Lanes!$C$2:$C$60,MATCH(LEFT(I91,FIND(" ",I91)-1),Lanes!$A$2:$A$60,0)),"?") -> V | I91: V10 Slacker and '90s indie rock | K91: Jangle | L91: The Northeast | M91: New York, NY | O91: jangle; close harmonies; storytelling; breezy; anthemic | P91: Two Cents Plus Tax closes out Versus's 1990s run with the band's most polished production to date, keeping the dual male-female vocal interplay while pushing the arrangements toward a slightly more expansive, mid-fi sound. It shows a band comfortable in its own established identity rather than chasing trends late in the decade. The record capped a run that made Versus one of New York's most consistent indie-rock bands of the era. | Q91: The last Versus album of the band's original 1990s run on Caroline Records, closing out a decade of steady New York indie-pop songwriting before the band's early-2000s hiatus. | R91: Documented | S91: Sunday Best; Crazy Eight | T91: Deep cut | X91: https://en.wikipedia.org/wiki/Versus_(band) | Y91: Medium
A92: A0091 | B92: Yo La Tengo | C92: Painful | D92: 1993 | E92: LP | F92: Matador Records | G92: =IF(LEFT(I92,3)="R1 ","L6",IF(D92>=2014,"L1",IF(D92>=1998,"L2",IF(D92>=1987,"L3",IF(D92>=1978,"L4",IF(D92>=1965,"L5","L6")))))) -> L3 | H92: =IFERROR(INDEX(Lanes!$C$2:$C$60,MATCH(LEFT(I92,FIND(" ",I92)-1),Lanes!$A$2:$A$60,0)),"?") -> V | I92: V10 Slacker and '90s indie rock | K92: Slacker | L92: The Northeast | M92: Hoboken, NJ | O92: feedback; hushed; drawl; glacial; cosmic | P92: With bassist James McNew now a full member, Yo La Tengo's Matador debut settles into the hushed-to-feedback dynamic that would define the band's mature sound, pairing Ira Kaplan and Georgia Hubley's quiet, conversational vocals with long stretches of guitar drone on 'I Heard You Looking.' It is a patient, unhurried record that trusts silence as much as noise. Kaplan himself has called it the point where Yo La Tengo really became a band rather than a project. | Q92: Yo La Tengo's first album for Matador Records and the first with James McNew on bass, marking the true beginning of the band's classic 1990s run into Electr-O-Pura and beyond. | R92: Documented | S92: I Heard You Looking; Big Day Coming | T92: Essential | X92: https://en.wikipedia.org/wiki/Yo_La_Tengo | Y92: Medium
A93: A0092 | B93: Yo La Tengo | C93: Electr-O-Pura | D93: 1995 | E93: LP | F93: Matador Records | G93: =IF(LEFT(I93,3)="R1 ","L6",IF(D93>=2014,"L1",IF(D93>=1998,"L2",IF(D93>=1987,"L3",IF(D93>=1978,"L4",IF(D93>=1965,"L5","L6")))))) -> L3 | H93: =IFERROR(INDEX(Lanes!$C$2:$C$60,MATCH(LEFT(I93,FIND(" ",I93)-1),Lanes!$A$2:$A$60,0)),"?") -> V | I93: V10 Slacker and '90s indie rock | K93: Slacker | L93: The Northeast | M93: Hoboken, NJ | O93: feedback; hushed; glacial; cosmic; drawl | P93: Electr-O-Pura pushes Painful's hushed-drone dynamic into longer, more exploratory song structures, with all three members now credited as co-writers rather than individual songwriters. Ira Kaplan's guitar noise gets more extended and abstract on tracks like 'Blue Line Swinger,' while quieter songs stay close and intimate. It is regarded by many longtime fans as the band's most purely rewarding mid-1990s record. | Q93: Continues the full-band songwriting approach Painful established, deepening Yo La Tengo's reputation as critics' favorites ahead of the even more eclectic I Can Hear the Heart Beating as One. | R93: Documented | S93: Blue Line Swinger; Decora | T93: Essential | X93: https://en.wikipedia.org/wiki/Yo_La_Tengo | Y93: Medium
... A97: A0096 | B97: The Grifters | C97: Ain't My Lookout | D97: 1996 | E97: LP | F97: Shangri-La Records / Sub Pop | G97: =IF(LEFT(I97,3)="R1 ","L6",IF(D97>=2014,"L1",IF(D97>=1998,"L2",IF(D97>=1987,"L3",IF(D97>=1978,"L4",IF(D97>=1965,"L5","L6")))))) -> L3 | H97: =IFERROR(INDEX(Lanes!$C$2:$C$60,MATCH(LEFT(I97,FIND(" ",I97)-1),Lanes!$A$2:$A$60,0)),"?") -> V | I97: V10 Slacker and '90s indie rock | K97: Lo-fi | L97: The South | M97: Memphis, TN | O97: drawl; storytelling; breezy; deadpan; polished | P97: Ain't My Lookout cleans up the Grifters' production considerably compared to their earlier, noisier records, letting the band's pop songwriting and Memphis blues-rock instincts come through more clearly. It marked the group's Sub Pop-distributed step toward a wider audience without abandoning the loose, unpretentious feel of their earlier work. It remains a favorite among fans who prefer the band's more song-focused mid-career run. | Q97: Follows Crappin' You Negative with a cleaner, more commercially aimed sound as the Grifters partnered with Sub Pop for wider distribution, part of the mid-1990s wave of lo-fi bands gaining major-indie backing. | R97: Documented | S97: Bronze Cast; Eureka Moment | T97: Recommended | X97: https://en.wikipedia.org/wiki/The_Grifters_(band) | Y97: Medium
A98: A0097 | B98: Seam | C98: Headsparks | D98: 1992 | E98: LP | F98: Homestead Records | G98: =IF(LEFT(I98,3)="R1 ","L6",IF(D98>=2014,"L1",IF(D98>=1998,"L2",IF(D98>=1987,"L3",IF(D98>=1978,"L4",IF(D98>=1965,"L5","L6")))))) -> L3 | H98: =IFERROR(INDEX(Lanes!$C$2:$C$60,MATCH(LEFT(I98,FIND(" ",I98)-1),Lanes!$A$2:$A$60,0)),"?") -> V | I98: V10 Slacker and '90s indie rock | J98: V12 | K98: Slowcore | L98: Chicago and the Midwest | M98: Chicago, IL | O98: hushed; glacial; deadpan; feedback; bleak | P98: Formed by former Bitch Magnet guitarist Sooyoung Park after relocating from Chapel Hill to Chicago, Seam's debut pairs slow, deliberate tempos with hushed vocals that occasionally give way to walls of guitar noise. It sits at the meeting point of slowcore and the era's noisier indie underground, patient where most of Seam's contemporaries were fast and loose. The record's restraint became the band's defining trait. | Q98: Sooyoung Park's post-Bitch Magnet project, moving from the Chapel Hill scene to Chicago and helping define the slowcore-adjacent, hushed-to-loud dynamic that ran alongside 1990s slacker rock. | R98: Documented | S98: Sussex; Rafael | T98: Recommended | X98: https://en.wikipedia.org/wiki/Seam_(band) | Y98: Medium
A99: A0098 | B99: Seam | C99: The Problem with Me | D99: 1993 | E99: LP | F99: Touch and Go Records | G99: =IF(LEFT(I99,3)="R1 ","L6",IF(D99>=2014,"L1",IF(D99>=1998,"L2",IF(D99>=1987,"L3",IF(D99>=1978,"L4",IF(D99>=1965,"L5","L6")))))) -> L3 | H99: =IFERROR(INDEX(Lanes!$C$2:$C$60,MATCH(LEFT(I99,FIND(" ",I99)-1),Lanes!$A$2:$A$60,0)),"?") -> V | I99: V10 Slacker and '90s indie rock | J99: V12 | K99: Slowcore | L99: Chicago and the Midwest | M99: Chicago, IL | O99: hushed; glacial; deadpan; bleak; feedback | P99: Seam's Touch and Go debut refines the hushed-to-loud dynamic of Headsparks into more fully developed songs, with Sooyoung Park's flat vocal delivery sitting over slow, spacious arrangements that occasionally erupt into distortion. It is a patient, melancholy record that never rushes to make its point. The band's understated approach influenced a wide swath of the emo and slowcore scenes that followed. | Q99: Seam's move to Touch and Go Records deepened their hushed, deliberate sound, an approach that would go on to directly influence Midwest emo and slowcore bands through the rest of the decade. | R99: Documented | S99: Shame; Little Chang | T99: Recommended | X99: https://en.wikipedia.org/wiki/Seam_(band) | Y99: Medium
A100: A0099 | B100: Seam | C100: Are You Driving Me Crazy? | D100: 1995 | E100: LP | F100: Touch and Go Records | G100: =IF(LEFT(I100,3)="R1 ","L6",IF(D100>=2014,"L1",IF(D100>=1998,"L2",IF(D100>=1987,"L3",IF(D100>=1978,"L4",IF(D100>=1965,"L5","L6")))))) -> L3 | H100: =IFERROR(INDEX(Lanes!$C$2:$C$60,MATCH(LEFT(I100,FIND(" ",I100)-1),Lanes!$A$2:$A$60,0)),"?") -> V | I100: V10 Slacker and '90s indie rock | J100: V12 | K100: Slowcore | L100: Chicago and the Midwest | M100: Chicago, IL | O100: hushed; glacial; bleak; deadpan; storytelling | P100: Seam's third album keeps the patient, hushed pace of its predecessors while adding new drummer Chris Manfrin's steadier rhythmic backbone, giving the songs a slightly more grounded feel than the band's earlier work. Sooyoung Park's lyrics stay understated and interior, matching the unhurried music. It continued the band's quiet influence on the era's slowcore and emo undergrounds without ever seeking a wider audience. | Q100: Continues Seam's Touch and Go run of hushed, deliberate indie rock, part of the same Chicago underground that included Tortoise and other members of the post-Bitch Magnet, post-hardcore diaspora. | R100: Documented | S100: Days of Thunder; Sky Blue Sky | T100: Deep cut | X100: https://en.wikipedia.org/wiki/Seam_(band) | Y100: Medium
A101: A0100 | B101: Chavez | C101: Gone Glimmering | D101: 1995 | E101: LP | F101: Matador Records | G101: =IF(LEFT(I101,3)="R1 ","L6",IF(D101>=2014,"L1",IF(D101>=1998,"L2",IF(D101>=1987,"L3",IF(D101>=1978,"L4",IF(D101>=1965,"L5","L6")))))) -> L3 | H101: =IFERROR(INDEX(Lanes!$C$2:$C$60,MATCH(LEFT(I101,FIND(" ",I101)-1),Lanes!$A$2:$A$60,0)),"?") -> V | I101: V10 Slacker and '90s indie rock | K101: Noise | L101: The Northeast | M101: New York, NY | O101: feedback; noise wall; harmonized guitars; shouted; anthemic | P101: Chavez's debut pairs Matt Sweeney and Clay Tarver's tightly harmonized twin-guitar riffs with an unusually muscular, almost classic-rock sense of scale for a Matador band, closer to a smarter, more disciplined take on noise rock than to shambling slacker pop. The songs are dense and riff-driven but never sloppy, a deliberate contrast to the looser bands around them on the label. It quickly became a touchstone for the era's more guitar-forward indie rock. | Q101: Part of Matador's mid-1990s New York roster alongside Pavement and Liz Phair, but pointed toward a tighter, more riff-driven post-hardcore sound that anticipated bands like Helmet and the Dismemberment Plan. | R101: Documented | S101: Break Up Your Band; Repeat the Ending | T101: Recommended | X101: https://en.wikipedia.org/wiki/Gone_Glimmering | Y101: Medium
A102: A0101 | B102: Chavez | C102: Ride the Fader | D102: 1996 | E102: LP | F102: Matador Records | G102: =IF(LEFT(I102,3)="R1 ","L6",IF(D102>=2014,"L1",IF(D102>=1998,"L2",IF(D102>=1987,"L3",IF(D102>=1978,"L4",IF(D102>=1965,"L5","L6")))))) -> L3 | H102: =IFERROR(INDEX(Lanes!$C$2:$C$60,MATCH(LEFT(I102,FIND(" ",I102)-1),Lanes!$A$2:$A$60,0)),"?") -> V | I102: V10 Slacker and '90s indie rock | K102: Noise | L102: The Northeast | M102: New York, NY | O102: feedback; noise wall; harmonized guitars; anthemic; shouted | P102: Chavez's second and final studio album sharpens the dense, harmonized-guitar attack of Gone Glimmering into something closer to arena-scale hard rock filtered through indie sensibilities, described by one reviewer as spare, brainy post-metal. It is a heavier, more confident record than the debut, built on riffs that stick without sacrificing the band's underground credibility. The band split not long after, leaving a small but influential two-album run. | Q102: The heavier, more muscular follow-up to Gone Glimmering, closing out Chavez's brief but influential run on Matador and leaving a clear mark on the following decade's post-hardcore and noise-rock revival. | R102: Documented | S102: Unreal Is Here; Nervous Breakthrough | T102: Recommended | X102: https://en.wikipedia.org/wiki/Ride_the_Fader | Y102: Medium
A103: A0102 | B103: Unrest | C103: Imperial f.f.r.r. | D103: 1992 | E103: LP | F103: TeenBeat Records | G103: =IF(LEFT(I103,3)="R1 ","L6",IF(D103>=2014,"L1",IF(D103>=1998,"L2",IF(D103>=1987,"L3",IF(D103>=1978,"L4",IF(D103>=1965,"L5","L6")))))) -> L3 | H103: =IFERROR(INDEX(Lanes!$C$2:$C$60,MATCH(LEFT(I103,FIND(" ",I103)-1),Lanes!$A$2:$A$60,0)),"?") -> V | I103: V10 Slacker and '90s indie rock | K103: Post-punk | L103: The Northeast | M103: Washington, D.C. | O103: jangle; deadpan; noise wall; feedback; short songs (under 2 minutes) | P103: With bassist Bridget Cross now in the lineup, Unrest's Imperial f.f.r.r. moves from the band's earlier noisier, more chaotic sound toward a leaner, more melodic minimalist pop, interspersing actual songs with avant-garde sound collages and stray noise. Mark Robinson's deadpan vocal delivery sits over jangly, economical guitar parts that feel closer to European post-punk than to American grunge. It was a turning point that pointed directly toward Perfect Teeth. | Q103: Built on Mark Robinson's own TeenBeat label and DC's DIY indie-pop underground, Imperial f.f.r.r. set up the more fully-realized pop songwriting of Perfect Teeth the following year. | R103: Documented | S103: Imperial | T103: Recommended | X103: https://en.wikipedia.org/wiki/Unrest_(band) | Y103: Medium
A104: A0103 | B104: Unrest | C104: Perfect Teeth | D104: 1993 | E104: LP | F104: 4AD Records | G104: =IF(LEFT(I104,3)="R1 ","L6",IF(D104>=2014,"L1",IF(D104>=1998,"L2",IF(D104>=1987,"L3",IF(D104>=1978,"L4",IF(D104>=1965,"L5","L6")))))) -> L3 | H104: =IFERROR(INDEX(Lanes!$C$2:$C$60,MATCH(LEFT(I104,FIND(" ",I104)-1),Lanes!$A$2:$A$60,0)),"?") -> V | I104: V10 Slacker and '90s indie rock | K104: Jangle | L104: The Northeast | M104: Washington, D.C. | O104: jangle; deadpan; close harmonies; breezy; pop-culture references | P104: Unrest's final album is its most purely melodic, distilling the minimalist pop hinted at on Imperial f.f.r.r. into tight, hook-filled songs like 'Make Out Club' and 'Cath Carroll.' Mark Robinson and Bridget Cross's vocal interplay gives the record a warmth that belies the band's earlier avant-garde noise experiments. Released just before the band's breakup, it is widely regarded as Unrest's definitive statement and a key link between DC's punk scene and its indie-pop underground. | Q104: The culmination of Unrest's evolution from noisy DC post-punk toward clean, hook-driven indie pop, released on 4AD and directly influencing the twee and indie-pop scenes that followed through TeenBeat's later roster. | R104: Documented | S104: Make Out Club; Cath Carroll; Sugar Shack | T104: Essential | X104: https://en.wikipedia.org/wiki/Unrest_(band) | Y104: Medium
A105: A0104 | B105: Eric's Trip | C105: Love Tara | D105: 1993 | E105: LP | F105: Sub Pop | G105: =IF(LEFT(I105,3)="R1 ","L6",IF(D105>=2014,"L1",IF(D105>=1998,"L2",IF(D105>=1987,"L3",IF(D105>=1978,"L4",IF(D105>=1965,"L5","L6")))))) -> L3 | H105: =IFERROR(INDEX(Lanes!$C$2:$C$60,MATCH(LEFT(I105,FIND(" ",I105)-1),Lanes!$A$2:$A$60,0)),"?") -> V | I105: V10 Slacker and '90s indie rock | K105: Lo-fi | L105: The UK, Ireland and Canada | M105: Moncton, New Brunswick, Canada | O105: lo-fi; feedback; drawl; heartbreak; hushed | P105: The first Canadian band signed to Sub Pop, Eric's Trip built Love Tara out of home four-track recordings, layering thick, melodic distortion under Rick White and Julie Doiron's alternating, intimate vocal turns. It is simultaneously scrappy and tender, closer in feel to Sebadoh's lo-fi confessionalism than to grunge despite the Sub Pop connection. The record remains a touchstone of Canadian indie rock's early-1990s underground. | Q105: A key Sub Pop signing from outside the Pacific Northwest, connecting Moncton's DIY four-track scene to the American lo-fi underground of Sebadoh and Guided by Voices. | R105: Documented | S105: Stove; Sixteen Wishes | T105: Recommended | X105: https://en.wikipedia.org/wiki/Eric%27s_Trip | Y105: Medium
A106: A0105 | B106: Eric's Trip | C106: Forever Again | D106: 1994 | E106: LP | F106: Sub Pop | G106: =IF(LEFT(I106,3)="R1 ","L6",IF(D106>=2014,"L1",IF(D106>=1998,"L2",IF(D106>=1987,"L3",IF(D106>=1978,"L4",IF(D106>=1965,"L5","L6")))))) -> L3 | H106: =IFERROR(INDEX(Lanes!$C$2:$C$60,MATCH(LEFT(I106,FIND(" ",I106)-1),Lanes!$A$2:$A$60,0)),"?") -> V | I106: V10 Slacker and '90s indie rock | K106: Lo-fi | L106: The UK, Ireland and Canada | M106: Moncton, New Brunswick, Canada | O106: lo-fi; feedback; drawl; heartbreak; hushed | P106: Forever Again keeps Eric's Trip's thick, home-recorded distortion intact while sharpening the songwriting, producing the closest thing the band had to a radio hit in 'View Master.' Julie Doiron and Rick White's dual vocal presence continues to give the songs an unusually personal, diaristic quality for a Sub Pop band. It stands as the clearest snapshot of the band before their 1996 breakup. | Q106: Continues Eric's Trip's fusion of Maritime Canadian DIY recording culture with the American lo-fi movement, extending Love Tara's approach into the band's most commercially visible moment. | R106: Documented | S106: View Master; Behind the Line | T106: Recommended | X106: https://en.wikipedia.org/wiki/Eric%27s_Trip | Y106: Medium
A107: A0106 | B107: Spoon | C107: Telephono | D107: 1996 | E107: LP | F107: Matador Records | G107: =IF(LEFT(I107,3)="R1 ","L6",IF(D107>=2014,"L1",IF(D107>=1998,"L2",IF(D107>=1987,"L3",IF(D107>=1978,"L4",IF(D107>=1965,"L5","L6")))))) -> L3 | H107: =IFERROR(INDEX(Lanes!$C$2:$C$60,MATCH(LEFT(I107,FIND(" ",I107)-1),Lanes!$A$2:$A$60,0)),"?") -> V | I107: V10 Slacker and '90s indie rock | K107: Post-punk | L107: Texas and Oklahoma | M107: Austin, TX | O107: shouted; noise wall; deadpan; feedback; short songs (under 2 minutes) | P107: Spoon's debut wears its Pixies and Wire influences plainly, all clipped post-punk riffs and Britt Daniel's sneering, half-shouted vocals over deliberately abrasive production. It is far noisier and rawer than the band's later, more minimalist work, closer to the mid-1990s Matador noise-pop underground than to the tight funk-rock they'd develop. The record marked Austin's entry into the same national indie conversation as Pavement and Chavez. | Q107: Spoon's Matador debut, drawing on Pixies-style post-punk before the band moved through Elektra to Merge and refined their sound into the minimalist funk of Girls Can Tell. | R107: Documented | S107: Not Turning Off; Don't Buy the Realistic | T107: Recommended | X107: https://en.wikipedia.org/wiki/Spoon_(band) | Y107: Medium
...

Sheet Lanes
A1: ID | B1: Lane | C1: Zone | D1: Era span | E1: Definition | F1: Parent lanes | G1: Child lanes | H1: Key scenes | I1: Key labels | J1: Albums (primary) | K1: Essential | L1: Start here
A2: C1 | B2: Indie twang / yallternative | C2: Core | D2: 2014– | E2: Loud, loose guitar rock with pedal steel and country phrasing, made by punk- and indie-raised bands in the 2010s–2020s; Crazy Horse tone, small-town detail, deadpan or drawled vocals. | F2: V1, V3, V9, V20, V10, V2 | H2: Asheville; Burlington; Philadelphia DIY; Pittsburgh | I2: Dear Life Records; Topshelf Records; ANTI-; Fire Talk; Transgressive | J2: =COUNTIF(Albums!$I$2:$I$2811,A2&" *") -> 54 | K2: =COUNTIFS(Albums!$I$2:$I$2811,A2&" *",Albums!$T$2:$T$2811,"Essential") -> 15 | L2: =COUNTIFS(Albums!$I$2:$I$2811,A2&" *",Albums!$U$2:$U$2811,"Y") -> 5
A3: C2 | B3: Barroom storytellers and deadpan songwriters | C3: Core | D3: 2014– | E3: Wordy, funny-sad songwriting in the John Prine / David Berman line: half-spoken vocals, long verses, jokes that turn into grief, bar-band or home-studio backing. | F3: V2, V25, V13, V1 | H3: Louisville / Sophomore Lounge; Asheville; Haw Creek / Lenderman circle; Nashville / Sophomore Lounge | I3: Sophomore Lounge; Drag City; Wharf Cat Records; Memorials of Distinction / Dog Day Records; Orindal Records | J3: =COUNTIF(Albums!$I$2:$I$2811,A3&" *") -> 41 | K3: =COUNTIFS(Albums!$I$2:$I$2811,A3&" *",Albums!$T$2:$T$2811,"Essential") -> 4 | L3: =COUNTIFS(Albums!$I$2:$I$2811,A3&" *",Albums!$U$2:$U$2811,"Y") -> 1
A4: C3 | B4: New alt-country and honky-tonk bands | C4: Core | D4: 2014– | E4: 2010s–2020s bands and songwriters playing recognizable country (honky-tonk, '90s country, bluegrass-inflected) with indie-scene provenance, labels, and audiences. | F4: V9, V6, V26, V19, V7 | I4: Anti-; New West Records; Keeled Scales; 4AD; Dear Life Records | J4: =COUNTIF(Albums!$I$2:$I$2811,A4&" *") -> 36 | K4: =COUNTIFS(Albums!$I$2:$I$2811,A4&" *",Albums!$T$2:$T$2811,"Essential") -> 7 | L4: =COUNTIFS(Albums!$I$2:$I$2811,A4&" *",Albums!$U$2:$U$2811,"Y") -> 1
A5: C4 | B5: Countrygaze and loud twang | C5: Core | D5: 2018– | E5: Shoegaze- and noise-rock-scale guitar walls under pedal steel, twang, and country-song structures; the Wednesday template. | F5: V12, V16, X9, V20, V3 | H5: Asheville; Inland Empire | I5: Orindal Records; Dead Oceans; Sub-Fi; Manic Static; Super Enema | J5: =COUNTIF(Albums!$I$2:$I$2811,A5&" *") -> 20 | K5: =COUNTIFS(Albums!$I$2:$I$2811,A5&" *",Albums!$T$2:$T$2811,"Essential") -> 5 | L5: =COUNTIFS(Albums!$I$2:$I$2811,A5&" *",Albums!$U$2:$U$2811,"Y") -> 2
A6: C5 | B6: Twangy indie folk | C6: Core | D6: 2014– | E6: Hushed or fervent acoustic-led songwriting with fiddle, pedal steel, and open tunings, from Big Thief's circle outward; folk lineage from Townes and Gillian Welch through the 2010s Bandcamp scene. | F6: V5, V8, V24, V25, V30, V11 | H6: Columbus; Chicago; Burlington; Philadelphia DIY | I6: Keeled Scales; 4AD; No Quarter; Saddle Creek; Ruination Record Co. | J6: =COUNTIF(Albums!$I$2:$I$2811,A6&" *") -> 178 | K6: =COUNTIFS(Albums!$I$2:$I$2811,A6&" *",Albums!$T$2:$T$2811,"Essential") -> 32 | L6: =COUNTIFS(Albums!$I$2:$I$2811,A6&" *",Albums!$U$2:$U$2811,"Y") -> 4
A7: C6 | B7: Cosmic country and the '70s revival | C7: Core | D7: 2005– | E7: Grateful Dead-, Gram Parsons- and Laurel Canyon-indebted guitar bands and songwriters: buttery lead guitar, harmonies, breezy tempos, long instrumental passages. | F7: V21, V27, V20, V28, V8, V4 | H7: Woodsist; Durham; Nashville DIY; Laurel Canyon | I7: Woodsist; Dead Oceans; Merge; Secretly Canadian; Thrill Jockey | J7: =COUNTIF(Albums!$I$2:$I$2811,A7&" *") -> 165 | K7: =COUNTIFS(Albums!$I$2:$I$2811,A7&" *",Albums!$T$2:$T$2811,"Essential") -> 19 | L7: =COUNTIFS(Albums!$I$2:$I$2811,A7&" *",Albums!$U$2:$U$2811,"Y") -> 7
A8: C7 | B8: Slacker, jangle, and power-pop revival | C8: Core | D8: 2008– | E8: 2010s–2020s guitar pop descended from Pavement, GBV, Flying Nun and Big Star: jangle, fuzz, conversational lyrics, short songs, DIY release culture. | F8: V10, V11, V17, V18, V16 | H8: Philadelphia; Philadelphia DIY; Chicago DIY; Melbourne | I8: Matador Records; Lame-O Records; Sub Pop; Carpark Records; Chapter Music | J8: =COUNTIF(Albums!$I$2:$I$2811,A8&" *") -> 151 | K8: =COUNTIFS(Albums!$I$2:$I$2811,A8&" *",Albums!$T$2:$T$2811,"Essential") -> 28 | L8: =COUNTIFS(Albums!$I$2:$I$2811,A8&" *",Albums!$U$2:$U$2811,"Y") -> 7
A9: C8 | B9: Modern slowcore and hushed twang | C9: Core | D9: 2014– | E9: Slow tempos, quiet dynamics, sparse arrangements and country-tinged melodies; the 2010s–2020s descendants of Low, Red House Painters, Duster and Bedhead, often with pedal steel. | F9: V12, V5, V1, V2 | H9: Boston; Philadelphia DIY; Durham/Triangle; Chicago | I9: Run for Cover Records; Captured Tracks; Double Double Whammy; Orindal Records; Dear Life Records | J9: =COUNTIF(Albums!$I$2:$I$2811,A9&" *") -> 58 | K9: =COUNTIFS(Albums!$I$2:$I$2811,A9&" *",Albums!$T$2:$T$2811,"Essential") -> 5 | L9: =COUNTIFS(Albums!$I$2:$I$2811,A9&" *",Albums!$U$2:$U$2811,"Y") -> 3
A10: C9 | B10: Emo-twang crossovers | C10: Core | D10: 2012– | E10: Bands from the emo and DIY punk circuit who folded country guitar, twang and Americana structures into emotional, anthemic rock. | F10: X6, V10, V9, V3 | H10: Asheville | I10: Lame-O Records; Rough Trade; ATO Records; Saddle Creek; Run for Cover | J10: =COUNTIF(Albums!$I$2:$I$2811,A10&" *") -> 24 | K10: =COUNTIFS(Albums!$I$2:$I$2811,A10&" *",Albums!$T$2:$T$2811,"Essential") -> 7 | L10: =COUNTIFS(Albums!$I$2:$I$2811,A10&" *",Albums!$U$2:$U$2811,"Y") -> 2
A11: V1 | B11: Molina and the Magnolia circle | C11: V | D11: 1996–2013 | E11: Jason Molina's projects (Songs: Ohia, Magnolia Electric Co., solo) and the Secretly Canadian / Will Johnson orbit: haunted folk that grew into Crazy Horse-scale country rock. | F11: V20, V12, V2, V25 | G11: C1, C2, C8 | H11: Denton; Chicago | I11: Secretly Canadian; Thrill Jockey; Keeled Scales; Idol/Munich; Misra/Munich | J11: =COUNTIF(Albums!$I$2:$I$2811,A11&" *") -> 46 | K11: =COUNTIFS(Albums!$I$2:$I$2811,A11&" *",Albums!$T$2:$T$2811,"Essential") -> 11 | L11: =COUNTIFS(Albums!$I$2:$I$2811,A11&" *",Albums!$U$2:$U$2811,"Y") -> 2
A12: V2 | B12: Drag City deadpan school | C12: V | D12: 1990– | E12: Silver Jews, Smog/Bill Callahan, Palace/Bonnie 'Prince' Billy and their Drag City kin: flat, wry, literary vocals over sparse or shambling country-tinged rock. | F12: V25, V29, V11, V22 | G12: C1, C2, C8, V1 | H12: Chicago Drag City; Louisville and Sophomore Lounge | I12: Drag City; Thrill Jockey; Sing, Eunuchs!; Raccoon/Warner Bros.; Sub Pop | J12: =COUNTIF(Albums!$I$2:$I$2811,A12&" *") -> 81 | K12: =COUNTIFS(Albums!$I$2:$I$2811,A12&" *",Albums!$T$2:$T$2811,"Essential") -> 19 | L12: =COUNTIFS(Albums!$I$2:$I$2811,A12&" *",Albums!$U$2:$U$2811,"Y") -> 2
A13: V3 | B13: Southern storytelling rock | C13: V | D13: 1996– | E13: Drive-By Truckers and the bands around them: three-guitar Southern rock carrying novelistic, unglamorous songs about the modern South. | F13: V28, V13, V9, V25 | G13: C1, C4, C9 | H13: Athens, Georgia; Memphis; Denton; Birmingham | I13: New West Records; ATO Records; Last Chance Records; Liberty & Lament Records; Bloodshot Records | J13: =COUNTIF(Albums!$I$2:$I$2811,A13&" *") -> 84 | K13: =COUNTIFS(Albums!$I$2:$I$2811,A13&" *",Albums!$T$2:$T$2811,"Essential") -> 6 | L13: =COUNTIFS(Albums!$I$2:$I$2811,A13&" *",Albums!$U$2:$U$2811,"Y") -> 2
A14: V4 | B14: Roots-inflected 2000s indie | C14: V | D14: 1998–2013 | E14: 2000s indie rock that absorbed country, folk and Americana textures without becoming an alt-country band: Wilco after A.M., My Morning Jacket, Okkervil River, Calexico, Lambchop, Band of Horses. | F14: V9, V16, V20, V22, V27 | G14: C1, C5, C6 | H14: Saddle Creek; Durham | I14: dBpm Records; Sub Pop; Merge Records; Dead Oceans; Jagjaguwar | J14: =COUNTIF(Albums!$I$2:$I$2811,A14&" *") -> 107 | K14: =COUNTIFS(Albums!$I$2:$I$2811,A14&" *",Albums!$T$2:$T$2811,"Essential") -> 25 | L14: =COUNTIFS(Albums!$I$2:$I$2811,A14&" *",Albums!$U$2:$U$2811,"Y") -> 2
A15: V5 | B15: Rootsy indie folk | C15: V | D15: 1996– | E15: Late-'90s to 2010s folk songwriters and duos with old-time, bluegrass and Appalachian roots rendered in indie terms: Gillian Welch, Iron & Wine, early Fleet Foxes, Bon Iver, Angel Olsen. | F15: V25, V24, R1, V30, V8 | G15: C5, C8, X3, X5 | H15: Philadelphia | I15: Acony; Sub Pop; Jagjaguwar; Nonesuch; Paradise of Bachelors | J15: =COUNTIF(Albums!$I$2:$I$2811,A15&" *") -> 70 | K15: =COUNTIFS(Albums!$I$2:$I$2811,A15&" *",Albums!$T$2:$T$2811,"Essential") -> 26 | L15: =COUNTIFS(Albums!$I$2:$I$2811,A15&" *",Albums!$U$2:$U$2811,"Y") -> 2
A16: V6 | B16: 2000s–2010s alt-country | C16: V | D16: 1998– | E16: Alt-country after the No Depression boom: Bloodshot and Lost Highway-era songwriters and bands (Neko Case, Ryan Adams, Richmond Fontaine, Lydia Loveless, Hurray for the Riff Raff). | F16: V9, V13, V26, V6 | G16: C2, C3, V6, V7 | H16: New Orleans; Portland alt-country; Columbus, Ohio; Chapel Hill | I16: Bloodshot Records; New West Records; Lost Highway Records; Decor Records; Yep Roc Records | J16: =COUNTIF(Albums!$I$2:$I$2811,A16&" *") -> 143 | K16: =COUNTIFS(Albums!$I$2:$I$2811,A16&" *",Albums!$T$2:$T$2811,"Essential") -> 32 | L16: =COUNTIFS(Albums!$I$2:$I$2811,A16&" *",Albums!$U$2:$U$2811,"Y") -> 10
A17: V7 | B17: Neo-traditional and 'new outlaw' country | C17: V | D17: 2012– | E17: Independent country of the 2010s–2020s that reached back to outlaw, Bakersfield and honky-tonk styles: Sturgill Simpson, Tyler Childers, Margo Price, Colter Wall, Charley Crockett. | F17: V23, V26, V24, V6 | G17: C3, X2 | I17: Son of Davy; New West Records; Hickman Holler Records / RCA; High Top Mountain Records; High Top Mountain Records / Thirty Tigers | J17: =COUNTIF(Albums!$I$2:$I$2811,A17&" *") -> 87 | K17: =COUNTIFS(Albums!$I$2:$I$2811,A17&" *",Albums!$T$2:$T$2811,"Essential") -> 23 | L17: =COUNTIFS(Albums!$I$2:$I$2811,A17&" *",Albums!$U$2:$U$2811,"Y") -> 2
A18: V8 | B18: American Primitive and solo guitar | C18: V | D18: 1959– | E18: Fingerstyle steel-string guitar from John Fahey and Takoma through Jack Rose, William Tyler, Marisa Anderson and Hayden Pedigo; instrumental Americana with drone and raga. | F18: R1 | G18: C5, C6, V5 | H18: Takoma; Philly Free Folk | I18: Takoma; Thrill Jockey; Tompkins Square; Three Lobed Recordings; Vanguard | J18: =COUNTIF(Albums!$I$2:$I$2811,A18&" *") -> 52 | K18: =COUNTIFS(Albums!$I$2:$I$2811,A18&" *",Albums!$T$2:$T$2811,"Essential") -> 19 | L18: =COUNTIFS(Albums!$I$2:$I$2811,A18&" *",Albums!$U$2:$U$2811,"Y") -> 2
A19: V9 | B19: No Depression and insurgent country | C19: V | D19: 1987–1999 | E19: The 1987–1999 alt-country boom: Uncle Tupelo, the Jayhawks, Son Volt, early Wilco, Whiskeytown, Old 97's, Bloodshot's insurgent-country roster and the Gothic country wing. | F19: V14, V16, V21, V26, V23 | G19: C1, C3, C9, V3, V4, V6, X3 | H19: Chicago insurgent country; Belleville and St. Louis; Minneapolis; Chapel Hill | I19: Bloodshot Records; Carrot Top Records; American Recordings; Thrill Jockey; Rough Trade Records | J19: =COUNTIF(Albums!$I$2:$I$2811,A19&" *") -> 84 | K19: =COUNTIFS(Albums!$I$2:$I$2811,A19&" *",Albums!$T$2:$T$2811,"Essential") -> 24 | L19: =COUNTIFS(Albums!$I$2:$I$2811,A19&" *",Albums!$U$2:$U$2811,"Y") -> 6
A20: V10 | B20: Slacker and '90s indie rock | C20: V | D20: 1989–1999 | E20: Pavement, Archers of Loaf, Superchunk, Built to Spill, Silkworm, Polvo, early Modest Mouse: loose, off-kilter guitar rock with conversational vocals, Matador/Merge/Touch and Go culture. | F20: V16, V17, V18, V29 | G20: C1, C7, C9 | H20: Durham and Chapel Hill; Boise; Olympia; Elephant 6 | I20: Matador Records; Merge Records; Up Records; Touch and Go Records; Sub Pop | J20: =COUNTIF(Albums!$I$2:$I$2811,A20&" *") -> 101 | K20: =COUNTIFS(Albums!$I$2:$I$2811,A20&" *",Albums!$T$2:$T$2811,"Essential") -> 21 | L20: =COUNTIFS(Albums!$I$2:$I$2811,A20&" *",Albums!$U$2:$U$2811,"Y") -> 2
A21: V11 | B21: Lo-fi and home taping | C21: V | D21: 1985–2000 | E21: Four-track and cassette culture: Guided by Voices, Sebadoh, Daniel Johnston, Elephant 6, the Microphones, early Mountain Goats; home recording treated as an aesthetic. | F21: V16, V29, V17 | G21: C5, C7, V2, X5 | H21: Elephant 6 Collective; Dayton lo-fi scene; Boombox home-taping; Austin outsider-tape scene | I21: Matador Records; K Records; Homestead Records; Merge Records; spinART Records | J21: =COUNTIF(Albums!$I$2:$I$2811,A21&" *") -> 68 | K21: =COUNTIFS(Albums!$I$2:$I$2811,A21&" *",Albums!$T$2:$T$2811,"Essential") -> 24 | L21: =COUNTIFS(Albums!$I$2:$I$2811,A21&" *",Albums!$U$2:$U$2811,"Y") -> 2
A22: V12 | B22: Slowcore and sadcore | C22: V | D22: 1988–2000 | E22: Galaxie 500, Low, Red House Painters, Codeine, Bedhead, Duster, American Music Club, Mazzy Star: slow tempos, quiet dynamics, sadness as method. | F22: V29, V16, X9 | G22: C4, C8, V1 | H22: San Francisco; Duluth; Boston; Dallas | I22: 4AD; Sub Pop; Vernon Yard; Rough Trade; Trance Syndicate | J22: =COUNTIF(Albums!$I$2:$I$2811,A22&" *") -> 73 | K22: =COUNTIFS(Albums!$I$2:$I$2811,A22&" *",Albums!$T$2:$T$2811,"Essential") -> 21 | L22: =COUNTIFS(Albums!$I$2:$I$2811,A22&" *",Albums!$U$2:$U$2811,"Y") -> 2
A23: V13 | B23: Americana songwriters before the label | C23: V | D23: 1986–1999 | E23: Songwriters who bridged country, folk and rock before 'Americana' was a format: Lucinda Williams, Steve Earle's '90s, Vic Chesnutt, Victoria Williams, Dave Alvin, Joe Henry. | F23: V24, V25, V19, V14 | G23: C2, V3, V6 | H23: Athens; Austin; Joshua Tree desert-folk scene | I23: HighTone Records; E-Squared Records; Mammoth Records; Texas Hotel Records; Lost Highway Records | J23: =COUNTIF(Albums!$I$2:$I$2811,A23&" *") -> 73 | K23: =COUNTIFS(Albums!$I$2:$I$2811,A23&" *",Albums!$T$2:$T$2811,"Essential") -> 31 | L23: =COUNTIFS(Albums!$I$2:$I$2811,A23&" *",Albums!$U$2:$U$2811,"Y") -> 2
A24: V14 | B24: Cowpunk and LA roots punk | C24: V | D24: 1978–1990 | E24: Punk bands who turned to country and rockabilly: X, the Blasters, the Gun Club, Rank and File, Lone Justice, Jason & the Scorchers, the Mekons' country turn. | F24: X14, V26, V21 | G24: C3, V13, V15, V19, V9 | H24: Los Angeles punk; Nashville cowpunk; Leeds post-punk / country turn; Los Angeles punk / roots-rock | I24: Slash Records; Enigma Records; EMI America; Elektra Records; Slash/Warner Bros. Records | J24: =COUNTIF(Albums!$I$2:$I$2811,A24&" *") -> 49 | K24: =COUNTIFS(Albums!$I$2:$I$2811,A24&" *",Albums!$T$2:$T$2811,"Essential") -> 16 | L24: =COUNTIFS(Albums!$I$2:$I$2811,A24&" *",Albums!$U$2:$U$2811,"Y") -> 2
A25: V15 | B25: Paisley Underground | C25: V | D25: 1981–1989 | E25: Early-'80s LA neo-psychedelia and roots rock: the Dream Syndicate, Green on Red, the Long Ryders, Rain Parade, Opal; Velvets and Byrds revived with punk energy. | F25: V29, V21, V14 | G25: C6, V10, V9 | H25: Paisley Underground | I25: Frontier; Enigma; Island; A&M; Mercury | J25: =COUNTIF(Albums!$I$2:$I$2811,A25&" *") -> 34 | K25: =COUNTIFS(Albums!$I$2:$I$2811,A25&" *",Albums!$T$2:$T$2811,"Essential") -> 9 | L25: =COUNTIFS(Albums!$I$2:$I$2811,A25&" *",Albums!$U$2:$U$2811,"Y") -> 2
A26: V16 | B26: American underground and college rock | C26: V | D26: 1979–1991 | E26: SST, Twin/Tone, Homestead and IRS-era bands: R.E.M., the Replacements, Hüsker Dü, Minutemen, Meat Puppets, Dinosaur Jr., Sonic Youth, Camper Van Beethoven, the Feelies. | F26: X14, V29, V17, V20 | G26: C4, C7, V10, V11, V12, V4, V9, X6, X8 | H26: SST/San Pedro; Minneapolis; Boston; Athens, Georgia | I26: SST Records; Homestead Records; I.R.S. Records; Twin/Tone Records; Sire Records | J26: =COUNTIF(Albums!$I$2:$I$2811,A26&" *") -> 102 | K26: =COUNTIFS(Albums!$I$2:$I$2811,A26&" *",Albums!$T$2:$T$2811,"Essential") -> 30 | L26: =COUNTIFS(Albums!$I$2:$I$2811,A26&" *",Albums!$U$2:$U$2811,"Y") -> 2
A27: V17 | B27: Jangle and power pop, Big Star to GBV | C27: V | D27: 1972–1995 | E27: Big Star, the dB's, Let's Active, Game Theory, Guadalcanal Diary, Teenage Fanclub, Velvet Crush: ringing guitars, harmonies, hooks in the Byrds/Beatles line. | F27: V21, V29 | G27: C7, V10, V11, V16, V18 | H27: Memphis (Ardent); Winston-Salem / Chapel Hill (Drive-In Studio); Glasgow; Athens | I27: Enigma Records; Creation Records; I.R.S. Records; DB Records; Elektra Records | J27: =COUNTIF(Albums!$I$2:$I$2811,A27&" *") -> 60 | K27: =COUNTIFS(Albums!$I$2:$I$2811,A27&" *",Albums!$T$2:$T$2811,"Essential") -> 20 | L27: =COUNTIFS(Albums!$I$2:$I$2811,A27&" *",Albums!$U$2:$U$2811,"Y") -> 2
A28: V18 | B28: Flying Nun and Antipodean indie | C28: V | D28: 1980–1995 | E28: Dunedin and Australian indie: the Clean, the Chills, the Verlaines, Tall Dwarfs, the Bats, the Go-Betweens, the Triffids; homemade jangle and drone. | F28: V29, V17 | G28: C7, V10 | H28: Dunedin; Brisbane; Christchurch; Perth | I28: Flying Nun; Merge Records; Beggars Banquet; Hot Records; Flying Nun / Slash | J28: =COUNTIF(Albums!$I$2:$I$2811,A28&" *") -> 53 | K28: =COUNTIFS(Albums!$I$2:$I$2811,A28&" *",Albums!$T$2:$T$2811,"Essential") -> 16 | L28: =COUNTIFS(Albums!$I$2:$I$2811,A28&" *",Albums!$U$2:$U$2811,"Y") -> 3
A29: V19 | B29: 1980s country rebels | C29: V | D29: 1980–1990 | E29: Mainstream-adjacent country that fought Nashville's gloss: Steve Earle's Guitar Town era, Dwight Yoakam, Lyle Lovett, k.d. lang, the Desert Rose Band, Rosanne Cash. | F29: V26, V23, V24, V14 | G29: C3, V13, V7, V9 | H29: Lubbock scene; Flatlanders/Lubbock scene | I29: MCA; Warner Bros.; Columbia; Reprise; MCA/Curb | J29: =COUNTIF(Albums!$I$2:$I$2811,A29&" *") -> 40 | K29: =COUNTIFS(Albums!$I$2:$I$2811,A29&" *",Albums!$T$2:$T$2811,"Essential") -> 13 | L29: =COUNTIFS(Albums!$I$2:$I$2811,A29&" *",Albums!$U$2:$U$2811,"Y") -> 3
... A36: V26 | B36: Honky-tonk, Bakersfield, and hard country | C36: V | D36: 1960–1980 | E36: Merle Haggard, Buck Owens, George Jones, Loretta Lynn, Tammy Wynette, Dolly Parton, Johnny Cash, Gary Stewart, Wynn Stewart: the hard-country mainstream the V keeps returning to. | F36: R1 | G36: C3, V14, V19, V21, V23, V24, V28, V6, V7, V9, X1 | H36: Bakersfield Sound; Countrypolitan; Texas honky-tonk | I36: Capitol; RCA Victor; Epic; Columbia; Decca | J36: =COUNTIF(Albums!$I$2:$I$2811,A36&" *") -> 72 | K36: =COUNTIFS(Albums!$I$2:$I$2811,A36&" *",Albums!$T$2:$T$2811,"Essential") -> 30 | L36: =COUNTIFS(Albums!$I$2:$I$2811,A36&" *",Albums!$U$2:$U$2811,"Y") -> 2
A37: V27 | B37: The Grateful Dead and California country-psych | C37: V | D37: 1969–1975 | E37: Workingman's Dead, American Beauty, Jerry Garcia's solo and bluegrass sides, New Riders of the Purple Sage: the Dead's country-folk turn and its jam offshoots. | F37: V21, R1, V22 | G37: C6, V4 | I37: Warner Bros.; Grateful Dead Records; Round Records; Arista; Columbia | J37: =COUNTIF(Albums!$I$2:$I$2811,A37&" *") -> 23 | K37: =COUNTIFS(Albums!$I$2:$I$2811,A37&" *",Albums!$T$2:$T$2811,"Essential") -> 10 | L37: =COUNTIFS(Albums!$I$2:$I$2811,A37&" *",Albums!$U$2:$U$2811,"Y") -> 2
A38: V28 | B38: Southern rock and country soul | C38: V | D38: 1969–1980 | E38: The Allman Brothers, Lynyrd Skynyrd, the Marshall Tucker Band, Little Feat, Tony Joe White, Dan Penn, Muscle Shoals: Southern guitar rock and swamp soul. | F38: V26, V22 | G38: C1, C6, V3, X11, X7 | H38: Capricorn Records scene; Jacksonville Southern rock scene; Los Angeles roots-rock scene; Muscle Shoals Sound scene | I38: Capricorn Records; MCA Records; Warner Bros. Records; Atco Records; Monument Records | J38: =COUNTIF(Albums!$I$2:$I$2811,A38&" *") -> 40 | K38: =COUNTIFS(Albums!$I$2:$I$2811,A38&" *",Albums!$T$2:$T$2811,"Essential") -> 14 | L38: =COUNTIFS(Albums!$I$2:$I$2811,A38&" *",Albums!$U$2:$U$2811,"Y") -> 2
A39: V29 | B39: Velvet Underground and proto-indie | C39: V | D39: 1967–1976 | E39: The Velvet Underground, Lou Reed, Nico, the Modern Lovers/Jonathan Richman: drone, deadpan and amateurism as virtues. | G39: V10, V11, V12, V15, V16, V17, V18, V2, X10, X14, X9 | H39: Andy Warhol's Factory; Boston underground rock scene; Ann Arbor and Detroit proto-punk scene; CBGB scene | I39: RCA Records; Verve; Elektra Records; Beserkley Records; Reprise Records | J39: =COUNTIF(Albums!$I$2:$I$2811,A39&" *") -> 29 | K39: =COUNTIFS(Albums!$I$2:$I$2811,A39&" *",Albums!$T$2:$T$2811,"Essential") -> 12 | L39: =COUNTIFS(Albums!$I$2:$I$2811,A39&" *",Albums!$U$2:$U$2811,"Y") -> 2
A40: V30 | B40: British folk rock (selective) | C40: V | D40: 1968–1975 | E40: Fairport Convention, Sandy Denny, Richard & Linda Thompson, Nick Drake, Bert Jansch: the UK strand of folk rock that indie folk keeps citing. | F40: R1 | G40: C5, V5, X5 | H40: Les Cousins folk club, Soho; Muswell Hill folk-rock scene; Witchseason Productions; Island Records folk-rock roster | I40: Island Records; Transatlantic Records; Hannibal Records; Charisma Records; CBS Records | J40: =COUNTIF(Albums!$I$2:$I$2811,A40&" *") -> 29 | K40: =COUNTIFS(Albums!$I$2:$I$2811,A40&" *",Albums!$T$2:$T$2811,"Essential") -> 15 | L40: =COUNTIFS(Albums!$I$2:$I$2811,A40&" *",Albums!$U$2:$U$2811,"Y") -> 3
A41: R1 | B41: Roots | C41: V | D41: before 1965 | E41: Pre-1965 country, folk and bluegrass foundations: Carter Family, Jimmie Rodgers, Hank Williams, Harry Smith's Anthology, Woody Guthrie, the Louvins, the Everlys, Lefty Frizzell, Bob Wills, Sun-era Cash, Patsy Cline, Stanley Brothers, Bill Monroe. | G41: V20, V21, V22, V23, V24, V25, V26, V27, V30, V5, V8, X1, X4 | H41: Memphis, Sun Records; Greenwich Village; Bakersfield sound | I41: Columbia; Capitol; Decca; Columbia/Legacy; Mercury | J41: =COUNTIF(Albums!$I$2:$I$2811,A41&" *") -> 33 | K41: =COUNTIFS(Albums!$I$2:$I$2811,A41&" *",Albums!$T$2:$T$2811,"Essential") -> 26 | L41: =COUNTIFS(Albums!$I$2:$I$2811,A41&" *",Albums!$U$2:$U$2811,"Y") -> 2
A42: X1 | B42: Mainstream Nashville, countrypolitan to bro-country | C42: Context | D42: 1960– | E42: The commercial country mainstream from the Nashville Sound to bro-country and Morgan Wallen. | F42: V26, R1 | G42: X12 | H42: Neotraditionalist country; Bro-country | I42: Capitol; MCA Records; Warner Bros. Nashville; Capitol Nashville; Arista Nashville | J42: =COUNTIF(Albums!$I$2:$I$2811,A42&" *") -> 12 | K42: =COUNTIFS(Albums!$I$2:$I$2811,A42&" *",Albums!$T$2:$T$2811,"Essential") -> 9 | L42: =COUNTIFS(Albums!$I$2:$I$2811,A42&" *",Albums!$U$2:$U$2811,"Y") -> 1
A43: X2 | B43: Red Dirt, Texas country, and arena Americana | C43: Context | D43: 1995– | E43: Oklahoma/Texas scene country and the arena-scale Americana of Chris Stapleton and Zach Bryan. | F43: V24, V23, V7 | H43: Red Dirt; Texas country | I43: Warner Records; Universal South; Smith Music Group; Universal/Republic; Bossier City Records | J43: =COUNTIF(Albums!$I$2:$I$2811,A43&" *") -> 10 | K43: =COUNTIFS(Albums!$I$2:$I$2811,A43&" *",Albums!$T$2:$T$2811,"Essential") -> 6 | L43: =COUNTIFS(Albums!$I$2:$I$2811,A43&" *",Albums!$U$2:$U$2811,"Y") -> 2
A44: X3 | B44: Big-tent Americana and stomp-clap folk | C44: Context | D44: 2000– | E44: Old Crow Medicine Show, the Avett Brothers, Mumford & Sons, the Lumineers, Brandi Carlile: the festival-scale Americana mainstream. | F44: V5, V9, X4 | I44: Nettwerk; American Recordings; Island Records/Glassnote Records; Dualtone; Sub Pop | J44: =COUNTIF(Albums!$I$2:$I$2811,A44&" *") -> 9 | K44: =COUNTIFS(Albums!$I$2:$I$2811,A44&" *",Albums!$T$2:$T$2811,"Essential") -> 5 | L44: =COUNTIFS(Albums!$I$2:$I$2811,A44&" *",Albums!$U$2:$U$2811,"Y") -> 1
A45: X4 | B45: Bluegrass, old-time, and newgrass | C45: Context | D45: 1965– | E45: Alison Krauss, Nickel Creek, Punch Brothers, Billy Strings, Molly Tuttle, Sierra Ferrell: the bluegrass line as its own tradition. | F45: R1 | G45: X3 | I45: Rounder; Nonesuch; Starday Records; Sugar Hill; ANTI- | J45: =COUNTIF(Albums!$I$2:$I$2811,A45&" *") -> 8 | K45: =COUNTIFS(Albums!$I$2:$I$2811,A45&" *",Albums!$T$2:$T$2811,"Essential") -> 6 | L45: =COUNTIFS(Albums!$I$2:$I$2811,A45&" *",Albums!$U$2:$U$2811,"Y") -> 1
A46: X5 | B46: Chamber, baroque, and freak folk | C46: Context | D46: 2000–2015 | E46: Sufjan Stevens, Joanna Newsom, Devendra Banhart, Beirut, the Decemberists: ornate indie folk that leads elsewhere. | F46: V5, V30, V11 | I46: Asthmatic Kitty; Drag City; Ba Da Bing; Young God; XL Recordings | J46: =COUNTIF(Albums!$I$2:$I$2811,A46&" *") -> 12 | K46: =COUNTIFS(Albums!$I$2:$I$2811,A46&" *",Albums!$T$2:$T$2811,"Essential") -> 7 | L46: =COUNTIFS(Albums!$I$2:$I$2811,A46&" *",Albums!$U$2:$U$2811,"Y") -> 1
A47: X6 | B47: Emo and Midwest emo | C47: Context | D47: 1994– | E47: Cap'n Jazz, American Football, Modern Baseball: the emo line from which C9 borrows. | F47: V16, X14 | G47: C9 | I47: Man With Gun; Polyvinyl; Crank!; Sub Pop; Jade Tree | J47: =COUNTIF(Albums!$I$2:$I$2811,A47&" *") -> 8 | K47: =COUNTIFS(Albums!$I$2:$I$2811,A47&" *",Albums!$T$2:$T$2811,"Essential") -> 4 | L47: =COUNTIFS(Albums!$I$2:$I$2811,A47&" *",Albums!$U$2:$U$2811,"Y") -> 1
A48: X7 | B48: Heartland rock | C48: Context | D48: 1975–1995 | E48: Springsteen, Petty, Mellencamp, Seger: arena-scale American rock that occasionally feeds the V (Nebraska). | F48: V22, V28 | I48: Columbia; Capitol; Backstreet/MCA; MCA; Riva | J48: =COUNTIF(Albums!$I$2:$I$2811,A48&" *") -> 9 | K48: =COUNTIFS(Albums!$I$2:$I$2811,A48&" *",Albums!$T$2:$T$2811,"Essential") -> 5 | L48: =COUNTIFS(Albums!$I$2:$I$2811,A48&" *",Albums!$U$2:$U$2811,"Y") -> 1
A49: X8 | B49: Grunge and '90s alt radio | C49: Context | D49: 1988–1998 | E49: Nirvana, Pearl Jam, Soundgarden, Mudhoney, Screaming Trees: the Seattle line and its radio aftermath. | F49: V16, V20 | H49: Seattle | I49: Epic; Sub Pop; DGC Records; A&M | J49: =COUNTIF(Albums!$I$2:$I$2811,A49&" *") -> 9 | K49: =COUNTIFS(Albums!$I$2:$I$2811,A49&" *",Albums!$T$2:$T$2811,"Essential") -> 4 | L49: =COUNTIFS(Albums!$I$2:$I$2811,A49&" *",Albums!$U$2:$U$2811,"Y") -> 1
A50: X9 | B50: Classic shoegaze and dream pop | C50: Context | D50: 1988–1996 | E50: My Bloody Valentine, Slowdive, Ride, Cocteau Twins, Swirlies: the guitar-wall vocabulary countrygaze borrows. | F50: V29 | G50: C4, V12 | I50: Creation Records; 4AD; Dedicated Records; Taang! Records | J50: =COUNTIF(Albums!$I$2:$I$2811,A50&" *") -> 14 | K50: =COUNTIFS(Albums!$I$2:$I$2811,A50&" *",Albums!$T$2:$T$2811,"Essential") -> 4 | L50: =COUNTIFS(Albums!$I$2:$I$2811,A50&" *",Albums!$U$2:$U$2811,"Y") -> 1
A51: X10 | B51: Post-punk and noise rock | C51: Context | D51: 1977– | E51: Wire, Mission of Burma, Big Black, Fugazi, and modern post-punk like Robber Robber: the rhythmic, angular line adjacent to the scene. | F51: X14, V29 | H51: Asheville; Burlington | I51: Harvest Records; Dischord Records; Ace of Hearts Records; Matador Records; Homestead Records | J51: =COUNTIF(Albums!$I$2:$I$2811,A51&" *") -> 14 | K51: =COUNTIFS(Albums!$I$2:$I$2811,A51&" *",Albums!$T$2:$T$2811,"Essential") -> 4 | L51: =COUNTIFS(Albums!$I$2:$I$2811,A51&" *",Albums!$U$2:$U$2811,"Y") -> 1
A52: X11 | B52: Modern Southern rock | C52: Context | D52: 2005– | E52: Blackberry Smoke, Whiskey Myers: Southern rock's mainstream continuation. | F52: V28 | I52: Wiggy Thump Records; BMG; Thirty Tigers; Tricki-Woo Records; Southern Ground | J52: =COUNTIF(Albums!$I$2:$I$2811,A52&" *") -> 13 | K52: =COUNTIFS(Albums!$I$2:$I$2811,A52&" *",Albums!$T$2:$T$2811,"Essential") -> 4 | L52: =COUNTIFS(Albums!$I$2:$I$2811,A52&" *",Albums!$U$2:$U$2811,"Y") -> 1
A53: X12 | B53: Pop and indie artists' country turns | C53: Context | D53: 2010– | E53: Kacey Musgraves, Orville Peck, CMAT, Beyoncé's Cowboy Carter: country as a mode for pop and indie artists. | F53: X1, V21 | I53: CMATBaby/AWAL; Mercury Nashville; MCA Nashville; Sub Pop; Columbia | J53: =COUNTIF(Albums!$I$2:$I$2811,A53&" *") -> 10 | K53: =COUNTIFS(Albums!$I$2:$I$2811,A53&" *",Albums!$T$2:$T$2811,"Essential") -> 4 | L53: =COUNTIFS(Albums!$I$2:$I$2811,A53&" *",Albums!$U$2:$U$2811,"Y") -> 2
A54: X13 | B54: Laurel Canyon and '70s soft rock | C54: Context | D54: 1968–1980 | E54: Joni Mitchell, CSN, Jackson Browne, the Eagles, Linda Ronstadt, Harry Nilsson: the LA singer-songwriter mainstream next door to country rock. | F54: V21, V22 | G54: C6 | H54: Laurel Canyon | I54: Asylum; Reprise; Atlantic Records; Capitol Records; Asylum Records | J54: =COUNTIF(Albums!$I$2:$I$2811,A54&" *") -> 12 | K54: =COUNTIFS(Albums!$I$2:$I$2811,A54&" *",Albums!$T$2:$T$2811,"Essential") -> 6 | L54: =COUNTIFS(Albums!$I$2:$I$2811,A54&" *",Albums!$U$2:$U$2811,"Y") -> 1
A55: X14 | B55: Punk and hardcore roots | C55: Context | D55: 1976–1985 | E55: Ramones, Black Flag, Minor Threat: the punk foundation under cowpunk, SST and the DIY network. | F55: V29 | G55: V14, V16, X10, X6 | H55: CBGB; SST; Dischord | I55: Sire; SST; Dischord Records; ROIR; CBS/Epic | J55: =COUNTIF(Albums!$I$2:$I$2811,A55&" *") -> 10 | K55: =COUNTIFS(Albums!$I$2:$I$2811,A55&" *",Albums!$T$2:$T$2811,"Essential") -> 4 | L55: =COUNTIFS(Albums!$I$2:$I$2811,A55&" *",Albums!$U$2:$U$2811,"Y") -> 1

Sheet Artists
A1: Artist | B1: Base | C1: Region | D1: Active years (in atlas) | E1: Primary lane | F1: Zone | G1: Key album IDs | H1: Albums in atlas | I1: Related artists | J1: Summary | K1: In field guide
A2: 16 Horsepower | B2: Denver, CO | C2: The West | D2: 1996–2000 | E2: V9 No Depression and insurgent country | F2: V | G2: A1489, A1490, A1491 | H2: =COUNTIF(Albums!$B$2:$B$2811,A2) -> 3
A3: 20/20 | B3: Los Angeles, CA | C3: The West | D3: 1979 | E3: V17 Jangle and power pop, Big Star to GBV | F3: V | G3: A0551 | H3: =COUNTIF(Albums!$B$2:$B$2811,A3) -> 1
A4: 22º Halo | B4: Philadelphia, PA | C4: Philadelphia | D4: 2024 | E4: C8 Modern slowcore and hushed twang | F4: Core | G4: A2621 | H4: =COUNTIF(Albums!$B$2:$B$2811,A4) -> 1
A5: 28th Day | B5: Chico, CA | C5: The West | D5: 1985 | E5: V15 Paisley Underground | F5: V | G5: A0416 | H5: =COUNTIF(Albums!$B$2:$B$2811,A5) -> 1
A6: 2nd Grade | B6: Philadelphia, PA | C6: Philadelphia | D6: 2026 | E6: C7 Slacker, jangle, and power-pop revival | F6: Core | G6: A2573 | H6: =COUNTIF(Albums!$B$2:$B$2811,A6) -> 1 | K6: Y
A7: The 3Ds | B7: Dunedin, New Zealand | C7: Australia and New Zealand | D7: 1992–1993 | E7: V18 Flying Nun and Antipodean indie | F7: V | G7: A0613, A0614 | H7: =COUNTIF(Albums!$B$2:$B$2811,A7) -> 2
A8: 49 Winchester | B8: Castlewood, VA | C8: The South | D8: 2024 | E8: X2 Red Dirt, Texas country, and arena Americana | F8: Context | G8: A2332 | H8: =COUNTIF(Albums!$B$2:$B$2811,A8) -> 1
A9: 764-HERO | B9: Seattle, WA | C9: The West | D9: 1998 | E9: V10 Slacker and '90s indie rock | F9: V | G9: A1859 | H9: =COUNTIF(Albums!$B$2:$B$2811,A9) -> 1
A10: Abbey Blackwell | B10: Seattle, WA | C10: The West | D10: 2023–2026 | E10: C5 Twangy indie folk | F10: Core | G10: A1690, A1688, A1689 | H10: =COUNTIF(Albums!$B$2:$B$2811,A10) -> 3 | K10: Y
A11: Abel | B11: Columbus, OH | C11: Chicago and the Midwest | D11: 2025 | E11: C1 Indie twang / yallternative | F11: Core | G11: A1585 | H11: =COUNTIF(Albums!$B$2:$B$2811,A11) -> 1
A12: The Able Tasmans | B12: Auckland, New Zealand | C12: Australia and New Zealand | D12: 1987–1990 | E12: V18 Flying Nun and Antipodean indie | F12: V | G12: A0608, A0609 | H12: =COUNTIF(Albums!$B$2:$B$2811,A12) -> 2
A13: Acetone | B13: Los Angeles, CA | C13: The West | D13: 1993–1996 | E13: V12 Slowcore and sadcore | F13: V | G13: A0240, A0241 | H13: =COUNTIF(Albums!$B$2:$B$2811,A13) -> 2
A14: Ada Lea | B14: Montreal, Quebec | C14: The UK, Ireland and Canada | D14: 2025 | E14: C6 Cosmic country and the '70s revival | F14: Core | G14: A2461 | H14: =COUNTIF(Albums!$B$2:$B$2811,A14) -> 1
A15: Adam Faucett | B15: Little Rock, AR | C15: The South | D15: 2007–2018 | E15: V3 Southern storytelling rock | F15: V | G15: A1889, A1890, A1891 | H15: =COUNTIF(Albums!$B$2:$B$2811,A15) -> 3
A16: Adeline Hotel | B16: Brooklyn, NY | C16: The Northeast | D16: 2021 | E16: C5 Twangy indie folk | F16: Core | G16: A2584 | H16: =COUNTIF(Albums!$B$2:$B$2811,A16) -> 1
A17: Adrianne Lenker | C17: The Northeast | D17: 2006–2024 | E17: C5 Twangy indie folk | F17: Core | G17: A1547, A1548, A1551, A1546 | H17: =COUNTIF(Albums!$B$2:$B$2811,A17) -> 7
A18: Adrianne Lenker & Buck Meek | C18: The Northeast | D18: 2014 | E18: C5 Twangy indie folk | F18: Core | G18: A1552, A1553 | H18: =COUNTIF(Albums!$B$2:$B$2811,A18) -> 2
A19: Advance Base | B19: Chicago, IL | C19: Chicago and the Midwest | D19: 2015 | E19: C2 Barroom storytellers and deadpan songwriters | F19: Core | G19: A2579 | H19: =COUNTIF(Albums!$B$2:$B$2811,A19) -> 1
A20: Age of Peace | B20: Los Angeles, CA | C20: The West | D20: 2026 | E20: C6 Cosmic country and the '70s revival | F20: Core | G20: A2224 | H20: =COUNTIF(Albums!$B$2:$B$2811,A20) -> 1
A21: Aïda Mekonnen Caby | B21: Brittany, France | C21: Elsewhere | D21: 2025 | E21: C5 Twangy indie folk | F21: Core | G21: A2645 | H21: =COUNTIF(Albums!$B$2:$B$2811,A21) -> 1
A22: Alan Jackson | B22: Newnan, GA | C22: The South | D22: 1991 | E22: X1 Mainstream Nashville, countrypolitan to bro-country | F22: Context | G22: A2316 | H22: =COUNTIF(Albums!$B$2:$B$2811,A22) -> 1
A23: Alasdair Roberts | B23: Glasgow, Scotland | C23: The UK, Ireland and Canada | D23: 2003 | E23: V2 Drag City deadpan school | F23: V | G23: A0716 | H23: =COUNTIF(Albums!$B$2:$B$2811,A23) -> 1
A24: Alejandro Escovedo | B24: Austin, TX | C24: Texas and Oklahoma | D24: 1992–2001 | E24: V13 Americana songwriters before the label | F24: V | G24: A0322, A0325, A0323, A0324 | H24: =COUNTIF(Albums!$B$2:$B$2811,A24) -> 4
A25: Alela Diane | B25: Nevada City, CA | C25: The West | D25: 2004–2018 | E25: V5 Rootsy indie folk | F25: V | G25: A1369, A1370, A1372, A1373 | H25: =COUNTIF(Albums!$B$2:$B$2811,A25) -> 4
A26: Alela Diane & Wild Divine | B26: Nevada City, CA | C26: The West | D26: 2011 | E26: V5 Rootsy indie folk | F26: V | G26: A1371 | H26: =COUNTIF(Albums!$B$2:$B$2811,A26) -> 1
A27: Alex Chilton | B27: Memphis, TN | C27: The South | D27: 1979–1985 | E27: V17 Jangle and power pop, Big Star to GBV | F27: V | G27: A0521, A0522 | H27: =COUNTIF(Albums!$B$2:$B$2811,A27) -> 2
A28: Alex G | B28: Philadelphia, PA | C28: Philadelphia | D28: 2011–2025 | E28: C7 Slacker, jangle, and power-pop revival | F28: Core | G28: A2730, A2732, A2733, A2278 | H28: =COUNTIF(Albums!$B$2:$B$2811,A28) -> 10 | K28: Y
A29: Alison Krauss & Union Station | B29: Nashville, TN | C29: The South | D29: 2001 | E29: X4 Bluegrass, old-time, and newgrass | F29: Context | G29: A2344 | H29: =COUNTIF(Albums!$B$2:$B$2811,A29) -> 1
A30: Allegra Krieger | B30: New York, NY | C30: The Northeast | D30: 2020–2023 | E30: C5 Twangy indie folk | F30: Core | G30: A1708, A1707 | H30: =COUNTIF(Albums!$B$2:$B$2811,A30) -> 2
A31: The Allman Betts Band | B31: Sarasota, FL | C31: The South | D31: 2019–2020 | E31: X11 Modern Southern rock | F31: Context | G31: A2517, A2518 | H31: =COUNTIF(Albums!$B$2:$B$2811,A31) -> 2
A32: The Allman Brothers Band | B32: Macon, GA | C32: The South | D32: 1969–1973 | E32: V28 Southern rock and country soul | F32: V | G32: A1127, A1129, A1130, A1131 | H32: =COUNTIF(Albums!$B$2:$B$2811,A32) -> 5
A33: Amalgamated Sons of Rest | B33: Chicago, IL | C33: Chicago and the Midwest | D33: 2002 | E33: V1 Molina and the Magnolia circle | F33: V | G33: A1821 | H33: =COUNTIF(Albums!$B$2:$B$2811,A33) -> 1
A34: Amanda Shires | B34: Nashville, TN | C34: The South | D34: 2011–2016 | E34: V6 2000s–2010s alt-country | F34: V | G34: A2035, A2036, A2037 | H34: =COUNTIF(Albums!$B$2:$B$2811,A34) -> 3
A35: Amen Dunes | B35: New York, NY | C35: The Northeast | D35: 2014–2018 | E35: C6 Cosmic country and the '70s revival | F35: Core | G35: A2201, A2202 | H35: =COUNTIF(Albums!$B$2:$B$2811,A35) -> 2
A36: American Aquarium | B36: Raleigh, NC | C36: The Carolinas | D36: 2009–2020 | E36: V3 Southern storytelling rock | F36: V | G36: A1237, A1238, A1888, A1239 | H36: =COUNTIF(Albums!$B$2:$B$2811,A36) -> 6
A37: American Football | B37: Urbana, IL | C37: Chicago and the Midwest | D37: 1999 | E37: X6 Emo and Midwest emo | F37: Context | G37: A2364 | H37: =COUNTIF(Albums!$B$2:$B$2811,A37) -> 1
A38: American Music Club | B38: San Francisco, CA | C38: The West | D38: 1988–1994 | E38: V12 Slowcore and sadcore | F38: V | G38: A0215, A0217, A0218, A0219 | H38: =COUNTIF(Albums!$B$2:$B$2811,A38) -> 5
A39: Andrew Combs | B39: Nashville, TN | C39: The South | D39: 2012–2017 | E39: V6 2000s–2010s alt-country | F39: V | G39: A2070, A2071, A2072 | H39: =COUNTIF(Albums!$B$2:$B$2811,A39) -> 3
A40: Angela Autumn | B40: Nashville, TN | C40: The South | D40: 2026 | E40: C6 Cosmic country and the '70s revival | F40: Core | G40: A2643 | H40: =COUNTIF(Albums!$B$2:$B$2811,A40) -> 1
... A48: The Apples in Stereo | B48: Denver, CO | C48: Chicago and the Midwest | D48: 1995–1997 | E48: V11 Lo-fi and home taping | F48: V | G48: A0144, A0145 | H48: =COUNTIF(Albums!$B$2:$B$2811,A48) -> 2
A49: Arbor Labor Union | B49: Athens, GA | C49: The South | D49: 2016–2025 | E49: C6 Cosmic country and the '70s revival | F49: Core | G49: A2685, A2686, A2687, A2688 | H49: =COUNTIF(Albums!$B$2:$B$2811,A49) -> 4 | K49: Y
A50: Arbouretum | B50: Baltimore, MD | C50: The Northeast | D50: 2007–2020 | E50: V1 Molina and the Magnolia circle | F50: V | G50: A1841, A1839, A1840, A1842 | H50: =COUNTIF(Albums!$B$2:$B$2811,A50) -> 5
A51: Archers of Loaf | B51: Chapel Hill, NC | C51: The Carolinas | D51: 1993–1998 | E51: V10 Slacker and '90s indie rock | F51: V | G51: A0053, A0054, A0055, A0056 | H51: =COUNTIF(Albums!$B$2:$B$2811,A51) -> 4 | K51: Y
A52: Arlo McKinley | B52: Cincinnati, OH | C52: Chicago and the Midwest | D52: 2020–2022 | E52: V7 Neo-traditional and 'new outlaw' country | F52: V | G52: A2157, A2158 | H52: =COUNTIF(Albums!$B$2:$B$2811,A52) -> 2
A53: Arthur Alexander | B53: Muscle Shoals, AL | C53: The South | D53: 1972 | E53: V28 Southern rock and country soul | F53: V | G53: A1157 | H53: =COUNTIF(Albums!$B$2:$B$2811,A53) -> 1
A54: Astrachan | B54: Chicago, IL | C54: Chicago and the Midwest | D54: 2025 | E54: C7 Slacker, jangle, and power-pop revival | F54: Core | G54: A2768 | H54: =COUNTIF(Albums!$B$2:$B$2811,A54) -> 1
A55: Austin Lucas | B55: Bloomington, IN | C55: Chicago and the Midwest | D55: 2009–2013 | E55: V3 Southern storytelling rock | F55: V | G55: A1883, A1884 | H55: =COUNTIF(Albums!$B$2:$B$2811,A55) -> 2
A56: Avett Brothers | B56: Concord, NC | C56: The Carolinas | D56: 2009 | E56: X3 Big-tent Americana and stomp-clap folk | F56: Context | G56: A2335 | H56: =COUNTIF(Albums!$B$2:$B$2811,A56) -> 1
A57: Babehoven | B57: Hudson Valley, NY | C57: The Northeast | D57: 2026 | E57: C8 Modern slowcore and hushed twang | F57: Core | G57: A2622 | H57: =COUNTIF(Albums!$B$2:$B$2811,A57) -> 1
A58: Bad Brains | B58: Washington, D.C. | C58: The Northeast | D58: 1982 | E58: X14 Punk and hardcore roots | F58: Context | G58: A2551 | H58: =COUNTIF(Albums!$B$2:$B$2811,A58) -> 1
A59: Badfinger | B59: Swansea, Wales | C59: The UK, Ireland and Canada | D59: 1971 | E59: V17 Jangle and power pop, Big Star to GBV | F59: V | G59: A0548 | H59: =COUNTIF(Albums!$B$2:$B$2811,A59) -> 1
A60: Bad Livers | B60: Austin, TX | C60: Texas and Oklahoma | D60: 1992–1997 | E60: V9 No Depression and insurgent country | F60: V | G60: A2797, A2798 | H60: =COUNTIF(Albums!$B$2:$B$2811,A60) -> 2
A61: Bailter Space | B61: Christchurch, New Zealand | C61: Australia and New Zealand | D61: 1988 | E61: V18 Flying Nun and Antipodean indie | F61: V | G61: A2609 | H61: =COUNTIF(Albums!$B$2:$B$2811,A61) -> 1
A62: The Band | B62: Toronto / Woodstock, NY | C62: The UK, Ireland and Canada | D62: 1968–1978 | E62: V22 Dylan and The Band | F62: V | G62: A0875, A0876, A0881, A0883 | H62: =COUNTIF(Albums!$B$2:$B$2811,A62) -> 9
A63: Band of Horses | B63: Charleston, SC | C63: The South | D63: 2006–2010 | E63: V4 Roots-inflected 2000s indie | F63: V | G63: A1324, A1325, A1326 | H63: =COUNTIF(Albums!$B$2:$B$2811,A63) -> 3
... A70: Beat Happening | B70: Olympia, WA | C70: The West | D70: 1985–1992 | E70: V16 American underground and college rock | F70: V | G70: A0502, A0503, A0188 | H70: =COUNTIF(Albums!$B$2:$B$2811,A70) -> 3
A71: Beck | B71: Los Angeles, CA | C71: The West | D71: 1994 | E71: V11 Lo-fi and home taping | F71: V | G71: A0189, A0190 | H71: =COUNTIF(Albums!$B$2:$B$2811,A71) -> 2 | K71: Y
A72: Bedhead | B72: Dallas, TX | C72: Texas and Oklahoma | D72: 1994–1998 | E72: V12 Slowcore and sadcore | F72: V | G72: A0224, A0226, A0225 | H72: =COUNTIF(Albums!$B$2:$B$2811,A72) -> 3
A73: Beirut | B73: Santa Fe, NM | C73: The West | D73: 2006–2007 | E73: X5 Chamber, baroque, and freak folk | F73: Context | G73: A2357, A2358 | H73: =COUNTIF(Albums!$B$2:$B$2811,A73) -> 2
A74: The Belair Lip Bombs | B74: Melbourne, Australia | C74: Australia and New Zealand | D74: 2025 | E74: C7 Slacker, jangle, and power-pop revival | F74: Core | G74: A2761 | H74: =COUNTIF(Albums!$B$2:$B$2811,A74) -> 1
A75: Bella White | B75: Calgary, Alberta | C75: The UK, Ireland and Canada | D75: 2023 | E75: C3 New alt-country and honky-tonk bands | F75: Core | G75: A1636 | H75: =COUNTIF(Albums!$B$2:$B$2811,A75) -> 1 | K75: Y
A76: Ben Seretan | B76: New York, NY | C76: The Northeast | D76: 2024 | E76: C5 Twangy indie folk | F76: Core | G76: A2646 | H76: =COUNTIF(Albums!$B$2:$B$2811,A76) -> 1
A77: Bert Jansch | B77: London, England | C77: The UK, Ireland and Canada | D77: 1965–1974 | E77: V30 British folk rock (selective) | F77: V | G77: A1275, A1276, A1277 | H77: =COUNTIF(Albums!$B$2:$B$2811,A77) -> 3
A78: The Beths | B78: Auckland, New Zealand | C78: Australia and New Zealand | D78: 2022 | E78: C7 Slacker, jangle, and power-pop revival | F78: Core | G78: A2303 | H78: =COUNTIF(Albums!$B$2:$B$2811,A78) -> 1
A79: Beulah | B79: San Francisco, CA | C79: The West | D79: 1997–1999 | E79: V10 Slacker and '90s indie rock | F79: V | G79: A2590, A1861 | H79: =COUNTIF(Albums!$B$2:$B$2811,A79) -> 2
A80: Beyoncé | B80: Houston, TX | C80: The South | D80: 2024 | E80: X12 Pop and indie artists' country turns | F80: Context | G80: A2530 | H80: =COUNTIF(Albums!$B$2:$B$2811,A80) -> 1
A81: Big Black | B81: Chicago, IL | C81: Chicago and the Midwest | D81: 1986–1987 | E81: X10 Post-punk and noise rock | F81: Context | G81: A2501, A2502 | H81: =COUNTIF(Albums!$B$2:$B$2811,A81) -> 2
A82: Big Dipper | B82: Boston, MA | C82: The Northeast | D82: 1987–1988 | E82: V16 American underground and college rock | F82: V | G82: A0495, A0496 | H82: =COUNTIF(Albums!$B$2:$B$2811,A82) -> 2
A83: Big Star | B83: Memphis, TN | C83: The South | D83: 1972–2005 | E83: V17 Jangle and power pop, Big Star to GBV | F83: V | G83: A0516, A0517, A0518, A0519 | H83: =COUNTIF(Albums!$B$2:$B$2811,A83) -> 4
A84: Big Thief | B84: Brooklyn, NY | C84: The Northeast | D84: 2016–2025 | E84: C5 Twangy indie folk | F84: Core | G84: A1539, A1540, A1541, A1542 | H84: =COUNTIF(Albums!$B$2:$B$2811,A84) -> 6 | K84: Y
A85: Big Vic | B85: Ann Arbor, MI | C85: The Northeast | D85: 2021 | E85: C4 Countrygaze and loud twang | F85: Core | G85: A1656 | H85: =COUNTIF(Albums!$B$2:$B$2811,A85) -> 1
A86: Bill Callahan | B86: Austin, TX | C86: Texas and Oklahoma | D86: 2007–2022 | E86: V2 Drag City deadpan school | F86: V | G86: A0680, A0681, A0678, A0679 | H86: =COUNTIF(Albums!$B$2:$B$2811,A86) -> 8 | K86: Y
A87: Bill Fox | B87: Cleveland, OH | C87: Chicago and the Midwest | D87: 1997–1998 | E87: V11 Lo-fi and home taping | F87: V | G87: A0182, A0183 | H87: =COUNTIF(Albums!$B$2:$B$2811,A87) -> 2
A88: Billie Marten | B88: Ripon, North Yorkshire, UK | C88: The UK, Ireland and Canada | D88: 2016–2025 | E88: C5 Twangy indie folk | F88: Core | G88: A1706, A1704, A1705, A1702 | H88: =COUNTIF(Albums!$B$2:$B$2811,A88) -> 5 | K88: Y
A89: Bill Monroe | B89: Rosine, KY | C89: The South | D89: 1992 | E89: R1 Roots | F89: V | G89: A0018 | H89: =COUNTIF(Albums!$B$2:$B$2811,A89) -> 1
A90: Bill Morrissey | B90: New Hampshire | C90: The Northeast | D90: 1992 | E90: V13 Americana songwriters before the label | F90: V | G90: A0333 | H90: =COUNTIF(Albums!$B$2:$B$2811,A90) -> 1
A91: Bill Orcutt | B91: San Francisco, CA | C91: The West | D91: 2011 | E91: V8 American Primitive and solo guitar | F91: V | G91: A1440 | H91: =COUNTIF(Albums!$B$2:$B$2811,A91) -> 1
A92: Billy Joe Shaver | B92: Nashville, TN | C92: Texas and Oklahoma | D92: 1973–1977 | E92: V23 Outlaw country | F92: V | G92: A0904, A0905, A0906 | H92: =COUNTIF(Albums!$B$2:$B$2811,A92) -> 3
A93: Billy Strings | B93: Nashville, TN | C93: The Northeast | D93: 2019 | E93: X4 Bluegrass, old-time, and newgrass | F93: Context | G93: A2347 | H93: =COUNTIF(Albums!$B$2:$B$2811,A93) -> 1
A94: The Bird Calls | B94: Brooklyn, NY | C94: The Northeast | D94: 2026 | E94: C2 Barroom storytellers and deadpan songwriters | F94: Core | G94: A2587 | H94: =COUNTIF(Albums!$B$2:$B$2811,A94) -> 1
A95: Blackberry Smoke | B95: Atlanta, GA | C95: The South | D95: 2012–2021 | E95: X11 Modern Southern rock | F95: Context | G95: A2510, A2511, A2512 | H95: =COUNTIF(Albums!$B$2:$B$2811,A95) -> 3
A96: Black Flag | B96: Hermosa Beach, CA | C96: The West | D96: 1981–1984 | E96: X14 Punk and hardcore roots | F96: Context | G96: A2548, A2549 | H96: =COUNTIF(Albums!$B$2:$B$2811,A96) -> 2
A97: Blackfoot | B97: Jacksonville, FL | C97: The South | D97: 1979 | E97: V28 Southern rock and country soul | F97: V | G97: A1163 | H97: =COUNTIF(Albums!$B$2:$B$2811,A97) -> 1
A98: The Black Swans | B98: Columbus, OH | C98: Chicago and the Midwest | D98: 2004–2007 | E98: V1 Molina and the Magnolia circle | F98: V | G98: A1844, A1845 | H98: =COUNTIF(Albums!$B$2:$B$2811,A98) -> 2
A99: The Blasters | B99: Downey, CA | C99: The West | D99: 1980–1985 | E99: V14 Cowpunk and LA roots punk | F99: V | G99: A0343, A0344, A0374, A0375 | H99: =COUNTIF(Albums!$B$2:$B$2811,A99) -> 4
A100: Blaze Foley | B100: Austin, TX | C100: Texas and Oklahoma | D100: 1989–2010 | E100: V24 Texas songwriters and progressive country | F100: V | G100: A0964, A0965 | H100: =COUNTIF(Albums!$B$2:$B$2811,A100) -> 2
... A120: Bon Iver | B120: Eau Claire, WI | C120: Chicago and the Midwest | D120: 2007–2011 | E120: V5 Rootsy indie folk | F120: V | G120: A1359, A1361, A1360 | H120: =COUNTIF(Albums!$B$2:$B$2811,A120) -> 3
A121: Bonnie 'Prince' Billy | B121: Louisville, KY | C121: The South | D121: 1999–2025 | E121: V2 Drag City deadpan school | F121: V | G121: A0690, A0692, A2779, A0691 | H121: =COUNTIF(Albums!$B$2:$B$2811,A121) -> 11 | K121: Y
A122: Bonnie 'Prince' Billy and the Cairo Gang | B122: Louisville, KY | C122: The South | D122: 2010 | E122: V2 Drag City deadpan school | F122: V | G122: A0698 | H122: =COUNTIF(Albums!$B$2:$B$2811,A122) -> 1
A123: Bonny Doon | B123: Detroit, MI | C123: Chicago and the Midwest | D123: 2017–2023 | E123: C7 Slacker, jangle, and power-pop revival | F123: Core | G123: A2747, A2288, A2746 | H123: =COUNTIF(Albums!$B$2:$B$2811,A123) -> 3 | K123: Y
A124: Bonny Light Horseman | B124: New York, NY | C124: The Northeast | D124: 2020–2024 | E124: C5 Twangy indie folk | F124: Core | G124: A2182, A2184, A2183 | H124: =COUNTIF(Albums!$B$2:$B$2811,A124) -> 3
A125: The Bottle Rockets | B125: Festus, MO | C125: Chicago and the Midwest | D125: 1992–2015 | E125: V6 2000s–2010s alt-country | F125: V | G125: A1471, A1470, A1472, A2010 | H125: =COUNTIF(Albums!$B$2:$B$2811,A125) -> 8
A126: Brad Goodall | B126: Huntington, WV | C126: The South | D126: 2022–2026 | E126: C2 Barroom storytellers and deadpan songwriters | F126: Core | G126: A1607, A1609, A1608 | H126: =COUNTIF(Albums!$B$2:$B$2811,A126) -> 3
A127: Brandi Carlile | B127: Seattle, WA | C127: The West | D127: 2018 | E127: X3 Big-tent Americana and stomp-clap folk | F127: Context | G127: A2339 | H127: =COUNTIF(Albums!$B$2:$B$2811,A127) -> 1
A128: Brennan Wedl | B128: Nashville, TN | C128: The South | D128: 2026 | E128: C3 New alt-country and honky-tonk bands | F128: Core | G128: A1648 | H128: =COUNTIF(Albums!$B$2:$B$2811,A128) -> 1
A129: Brennen Leigh | B129: Nashville, TN | C129: Chicago and the Midwest | D129: 2020–2022 | E129: V7 Neo-traditional and 'new outlaw' country | F129: V | G129: A2175, A2176 | H129: =COUNTIF(Albums!$B$2:$B$2811,A129) -> 2
A130: Brent Cobb | B130: Ellaville, GA | C130: The South | D130: 2016–2023 | E130: V7 Neo-traditional and 'new outlaw' country | F130: V | G130: A2153, A2151, A2152 | H130: =COUNTIF(Albums!$B$2:$B$2811,A130) -> 3
A131: Bridget St John | B131: London, England | C131: The UK, Ireland and Canada | D131: 1969 | E131: V30 British folk rock (selective) | F131: V | G131: A1285 | H131: =COUNTIF(Albums!$B$2:$B$2811,A131) -> 1
A132: Bright Eyes | B132: Omaha, NE | C132: Chicago and the Midwest | D132: 1998–2007 | E132: V4 Roots-inflected 2000s indie | F132: V | G132: A0186, A1322, A1321, A1323 | H132: =COUNTIF(Albums!$B$2:$B$2811,A132) -> 6
...

Sheet Scenes
A1: Scene | B1: Place | C1: Years | D1: Key labels | E1: Key artists | F1: Note | G1: Albums tagged

Sheet Labels
A1: Label | B1: Base | C1: Years active | D1: Zones and lanes | E1: Why it matters | F1: In field guide | G1: Albums in atlas
A2: Merge | B2: Durham, NC | E2: Superchunk's label. Home to Fust, Friendship and many Carolina acts. | F2: Y | G2: =COUNTIF(Albums!$F$2:$F$2811,A2&"*") -> 45
A3: Dear Life Records | B3: Asheville, NC | E3: Small label tied to the Wednesday and Lenderman circle. | F3: Y | G3: =COUNTIF(Albums!$F$2:$F$2811,A3&"*") -> 20
A4: Anti- | B4: Los Angeles | E4: Released Manning Fireworks and Waxahatchee's recent records. | F4: Y | G4: =COUNTIF(Albums!$F$2:$F$2811,A4&"*") -> 27
A5: Paradise of Bachelors | B5: Chapel Hill, NC | E5: Twangy folk and cosmic country. Hiss Golden Messenger started here. | F5: Y | G5: =COUNTIF(Albums!$F$2:$F$2811,A5&"*") -> 14
A6: Sophomore Lounge | B6: Louisville, KY | E6: Ryan Davis's label, running for nearly two decades. Grace Rogers and Arbor Labor Union. | F6: Y | G6: =COUNTIF(Albums!$F$2:$F$2811,A6&"*") -> 8
A7: Curation Records | B7: California | E7: Dead-indebted guitar rock and jangle: Silver Synthetic, Sean Thompson's Weird Ears, Sunday Mourners. | F7: Y | G7: =COUNTIF(Albums!$F$2:$F$2811,A7&"*") -> 1
A8: Keeled Scales | B8: Austin | E8: Soft Texas indie, including Lomelda. | F8: Y | G8: =COUNTIF(Albums!$F$2:$F$2811,A8&"*") -> 24
A9: Exploding in Sound | B9: Brooklyn | E9: The best archive of noisy slacker rock. | F9: Y | G9: =COUNTIF(Albums!$F$2:$F$2811,A9&"*") -> 2
A10: Fire Talk | B10: Brooklyn | E10: Adventurous indie rock, including Burlington's Robber Robber. | F10: Y | G10: =COUNTIF(Albums!$F$2:$F$2811,A10&"*") -> 9
A11: Lame-O Records | B11: Philadelphia | E11: Philly's DIY indie and power pop. | F11: Y | G11: =COUNTIF(Albums!$F$2:$F$2811,A11&"*") -> 16
A12: Drag City | B12: Chicago | E12: Silver Jews, Palace, Smog and early Pavement. The home of the deadpan lyrical tradition. | F12: Y | G12: =COUNTIF(Albums!$F$2:$F$2811,A12&"*") -> 74
A13: Bloodshot | B13: Chicago | E13: The '90s "insurgent country" label. Good for classic alt-country. | F13: Y | G13: =COUNTIF(Albums!$F$2:$F$2811,A13&"*") -> 47
... A16: Flying Nun | B16: New Zealand | E16: The roots of jangly slacker rock. | F16: Y | G16: =COUNTIF(Albums!$F$2:$F$2811,A16&"*") -> 31

Sheet Tags
A1: Category | B1: Tag | C1: Definition | D1: Albums using it
A2: Instruments | B2: pedal steel | C2: Pedal steel guitar is prominent in the arrangements. | D2: =COUNTIF(Albums!$O$2:$O$2811,"*"&B2&"*") -> 462
A3: Instruments | B3: fiddle | C3: Fiddle or violin plays a lead or featured role. | D3: =COUNTIF(Albums!$O$2:$O$2811,"*"&B3&"*") -> 189
A4: Instruments | B4: banjo | C4: Banjo is featured. | D4: =COUNTIF(Albums!$O$2:$O$2811,"*"&B4&"*") -> 92
A5: Instruments | B5: mandolin | C5: Mandolin is featured. | D5: =COUNTIF(Albums!$O$2:$O$2811,"*"&B5&"*") -> 46
A6: Instruments | B6: slide guitar | C6: Bottleneck or lap-steel slide guitar is a signature texture. | D6: =COUNTIF(Albums!$O$2:$O$2811,"*"&B6&"*") -> 108
A7: Instruments | B7: harmonica | C7: Harmonica is prominent. | D7: =COUNTIF(Albums!$O$2:$O$2811,"*"&B7&"*") -> 85
A8: Instruments | B8: piano | C8: Piano or organ carries songs. | D8: =COUNTIF(Albums!$O$2:$O$2811,"*"&B8&"*") -> 133
A9: Instruments | B9: horns | C9: Brass or saxophone arrangements. | D9: =COUNTIF(Albums!$O$2:$O$2811,"*"&B9&"*") -> 113
A10: Instruments | B10: strings | C10: String section or orchestral arrangements. | D10: =COUNTIF(Albums!$O$2:$O$2811,"*"&B10&"*") -> 183
A11: Instruments | B11: drum machine | C11: Programmed drums are a defining texture. | D11: =COUNTIF(Albums!$O$2:$O$2811,"*"&B11&"*") -> 83
A12: Instruments | B12: synths | C12: Synthesizers are a defining texture. | D12: =COUNTIF(Albums!$O$2:$O$2811,"*"&B12&"*") -> 136
A13: Instruments | B13: fingerpicked acoustic | C13: Fingerstyle acoustic guitar is the core of the sound. | D13: =COUNTIF(Albums!$O$2:$O$2811,"*"&B13&"*") -> 683
... A51: Mood | B51: glacial | C51: Extremely slow and still. | D51: =COUNTIF(Albums!$O$2:$O$2811,"*"&B51&"*") -> 100

Sheet Paths
A1: Path | B1: Step | C1: Album ID | D1: Artist | E1: Album | F1: Year | G1: Lane | H1: Connection to the next step

Sheet Borderline Log
A1: # | B1: Item | C1: Album ID | D1: Decision | E1: Reason | F1: Source
A2: 1 | B2: The Carter Family – The Essential Carter Family (2013) | C2: A0001 | D2: Primary R1 | E2: R1 singles-era compilation; recordings from 1927-1941 across Victor, ARC and Decca, gathered on this 2013 Columbia/Legacy set (no LP existed in the group's lifetime). | F2: lane research
A3: 2 | B3: Jimmie Rodgers – The Essential Jimmie Rodgers (1997) | C3: A0002 | D3: Primary R1 | E3: R1 singles-era compilation; recordings from 1927-1931 for RCA Victor, collected on this 1997 RCA set. | F3: lane research
A4: 3 | B4: Hank Williams – 40 Greatest Hits (1978) | C4: A0003 | D4: Primary R1 | E4: R1 singles-era compilation; recordings cut for MGM 1947-1952, gathered on this 1978 Mercury (PolyGram) set. Designated start-here album for the lane per assignment brief. | F4: lane research
A5: 4 | B5: Various Artists – Anthology of American Folk Music (1952) | C5: A0004 | D5: Primary R1 | E5: Compiled by Harry Smith from 1926-1933 commercial 78s by many different artists; logged under 'Various Artists' as the brief's other designated start-here album. | F5: lane research
A6: 5 | B6: Woody Guthrie – This Land Is Your Land: The Asch Recordings, Vol. 1 (1997) | C6: A0006 | D6: Primary R1 | E6: Posthumous compilation of Guthrie's 1940s-50s Asch/Folkways sides, issued 1997; standard modern single-volume introduction to that catalog. | F6: lane research
A7: 6 | B7: The Everly Brothers – The Best of The Everly Brothers (1959) | C7: A0010 | D7: Primary R1 | E7: Era-original hits compilation on the duo's own Cadence label, gathering their 1957-59 singles; included alongside the folk-ballads LP as the canonical career-defining set. | F7: lane research
A8: 7 | B8: Lefty Frizzell – Look What Thoughts Will Do (1997) | C8: A0011 | D8: Primary R1 | E8: R1 singles-era compilation; recordings for Columbia 1950-1959, gathered on this 1997 Columbia/Legacy set. | F8: lane research
A9: 8 | B9: Bob Wills & His Texas Playboys – The Essential Bob Wills (1935-1947) (1992) | C9: A0012 | D9: Primary R1 | E9: R1 singles-era compilation; recordings for Columbia/OKeh/Vocalion 1935-1947, gathered on this 1992 Columbia/Legacy set. | F9: lane research
A10: 9 | B10: Johnny Cash – Johnny Cash Sings the Songs That Made Him Famous (1958) | C10: A0014 | D10: Primary R1 | E10: Sun-label compilation of Cash's 1956-58 singles, issued 1958 after his move to Columbia; kept here as part of his 'Sun years' per the assignment brief. | F10: lane research
A11: 10 | B11: Johnny Cash – The Fabulous Johnny Cash (1958) | C11: A0015 | D11: Primary R1 | E11: Technically Cash's first Columbia LP (not a Sun release), cut immediately after leaving Sun in 1958; included per the assignment brief's 'Sun years' seed list as the closing record of that era. | F11: lane research
A12: 11 | B12: Bill Monroe – The Essential Bill Monroe (1945-1949) (1992) | C12: A0018 | D12: Primary R1 | E12: R1 singles-era compilation; recordings for Columbia 1945-1949, gathered on this 1992 Columbia/Legacy set. | F12: lane research
A13: 12 | B13: Lead Belly – Where Did You Sleep Last Night: Lead Belly Legacy, Vol. 1 (1996) | C13: A0024 | D13: Primary R1 | E13: Posthumous compilation of prewar/1940s recordings, issued 1996 by Smithsonian Folkways as the first volume of a Lead Belly retrospective series. | F13: lane research
... A370: 369 | B370: Cordelia's Dad – Cordelia's Dad (1990) | C370: A2806 | D370: Primary V9 | E370: Punk-folk hybrid rather than country-rock twang; included per assignment for its documented role in the pre-history of the No Depression scene. | F370: lane research

Sheet Needs Verification
A1: Artist | B1: Album | C1: Year (claimed) | D1: Lane file | E1: Why not verified
A2: Florry | B2: Brown Bunny | C2: 2018 | D2: C1 | E2: Debut LP mentioned in Florry's Big Fall Bandcamp bio (Sister Polygon, 2018); no tracklist or dedicated page found to confirm key tracks.
A3: Bella White | B3: Just Like Leaving | C3: 2020 | D3: C3 | E3: Year confirmed via Wikipedia/Bandcamp but original 2020 label unclear (Wikipedia only confirms she is 'signed to Rounder Records' without dating the signing); need a scrape of the original 2020 release credits.
A4: Kiely Connell | B4: My Own Company | C4: 2024 | D4: C3 | E4: Named by Terry with a Tucker Martine production credit, but not found on Kiely Connell's Bandcamp page (which describes Calumet Queen, 2026, as her debut); could not verify via a scraped source within budget.
A5: Desiree Cannon | B5: Radio Heat | C5: 2024 | D5: C3 | E5: Terry lists label as Gar Hole Records; her Bandcamp page (desireecannon.bandcamp.com) returned 404 and no alternate verification source was found within budget.
A6: Maddy Kirgo | B6: Shadow on My Light | C6: 2024 | D6: C3 | E6: Terry covered this New Orleans songwriter's album but her Bandcamp page (maddykirgo.bandcamp.com) returned 404 and no alternate source was found within budget.
A7: JP Harris | B7: Shaving A Dead Man | C7: 2026 | D7: C3 | E7: A newer JP Harris album spotted in Bandcamp search results (Oct 2026) but not yet confirmed with a full scrape of its own page; flagging for completion by a future pass.
A8: midwest, post death | B8: post recovery | D8: C4C9 | E8: Field-guide C9 artist; only found via secondhand Bandcamp collection listings and a short blog mention (mediamagpies.com) describing it as rough-hewn, chaotic and catchy. Could not confirm release year, label, or track listing from a primary source (official Bandcamp/Instagram/Linktree pages did not resolve to a scrapable discography page within budget). Needs a direct Bandcamp or Wikipedia page to verify.
A9: Julia Jacklin | B9: The Gem | D9: C5a | E9: Released 25 September 2026 (day of research); confirmed via Wikipedia and Bandcamp (label 4AD) but no track titles could be confirmed from a scraped page in time.
A10: Charlotte Cornfield | B10: Hurts Like Hell | D10: C5a | E10: Confirmed year 2026 and label Merge Records via Wikipedia, but no track titles could be confirmed from a scraped page in time.
A11: Allegra Krieger | B11: Art of the Unseen Infinity Machine | D11: C5a | E11: Terry dates this 2024 (Northern Spy is the likely label based on Krieger's catalog) but no scraped page confirming year/label was reached within budget.
A12: Mold Gold | B12: I'm Sorry I Dropped You As a Baby | C12: 2025 | D12: C5b | E12: Bandcamp handle guess 404'd within budget; not verified.
A13: Farmer Dave Scher | B13: (unspecified solo LP) | D13: C6a | E13: Seed artist (ex-Beachwood Sparks/Jonathan Wilson band); his bandcamp page had no release list with dates and no additional scrape was made within budget.
A14: The Dead Tongues | B14: (unspecified LP) | D14: C6a | E14: Seed artist; bandcamp page had no release list with dates/labels and no Wikipedia page was found within budget.
A15: Chris Forsyth | B15: (unspecified LP) | D15: C6a | E15: Seed artist (Garcia Peoples/Solar Motel Band); Wikipedia page 404'd and bandcamp /music index gave no dates/labels within budget.
A16: Cut Worms | B16: Transmitter | C16: 2026 | D16: C6a | E16: Confirmed year/label (2026, Jagjaguwar) via Wikipedia, but no tracklist could be confirmed for key_tracks within budget.
A17: Tony Molina | B17: Dissed and Dismissed | C17: 2013 | D17: C7b | E17: Could not confirm exact year/label within budget; Wikipedia artist page 404'd and Bandcamp query mode returned a mismatched track instead of album metadata.
A18: Lawn | B18: Blood on the Tracks | C18: 2018 | D18: C7b | E18: Year confirmed only via Terry's post naming it as the band's 2018 debut; original label not confirmed within budget.
A19: Major Murphy | B19: No. 1 | C19: 2018 | D19: C7b | E19: Year per Terry's post; label not confirmed within budget (Bandcamp album page not scraped).
A20: Ben Chapman | B20: Downbeat | D20: DEEP | E20: Nashville-based alt-country/Americana artist (r/altcountry community favorite, Anderson East-produced); could not confirm exact release year or label from any page actually scraped (Bandcamp handle 404'd, and the one profile piece read did not state a year). Worth another agent's follow-up for C3.
A21: Hank Snow | B21: canonical RCA Victor compilation (title unconfirmed) | D21: R1 | E21: Could not find a fetchable source confirming the exact title/year/label of a canonical Hank Snow RCA Victor compilation; general bio confirmed (RCA Victor, Nashville from 1949) but no specific album title verified.
A22: Dock Boggs | B22: 1963 Folkways LP (title unconfirmed) | D22: R1 | E22: Wikipedia confirms he recorded three albums for Folkways 1963-1968 after rediscovery by Mike Seeger, but no fetchable source gave the exact title/catalog number/year of the individual 1963 LP the assignment brief points to.
