Workbook

Sheet README
A1: The V — Album Atlas
A2: An album-level atlas of indie twang, slacker rock, and everything that fed them. Companion to V_Map.docx and to the Slacker Rock & Alt-Country Field Guide (whose Region and Style vocabulary it reuses).
A4: THE SHAPE. Picture a V. The bottom point is the modern indie-twang and slacker scene (2014–now). Climbing the V goes back in time through the genres that fed it; the V widens with each era.
A5: LAYER (vertical, from the original release year): L1 Now 2014–2026 · L2 Bridge 1998–2013 · L3 Nineties 1987–1997 · L4 Underground 1978–1986 · L5 Classic 1965–1977 · L6 Roots before 1965 (the R1 roots lane is always L6).
A6: ZONE (horizontal, from the primary lane): Core = the scenes happening now (completionist) · V = direct ancestors and close siblings (deep) · Context = popular branches whose main line leads elsewhere (landmarks only). Row colour: orange = Core, blue = V, grey = Context.
A8: SHEETS. Albums — one row per album (Layer and Zone are formulas). Artists — one row per artist with key album IDs. Lanes — the 54 lanes with parents/children and a live album count. Scenes, Labels — gazetteer. Tags — the controlled descriptor vocabulary. Paths — the listening paths from V_Map.docx. Borderline Log — every judgment call. Needs Verification — candidates that could not be verified (never in Albums). QA Log — every error-correction run. Stats — live counts by layer × zone, lane, year and priority.
A10: HOW TO USE. Filter Albums by Zone/Lane/Priority, or search a descriptor (e.g. 'pedal steel'). 'Start here' marks one or two entry points per lane. The Terry column links Josh Terry's No Expectations coverage. Lineage basis: Documented = established by interview, cover, credit, shared member or critic; Inferred = resemblance only.
A11: YOUR COLUMNS. Heard (Y/N), Rating (1–5) and My notes are blank for you; they have dropdowns. Example: Heard = Y, Rating = 4, My notes = 'side two is the one'.
A13: CONFIDENCE. High = two independent sources agree on artist, title, original year and original label; Medium = one reliable source. Sources lists the verification URLs.
A14: Active years on the Artists sheet are the span of that artist's releases in this atlas, not a full career span.

Sheet Albums
A1: ID | B1: Artist | C1: Album | D1: Year | E1: Type | F1: Label | G1: Layer | H1: Zone | I1: Primary lane | J1: Secondary lanes | K1: Style | L1: Region | M1: Base | N1: Scene | O1: Descriptors | P1: Description | Q1: Lineage | R1: Lineage basis | S1: Key tracks | T1: Priority | U1: Start here | V1: Terry | W1: In field guide | X1: Sources | Y1: Confidence | Z1: Heard | AA1: Rating | AB1: My notes
A2: A0001 | B2: Spencer Radcliffe | C2: Keeper | D2: 2014 | E2: LP | F2: Self-released | G2: =IF(LEFT(I2,3)="R1 ","L6",IF(D2>=2014,"L1",IF(D2>=1998,"L2",IF(D2>=1987,"L3",IF(D2>=1978,"L4",IF(D2>=1965,"L5","L6")))))) -> L1 | H2: =IFERROR(INDEX(Lanes!$C$2:$C$60,MATCH(LEFT(I2,FIND(" ",I2)-1),Lanes!$A$2:$A$60,0)),"?") -> Core | I2: C1 Indie twang / yallternative | K2: Lo-fi | L2: Chicago and the Midwest | M2: Ohio (formerly Chicago) | O2: lo-fi; deadpan; bleak; hushed; small-town | P2: An early self-released Spencer Radcliffe LP of sparse, home-recorded songs. Its hushed vocals and simple guitar sketches anticipate the twangier, more rock-oriented turn of his later solo work. | Q2: An early entry in Radcliffe's long solo catalogue that eventually feeds into the twangier Ohio Vision. | R2: Inferred | S2: Child's Pose; Tina; Marlena | T2: Deep cut | W2: Y | X2: https://spencerradcliffe.bandcamp.com/album/keeper | Y2: Medium
A3: A0002 | B3: Ratboys | C3: AOID | D3: 2015 | E3: LP | F3: Topshelf Records | G3: =IF(LEFT(I3,3)="R1 ","L6",IF(D3>=2014,"L1",IF(D3>=1998,"L2",IF(D3>=1987,"L3",IF(D3>=1978,"L4",IF(D3>=1965,"L5","L6")))))) -> L1 | H3: =IFERROR(INDEX(Lanes!$C$2:$C$60,MATCH(LEFT(I3,FIND(" ",I3)-1),Lanes!$A$2:$A$60,0)),"?") -> Core | I3: C1 Indie twang / yallternative | K3: Crossover | L3: Chicago and the Midwest | M3: Chicago, IL | O3: Telecaster twang; deadpan; drawl; small-town; jangle | P3: Ratboys' debut LP: unhurried, twang-flecked indie rock built around Julia Steiner's plainspoken voice and long, patient song structures. A quieter, more folk-adjacent record than the band's later output, closer to their alt-country roots. | Q3: Grew out of Steiner and Sagan's college-band beginnings at Notre Dame; set the twangy-indie template the band expanded on GN and Printer's Devil. | R3: Documented | S3: Not Equal; Flat Foot | T3: Deep cut | V3: https://www.noexpectations.fyi/p/ratboys-mandy-indiana-ulrika-spacek-bad-bunny | W3: Y | X3: https://en.wikipedia.org/wiki/Ratboys https://ratboys.bandcamp.com/music | Y3: High
A4: A0003 | B4: Spencer Radcliffe | C4: Looking In | D4: 2015 | E4: LP | F4: Run For Cover Records | G4: =IF(LEFT(I4,3)="R1 ","L6",IF(D4>=2014,"L1",IF(D4>=1998,"L2",IF(D4>=1987,"L3",IF(D4>=1978,"L4",IF(D4>=1965,"L5","L6")))))) -> L1 | H4: =IFERROR(INDEX(Lanes!$C$2:$C$60,MATCH(LEFT(I4,FIND(" ",I4)-1),Lanes!$A$2:$A$60,0)),"?") -> Core | I4: C1 Indie twang / yallternative | K4: Lo-fi | L4: Chicago and the Midwest | M4: Chicago, IL | O4: lo-fi; deadpan; hushed; bleak; small-town | P4: Radcliffe's first Run For Cover full-length: patchwork indie pop and lo-fi textures held together by his flat, equivocal voice. It is homemade and a little strange, for listeners who like bedroom pop with rough edges. | Q4: Sounds part of the same Run for Cover/Topshelf-adjacent 2010s indie underground as Ratboys. | R4: Inferred | S4: Mia; Yankee; Looking In | T4: Deep cut | W4: Y | X4: https://spencerradcliffe.bandcamp.com/album/looking-in https://www.discogs.com/master/894018-Spencer-Radcliffe-Looking-In | Y4: High
A5: A0004 | B5: Ratboys | C5: GN | D5: 2017 | E5: LP | F5: Topshelf Records | G5: =IF(LEFT(I5,3)="R1 ","L6",IF(D5>=2014,"L1",IF(D5>=1998,"L2",IF(D5>=1987,"L3",IF(D5>=1978,"L4",IF(D5>=1965,"L5","L6")))))) -> L1 | H5: =IFERROR(INDEX(Lanes!$C$2:$C$60,MATCH(LEFT(I5,FIND(" ",I5)-1),Lanes!$A$2:$A$60,0)),"?") -> Core | I5: C1 Indie twang / yallternative | K5: Crossover | L5: Chicago and the Midwest | M5: Chicago, IL | O5: Telecaster twang; drawl; jangle; small-town; storytelling | P5: Second Ratboys LP: warm, unhurried indie rock with country phrasing and Steiner's conversational storytelling. Quieter and more spacious than the band's later, harder-rocking records. | Q5: Bridges the band's early alt-country leanings with the bigger, distorted guitar sound they'd bring on Printer's Devil. | R5: Documented | S5: GM; Peter the Wild Boy | T5: Recommended | W5: Y | X5: https://en.wikipedia.org/wiki/Ratboys | Y5: Medium
A6: A0005 | B6: MJ Lenderman | C6: Lucky | D6: 2019 | E6: EP | F6: Self-released | G6: =IF(LEFT(I6,3)="R1 ","L6",IF(D6>=2014,"L1",IF(D6>=1998,"L2",IF(D6>=1987,"L3",IF(D6>=1978,"L4",IF(D6>=1965,"L5","L6")))))) -> L1 | H6: =IFERROR(INDEX(Lanes!$C$2:$C$60,MATCH(LEFT(I6,FIND(" ",I6)-1),Lanes!$A$2:$A$60,0)),"?") -> Core | I6: C1 Indie twang / yallternative | K6: Lo-fi | L6: The Carolinas | M6: Asheville, NC | N6: Asheville | O6: lo-fi; fingerpicked acoustic; drawl; hushed; small-town | P6: A small bedroom EP, quieter and rougher than anything he would release later. It already carries his plainspoken, half-joking phrasing over hissy home-recorded guitar. | Q6: Sounds like an early sketch of the bedroom-recorded songwriting Lenderman developed on his Dear Life releases. | R6: Inferred | S6: No Mercy; SUV | T6: Deep cut | W6: Y | X6: https://mjlenderman.bandcamp.com/album/lucky https://en.wikipedia.org/wiki/MJ_Lenderman | Y6: High
A7: A0006 | B7: MJ Lenderman | C7: MJ Lenderman | D7: 2019 | E7: LP | F7: Self-released | G7: =IF(LEFT(I7,3)="R1 ","L6",IF(D7>=2014,"L1",IF(D7>=1998,"L2",IF(D7>=1987,"L3",IF(D7>=1978,"L4",IF(D7>=1965,"L5","L6")))))) -> L1 | H7: =IFERROR(INDEX(Lanes!$C$2:$C$60,MATCH(LEFT(I7,FIND(" ",I7)-1),Lanes!$A$2:$A$60,0)),"?") -> Core | I7: C1 Indie twang / yallternative | K7: Lo-fi | L7: The Carolinas | M7: Asheville, NC | N7: Asheville | O7: lo-fi; deadpan; fingerpicked acoustic; drawl; small-town | P7: Lenderman's home-recorded debut: hissy four-track guitar songs, half-mumbled vocals and jokes buried in genuine heartbreak. It is rougher and slower than his later work but already has the deadpan, small-town eye for detail that defines his writing. | Q7: Grew out of Asheville's DIY bedroom-recording scene before Lenderman joined Wednesday full-time; a direct line to the funnier, sadder songwriting of Boat Songs and Manning Fireworks. | R7: Documented | S7: Come Over; Ghost Town; Southern Birds | T7: Deep cut | W7: Y | X7: https://en.wikipedia.org/wiki/MJ_Lenderman https://mjlenderman.bandcamp.com/music https://mjlenderman.bandcamp.com/album/mj-lenderman | Y7: High
A8: A0007 | B8: Ratboys | C8: Printer's Devil | D8: 2020 | E8: LP | F8: Topshelf Records | G8: =IF(LEFT(I8,3)="R1 ","L6",IF(D8>=2014,"L1",IF(D8>=1998,"L2",IF(D8>=1987,"L3",IF(D8>=1978,"L4",IF(D8>=1965,"L5","L6")))))) -> L1 | H8: =IFERROR(INDEX(Lanes!$C$2:$C$60,MATCH(LEFT(I8,FIND(" ",I8)-1),Lanes!$A$2:$A$60,0)),"?") -> Core | I8: C1 Indie twang / yallternative | K8: Crossover | L8: Chicago and the Midwest | M8: Chicago, IL | O8: Telecaster twang; drawl; anthemic; storytelling; jangle | P8: Ratboys' loudest, most confident record to that point: bigger choruses and full-band muscle layered over the same plainspoken, twang-inflected songwriting. It suits listeners who like their indie rock warm, hooky and a little country. | Q8: Marks the move from their earlier folk-adjacent sound toward the anthemic guitar rock of The Window and Singin' to an Empty Chair. | R8: Documented | S8: Printer's Devil; Look to | T8: Essential | W8: Y | X8: https://en.wikipedia.org/wiki/Ratboys https://ratboys.bandcamp.com/music | Y8: High
A9: A0008 | B9: Florry | C9: Big Fall | D9: 2021 | E9: LP | F9: 12XU | G9: =IF(LEFT(I9,3)="R1 ","L6",IF(D9>=2014,"L1",IF(D9>=1998,"L2",IF(D9>=1987,"L3",IF(D9>=1978,"L4",IF(D9>=1965,"L5","L6")))))) -> L1 | H9: =IFERROR(INDEX(Lanes!$C$2:$C$60,MATCH(LEFT(I9,FIND(" ",I9)-1),Lanes!$A$2:$A$60,0)),"?") -> Core | I9: C1 Indie twang / yallternative | K9: Alt-country | L9: Philadelphia | M9: Philadelphia, PA | N9: Philadelphia DIY | O9: pedal steel; drawl; Crazy Horse fuzz; small-town; funny-sad | P9: Florry's turn toward Gram Parsons-style Cosmic American Music: pedal steel, honky-tonk piano and Neil Young-indebted guitar wrapped around Francie Medosch's songwriting. It is warm, loose and hopeful, made for fans of ragged '70s country-rock. | Q9: Sounds indebted to Parsons' Cosmic American Music and Neil Young; precedes the caustic barroom twang of The Holey Bible. | R9: Both | S9: You Don't Know; Big Fall; Older Girlfriend | T9: Recommended | W9: Y | X9: https://florry.bandcamp.com/album/big-fall https://www.discogs.com/release/21232099-Florry-Big-Fall | Y9: High
A10: A0009 | B10: MJ Lenderman | C10: Ghost of Your Guitar Solo | D10: 2021 | E10: LP | F10: Dear Life Records | G10: =IF(LEFT(I10,3)="R1 ","L6",IF(D10>=2014,"L1",IF(D10>=1998,"L2",IF(D10>=1987,"L3",IF(D10>=1978,"L4",IF(D10>=1965,"L5","L6")))))) -> L1 | H10: =IFERROR(INDEX(Lanes!$C$2:$C$60,MATCH(LEFT(I10,FIND(" ",I10)-1),Lanes!$A$2:$A$60,0)),"?") -> Core | I10: C1 Indie twang / yallternative | K10: Slacker | L10: The Carolinas | M10: Asheville, NC | N10: Asheville | O10: lo-fi; deadpan; funny-sad; drawl; pop-culture references | P10: A scrappy, tossed-off-sounding set of slacker-rock songs that bridges his earliest bedroom tapes and the more assured Boat Songs. It is full of one-liners about basketball, bad decisions and long-gone relationships, delivered in his flat, dry voice over loose, fuzzy guitars. | Q10: A Dear Life Records release recorded as Lenderman's own songwriting was starting to draw notice alongside his role in Wednesday. | R10: Documented | S10: Someone Get The Grill Out Of The Rain; I Ate Too Much At The Fair; Catholic Priest | T10: Deep cut | W10: Y | X10: https://mjlenderman.bandcamp.com/album/ghost-of-your-guitar-solo https://en.wikipedia.org/wiki/MJ_Lenderman | Y10: High
A11: A0010 | B11: MJ Lenderman | C11: Knockin' | D11: 2021 | E11: EP | F11: Dear Life Records | G11: =IF(LEFT(I11,3)="R1 ","L6",IF(D11>=2014,"L1",IF(D11>=1998,"L2",IF(D11>=1987,"L3",IF(D11>=1978,"L4",IF(D11>=1965,"L5","L6")))))) -> L1 | H11: =IFERROR(INDEX(Lanes!$C$2:$C$60,MATCH(LEFT(I11,FIND(" ",I11)-1),Lanes!$A$2:$A$60,0)),"?") -> Core | I11: C1 Indie twang / yallternative | K11: Slacker | L11: The Carolinas | M11: Asheville, NC | N11: Asheville | O11: lo-fi; deadpan; funny-sad; drawl; short songs (under 2 minutes) | P11: A short stopgap EP released ahead of Boat Songs, loose and quick in feel. It carries the same wry, downbeat humor as his full-lengths in miniature, with fuzzy guitars and his dry, understated voice. | Q11: Fits between Ghost of Your Guitar Solo and Boat Songs as Lenderman's songwriting sharpened toward the deadpan style that broke through in 2022. | R11: Documented | S11: Knockin'; Happiness | T11: Deep cut | W11: Y | X11: https://mjlenderman.bandcamp.com/album/knockin https://en.wikipedia.org/wiki/MJ_Lenderman | Y11: High
A12: A0011 | B12: Ratboys | C12: Happy Birthday, Ratboy | D12: 2021 | E12: LP | F12: Topshelf Records | G12: =IF(LEFT(I12,3)="R1 ","L6",IF(D12>=2014,"L1",IF(D12>=1998,"L2",IF(D12>=1987,"L3",IF(D12>=1978,"L4",IF(D12>=1965,"L5","L6")))))) -> L1 | H12: =IFERROR(INDEX(Lanes!$C$2:$C$60,MATCH(LEFT(I12,FIND(" ",I12)-1),Lanes!$A$2:$A$60,0)),"?") -> Core | I12: C1 Indie twang / yallternative | K12: Crossover | L12: Chicago and the Midwest | M12: Chicago, IL | O12: jangle; drawl; anthemic; small-town; storytelling | P12: A tenth-anniversary record revisiting older songs with the full band, playing them at their most direct and hooky. It sits between the loose twang of GN and the polish of The Window. | Q12: A victory-lap record marking Ratboys' first decade before their Chris Walla-produced pivot. | R12: Documented | S12: Go Outside | T12: Deep cut | W12: Y | X12: https://en.wikipedia.org/wiki/Ratboys https://ratboys.bandcamp.com/music | Y12: High
A13: A0012 | B13: Trace Mountains | C13: House of Confusion | D13: 2021 | E13: LP | F13: Lame-O Records | G13: =IF(LEFT(I13,3)="R1 ","L6",IF(D13>=2014,"L1",IF(D13>=1998,"L2",IF(D13>=1987,"L3",IF(D13>=1978,"L4",IF(D13>=1965,"L5","L6")))))) -> L1 | H13: =IFERROR(INDEX(Lanes!$C$2:$C$60,MATCH(LEFT(I13,FIND(" ",I13)-1),Lanes!$A$2:$A$60,0)),"?") -> Core | I13: C1 Indie twang / yallternative | J13: C7 | K13: Crossover | L13: The Northeast | M13: New York, NY | O13: jangle; synths; drawl; breezy; small-town | P13: Dave Benton's Trace Mountains project leans further into warmly recorded, country-tinged indie pop on this record, mixing jangling guitars with synths and unhurried melodies. Benton's soft, conversational voice keeps things intimate even when the arrangements fill out. It suits listeners who like gentle, twang-flecked indie rock. | Q13: A former LVL UP member's move toward twangier songwriting, released on Philadelphia's Lame-O Records alongside Slaughter Beach, Dog; its country tint sounds akin to the wider indie-twang turn. | R13: Both | S13: Seen it Coming; On My Knees; Heart of Gold | T13: Recommended | X13: https://lame-orecords.bandcamp.com/music https://tracemountains.bandcamp.com/album/house-of-confusion | Y13: High
A14: A0013 | B14: Good Looks | C14: Bummer Year | D14: 2022 | E14: LP | F14: Keeled Scales | G14: =IF(LEFT(I14,3)="R1 ","L6",IF(D14>=2014,"L1",IF(D14>=1998,"L2",IF(D14>=1987,"L3",IF(D14>=1978,"L4",IF(D14>=1965,"L5","L6")))))) -> L1 | H14: =IFERROR(INDEX(Lanes!$C$2:$C$60,MATCH(LEFT(I14,FIND(" ",I14)-1),Lanes!$A$2:$A$60,0)),"?") -> Core | I14: C1 Indie twang / yallternative | K14: Crossover | L14: Texas and Oklahoma | M14: Austin, TX | O14: Telecaster twang; long solos; drawl; small-town; political | P14: Austin quartet's debut: blue-collar, plainspoken indie rock with Replacements swagger and War on Drugs-style desert-rock riffs from guitarist Jake Ames, writing about home and growing up around conservatives. | Q14: Bandleader Tyler Jordan met Jake Ames at Kerrville Folk Festival song swaps (where they also crossed paths with Buck Meek and Adrianne Lenker); Keeled Scales labelmates of Katy Kirby. | R14: Documented | S14: Almost Automatic; Bummer Year; Walker Lake | T14: Essential | V14: https://www.noexpectations.fyi/p/the-60-best-albums-of-2022-according | X14: https://goodlooksband.bandcamp.com/album/bummer-year https://www.noexpectations.fyi/p/margaux-good-looks-bloomsday-new-music https://keeledscales.bandcamp.com/music | Y14: High
A15: A0014 | B15: Greg Freeman | C15: I Looked Out | D15: 2022 | E15: LP | F15: Self-released | G15: =IF(LEFT(I15,3)="R1 ","L6",IF(D15>=2014,"L1",IF(D15>=1998,"L2",IF(D15>=1987,"L3",IF(D15>=1978,"L4",IF(D15>=1965,"L5","L6")))))) -> L1 | H15: =IFERROR(INDEX(Lanes!$C$2:$C$60,MATCH(LEFT(I15,FIND(" ",I15)-1),Lanes!$A$2:$A$60,0)),"?") -> Core | I15: C1 Indie twang / yallternative | K15: Crossover | L15: Burlington, Vermont | M15: Burlington, VT | N15: Burlington, Vermont | O15: pedal steel; Telecaster twang; long solos; storytelling; drawl | P15: Freeman's quietly released debut: thunderous overdriven guitars and plaintive pedal steel under vivid, semi-biblical images of shipwrecks and doomed drifters. Word of mouth turned it into a cult favorite well after its original release. | Q15: Part of the Burlington, Vermont scene around Freeman and Lily Seabird; it set up his later label releases. | R15: Documented | S15: Horns; Long Distance Driver; Colorado | T15: Essential | V15: https://www.noexpectations.fyi/p/meta-verification-free-range-greg-freeman | W15: Y | X15: https://gregfreeman.bandcamp.com/album/i-looked-out https://www.noexpectations.fyi/p/meta-verification-free-range-greg-freeman | Y15: High
A16: A0015 | B16: MJ Lenderman | C16: Boat Songs | D16: 2022 | E16: LP | F16: Dear Life Records | G16: =IF(LEFT(I16,3)="R1 ","L6",IF(D16>=2014,"L1",IF(D16>=1998,"L2",IF(D16>=1987,"L3",IF(D16>=1978,"L4",IF(D16>=1965,"L5","L6")))))) -> L1 | H16: =IFERROR(INDEX(Lanes!$C$2:$C$60,MATCH(LEFT(I16,FIND(" ",I16)-1),Lanes!$A$2:$A$60,0)),"?") -> Core | I16: C1 Indie twang / yallternative | K16: Crossover | L16: The Carolinas | M16: Asheville, NC | N16: Asheville | O16: Crazy Horse fuzz; deadpan; funny-sad; pop-culture references; drawl | P16: The album that put Lenderman on the map: loping, overdriven guitar rock with a country tilt, sung in a bone-dry deadpan about Dan Marino, Michael Jordan's baseball career and other small American humiliations. Funny and sneakily devastating within the same verse. | Q16: Builds directly on Neil Young & Crazy Horse's guitar tone and the deadpan-funny-sad lineage of Drag City songwriters; opened the door to Manning Fireworks and his growing profile in Wednesday. | R16: Documented | S16: TLC Cage Match; Hangover Game; You Have Bought Yourself a Boat | T16: Essential | V16: https://www.noexpectations.fyi/p/the-60-best-albums-of-2022-according | W16: Y | X16: https://en.wikipedia.org/wiki/MJ_Lenderman https://www.noexpectations.fyi/p/the-60-best-albums-of-2022-according https://mjlenderman.bandcamp.com/album/boat-songs | Y16: High
A17: A0016 | B17: Thomas Dollbaum | C17: Wellswood | D17: 2022 | E17: LP | F17: Big Legal Mess Records | G17: =IF(LEFT(I17,3)="R1 ","L6",IF(D17>=2014,"L1",IF(D17>=1998,"L2",IF(D17>=1987,"L3",IF(D17>=1978,"L4",IF(D17>=1965,"L5","L6")))))) -> L1 | H17: =IFERROR(INDEX(Lanes!$C$2:$C$60,MATCH(LEFT(I17,FIND(" ",I17)-1),Lanes!$A$2:$A$60,0)),"?") -> Core | I17: C1 Indie twang / yallternative | K17: Alt-country | L17: The South | M17: New Orleans, LA | O17: Telecaster twang; drawl; baritone; storytelling; Southern gothic | P17: Thomas Dollbaum's debut LP: dark rural storytelling sung in a rangy baritone, with Southern gothic detail and spare, dusty arrangements. It is for listeners who like their country songs literary, slow and haunted. | Q17: Sounds rooted in the alt-country storytelling lineage of Townes Van Zandt and Jason Molina. | R17: Inferred | S17: Florida; God's Country; Gold Teeth | T17: Recommended | W17: Y | X17: https://thomasdollbaum.bandcamp.com/album/wellswood https://newreleases.discogs.com/us/release/117307-thomas-dollbaum-wellswood | Y17: High
A18: A0017 | B18: Dari Bay | C18: Longest Day Of The Year | D18: 2023 | E18: LP | F18: Self-released | G18: =IF(LEFT(I18,3)="R1 ","L6",IF(D18>=2014,"L1",IF(D18>=1998,"L2",IF(D18>=1987,"L3",IF(D18>=1978,"L4",IF(D18>=1965,"L5","L6")))))) -> L1 | H18: =IFERROR(INDEX(Lanes!$C$2:$C$60,MATCH(LEFT(I18,FIND(" ",I18)-1),Lanes!$A$2:$A$60,0)),"?") -> Core | I18: C1 Indie twang / yallternative | K18: Slacker | L18: Burlington, Vermont | M18: Burlington, VT | N18: Burlington, Vermont | O18: jangle; drawl; lo-fi; hushed; small-town | P18: Zachary James's efficient, hooky home-recording project: '90s alt-rock and Pavement/Big Star-style jangle folded into twangy, deceptively simple songs. It is short, bright and replayable, for fans of warm, lo-fi guitar pop. | Q18: Part of the same Burlington scene as Greg Freeman; its songwriting sounds indebted to Judee Sill, Alex Chilton and Elliott Smith. | R18: Both | S18: Wait For You; Shy Of A Nurse; Walk On Down | T18: Essential | V18: https://www.noexpectations.fyi/p/the-60-best-albums-of-2023 | X18: https://daribay.bandcamp.com/album/longest-day-of-the-year https://www.noexpectations.fyi/p/the-30-best-albums-of-2023-so-far-midyear-list | Y18: High
A19: A0018 | B19: Florry | C19: Sweet Guitar Solos | D19: 2023 | E19: EP | F19: Dear Life Records | G19: =IF(LEFT(I19,3)="R1 ","L6",IF(D19>=2014,"L1",IF(D19>=1998,"L2",IF(D19>=1987,"L3",IF(D19>=1978,"L4",IF(D19>=1965,"L5","L6")))))) -> L1 | H19: =IFERROR(INDEX(Lanes!$C$2:$C$60,MATCH(LEFT(I19,FIND(" ",I19)-1),Lanes!$A$2:$A$60,0)),"?") -> Core | I19: C1 Indie twang / yallternative | K19: Cowpunk | L19: Philadelphia | M19: Philadelphia, PA | N19: Philadelphia DIY | O19: Telecaster twang; drawl; rowdy; drinking songs; lo-fi | P19: A short, ramshackle punk-country EP that sounds built for beers in a small, sticky room. It works as a loose bridge between Big Fall and the fuller-band Holey Bible, with rough guitars and Medosch's warbling voice up front. | Q19: Part of the same Dear Life Records-era run of scrappy, caustic Philly country as The Holey Bible. | R19: Documented | S19: Cowgirl in a Ditch; Lisa's Birthday; Big Fall | T19: Deep cut | V19: https://www.noexpectations.fyi/p/internet-horror-tom-verlaine-david-berman | W19: Y | X19: https://florry.bandcamp.com/album/sweet-guitar-solos | Y19: Medium
A20: A0019 | B20: Florry | C20: The Holey Bible | D20: 2023 | E20: LP | F20: Dear Life Records | G20: =IF(LEFT(I20,3)="R1 ","L6",IF(D20>=2014,"L1",IF(D20>=1998,"L2",IF(D20>=1987,"L3",IF(D20>=1978,"L4",IF(D20>=1965,"L5","L6")))))) -> L1 | H20: =IFERROR(INDEX(Lanes!$C$2:$C$60,MATCH(LEFT(I20,FIND(" ",I20)-1),Lanes!$A$2:$A$60,0)),"?") -> Core | I20: C1 Indie twang / yallternative | K20: Alt-country | L20: Philadelphia | M20: Philadelphia, PA | N20: Philadelphia DIY | O20: pedal steel; fiddle; drawl; rowdy; small-town | P20: Florry's Dear Life Records debut proper: raucous, barroom-ready country-rock with a half-broken pedal steel, fiddle and a full band behind Francie Medosch's caustic, warble-voiced songwriting. It sits somewhere between the Replacements and Drive-By Truckers, built for loud rooms and cold beer. | Q20: A Dear Life Records release that sounds of a piece with the indie-twang of Greg Freeman and Lily Seabird. | R20: Both | S20: Drunk and High; Big Fall; Cowgirl in a Ditch | T20: Essential | U20: Y | V20: https://www.noexpectations.fyi/p/the-60-best-albums-of-2023 | W20: Y | X20: https://florry.bandcamp.com/album/the-holey-bible-2 https://www.noexpectations.fyi/p/new-music-sam-evian-villagerrr-rosali-sun-seeker | Y20: High
A21: A0020 | B21: MJ Lenderman | C21: And the Wind (Live and Loose!) | D21: 2023 | E21: Live | F21: ANTI- | G21: =IF(LEFT(I21,3)="R1 ","L6",IF(D21>=2014,"L1",IF(D21>=1998,"L2",IF(D21>=1987,"L3",IF(D21>=1978,"L4",IF(D21>=1965,"L5","L6")))))) -> L1 | H21: =IFERROR(INDEX(Lanes!$C$2:$C$60,MATCH(LEFT(I21,FIND(" ",I21)-1),Lanes!$A$2:$A$60,0)),"?") -> Core | I21: C1 Indie twang / yallternative | K21: Crossover | L21: The Carolinas | M21: Asheville, NC | N21: Asheville | O21: Crazy Horse fuzz; long solos; live in the room; drawl; rowdy | P21: A loose, rowdy live document of the Boat Songs-era band, billed as MJ Lenderman & the Wind. The studio songs stretch out with extra guitar interplay and the crowd noise left intact, making it a good fit for fans who want the band's ragged, Crazy Horse-style side. | Q21: Captures the touring band that would carry over into the Manning Fireworks era, showing how the songs mutate on stage. | R21: Documented | S21: TLC Cage Match; Under Control | T21: Recommended | W21: Y | X21: https://mjlenderman.bandcamp.com/music https://en.wikipedia.org/wiki/MJ_Lenderman https://en.wikipedia.org/wiki/And_the_Wind_(Live_and_Loose!) | Y21: High
A22: A0021 | B22: Ratboys | C22: The Window | D22: 2023 | E22: LP | F22: Topshelf Records | G22: =IF(LEFT(I22,3)="R1 ","L6",IF(D22>=2014,"L1",IF(D22>=1998,"L2",IF(D22>=1987,"L3",IF(D22>=1978,"L4",IF(D22>=1965,"L5","L6")))))) -> L1 | H22: =IFERROR(INDEX(Lanes!$C$2:$C$60,MATCH(LEFT(I22,FIND(" ",I22)-1),Lanes!$A$2:$A$60,0)),"?") -> Core | I22: C1 Indie twang / yallternative | K22: Crossover | L22: Chicago and the Midwest | M22: Chicago, IL | O22: Telecaster twang; drawl; storytelling; anthemic; harmonized guitars | P22: Chris Walla-produced fifth LP blending alt-rock, country twang and a little emo, the fullest version of Ratboys' patient songwriting. Highlights include the elegiac 'Black Earth, WI' and the wired 'Morning Zoo'. | Q22: Sounds of a piece with Wednesday and MJ Lenderman in the current wave of twangy Midwest/Southern indie rock. | R22: Inferred | S22: Black Earth, WI; Morning Zoo; The Window | T22: Essential | V22: https://www.noexpectations.fyi/p/julia-steiner-ratboys-the-window-interview | W22: Y | X22: https://en.wikipedia.org/wiki/Ratboys https://www.noexpectations.fyi/p/best-new-tracks-july-2023 https://ratboys.bandcamp.com/music | Y22: High
A23: A0022 | B23: Squirrel Flower | C23: Tomorrow's Fire | D23: 2023 | E23: LP | F23: Polyvinyl | G23: =IF(LEFT(I23,3)="R1 ","L6",IF(D23>=2014,"L1",IF(D23>=1998,"L2",IF(D23>=1987,"L3",IF(D23>=1978,"L4",IF(D23>=1965,"L5","L6")))))) -> L1 | H23: =IFERROR(INDEX(Lanes!$C$2:$C$60,MATCH(LEFT(I23,FIND(" ",I23)-1),Lanes!$A$2:$A$60,0)),"?") -> Core | I23: C1 Indie twang / yallternative | K23: Crossover | L23: The Northeast | M23: Chicago, IL / Iowa | O23: Crazy Horse fuzz; drawl; anthemic; storytelling; feedback | P23: Ella Williams's fourth Squirrel Flower album is dense, expansive guitar rock about work, anxiety and climate dread, cut with Alex Farrar (MJ Lenderman, Wednesday) and players from Wednesday, Bon Iver and the War on Drugs. | Q23: Farrar's production ties Squirrel Flower directly into the Asheville Drop of Sun network that also produced Wednesday and MJ Lenderman. | R23: Documented | S23: Intheskatepark; Alley Light; When a Plant Is Dying | T23: Recommended | V23: https://www.noexpectations.fyi/p/squirrel-flower-tomorrows-fire-interview | X23: https://en.wikipedia.org/wiki/Squirrel_Flower https://www.noexpectations.fyi/p/squirrel-flower-tomorrows-fire-interview https://www.polyvinylrecords.com/products/squirrel-flower-tomorrows-fire | Y23: High
A24: A0023 | B24: Brown Horse | C24: Reservoir | D24: 2024 | E24: LP | F24: Loose Music | G24: =IF(LEFT(I24,3)="R1 ","L6",IF(D24>=2014,"L1",IF(D24>=1998,"L2",IF(D24>=1987,"L3",IF(D24>=1978,"L4",IF(D24>=1965,"L5","L6")))))) -> L1 | H24: =IFERROR(INDEX(Lanes!$C$2:$C$60,MATCH(LEFT(I24,FIND(" ",I24)-1),Lanes!$A$2:$A$60,0)),"?") -> Core | I24: C1 Indie twang / yallternative | K24: Alt-country | L24: The UK, Ireland and Canada | M24: Norwich, UK | O24: pedal steel; slide guitar; drawl; small-town; storytelling | P24: Debut LP from Norwich's Brown Horse: stark, road-worn alt-country with twangy guitars and weary, shared vocals. It establishes the band's slow-burning songwriting before the fuller sound of All the Right Weaknesses. | Q24: A UK band that sounds steeped in the American alt-country/Crazy Horse tradition, close in spirit to Wednesday and Greg Freeman. | R24: Inferred | S24: Stealing Horses; Reservoir; Shoot Back | T24: Recommended | W24: Y | X24: https://brownhorse.bandcamp.com/album/reservoir https://newreleases.discogs.com/release/201904-brown-horse-reservoir | Y24: High
A25: A0024 | B25: The Clearwater Swimmers | C25: The Clearwater Swimmers | D25: 2024 | E25: LP | F25: New Martian Records | G25: =IF(LEFT(I25,3)="R1 ","L6",IF(D25>=2014,"L1",IF(D25>=1998,"L2",IF(D25>=1987,"L3",IF(D25>=1978,"L4",IF(D25>=1965,"L5","L6")))))) -> L1 | H25: =IFERROR(INDEX(Lanes!$C$2:$C$60,MATCH(LEFT(I25,FIND(" ",I25)-1),Lanes!$A$2:$A$60,0)),"?") -> Core | I25: C1 Indie twang / yallternative | J25: C8 | K25: Country rock | L25: The Northeast | M25: Queens, NY | O25: Crazy Horse fuzz; hushed; storytelling; small-town; drawl | P25: The Clearwater Swimmers' self-titled debut flips between hushed intimacy and full electric-guitar surges, recalling Neil Young's Harvest Moon and Jason Molina's Magnolia Electric Co. It suits listeners who like quiet folk that can suddenly turn loud. | Q25: Sounds indebted to the Neil Young/Crazy Horse and Molina/Magnolia Electric Co. lineage that defines indie twang. | R25: Inferred | S25: Heaven is A Bar; Gas Food Lodging; Weathervane | T25: Recommended | V25: https://www.noexpectations.fyi/p/new-indie-rock-albums-sept-oct-merce-lemon-lutalo | X25: https://www.rootshighway.it/outtakes/2024/swimmers.htm https://rockingmagpie.wordpress.com/2024/10/04/clearwater-swimmers-clearwater-swimmers/ | Y25: High
A26: A0025 | B26: David Nance & Mowed Sound | C26: David Nance & Mowed Sound | D26: 2024 | E26: LP | F26: Third Man Records | G26: =IF(LEFT(I26,3)="R1 ","L6",IF(D26>=2014,"L1",IF(D26>=1998,"L2",IF(D26>=1987,"L3",IF(D26>=1978,"L4",IF(D26>=1965,"L5","L6")))))) -> L1 | H26: =IFERROR(INDEX(Lanes!$C$2:$C$60,MATCH(LEFT(I26,FIND(" ",I26)-1),Lanes!$A$2:$A$60,0)),"?") -> Core | I26: C1 Indie twang / yallternative | K26: Crossover | L26: Chicago and the Midwest | M26: Omaha, NE | O26: Crazy Horse fuzz; long solos; drawl; rowdy; feedback | P26: Nance's record with his full band Mowed Sound: interlocking, jammed-out guitar rock that sounds deeply indebted to Crazy Horse. Long, ragged solos and a heavy, loose rhythm section push the songs well past the three-minute mark. | Q26: Sounds like a Midwest continuation of the Crazy Horse guitar-jam trunk line that also runs through Wednesday and MJ Lenderman. | R26: Inferred | S26: Mock the Hours; Tumbleweed; Side Eyed Sam | T26: Recommended | V26: https://www.noexpectations.fyi/p/the-most-anticipated-albums-of-2024 | X26: https://davidnance.bandcamp.com/album/david-nance-mowed-sound https://www.noexpectations.fyi/p/the-most-anticipated-albums-of-2024 | Y26: High
A27: A0026 | B27: Dialup Ghost | C27: May You Live Forever in Cowboy Heaven | D27: 2024 | E27: LP | F27: Self-released | G27: =IF(LEFT(I27,3)="R1 ","L6",IF(D27>=2014,"L1",IF(D27>=1998,"L2",IF(D27>=1987,"L3",IF(D27>=1978,"L4",IF(D27>=1965,"L5","L6")))))) -> L1 | H27: =IFERROR(INDEX(Lanes!$C$2:$C$60,MATCH(LEFT(I27,FIND(" ",I27)-1),Lanes!$A$2:$A$60,0)),"?") -> Core | I27: C1 Indie twang / yallternative | K27: Cowpunk | L27: The South | M27: Nashville, TN | O27: fiddle; drawl; rowdy; small-town; funny-sad | P27: A Nashville band's ramshackle, woozy-twang record with fiddle and Built to Spill/Elephant 6-style energy. The songs are loose and wordy, with homemade production and big, sloppy singalong moments. | Q27: Sounds indebted to Neil Young and Silver Jews, sitting within the same trunk lines as the rest of the Core. | R27: Inferred | S27: Rhinestones; Shovel Song; Forever in Heaven | T27: Deep cut | V27: https://www.noexpectations.fyi/p/4-great-albums-from-2024 | X27: https://dialupghost.bandcamp.com/album/may-you-live-forever-in-cowboy-heaven | Y27: Medium
A28: A0027 | B28: Good Looks | C28: Lived Here For A While | D28: 2024 | E28: LP | F28: Keeled Scales | G28: =IF(LEFT(I28,3)="R1 ","L6",IF(D28>=2014,"L1",IF(D28>=1998,"L2",IF(D28>=1987,"L3",IF(D28>=1978,"L4",IF(D28>=1965,"L5","L6")))))) -> L1 | H28: =IFERROR(INDEX(Lanes!$C$2:$C$60,MATCH(LEFT(I28,FIND(" ",I28)-1),Lanes!$A$2:$A$60,0)),"?") -> Core | I28: C1 Indie twang / yallternative | K28: Crossover | L28: Texas and Oklahoma | M28: Austin, TX | O28: Telecaster twang; anthemic; drawl; storytelling; long solos | P28: Good Looks' second LP: conversational, big-hearted indie rock with big riffs and a steady, resilient mood. Its plainspoken storytelling about working people sits over warm, twangy guitars. | Q28: Continues the band's blue-collar Austin storytelling from Bummer Year into a bigger, more electric sound. | R28: Documented | S28: If It's Gone; Can You See Me Tonight?; Day of Judgment | T28: Essential | V28: https://www.noexpectations.fyi/p/the-60-best-albums-of-2024 | X28: https://goodlooksband.bandcamp.com/album/lived-here-for-a-while https://www.noexpectations.fyi/p/the-30-best-albums-of-2024-so-far | Y28: High
A29: A0028 | B29: Merce Lemon | C29: Watch Me Drive Them Dogs Wild | D29: 2024 | E29: LP | F29: Self-released | G29: =IF(LEFT(I29,3)="R1 ","L6",IF(D29>=2014,"L1",IF(D29>=1998,"L2",IF(D29>=1987,"L3",IF(D29>=1978,"L4",IF(D29>=1965,"L5","L6")))))) -> L1 | H29: =IFERROR(INDEX(Lanes!$C$2:$C$60,MATCH(LEFT(I29,FIND(" ",I29)-1),Lanes!$A$2:$A$60,0)),"?") -> Core | I29: C1 Indie twang / yallternative | K29: Crossover | L29: The Northeast | M29: Pittsburgh, PA | O29: pedal steel; feedback; drawl; storytelling; small-town | P29: The Pittsburgh songwriter's breakout LP: warbling steel and outlaw-tinged guitars swelling into feedback-heavy catharsis. Her songs of loss, land and family community are sung in a clear, plain voice that the band slowly overwhelms. | Q29: Sounds close to the Asheville indie-twang of Florry and Wednesday. | R29: Inferred | S29: Backyard Lover; Rain; Crow | T29: Recommended | V29: https://www.noexpectations.fyi/p/the-60-best-albums-of-2024 | X29: https://mercelemon.bandcamp.com/album/watch-me-drive-them-dogs-wild https://www.noexpectations.fyi/p/new-indie-rock-albums-sept-oct-merce-lemon-lutalo | Y29: High
A30: A0029 | B30: MJ Lenderman | C30: Manning Fireworks | D30: 2024 | E30: LP | F30: ANTI- | G30: =IF(LEFT(I30,3)="R1 ","L6",IF(D30>=2014,"L1",IF(D30>=1998,"L2",IF(D30>=1987,"L3",IF(D30>=1978,"L4",IF(D30>=1965,"L5","L6")))))) -> L1 | H30: =IFERROR(INDEX(Lanes!$C$2:$C$60,MATCH(LEFT(I30,FIND(" ",I30)-1),Lanes!$A$2:$A$60,0)),"?") -> Core | I30: C1 Indie twang / yallternative | K30: Crossover | L30: The Carolinas | M30: Asheville, NC | N30: Asheville | O30: Crazy Horse fuzz; pedal steel; deadpan; funny-sad; long solos | P30: Lenderman's breakthrough on a bigger indie label: warmer production, pedal steel and long, unhurried guitar solos wrapped around some of his sharpest, saddest jokes yet. The songs circle men who can't quite say what they mean, sung in his dry drawl over a loose, Crazy Horse-style band. | Q30: Sounds indebted to Neil Young's guitar sound and the funny-sad Drag City songwriting tradition; released the same year he played a key role on Waxahatchee's Tigers Blood. | R30: Both | S30: She's Leaving You; Wristwatch; Rudolph | T30: Essential | U30: Y | V30: https://www.noexpectations.fyi/p/the-60-best-albums-of-2024 | W30: Y | X30: https://en.wikipedia.org/wiki/MJ_Lenderman https://www.noexpectations.fyi/p/the-60-best-albums-of-2024 https://mjlenderman.bandcamp.com/album/manning-fireworks | Y30: High
A31: A0030 | B31: Real Companion | C31: Nü-metal Heroes | D31: 2024 | E31: LP | F31: Self-released | G31: =IF(LEFT(I31,3)="R1 ","L6",IF(D31>=2014,"L1",IF(D31>=1998,"L2",IF(D31>=1987,"L3",IF(D31>=1978,"L4",IF(D31>=1965,"L5","L6")))))) -> L1 | H31: =IFERROR(INDEX(Lanes!$C$2:$C$60,MATCH(LEFT(I31,FIND(" ",I31)-1),Lanes!$A$2:$A$60,0)),"?") -> Core | I31: C1 Indie twang / yallternative | J31: C2 | K31: Heartland rock | L31: The Carolinas | M31: Boone, NC | N31: Asheville | O31: deadpan; storytelling; small-town; drinking songs; funny-sad | P31: Songs about aging, addiction and small-town North Carolina life, told in long, wry, half-spoken verses that turn dark memories into deadpan jokes. Unhurried heartland-rock backing with warm, fuzzy guitars keeps it plainspoken and barroom-adjacent, for fans of conversational, funny-sad songwriting. | Q31: Sounds close to the Asheville guitar tone of MJ Lenderman's circle, applied to Prine-style conversational storytelling. | R31: Inferred | S31: Great Valley; Piedmont Reason; Hometown Snakes | T31: Deep cut | X31: https://realcompanion.bandcamp.com/album/n-metal-heroes | Y31: Medium
A32: A0031 | B32: Why Bonnie | C32: Wish on the Bone | D32: 2024 | E32: LP | F32: Fire Talk | G32: =IF(LEFT(I32,3)="R1 ","L6",IF(D32>=2014,"L1",IF(D32>=1998,"L2",IF(D32>=1987,"L3",IF(D32>=1978,"L4",IF(D32>=1965,"L5","L6")))))) -> L1 | H32: =IFERROR(INDEX(Lanes!$C$2:$C$60,MATCH(LEFT(I32,FIND(" ",I32)-1),Lanes!$A$2:$A$60,0)),"?") -> Core | I32: C1 Indie twang / yallternative | K32: Crossover | L32: Texas and Oklahoma | M32: Austin, TX (via Houston) | O32: pedal steel; fiddle; drawl; anthemic; close harmonies | P32: Blair Howerton's second Why Bonnie LP: twangy, expansive rock that widens the country-coded debut 90 in November into more cinematic, ambitious soundscapes. Fiddle and harmonies still anchor the quieter moments, while the louder songs swell into big, glossy guitar rock. | Q32: Follows 90 in November, whose country sound sits near Waxahatchee and Wednesday, before opening out toward Broken Social Scene/HAIM-style pop-rock. | R32: Both | S32: Wish On The Bone; Dotted Line; Headlight Sun | T32: Recommended | V32: https://www.noexpectations.fyi/p/new-lps-why-bonnie-bug-club-lia-kohl-sima | X32: https://whybonnie.bandcamp.com/album/wish-on-the-bone https://en.wikipedia.org/wiki/Why_Bonnie | Y32: High
A33: A0032 | B33: Abel | C33: How to Get Away with Nothing | D33: 2025 | E33: LP | F33: Candlepin Records | G33: =IF(LEFT(I33,3)="R1 ","L6",IF(D33>=2014,"L1",IF(D33>=1998,"L2",IF(D33>=1987,"L3",IF(D33>=1978,"L4",IF(D33>=1965,"L5","L6")))))) -> L1 | H33: =IFERROR(INDEX(Lanes!$C$2:$C$60,MATCH(LEFT(I33,FIND(" ",I33)-1),Lanes!$A$2:$A$60,0)),"?") -> Core | I33: C1 Indie twang / yallternative | K33: Alt-country | L33: Chicago and the Midwest | M33: Columbus, OH | O33: jangle; deadpan; drawl; lo-fi; funny-sad | P33: Columbus songwriter Abel's self-lacerating, ramshackle country-jangle LP. It is loud guitar music for quiet people, with jangly guitars, clattering drums and bruised, self-deprecating lyrics. | Q33: Sounds part of the small-label DIY twang network alongside Ohio- and Midwest-based indie-country peers like Spencer Radcliffe. | R33: Inferred | S33: Grass; Loathe; Scarecrow | T33: Recommended | V33: https://www.noexpectations.fyi/p/the-100-best-albums-of-2025 | X33: https://abelcolumbus.bandcamp.com/album/how-to-get-away-with-nothing https://www.noexpectations.fyi/p/best-new-albums-september-2025-big-thief-mae-powell-abel | Y33: High
A34: A0033 | B34: Brown Horse | C34: All The Right Weaknesses | D34: 2025 | E34: LP | F34: Loose Music | G34: =IF(LEFT(I34,3)="R1 ","L6",IF(D34>=2014,"L1",IF(D34>=1998,"L2",IF(D34>=1987,"L3",IF(D34>=1978,"L4",IF(D34>=1965,"L5","L6")))))) -> L1 | H34: =IFERROR(INDEX(Lanes!$C$2:$C$60,MATCH(LEFT(I34,FIND(" ",I34)-1),Lanes!$A$2:$A$60,0)),"?") -> Core | I34: C1 Indie twang / yallternative | K34: Alt-country | L34: The UK, Ireland and Canada | M34: Norwich, UK | O34: pedal steel; slide guitar; drawl; Crazy Horse fuzz; storytelling | P34: Brown Horse's second LP: soaring guitars, blissful pedal steel and earnest vocals melding slacker rock, folk and alt-country. It sits near Greg Freeman, Wednesday and Neil Young in feel, loud but tender. | Q34: Sounds indebted to Lucinda Williams, Jason Molina and Silver Jews; part of the UK's small but active indie-twang scene. | R34: Inferred | S34: Verna Bloom; Wisteria Vine; Dog Rose | T34: Essential | V34: https://www.noexpectations.fyi/p/the-100-best-albums-of-2025 | W34: Y | X34: https://brownhorse.bandcamp.com/album/all-the-right-weaknesses https://www.noexpectations.fyi/p/the-40-best-albums-of-2025-so-far | Y34: High
A35: A0034 | B35: Chico States | C35: I Saw A Galloping Horse Cover No Ground | D35: 2025 | E35: LP | F35: Anything Bagel | G35: =IF(LEFT(I35,3)="R1 ","L6",IF(D35>=2014,"L1",IF(D35>=1998,"L2",IF(D35>=1987,"L3",IF(D35>=1978,"L4",IF(D35>=1965,"L5","L6")))))) -> L1 | H35: =IFERROR(INDEX(Lanes!$C$2:$C$60,MATCH(LEFT(I35,FIND(" ",I35)-1),Lanes!$A$2:$A$60,0)),"?") -> Core | I35: C1 Indie twang / yallternative | K35: Country folk | L35: The Northeast | M35: Maine | O35: pedal steel; drawl; storytelling; small-town; harmonica | P35: Joseph Barresi's Chico States LP: dusky, encyclopedic Americana with pedal steel and scrappy harmonies. It mixes personal minutiae with train-line and travel history, like a homemade folk archive. | Q35: Sounds indebted to Lomax-style folk documentation and cosmic Americana, close to the Northeast's alt-country underground. | R35: Inferred | S35: Out On The Porch Swing; Silver Dagger; Me and Kit Carruthers | T35: Deep cut | V35: https://www.noexpectations.fyi/p/the-100-best-albums-of-2025 | X35: https://chicostates.bandcamp.com/album/i-saw-a-galloping-horse-cover-no-ground https://www.noexpectations.fyi/p/joyer-cistern-flock-of-dimes-chico-states-album-reviews | Y35: High
A36: A0035 | B36: Florry | C36: Sounds Like... | D36: 2025 | E36: LP | F36: Dear Life Records | G36: =IF(LEFT(I36,3)="R1 ","L6",IF(D36>=2014,"L1",IF(D36>=1998,"L2",IF(D36>=1987,"L3",IF(D36>=1978,"L4",IF(D36>=1965,"L5","L6")))))) -> L1 | H36: =IFERROR(INDEX(Lanes!$C$2:$C$60,MATCH(LEFT(I36,FIND(" ",I36)-1),Lanes!$A$2:$A$60,0)),"?") -> Core | I36: C1 Indie twang / yallternative | K36: Alt-country | L36: Burlington, Vermont | M36: Burlington, VT (via Philadelphia) | O36: pedal steel; fiddle; drawl; rowdy; storytelling | P36: Florry's second full-band album: rambunctious barroom twang with Rolling Thunder-style energy alongside quieter, more understated songs. Fiddle, pedal steel and loose group vocals keep it feeling like a party that occasionally sobers up. | Q36: Continues the Dear Life Records run of The Holey Bible; sounds close to the Asheville indie-twang of MJ Lenderman and Wednesday. | R36: Both | S36: Hey Baby; Truck Flipped Over '19; Big Something | T36: Essential | V36: https://www.noexpectations.fyi/p/the-100-best-albums-of-2025 | W36: Y | X36: https://florry.bandcamp.com/album/sounds-like https://www.noexpectations.fyi/p/the-40-best-albums-of-2025-so-far | Y36: High
A37: A0036 | B37: Greg Freeman | C37: Burnover | D37: 2025 | E37: LP | F37: Transgressive | G37: =IF(LEFT(I37,3)="R1 ","L6",IF(D37>=2014,"L1",IF(D37>=1998,"L2",IF(D37>=1987,"L3",IF(D37>=1978,"L4",IF(D37>=1965,"L5","L6")))))) -> L1 | H37: =IFERROR(INDEX(Lanes!$C$2:$C$60,MATCH(LEFT(I37,FIND(" ",I37)-1),Lanes!$A$2:$A$60,0)),"?") -> Core | I37: C1 Indie twang / yallternative | K37: Crossover | L37: Burlington, Vermont | M37: Burlington, VT | N37: Burlington, Vermont | O37: pedal steel; Telecaster twang; storytelling; anthemic; drawl | P37: Freeman's proper label follow-up melds energetic indie rock with an ambling twang and Americana touches. It is explosive and purposeful, with wordy, hooky songwriting that sometimes recalls Elvis Costello. | Q37: Builds on the cult success of I Looked Out and Freeman's place in the Burlington scene alongside Lily Seabird. | R37: Documented | S37: Point and Shoot; Curtain; Gone (Can Mean A Lot of Things) | T37: Essential | V37: https://www.noexpectations.fyi/p/the-100-best-albums-of-2025 | W37: Y | X37: https://gregfreeman.bandcamp.com/album/burnover https://www.noexpectations.fyi/p/the-100-best-albums-of-2025 | Y37: High
A38: A0037 | B38: Oldstar | C38: Of the Highway | D38: 2025 | E38: LP | F38: Self-released | G38: =IF(LEFT(I38,3)="R1 ","L6",IF(D38>=2014,"L1",IF(D38>=1998,"L2",IF(D38>=1987,"L3",IF(D38>=1978,"L4",IF(D38>=1965,"L5","L6")))))) -> L1 | H38: =IFERROR(INDEX(Lanes!$C$2:$C$60,MATCH(LEFT(I38,FIND(" ",I38)-1),Lanes!$A$2:$A$60,0)),"?") -> Core | I38: C1 Indie twang / yallternative | K38: Alt-country | L38: The South | M38: Panama City Beach, FL | O38: Telecaster twang; fiddle; drawl; small-town; road songs | P38: Oldstar's studio debut: raucous, meaty overdriven country rock with fiddle and outlaw phrasing, recalling Lenderman, Steve Earle, Drive-By Truckers and Being There-era Wilco. A concept record about highway wandering, bar to bar. | Q38: Sounds indebted to outlaw country and Wilco's Being There; close in spirit to young Southern indie-twang songwriters like Thomas Dollbaum and i26connector. | R38: Inferred | S38: Lowland; California; Honkeytonk | T38: Recommended | V38: https://www.noexpectations.fyi/p/the-100-best-albums-of-2025 | W38: Y | X38: https://oldst4r.bandcamp.com/album/of-the-highway https://www.noexpectations.fyi/p/the-40-best-albums-of-2025-so-far | Y38: High
A39: A0038 | B39: Snocaps | C39: Snocaps | D39: 2025 | E39: Collab | F39: ANTI- | G39: =IF(LEFT(I39,3)="R1 ","L6",IF(D39>=2014,"L1",IF(D39>=1998,"L2",IF(D39>=1987,"L3",IF(D39>=1978,"L4",IF(D39>=1965,"L5","L6")))))) -> L1 | H39: =IFERROR(INDEX(Lanes!$C$2:$C$60,MATCH(LEFT(I39,FIND(" ",I39)-1),Lanes!$A$2:$A$60,0)),"?") -> Core | I39: C1 Indie twang / yallternative | J39: C5 | K39: Indie folk | L39: The Carolinas | M39: Asheville, NC | O39: close harmonies; jangle; duets; breezy; harmonized guitars | P39: A surprise-released full-band project pairing Katie and Allison Crutchfield (Waxahatchee, P.S. Eliot) with MJ Lenderman and Brad Cook. It is warm, harmony-driven indie rock with country edges rather than a solo Lenderman vehicle, built around the sisters' blended voices. | Q39: Connects Lenderman's Asheville circle directly to Waxahatchee's through shared members. | R39: Documented | S39: Coast; Heathcliff; Wasteland | T39: Recommended | X39: https://www.anti.com/news/snocaps-new-group-from-allison-katie-crutchfield-feat-mj-lenderman-brad-coo/ https://www.discogs.com/artist/16855249-Snocaps https://snocaps.bandcamp.com/ ; https://en.wikipedia.org/wiki/Snocaps_(album) | Y39: High
A40: A0039 | B40: Spencer Radcliffe | C40: Ohio Vision | D40: 2025 | E40: LP | F40: Orindal Records | G40: =IF(LEFT(I40,3)="R1 ","L6",IF(D40>=2014,"L1",IF(D40>=1998,"L2",IF(D40>=1987,"L3",IF(D40>=1978,"L4",IF(D40>=1965,"L5","L6")))))) -> L1 | H40: =IFERROR(INDEX(Lanes!$C$2:$C$60,MATCH(LEFT(I40,FIND(" ",I40)-1),Lanes!$A$2:$A$60,0)),"?") -> Core | I40: C1 Indie twang / yallternative | K40: Crossover | L40: Chicago and the Midwest | M40: Ohio (formerly Chicago) | O40: Telecaster twang; drawl; deadpan; small-town; long solos | P40: Radcliffe's twangy return: fuzzy, hypnotic rock and rambling jams chronicling a return home to Ohio. It is propulsive and relaxed by turns, Midwest indie rock with a country lean. | Q40: Sounds of a piece with the current wave of Midwest indie-twang alongside Ratboys and i26connector. | R40: Inferred | S40: Shield and Sword; Daily Driver; Portage Rising | T40: Recommended | V40: https://www.noexpectations.fyi/p/the-100-best-albums-of-2025 | W40: Y | X40: https://spencerradcliffe.bandcamp.com/album/ohio-vision https://www.noexpectations.fyi/p/spencer-radcliffe-sword-ii-stella-donnelly-saintseneca-review | Y40: High
A41: A0040 | B41: Thomas Dollbaum | C41: Drive All Night | D41: 2025 | E41: EP | F41: Dear Life Records | G41: =IF(LEFT(I41,3)="R1 ","L6",IF(D41>=2014,"L1",IF(D41>=1998,"L2",IF(D41>=1987,"L3",IF(D41>=1978,"L4",IF(D41>=1965,"L5","L6")))))) -> L1 | H41: =IFERROR(INDEX(Lanes!$C$2:$C$60,MATCH(LEFT(I41,FIND(" ",I41)-1),Lanes!$A$2:$A$60,0)),"?") -> Core | I41: C1 Indie twang / yallternative | K41: Alt-country | L41: The South | M41: New Orleans, LA | O41: drawl; baritone; storytelling; small-town; hushed | P41: A short EP of hushed, tragic story-songs set on Florida backroads. It works as a brief bridge between Wellswood and Birds of Paradise, with Dollbaum's baritone close to the mic over quiet guitar. | Q41: Brings Dollbaum's alt-country storytelling into the Dear Life Records fold alongside Florry. | R41: Documented | S41: Drive All Night; Angus Valley; Lives of Saints | T41: Deep cut | W41: Y | X41: https://thomasdollbaum.bandcamp.com/album/drive-all-night | Y41: Medium
A42: A0041 | B42: Brown Horse | C42: Total Dive | D42: 2026 | E42: LP | F42: Fluff and Gravy Records | G42: =IF(LEFT(I42,3)="R1 ","L6",IF(D42>=2014,"L1",IF(D42>=1998,"L2",IF(D42>=1987,"L3",IF(D42>=1978,"L4",IF(D42>=1965,"L5","L6")))))) -> L1 | H42: =IFERROR(INDEX(Lanes!$C$2:$C$60,MATCH(LEFT(I42,FIND(" ",I42)-1),Lanes!$A$2:$A$60,0)),"?") -> Core | I42: C1 Indie twang / yallternative | K42: Alt-country | L42: The UK, Ireland and Canada | M42: Norwich, UK | O42: pedal steel; Crazy Horse fuzz; drawl; storytelling; anthemic | P42: Brown Horse's third LP: brooding, twangy guitar rock with fuzzy riffs, pedal steel and country-rock arrangements. It keeps the band's weary vocals and slow-building dynamics but leans heavier than before. | Q42: Continues the band's alt-country arc from Reservoir and All the Right Weaknesses. | R42: Documented | S42: Sorrow Reigns; Twisters; Heart Of The Country | T42: Recommended | V42: https://www.noexpectations.fyi/p/the-40-best-albums-of-2026-so-far | W42: Y | X42: https://brownhorse.bandcamp.com/album/total-dive | Y42: Medium
A43: A0042 | B43: Convinced Friend | C43: Nowhere Songs | D43: 2026 | E43: LP | F43: Self-released | G43: =IF(LEFT(I43,3)="R1 ","L6",IF(D43>=2014,"L1",IF(D43>=1998,"L2",IF(D43>=1987,"L3",IF(D43>=1978,"L4",IF(D43>=1965,"L5","L6")))))) -> L1 | H43: =IFERROR(INDEX(Lanes!$C$2:$C$60,MATCH(LEFT(I43,FIND(" ",I43)-1),Lanes!$A$2:$A$60,0)),"?") -> Core | I43: C1 Indie twang / yallternative | K43: Alt-country | L43: The Northeast | M43: Providence, RI | O43: pedal steel; drawl; storytelling; small-town; close harmonies | P43: A.S. Wilson's second Convinced Friend LP: compact, forceful tracks fusing serene twang with apocalyptic indie rock. The songs reflect on home, loss and a changing coastline, moving from calm to loud without warning. | Q43: Sounds close to the Northeast slowcore/twang orbit of Horse Jumper of Love and Friendship. | R43: Inferred | S43: Big Score; On Fire; Robitussin | T43: Recommended | V43: https://www.noexpectations.fyi/p/convinced-friend-dos-santos-graham-hunt | X43: https://convincedfriend.bandcamp.com/album/nowhere-songs | Y43: Medium
A44: A0043 | B44: Greg Freeman | C44: All Set the Bone | D44: 2026 | E44: LP | F44: Transgressive | G44: =IF(LEFT(I44,3)="R1 ","L6",IF(D44>=2014,"L1",IF(D44>=1998,"L2",IF(D44>=1987,"L3",IF(D44>=1978,"L4",IF(D44>=1965,"L5","L6")))))) -> L1 | H44: =IFERROR(INDEX(Lanes!$C$2:$C$60,MATCH(LEFT(I44,FIND(" ",I44)-1),Lanes!$A$2:$A$60,0)),"?") -> Core | I44: C1 Indie twang / yallternative | K44: Crossover | L44: Burlington, Vermont | M44: Burlington, VT | N44: Burlington, Vermont | O44: pedal steel; long solos; storytelling; political; anthemic | P44: Freeman's third full-length pushes his indie-twang songwriting toward heavier, more fractured arrangements. Pedal steel still runs through it, but the guitars are knottier and louder. | Q44: A more ambitious, geographically displaced follow-up to Burnover, reflecting Freeman's move from Vermont odd jobs to full-time touring musician. | R44: Documented | S44: Cahokia; Indu; Hail Mary | T44: Recommended | V44: https://www.noexpectations.fyi/p/tommy-goodroad-swapmeet-kevin-copeland | W44: Y | X44: https://gregfreeman.bandcamp.com/album/all-set-the-bone https://www.noexpectations.fyi/p/tommy-goodroad-swapmeet-kevin-copeland | Y44: High
A45: A0044 | B45: i26connector | C45: i26connector | D45: 2026 | E45: LP | F45: Self-released | G45: =IF(LEFT(I45,3)="R1 ","L6",IF(D45>=2014,"L1",IF(D45>=1998,"L2",IF(D45>=1987,"L3",IF(D45>=1978,"L4",IF(D45>=1965,"L5","L6")))))) -> L1 | H45: =IFERROR(INDEX(Lanes!$C$2:$C$60,MATCH(LEFT(I45,FIND(" ",I45)-1),Lanes!$A$2:$A$60,0)),"?") -> Core | I45: C1 Indie twang / yallternative | J45: C9 | K45: Southern rock | L45: The Carolinas | M45: Asheville, NC | N45: Asheville | O45: pedal steel; drawl; small-town; storytelling; anthemic | P45: An Asheville project's debut, self-tagged 'Emo Southern Rock': wailing pedal steel and booming riffs under conversational lyrics. The songs swing from barroom talk to apocalyptic brooding. | Q45: Sounds close to the Asheville scene around MJ Lenderman and Wednesday, blending twangy Southern rock with an emo-adjacent intensity. | R45: Inferred | S45: I-26 Connector; Bethel; World Champion | T45: Recommended | V45: https://www.noexpectations.fyi/p/i26connector-ellie-o-neill-red-pk-amaya-pena | W45: Y | X45: https://i26connector.bandcamp.com/album/i26connector https://www.noexpectations.fyi/p/the-40-best-albums-of-2026-so-far | Y45: High
A46: A0045 | B46: Kevin Copeland | C46: Only Love Songs | D46: 2026 | E46: LP | F46: Self-released | G46: =IF(LEFT(I46,3)="R1 ","L6",IF(D46>=2014,"L1",IF(D46>=1998,"L2",IF(D46>=1987,"L3",IF(D46>=1978,"L4",IF(D46>=1965,"L5","L6")))))) -> L1 | H46: =IFERROR(INDEX(Lanes!$C$2:$C$60,MATCH(LEFT(I46,FIND(" ",I46)-1),Lanes!$A$2:$A$60,0)),"?") -> Core | I46: C1 Indie twang / yallternative | K46: Country folk | L46: Burlington, Vermont | M46: Burlington, VT | N46: Burlington, Vermont | O46: Telecaster twang; drawl; fingerpicked acoustic; funny-sad; storytelling | P46: Kevin Copeland's solo debut: punchy, twangy pop-rock and winsome folk. 'That's All Over Now' is an outright country barnstormer, while 'MONEY' leans into a bluesy stomp. | Q46: Sounds part of the Vermont/Northeast indie-folk-to-twang orbit of Greg Freeman and Lily Seabird. | R46: Inferred | S46: That's All Over Now; Trains and Angels; MONEY | T46: Deep cut | V46: https://www.noexpectations.fyi/p/tommy-goodroad-swapmeet-kevin-copeland | X46: https://kevincopeland.bandcamp.com/album/only-love-songs | Y46: Medium
A47: A0046 | B47: Ovven | C47: Gnawing at the Cord | D47: 2026 | E47: LP | F47: Self-released | G47: =IF(LEFT(I47,3)="R1 ","L6",IF(D47>=2014,"L1",IF(D47>=1998,"L2",IF(D47>=1987,"L3",IF(D47>=1978,"L4",IF(D47>=1965,"L5","L6")))))) -> L1 | H47: =IFERROR(INDEX(Lanes!$C$2:$C$60,MATCH(LEFT(I47,FIND(" ",I47)-1),Lanes!$A$2:$A$60,0)),"?") -> Core | I47: C1 Indie twang / yallternative | K47: Alt-country | L47: The South | M47: Nashville, TN | O47: Crazy Horse fuzz; pedal steel; drawl; small-town; funny-sad | P47: Owen Burton's debut as Ovven: a fuzz-guitar alt-country record with loud, driving arrangements and a drawled, plainspoken voice. It suits listeners who like Crazy Horse-style guitar under country song shapes. | Q47: Sounds close to the Asheville-adjacent indie-twang of Wednesday and MJ Lenderman. | R47: Inferred | S47: Abbreviated; Dishes; Crows | T47: Recommended | W47: Y | X47: https://ovven.bandcamp.com/album/gnawing-at-the-cord | Y47: Medium
A48: A0047 | B48: Ratboys | C48: Singin' to an Empty Chair | D48: 2026 | E48: LP | F48: New West Records | G48: =IF(LEFT(I48,3)="R1 ","L6",IF(D48>=2014,"L1",IF(D48>=1998,"L2",IF(D48>=1987,"L3",IF(D48>=1978,"L4",IF(D48>=1965,"L5","L6")))))) -> L1 | H48: =IFERROR(INDEX(Lanes!$C$2:$C$60,MATCH(LEFT(I48,FIND(" ",I48)-1),Lanes!$A$2:$A$60,0)),"?") -> Core | I48: C1 Indie twang / yallternative | K48: Crossover | L48: Chicago and the Midwest | M48: Chicago, IL | O48: Telecaster twang; anthemic; drawl; harmonized guitars; storytelling | P48: Ratboys' latest LP: massive-sounding, anthemic indie rock with lilting twang and frantic shredding. Julia Steiner's plainspoken voice holds the center while the guitars push the songs toward big, cathartic endings. | Q48: Continues the arc from AOID's quiet twang through The Window's alt-rock/country/emo blend. | R48: Documented | S48: Empty Chair | T48: Recommended | V48: https://www.noexpectations.fyi/p/ratboys-mandy-indiana-ulrika-spacek-bad-bunny | W48: Y | X48: https://en.wikipedia.org/wiki/Ratboys https://www.noexpectations.fyi/p/the-40-best-albums-of-2026-so-far | Y48: High
A49: A0048 | B49: Thomas Dollbaum | C49: Birds of Paradise | D49: 2026 | E49: LP | F49: Dear Life Records | G49: =IF(LEFT(I49,3)="R1 ","L6",IF(D49>=2014,"L1",IF(D49>=1998,"L2",IF(D49>=1987,"L3",IF(D49>=1978,"L4",IF(D49>=1965,"L5","L6")))))) -> L1 | H49: =IFERROR(INDEX(Lanes!$C$2:$C$60,MATCH(LEFT(I49,FIND(" ",I49)-1),Lanes!$A$2:$A$60,0)),"?") -> Core | I49: C1 Indie twang / yallternative | K49: Alt-country | L49: The South | M49: New Orleans, LA | O49: drawl; baritone; storytelling; Southern gothic; close harmonies | P49: Dollbaum's second LP: roaring Americana shading into tender folk, sung in a rangy, raspy baritone with strong harmonies. It plays like a goodbye letter to lost loved ones, set among Florida's pine flatwoods. | Q49: Sounds indebted to Townes Van Zandt and Jason Molina while stepping out of their shadow. | R49: Inferred | S49: Visitation; Rabbits; Coyote | T49: Essential | V49: https://www.noexpectations.fyi/p/the-40-best-albums-of-2026-so-far | W49: Y | X49: https://thomasdollbaum.bandcamp.com/album/birds-of-paradise | Y49: Medium
A50: A0049 | B50: Twisted Teens | C50: Florida Water Blues | D50: 2026 | E50: LP | F50: Self-released | G50: =IF(LEFT(I50,3)="R1 ","L6",IF(D50>=2014,"L1",IF(D50>=1998,"L2",IF(D50>=1987,"L3",IF(D50>=1978,"L4",IF(D50>=1965,"L5","L6")))))) -> L1 | H50: =IFERROR(INDEX(Lanes!$C$2:$C$60,MATCH(LEFT(I50,FIND(" ",I50)-1),Lanes!$A$2:$A$60,0)),"?") -> Core | I50: C1 Indie twang / yallternative | K50: Cowpunk | L50: The South | M50: New Orleans, LA | O50: drawl; rowdy; small-town; storytelling; road songs | P50: New Orleans band's 13-song LP steeped in Gulf Coast heat and road-worn twang; loose, rowdy cowpunk energy carried across tracks like the title cut and 'Swamp'. | Q50: Part of the current New Orleans indie-twang scene alongside Thomas Dollbaum, touring with Kurt Vile. | R50: Inferred | S50: Florida Water Blues; Swamp; Javelina | T50: Deep cut | W50: Y | X50: https://twistedteens.bandcamp.com/album/florida-water-blues | Y50: Medium
A51: A0050 | B51: Wild Pink | C51: Still Coming Down | D51: 2026 | E51: LP | F51: Fire Talk | G51: =IF(LEFT(I51,3)="R1 ","L6",IF(D51>=2014,"L1",IF(D51>=1998,"L2",IF(D51>=1987,"L3",IF(D51>=1978,"L4",IF(D51>=1965,"L5","L6")))))) -> L1 | H51: =IFERROR(INDEX(Lanes!$C$2:$C$60,MATCH(LEFT(I51,FIND(" ",I51)-1),Lanes!$A$2:$A$60,0)),"?") -> Core | I51: C1 Indie twang / yallternative | K51: Crossover | L51: The Northeast | M51: Brooklyn/Queens, NY | O51: pedal steel; drawl; anthemic; storytelling; small-town | P51: Wild Pink's most twang-coded record: driving, intense indie rock with pedal steel threading through the arrangements. Its lyrics about contemporary malaise are searing, funny and wrenching by turns. | Q51: Sounds like Wild Pink's turn toward the Core indie-twang sound; ruled into C1 as a specific stylistic pivot rather than the band's whole catalogue. | R51: Inferred | S51: Box Store; Round Of Applause At The End Of The World; Still Coming Down | T51: Recommended | V51: https://www.noexpectations.fyi/p/wild-pink-squirrel-flower-paul-spring-brennan-wedl | X51: https://wildpink.bandcamp.com/album/still-coming-down https://en.wikipedia.org/wiki/Wild_Pink | Y51: High
A52: A0051 | B52: Advance Base | C52: Nephew in the Wild | D52: 2015 | E52: LP | F52: Orindal Records | G52: =IF(LEFT(I52,3)="R1 ","L6",IF(D52>=2014,"L1",IF(D52>=1998,"L2",IF(D52>=1987,"L3",IF(D52>=1978,"L4",IF(D52>=1965,"L5","L6")))))) -> L1 | H52: =IFERROR(INDEX(Lanes!$C$2:$C$60,MATCH(LEFT(I52,FIND(" ",I52)-1),Lanes!$A$2:$A$60,0)),"?") -> Core | I52: C2 Barroom storytellers and deadpan songwriters | K52: Country folk | L52: Chicago and the Midwest | M52: Chicago, IL | O52: drum machine; deadpan; funny-sad; small-town; bleak | P52: Owen Ashworth's post-Casiotone project sets deadpan, plainly sung short stories about Michigan, Christmas and lost people over minimal drum machine and synth. The songs are small and exact, with the quiet electronics leaving the narratives in front. | Q52: Carries the deadpan storytelling of the Drag City school (Silver Jews) into Ashworth's own Orindal Records orbit, following directly from his Casiotone for the Painfully Alone records. | R52: Both | S52: Christmas in Dearborn; Nephew in the Wild; Kitty Winn | T52: Recommended | X52: https://orindalrecords.bandcamp.com/music https://advancebase.bandcamp.com/album/nephew-in-the-wild | Y52: High
A53: A0052 | B53: Daughn Gibson | C53: Carnation | D53: 2015 | E53: LP | F53: Sub Pop | G53: =IF(LEFT(I53,3)="R1 ","L6",IF(D53>=2014,"L1",IF(D53>=1998,"L2",IF(D53>=1987,"L3",IF(D53>=1978,"L4",IF(D53>=1965,"L5","L6")))))) -> L1 | H53: =IFERROR(INDEX(Lanes!$C$2:$C$60,MATCH(LEFT(I53,FIND(" ",I53)-1),Lanes!$A$2:$A$60,0)),"?") -> Core | I53: C2 Barroom storytellers and deadpan songwriters | K53: Country folk | L53: The Northeast | M53: Carlisle, PA | O53: baritone; drum machine; storytelling; bleak; drawl | P53: The former Pearls and Brass drummer's third album drapes his cavernous, deadpan baritone over sampled loops and drum machines rather than a bar band. Its storytelling core of plainspoken, dark, small-town character studies fits the same funny-sad lineage as his songwriting peers. | Q53: Follows All Hell (2012) and Me Moan (2013), both pre-2014 and outside this lane's window; Carnation extends his baritone-narrator style into a more electronic production. | R53: Documented | S53: Daddy I Cut My Hair; Shatter You Through; Bled to Death | T53: Recommended | W53: Y | X53: https://en.wikipedia.org/wiki/Daughn_Gibson https://www.subpop.com/releases/daughn_gibson/carnation | Y53: High
A54: A0053 | B54: State Champion | C54: Fantasy Error | D54: 2015 | E54: LP | F54: Sophomore Lounge | G54: =IF(LEFT(I54,3)="R1 ","L6",IF(D54>=2014,"L1",IF(D54>=1998,"L2",IF(D54>=1987,"L3",IF(D54>=1978,"L4",IF(D54>=1965,"L5","L6")))))) -> L1 | H54: =IFERROR(INDEX(Lanes!$C$2:$C$60,MATCH(LEFT(I54,FIND(" ",I54)-1),Lanes!$A$2:$A$60,0)),"?") -> Core | I54: C2 Barroom storytellers and deadpan songwriters | K54: Alt-country | L54: The South | M54: Louisville, KY | N54: Louisville and Sophomore Lounge | O54: deadpan; drawl; storytelling; fiddle; banjo | P54: A punked-up country record steeped in Louisville's weird, unassuming rock scene, with fiddle and banjo scrapping against fuzzy guitars behind Ryan Davis's character sketches of postmasters, coroners and drinkers. It sounds close to Souled American and Palace Brothers, rough and funny. | Q54: Early-period State Champion, before Davis's Roadhouse Band turn; sounds indebted to the Drag City/Palace lineage that runs to Silver Jews and Purple Mountains. | R54: Both | S54: Fantasy Error; Sunbathing I; There Is a Highlight Reel | T54: Recommended | X54: https://sophomorelounge.bandcamp.com/album/state-champion-fantasy-error | Y54: Medium
A55: A0054 | B55: Jonny Fritz | C55: Sweet Creep | D55: 2016 | E55: LP | F55: ATO Records | G55: =IF(LEFT(I55,3)="R1 ","L6",IF(D55>=2014,"L1",IF(D55>=1998,"L2",IF(D55>=1987,"L3",IF(D55>=1978,"L4",IF(D55>=1965,"L5","L6")))))) -> L1 | H55: =IFERROR(INDEX(Lanes!$C$2:$C$60,MATCH(LEFT(I55,FIND(" ",I55)-1),Lanes!$A$2:$A$60,0)),"?") -> Core | I55: C2 Barroom storytellers and deadpan songwriters | K55: Country folk | L55: The South | M55: Nashville, TN | O55: synths; drum machine; drawl; funny-sad; storytelling | P55: Fritz folds synths and drum samples into his unconventional, wisecracking country songwriting, moving past the straighter honky-tonk of Dad Country toward a more hopeful, idiosyncratic sound. Titles like 'Chihuahua Rescue' signal the deadpan comic streak underneath. | Q55: Follows Dad Country (2013); as Jonny Corndawg-turned-Fritz's later work, it sits at the more experimental, funny-sad end of the outlaw-adjacent Nashville scene. | R55: Documented | S55: Are You Thirsty; Stadium Inn; Chihuahua Rescue | T55: Deep cut | X55: https://atorecords.com/releases/jonny-fritz-sweet-creep/ https://open.spotify.com/artist/0dfNZ0xBHU3UipMv5gn9Se | Y55: Medium
A56: A0055 | B56: Dougie Poole | C56: Wideass Highway | D56: 2017 | E56: LP | F56: Self-released | G56: =IF(LEFT(I56,3)="R1 ","L6",IF(D56>=2014,"L1",IF(D56>=1998,"L2",IF(D56>=1987,"L3",IF(D56>=1978,"L4",IF(D56>=1965,"L5","L6")))))) -> L1 | H56: =IFERROR(INDEX(Lanes!$C$2:$C$60,MATCH(LEFT(I56,FIND(" ",I56)-1),Lanes!$A$2:$A$60,0)),"?") -> Core | I56: C2 Barroom storytellers and deadpan songwriters | K56: Alt-country | L56: The Northeast | M56: Brooklyn, NY | O56: drum machine; synths; baritone; deadpan; small-town | P56: Poole's self-released debut, a bedroom-recorded set built from drum machines and synthesizers under twangy vocal melodies, already showing the wry, deadpan lyric style he'd sharpen on later records. Rougher and more lo-fi than what followed, it is a deep cut for fans who want the beginning of the story. | Q56: The starting point for Poole's country-by-way-of-DIY-indie sound that would develop through The Freelancer's Blues and The Rainbow Wheel of Death. | R56: Documented | S56: Don't You Think I'm Funny Anymore?; Less Young but as Dumb; Port Authority Hymn | T56: Deep cut | W56: Y | X56: https://dougiepoole.bandcamp.com/album/wideass-highway | Y56: Medium
A57: A0056 | B57: State Champion | C57: Send Flowers | D57: 2018 | E57: LP | F57: Sophomore Lounge | G57: =IF(LEFT(I57,3)="R1 ","L6",IF(D57>=2014,"L1",IF(D57>=1998,"L2",IF(D57>=1987,"L3",IF(D57>=1978,"L4",IF(D57>=1965,"L5","L6")))))) -> L1 | H57: =IFERROR(INDEX(Lanes!$C$2:$C$60,MATCH(LEFT(I57,FIND(" ",I57)-1),Lanes!$A$2:$A$60,0)),"?") -> Core | I57: C2 Barroom storytellers and deadpan songwriters | K57: Alt-country | L57: The South | M57: Louisville, KY | N57: Louisville and Sophomore Lounge | O57: deadpan; drawl; storytelling; funny-sad; pedal steel | P57: Ryan Davis's main band before his Roadhouse records: loose, twangy full-band arrangements built to carry his dense, surrealist wordplay. Send Flowers is their most fully realized record, with fiddle and ragged guitars under long, funny-sad verses. It sounds like a missing link between Silver Jews and the current Louisville deadpan-songwriter scene. | Q57: Direct predecessor to Ryan Davis & the Roadhouse Band through Davis himself; sounds rooted in the Drag City deadpan lineage. | R57: Both | S57: My Over, My Under; Death Preferences; Lifetime Sentence | T57: Recommended | X57: https://sophomorelounge.bandcamp.com/album/state-champion-send-flowers https://www.discogs.com/master/1963021-State-Champion-Send-Flowers | Y57: High
A58: A0057 | B58: Diva Sweetly | C58: In The Living Room | D58: 2019 | E58: LP | F58: Seal Mountain Records | G58: =IF(LEFT(I58,3)="R1 ","L6",IF(D58>=2014,"L1",IF(D58>=1998,"L2",IF(D58>=1987,"L3",IF(D58>=1978,"L4",IF(D58>=1965,"L5","L6")))))) -> L1 | H58: =IFERROR(INDEX(Lanes!$C$2:$C$60,MATCH(LEFT(I58,FIND(" ",I58)-1),Lanes!$A$2:$A$60,0)),"?") -> Core | I58: C2 Barroom storytellers and deadpan songwriters | J58: C4 | K58: Punk | L58: The Carolinas | M58: Asheville, NC | N58: Asheville | O58: shouted; short songs (under 2 minutes); funny-sad; small-town; drawl | P58: A scrappy pop-punk and emo-pop record with late-'90s-indebted alt-rock energy. It is much more hook-driven and busy than the noise-country of the atlas core, with fast tempos and crowded arrangements. | Q58: Sounds rooted in scrappier punk and emo rather than the storytelling style of the countrygaze bands. | R58: Inferred | S58: Cult; Detox Island | T58: Deep cut | W58: Y | X58: https://en.wikipedia.org/wiki/Karly_Hartzman https://pitchfork.com/reviews/albums/diva-sweetly-in-the-living-room/ https://divasweetly.bandcamp.com/album/in-the-living-room | Y58: High
A59: A0058 | B59: Dougie Poole | C59: The Freelancer's Blues | D59: 2019 | E59: LP | F59: Wharf Cat Records | G59: =IF(LEFT(I59,3)="R1 ","L6",IF(D59>=2014,"L1",IF(D59>=1998,"L2",IF(D59>=1987,"L3",IF(D59>=1978,"L4",IF(D59>=1965,"L5","L6")))))) -> L1 | H59: =IFERROR(INDEX(Lanes!$C$2:$C$60,MATCH(LEFT(I59,FIND(" ",I59)-1),Lanes!$A$2:$A$60,0)),"?") -> Core | I59: C2 Barroom storytellers and deadpan songwriters | K59: Alt-country | L59: The Northeast | M59: Brooklyn, NY | O59: pedal steel; baritone; drawl; funny-sad; small-town | P59: Poole's second LP graduates from bedroom drum-machine country to a full honky-tonk band with wailing pedal steel. It updates classic countrypolitan storytelling for a young, broke, romantically alienated urban narrator, sung in his dry baritone. | Q59: Follows his debut Wideass Highway; sounds like Haggard/Nelson/Kristofferson-style storytelling country moved into an ironic, digital-age idiom. | R59: Both | S59: The Freelancer's Blues; Vaping on the Job; Los Angeles | T59: Recommended | W59: Y | X59: https://dougiepoole.bandcamp.com/album/the-freelancers-blues https://jonathanschenke.com/tag/dougie-poole/ | Y59: High
A60: A0059 | B60: Purple Mountains | C60: Purple Mountains | D60: 2019 | E60: LP | F60: Drag City | G60: =IF(LEFT(I60,3)="R1 ","L6",IF(D60>=2014,"L1",IF(D60>=1998,"L2",IF(D60>=1987,"L3",IF(D60>=1978,"L4",IF(D60>=1965,"L5","L6")))))) -> L1 | H60: =IFERROR(INDEX(Lanes!$C$2:$C$60,MATCH(LEFT(I60,FIND(" ",I60)-1),Lanes!$A$2:$A$60,0)),"?") -> Core | I60: C2 Barroom storytellers and deadpan songwriters | J60: V2 | K60: Alt-country | L60: The South | M60: Chicago, IL | N60: Chicago Drag City | O60: deadpan; funny-sad; storytelling; pedal steel; bleak | P60: David Berman's only album after retiring Silver Jews a decade earlier, made with members of Woods as his backing band, is his most bluntly autobiographical record, its jokes about divorce, depression and aging landing harder for being sung in the same flat, wry voice as ever. Berman died less than a month after its release, days before a scheduled tour, which makes songs like 'All My Happiness Is Gone' retroactively devastating. It stands as the culmination of his songwriting and a touchstone for the deadpan storytellers of this lane. | Q60: David Berman's return after Silver Jews, rooted entirely in the Drag City deadpan lineage that runs from Starlite Walker through this final album. | R60: Documented | S60: All My Happiness Is Gone; Snow Is Falling in Manhattan; Margaritas at the Mall | T60: Essential | W60: Y | X60: https://en.wikipedia.org/wiki/Purple_Mountains_(album) | Y60: Medium
A61: A0060 | B61: Josh Halper | C61: Alrightnik | D61: 2020 | E61: LP | F61: Self-released | G61: =IF(LEFT(I61,3)="R1 ","L6",IF(D61>=2014,"L1",IF(D61>=1998,"L2",IF(D61>=1987,"L3",IF(D61>=1978,"L4",IF(D61>=1965,"L5","L6")))))) -> L1 | H61: =IFERROR(INDEX(Lanes!$C$2:$C$60,MATCH(LEFT(I61,FIND(" ",I61)-1),Lanes!$A$2:$A$60,0)),"?") -> Core | I61: C2 Barroom storytellers and deadpan songwriters | K61: Indie folk | L61: The South | M61: Nashville, TN | O61: fingerpicked acoustic; storytelling; funny-sad; heartbreak | P61: Halper's debut mixes wry self-reflection with intricate fingerpicked instrumentals. Its title, Yiddish slang for a crass nouveau-riche success story, sets up the self-deprecating tone he'd carry into Schlemiel. | Q61: Debut predecessor to Schlemiel; sounds indebted to Elliott Smith and fingerstyle players like Leo Kottke and William Tyler. | R61: Both | S61: Whale In A Field; Who Knows; Honest Feeling | T61: Deep cut | X61: https://joshhalper.bandcamp.com/album/alrightnik https://www.discogs.com/release/16738404-Josh-Halper-Alrightnik | Y61: High
A62: A0061 | B62: Tre Burt | C62: Caught It From the Rye | D62: 2020 | E62: LP | F62: Oh Boy Records | G62: =IF(LEFT(I62,3)="R1 ","L6",IF(D62>=2014,"L1",IF(D62>=1998,"L2",IF(D62>=1987,"L3",IF(D62>=1978,"L4",IF(D62>=1965,"L5","L6")))))) -> L1 | H62: =IFERROR(INDEX(Lanes!$C$2:$C$60,MATCH(LEFT(I62,FIND(" ",I62)-1),Lanes!$A$2:$A$60,0)),"?") -> Core | I62: C2 Barroom storytellers and deadpan songwriters | J62: C5 | K62: Country folk | L62: The West | M62: Sacramento, CA | O62: storytelling; drawl; fingerpicked acoustic; lo-fi; heartbreak | P62: Tre Burt's debut sets talky, literary verses over lo-fi fingerpicked guitar and rootsy production, favoring character sketches and slow-building narrative over hooks. It was independently released in 2019 before John Prine himself signed Burt to Oh Boy Records for its wider 2020 release. It plays like a front-porch reading more than a rock show, aimed at listeners who want the Prine lineage of plainspoken, half-sung storytelling. | Q62: Directly anointed by John Prine, who signed Burt to his own Oh Boy Records, tying Burt's storytelling explicitly to the Prine/Tom T. Hall deadpan tradition that feeds the modern barroom-storyteller scene. | R62: Documented | S62: Caught It From the Rye; What Good; Franklin's Tunnel | T62: Recommended | X62: https://treburtmusic.bandcamp.com/album/caught-it-from-the-rye https://en.wikipedia.org/wiki/Tr%C3%A9_Burt | Y62: High
A63: A0062 | B63: Dan Wriggins | C63: Mr. Chill | D63: 2021 | E63: EP | F63: Orindal Records | G63: =IF(LEFT(I63,3)="R1 ","L6",IF(D63>=2014,"L1",IF(D63>=1998,"L2",IF(D63>=1987,"L3",IF(D63>=1978,"L4",IF(D63>=1965,"L5","L6")))))) -> L1 | H63: =IFERROR(INDEX(Lanes!$C$2:$C$60,MATCH(LEFT(I63,FIND(" ",I63)-1),Lanes!$A$2:$A$60,0)),"?") -> Core | I63: C2 Barroom storytellers and deadpan songwriters | K63: Country folk | L63: Philadelphia | M63: Philadelphia, PA | N63: Philadelphia DIY | O63: deadpan; storytelling; hushed; piano; funny-sad | P63: Friendship frontman Dan Wriggins' solo debut strips his prose-poem lyrics down to quiet drums, classical guitar, and a big melodic organ, letting a wounded, deadpan voice turn diary-plain lines into gutting little jokes. Produced by bandmate Michael Cormier, it is five songs of fragmentary memory and small-town Maine imagery delivered with total seriousness despite the title. It works as a quieter, more confessional companion to Friendship's barroom rock. | Q63: Extends the Philadelphia Friendship/Orindal circle's plainspoken, half-spoken songwriting, itself indebted to the Drag City deadpan school of Silver Jews and Smog that runs through the whole 2020s barroom-storyteller scene. | R63: Documented | S63: Mr. Chill; Yellow Bricks; Lucinda on June Bug | T63: Deep cut | X63: https://danwriggins.bandcamp.com/album/mr-chill-2 https://www.discogs.com/search/?q=Dan+Wriggins+Mr+Chill&type=master | Y63: High
A64: A0063 | B64: Tre Burt | C64: You, Yeah, You | D64: 2021 | E64: LP | F64: Oh Boy Records | G64: =IF(LEFT(I64,3)="R1 ","L6",IF(D64>=2014,"L1",IF(D64>=1998,"L2",IF(D64>=1987,"L3",IF(D64>=1978,"L4",IF(D64>=1965,"L5","L6")))))) -> L1 | H64: =IFERROR(INDEX(Lanes!$C$2:$C$60,MATCH(LEFT(I64,FIND(" ",I64)-1),Lanes!$A$2:$A$60,0)),"?") -> Core | I64: C2 Barroom storytellers and deadpan songwriters | K64: Country folk | L64: The South | M64: Sacramento, CA / Durham, NC | O64: storytelling; funny-sad; close harmonies; drawl; heartbreak | P64: Burt's second album narrates a cast of invented heroes and villains with a poet's eye for detail, closer to short fiction than confession. Fuller band arrangements surround his plainspoken, slightly raspy delivery without softening it, for listeners who want storytelling folk with some groove. | Q64: Released on John Prine's Oh Boy Records, keeping Burt's storytelling tied to his mentor Prine and the plainspoken folk tradition he represents. | R64: Documented | S64: Sweet Misery; Carnival Mirror; Tell Mary | T64: Recommended | X64: https://treburtmusic.bandcamp.com/album/you-yeah-you https://en.wikipedia.org/wiki/Tr%C3%A9_Burt | Y64: High
A65: A0064 | B65: Brad Goodall | C65: Live At Levon Helm Studios | D65: 2022 | E65: Live | F65: Self-released | G65: =IF(LEFT(I65,3)="R1 ","L6",IF(D65>=2014,"L1",IF(D65>=1998,"L2",IF(D65>=1987,"L3",IF(D65>=1978,"L4",IF(D65>=1965,"L5","L6")))))) -> L1 | H65: =IFERROR(INDEX(Lanes!$C$2:$C$60,MATCH(LEFT(I65,FIND(" ",I65)-1),Lanes!$A$2:$A$60,0)),"?") -> Core | I65: C2 Barroom storytellers and deadpan songwriters | K65: Country folk | L65: The South | M65: Huntington, WV | O65: piano; live in the room; storytelling; funny-sad; drawl | P65: A live set cut at Levon Helm Studios, revisiting Made In America highlights in a stripped, in-the-room performance. Goodall's rolling piano and wry vocals come across warm and direct, with the room sound left in. | Q65: Live companion to Made In America, recorded shortly after that LP's release. | R65: Documented | S65: Made In America; Changed Man; Hometown | T65: Deep cut | V65: https://www.noexpectations.fyi/p/in-defense-of-live-albums | X65: https://bradgoodall.bandcamp.com/album/live-at-levon-helm-studios https://www.noexpectations.fyi/p/in-defense-of-live-albums | Y65: High
A66: A0065 | B66: Brad Goodall | C66: Made In America | D66: 2022 | E66: LP | F66: Self-released | G66: =IF(LEFT(I66,3)="R1 ","L6",IF(D66>=2014,"L1",IF(D66>=1998,"L2",IF(D66>=1987,"L3",IF(D66>=1978,"L4",IF(D66>=1965,"L5","L6")))))) -> L1 | H66: =IFERROR(INDEX(Lanes!$C$2:$C$60,MATCH(LEFT(I66,FIND(" ",I66)-1),Lanes!$A$2:$A$60,0)),"?") -> Core | I66: C2 Barroom storytellers and deadpan songwriters | K66: Country folk | L66: The South | M66: Huntington, WV | O66: piano; storytelling; funny-sad; small-town; drawl | P66: The ex-Ona keyboardist's debut swaps that band's rock for piano-man virtuosity and Zevon-ish snark. It is funny without playing as a comedy record, closer to plainspoken confession set to rolling piano. | Q66: Follows Goodall's time in Ona; sounds indebted to the Randy Newman/Warren Zevon line of wry piano storytelling. | R66: Both | S66: Made In America; The Ballad of Johnny Vegas; Changed Man | T66: Recommended | V66: https://www.noexpectations.fyi/p/mildred-brad-goodall-youbet-bruce-springsteen-pearla | X66: https://bradgoodall.bandcamp.com/album/made-in-america https://www.noexpectations.fyi/p/mildred-brad-goodall-youbet-bruce-springsteen-pearla | Y66: High
A67: A0066 | B67: Frank Meadows | C67: Dead Weight | D67: 2022 | E67: LP | F67: Ruination Record Co. | G67: =IF(LEFT(I67,3)="R1 ","L6",IF(D67>=2014,"L1",IF(D67>=1998,"L2",IF(D67>=1987,"L3",IF(D67>=1978,"L4",IF(D67>=1965,"L5","L6")))))) -> L1 | H67: =IFERROR(INDEX(Lanes!$C$2:$C$60,MATCH(LEFT(I67,FIND(" ",I67)-1),Lanes!$A$2:$A$60,0)),"?") -> Core | I67: C2 Barroom storytellers and deadpan songwriters | J67: C6 | K67: Country folk | L67: The Northeast | M67: Brooklyn, NY (via North Carolina) | O67: piano; storytelling; drawl; funny-sad; road songs | P67: A piano-led, songs-first country record from the Fust bassist and Dear Life Records co-owner, mixing Neil Young-style keyboard balladry with Lambchop-esque narrative turns and field-recording interludes. | Q67: Meadows co-runs Dear Life Records and plays in Fust, linking this solo record directly to that North Carolina/Brooklyn alt-country network. | R67: Documented | S67: Everybody's Birthday; Dead Weight; Time Enough | T67: Deep cut | X67: https://ruinationrecordco.bandcamp.com/music https://frankmeadows.bandcamp.com/album/dead-weight | Y67: High
A68: A0067 | B68: Izaak Opatz | C68: Extra Medium | D68: 2022 | E68: LP | F68: Mama Bird Recording Co. | G68: =IF(LEFT(I68,3)="R1 ","L6",IF(D68>=2014,"L1",IF(D68>=1998,"L2",IF(D68>=1987,"L3",IF(D68>=1978,"L4",IF(D68>=1965,"L5","L6")))))) -> L1 | H68: =IFERROR(INDEX(Lanes!$C$2:$C$60,MATCH(LEFT(I68,FIND(" ",I68)-1),Lanes!$A$2:$A$60,0)),"?") -> Core | I68: C2 Barroom storytellers and deadpan songwriters | K68: Country folk | L68: The West | M68: Missoula, MT | O68: drawl; storytelling; funny-sad; small-town; hushed | P68: Smart, unfussy, mildly twangy folk built around dry, plainspoken wit about small-town Montana life. It sounds as gentle as Bahamas or Andy Shauf, but the lyrics carry the same funny-sad economy as his barroom-storyteller peers. | Q68: Missoula, Montana songwriter whose work sits at the folk/country-adjacent end of the deadpan-storyteller lineage. | R68: Inferred | S68: Passenger Seat; Married with Kids; Chinook Wind | T68: Deep cut | V68: https://www.noexpectations.fyi/p/the-60-best-albums-of-2022-according | X68: https://izaakopatz.bandcamp.com/album/extra-medium https://www.noexpectations.fyi/p/the-60-best-albums-of-2022-according | Y68: High
A69: A0068 | B69: Colin Miller | C69: Haw Creek | D69: 2023 | E69: LP | F69: Ruination Records | G69: =IF(LEFT(I69,3)="R1 ","L6",IF(D69>=2014,"L1",IF(D69>=1998,"L2",IF(D69>=1987,"L3",IF(D69>=1978,"L4",IF(D69>=1965,"L5","L6")))))) -> L1 | H69: =IFERROR(INDEX(Lanes!$C$2:$C$60,MATCH(LEFT(I69,FIND(" ",I69)-1),Lanes!$A$2:$A$60,0)),"?") -> Core | I69: C2 Barroom storytellers and deadpan songwriters | K69: Alt-country | L69: The Carolinas | M69: Asheville, NC | N69: Asheville | O69: fingerpicked acoustic; lo-fi; small-town; Southern gothic; hushed | P69: Miller's debut full-length: hushed, homespun songwriting set against tape-hiss production and found-sound experiments. Pump organ, dulcimer-like textures and quiet guitar give it a front-porch, family-archive feel. | Q69: Predates Losin'; sounds close to the Asheville scene around MJ Lenderman and Wednesday. | R69: Inferred | S69: Sweetheartmetalbaby; Nosebleeds; Fallin | T69: Recommended | W69: Y | X69: https://colinmiller.bandcamp.com/album/haw-creek https://en.wikipedia.org/wiki/Colin_Miller_(musician) | Y69: High
A70: A0069 | B70: Dougie Poole | C70: The Rainbow Wheel of Death | D70: 2023 | E70: LP | F70: Wharf Cat Records | G70: =IF(LEFT(I70,3)="R1 ","L6",IF(D70>=2014,"L1",IF(D70>=1998,"L2",IF(D70>=1987,"L3",IF(D70>=1978,"L4",IF(D70>=1965,"L5","L6")))))) -> L1 | H70: =IFERROR(INDEX(Lanes!$C$2:$C$60,MATCH(LEFT(I70,FIND(" ",I70)-1),Lanes!$A$2:$A$60,0)),"?") -> Core | I70: C2 Barroom storytellers and deadpan songwriters | K70: Alt-country | L70: The Northeast | M70: Brooklyn, NY | O70: drum machine; synths; baritone; funny-sad; deadpan | P70: Poole's third solo LP pairs his golden, deadpan baritone with a live band plus old-school synthesizers, widening his millennial-malaise persona into songs about mortality and time rather than just dead-end jobs. The title track, named for the Mac beachball icon, is eerie and gently funny. | Q70: Poole's country songwriting sounds descended from Haggard/Nelson/Kristofferson filtered through Brooklyn's DIY scene; the drum-machine-plus-pedal-steel sound recalls Silver Jews. | R70: Inferred | S70: The Rainbow Wheel of Death; High School Gym; Must Be In Here Somewhere | T70: Essential | V70: https://www.noexpectations.fyi/p/the-30-best-albums-of-2023-so-far-midyear-list | W70: Y | X70: https://dougiepoole.bandcamp.com/album/the-rainbow-wheel-of-death https://www.noexpectations.fyi/p/the-30-best-albums-of-2023-so-far-midyear-list | Y70: High
A71: A0070 | B71: Pony Bradshaw | C71: North Georgia Rounder | D71: 2023 | E71: LP | F71: Black Mountain // Soundly Music | G71: =IF(LEFT(I71,3)="R1 ","L6",IF(D71>=2014,"L1",IF(D71>=1998,"L2",IF(D71>=1987,"L3",IF(D71>=1978,"L4",IF(D71>=1965,"L5","L6")))))) -> L1 | H71: =IFERROR(INDEX(Lanes!$C$2:$C$60,MATCH(LEFT(I71,FIND(" ",I71)-1),Lanes!$A$2:$A$60,0)),"?") -> Core | I71: C2 Barroom storytellers and deadpan songwriters | K71: Alt-country | L71: The South | M71: North Georgia | O71: fingerpicked acoustic; storytelling; small-town; drawl; road songs | P71: Bradshaw's character-driven songwriting captures life split between the north Georgia mountains and the touring road, recorded in five live days at Fellowship Hall Sound. Reviewers place him alongside Jason Isbell for narrative-driven, plainspoken Southern songwriting shot through with dry humor. | Q71: Follows his 2021 LP Calico Jim, cut at the same Little Rock studio; part of a loose north-Georgia Appalachian storytelling trilogy completed by Thus Spoke the Fool. | R71: Documented | S71: Foxfire Wine; North Georgia Rounder; Go Down, Appalachia | T71: Recommended | V71: https://www.noexpectations.fyi/p/the-60-best-albums-of-2023 | X71: https://theponybradshaw.bandcamp.com/album/north-georgia-rounder https://www.noexpectations.fyi/p/the-60-best-albums-of-2023 | Y71: High
A72: A0071 | B72: Ryan Davis & the Roadhouse Band | C72: Dancing on the Edge | D72: 2023 | E72: LP | F72: Sophomore Lounge | G72: =IF(LEFT(I72,3)="R1 ","L6",IF(D72>=2014,"L1",IF(D72>=1998,"L2",IF(D72>=1987,"L3",IF(D72>=1978,"L4",IF(D72>=1965,"L5","L6")))))) -> L1 | H72: =IFERROR(INDEX(Lanes!$C$2:$C$60,MATCH(LEFT(I72,FIND(" ",I72)-1),Lanes!$A$2:$A$60,0)),"?") -> Core | I72: C2 Barroom storytellers and deadpan songwriters | K72: Crossover | L72: The South | M72: Louisville, KY | N72: Louisville and Sophomore Lounge | O72: deadpan; storytelling; pedal steel; drawl; cosmic | P72: Davis's first billed Roadhouse Band record: a double-LP set of long, expansive songs that mix folk-rooted wordplay with synth textures, organ swells and pedal steel. The mood is melancholic and gentle rather than rowdy. A good entry point for the barfly-poet strain of the scene before New Threats from the Soul refined it further. | Q72: Follows Davis's work fronting State Champion; sounds indebted to Souled American, David Berman and Neil Young. | R72: Both | S72: Flashes of Orange; Junk Drawer Heart; Free From the Guillotine | T72: Essential | V72: https://www.noexpectations.fyi/p/hana-stretton-neptunes-core-bullseye-mallory-hawk | W72: Y | X72: https://sophomorelounge.bandcamp.com/album/ryan-davis-the-roadhouse-band-dancing-on-the-edge https://www.noexpectations.fyi/p/hana-stretton-neptunes-core-bullseye-mallory-hawk | Y72: High
A73: A0072 | B73: Fust | C73: Songs of the Rail | D73: 2024 | E73: Compilation | F73: Dear Life Records | G73: =IF(LEFT(I73,3)="R1 ","L6",IF(D73>=2014,"L1",IF(D73>=1998,"L2",IF(D73>=1987,"L3",IF(D73>=1978,"L4",IF(D73>=1965,"L5","L6")))))) -> L1 | H73: =IFERROR(INDEX(Lanes!$C$2:$C$60,MATCH(LEFT(I73,FIND(" ",I73)-1),Lanes!$A$2:$A$60,0)),"?") -> Core | I73: C2 Barroom storytellers and deadpan songwriters | J73: C1 | K73: Alt-country | L73: The Carolinas | M73: Durham, NC | O73: lo-fi; drawl; storytelling; small-town; funny-sad | P73: A compilation of Aaron Dowdy's early home-recorded songs, released as a single sprawling document of the years before Fust became a full band. Rough, home-taped country songs with Dowdy's drawl up front show the roots of the band's later, fuller storytelling. It is for fans who want to hear the sketches behind the band records. | Q73: Predates and directly seeds the full-band Fust sound heard on Genevieve and Big Ugly; a look at the songwriter's home-recording origins before the Dear Life Records band era. | R73: Documented | S73: Abandon; Dark One; Run to the Wolf | T73: Deep cut | W73: Y | X73: https://dearliferecs.bandcamp.com/music https://fust.bandcamp.com/album/songs-of-the-rail https://en.wikipedia.org/wiki/Fust_(band) | Y73: High
A74: A0073 | B74: Jesse Welles | C74: Hells Welles | D74: 2024 | E74: LP | F74: Self-released | G74: =IF(LEFT(I74,3)="R1 ","L6",IF(D74>=2014,"L1",IF(D74>=1998,"L2",IF(D74>=1987,"L3",IF(D74>=1978,"L4",IF(D74>=1965,"L5","L6")))))) -> L1 | H74: =IFERROR(INDEX(Lanes!$C$2:$C$60,MATCH(LEFT(I74,FIND(" ",I74)-1),Lanes!$A$2:$A$60,0)),"?") -> Core | I74: C2 Barroom storytellers and deadpan songwriters | K74: Country folk | L74: The South | M74: Fayetteville, AR | O74: deadpan; political; storytelling; fingerpicked acoustic; funny-sad | P74: A sprawling album that gathers Jesse Welles' viral topical folk songs into a full deadpan-protest record, delivered in a flat, half-amused talk-sing that turns the grimmest subjects into wry asides. Built mostly on acoustic guitar and harmonica, it sounds like a modern update of Woody Guthrie topical folk filtered through Prine's dry humor. It suits listeners who want current-events songwriting that jokes its way toward grief rather than shouting. | Q74: Sounds like a revival of the Guthrie/Prine topical-folk lineage for the social-media era, reaching listeners through viral video rather than the club circuit. | R74: Inferred | S74: Fentanyl; War Isn't Murder; Cancer | T74: Recommended | X74: https://jessewelles.bandcamp.com/album/hells-welles https://en.wikipedia.org/wiki/Jesse_Welles | Y74: High
A75: A0074 | B75: Pony Bradshaw | C75: Thus Spoke the Fool | D75: 2024 | E75: LP | F75: Black Mountain Music / Soundly Music | G75: =IF(LEFT(I75,3)="R1 ","L6",IF(D75>=2014,"L1",IF(D75>=1998,"L2",IF(D75>=1987,"L3",IF(D75>=1978,"L4",IF(D75>=1965,"L5","L6")))))) -> L1 | H75: =IFERROR(INDEX(Lanes!$C$2:$C$60,MATCH(LEFT(I75,FIND(" ",I75)-1),Lanes!$A$2:$A$60,0)),"?") -> Core | I75: C2 Barroom storytellers and deadpan songwriters | K75: Alt-country | L75: The South | M75: North Georgia | O75: fingerpicked acoustic; storytelling; small-town; drawl; spiritual or gospel | P75: Bradshaw's character-driven historical songwriting, humanizing north-Georgia history and working-class locals. His rough, drawled voice sits over sparse, Appalachian-rooted arrangements. | Q75: Follows Calico Jim and North Georgia Rounder in his run of north-Georgia story records. | R75: Documented | S75: Ginseng Daddy; The Long Man; Housebroke | T75: Recommended | V75: https://www.noexpectations.fyi/p/best-country-albums-of-2024 | X75: https://open.spotify.com/album/4K8fgkZb2es57x2enGQa9n https://music.apple.com/us/album/thus-spoke-the-fool/1749371421 | Y75: Medium
A76: A0075 | B76: Styrofoam Winos | C76: Real Time | D76: 2024 | E76: LP | F76: Sophomore Lounge | G76: =IF(LEFT(I76,3)="R1 ","L6",IF(D76>=2014,"L1",IF(D76>=1998,"L2",IF(D76>=1987,"L3",IF(D76>=1978,"L4",IF(D76>=1965,"L5","L6")))))) -> L1 | H76: =IFERROR(INDEX(Lanes!$C$2:$C$60,MATCH(LEFT(I76,FIND(" ",I76)-1),Lanes!$A$2:$A$60,0)),"?") -> Core | I76: C2 Barroom storytellers and deadpan songwriters | K76: Country folk | L76: The South | M76: Nashville, TN | N76: Louisville and Sophomore Lounge | O76: harmonized guitars; storytelling; breezy; funny-sad; drawl | P76: Three Nashville songwriters trading instruments and lead vocals on an easygoing patio album with shaggy-dog charm. Feelies-ish jangle and Little Feat-style tempo shifts run through their group songwriting. | Q76: Sounds close to the Nashville dive-bar scene of Lambchop and Silver Jews, and to Ryan Davis & the Roadhouse Band. | R76: Inferred | S76: Angel Flies Over; Magic Mind; Don't Mind Me | T76: Recommended | V76: https://www.noexpectations.fyi/p/new-indie-rock-albums-sept-oct-merce-lemon-lutalo | X76: https://styrofoamwinos.bandcamp.com/album/real-time https://www.noexpectations.fyi/p/new-indie-rock-albums-sept-oct-merce-lemon-lutalo | Y76: High
A77: A0076 | B77: Colin Miller | C77: Losin' | D77: 2025 | E77: LP | F77: Mtn Laurel Recording Co. | G77: =IF(LEFT(I77,3)="R1 ","L6",IF(D77>=2014,"L1",IF(D77>=1998,"L2",IF(D77>=1987,"L3",IF(D77>=1978,"L4",IF(D77>=1965,"L5","L6")))))) -> L1 | H77: =IFERROR(INDEX(Lanes!$C$2:$C$60,MATCH(LEFT(I77,FIND(" ",I77)-1),Lanes!$A$2:$A$60,0)),"?") -> Core | I77: C2 Barroom storytellers and deadpan songwriters | K77: Alt-country | L77: The Carolinas | M77: Asheville, NC | N77: Asheville | O77: fingerpicked acoustic; deadpan; storytelling; small-town; funny-sad | P77: A bittersweet, sharpened set of folk-rock songs full of shared-memory and loss storytelling drawn from his Asheville circle. Miller's plainspoken, half-sung delivery and homespun production put the focus on the writing over any studio polish. | Q77: Follows Miller's debut Haw Creek; sounds of a piece with the Asheville scene around MJ Lenderman and Wednesday. | R77: Both | S77: Birdhouse; Porchlight; Thunder Road | T77: Recommended | V77: https://www.noexpectations.fyi/p/uwade-mei-semones-colin-miller-eli-winter | W77: Y | X77: https://colinmiller.bandcamp.com/album/losin https://en.wikipedia.org/wiki/Colin_Miller_(musician) | Y77: High
A78: A0077 | B78: Eliza Niemi | C78: Progress Bakery | D78: 2025 | E78: LP | F78: Self-released | G78: =IF(LEFT(I78,3)="R1 ","L6",IF(D78>=2014,"L1",IF(D78>=1998,"L2",IF(D78>=1987,"L3",IF(D78>=1978,"L4",IF(D78>=1965,"L5","L6")))))) -> L1 | H78: =IFERROR(INDEX(Lanes!$C$2:$C$60,MATCH(LEFT(I78,FIND(" ",I78)-1),Lanes!$A$2:$A$60,0)),"?") -> Core | I78: C2 Barroom storytellers and deadpan songwriters | K78: Indie folk | L78: The UK, Ireland and Canada | M78: Toronto, ON | O78: strings; storytelling; funny-sad; lo-fi; hushed | P78: A cellist-songwriter's wry, meticulously detailed record, pairing relaxed, lush chamber-pop arrangements (cello interludes throughout) with DIY-punk detours and dryly funny lyrics. Closer to bedroom chamber-folk than a bar band, but its joke-then-gut-punch songwriting places it near the deadpan storyteller lineage. | Q78: A borderline Core inclusion: less bar-band than her C2 peers, but shares the funny-sad lyrical mode with Prine/Berman-style songwriters. | R78: Inferred | S78: Novelist Sad Face; Dusty; Melodies Like Mark | T78: Deep cut | V78: https://www.noexpectations.fyi/p/reviews-pry-blasucci-lifeguard-daughter-swords-niemi | X78: https://elizaniemi.bandcamp.com/album/progress-bakery https://www.noexpectations.fyi/p/reviews-pry-blasucci-lifeguard-daughter-swords-niemi | Y78: High
A79: A0078 | B79: Jonny Fritz | C79: Debbie Downers | D79: 2025 | E79: LP | F79: Gar Hole Records | G79: =IF(LEFT(I79,3)="R1 ","L6",IF(D79>=2014,"L1",IF(D79>=1998,"L2",IF(D79>=1987,"L3",IF(D79>=1978,"L4",IF(D79>=1965,"L5","L6")))))) -> L1 | H79: =IFERROR(INDEX(Lanes!$C$2:$C$60,MATCH(LEFT(I79,FIND(" ",I79)-1),Lanes!$A$2:$A$60,0)),"?") -> Core | I79: C2 Barroom storytellers and deadpan songwriters | K79: Country folk | L79: The South | M79: Nashville, TN | O79: drawl; storytelling; funny-sad; small-town; anthemic | P79: Fritz's return after a long break turns blue-collar everyday life into wry, anthemic country songs. Honky-tonk band arrangements back his nasal, joke-laced delivery, with the humor always edging toward sadness. | Q79: Follows Sweet Creep (2016) after a near-decade recording gap; continues his idiosyncratic, joke-laced country songwriting. | R79: Documented | S79: Debbie Downers; The Boss; Hot Chicken Condos | T79: Deep cut | X79: https://jonnyfritz.bandcamp.com/album/debbie-downers https://en.wikipedia.org/wiki/Jonny_Fritz | Y79: High
A80: A0079 | B80: Josh Halper | C80: Schlemiel | D80: 2025 | E80: LP | F80: Self-released | G80: =IF(LEFT(I80,3)="R1 ","L6",IF(D80>=2014,"L1",IF(D80>=1998,"L2",IF(D80>=1987,"L3",IF(D80>=1978,"L4",IF(D80>=1965,"L5","L6")))))) -> L1 | H80: =IFERROR(INDEX(Lanes!$C$2:$C$60,MATCH(LEFT(I80,FIND(" ",I80)-1),Lanes!$A$2:$A$60,0)),"?") -> Core | I80: C2 Barroom storytellers and deadpan songwriters | K80: Indie folk | L80: The South | M80: Nashville, TN | O80: fingerpicked acoustic; piano; storytelling; funny-sad; heartbreak | P80: A keys-heavy, conversational sophomore album about relationships, mixing fingerpicked folk, indie rock and pop confessionals. The Yiddish title signals the same rueful, self-deprecating humor that runs through his songwriting. | Q80: Follows Halper's 2020 debut Alrightnik; a Nashville songwriter working the same wry, wordy vein as his singer-songwriter peers. | R80: Inferred | S80: Schlemiel; For Chavah; Late Summer Days | T80: Deep cut | V80: https://www.noexpectations.fyi/p/best-new-albums-september-2025-big-thief-mae-powell-abel | X80: https://joshhalper.bandcamp.com/album/schlemiel https://www.noexpectations.fyi/p/best-new-albums-september-2025-big-thief-mae-powell-abel | Y80: High
A81: A0080 | B81: Mess Esque | C81: Jay Marie, Comfort Me | D81: 2025 | E81: LP | F81: Drag City | G81: =IF(LEFT(I81,3)="R1 ","L6",IF(D81>=2014,"L1",IF(D81>=1998,"L2",IF(D81>=1987,"L3",IF(D81>=1978,"L4",IF(D81>=1965,"L5","L6")))))) -> L1 | H81: =IFERROR(INDEX(Lanes!$C$2:$C$60,MATCH(LEFT(I81,FIND(" ",I81)-1),Lanes!$A$2:$A$60,0)),"?") -> Core | I81: C2 Barroom storytellers and deadpan songwriters | J81: C8 | K81: Country folk | L81: Australia and New Zealand | M81: Melbourne, Australia | O81: deadpan; drawl; hushed; storytelling; funny-sad | P81: Mess Esque is Helen Franzmann (McKisko) and Mick Turner (Dirty Three), and this is a twisted, handmade folk record that builds a warm, dreamlike world out of plainspoken vocals and loose, unhurried arrangements. Turner's shimmering guitar loops circle under Franzmann's voice. It sounds openhearted and slightly askew at once. | Q81: Released on Drag City alongside Bill Callahan and Bonnie 'Prince' Billy, placing Mess Esque within that label's wry, left-of-center songwriting world. | R81: Documented | S81: Light Showroom; That Chair; Crow's Ash Tree | T81: Deep cut | V81: https://www.noexpectations.fyi/p/the-100-best-albums-of-2025 | X81: https://messesque.bandcamp.com/album/jay-marie-comfort-me https://www.noexpectations.fyi/p/the-100-best-albums-of-2025 https://sun-13.com | Y81: High
A82: A0081 | B82: Mildred | C82: mild | D82: 2025 | E82: EP | F82: Memorials of Distinction / Dog Day Records | G82: =IF(LEFT(I82,3)="R1 ","L6",IF(D82>=2014,"L1",IF(D82>=1998,"L2",IF(D82>=1987,"L3",IF(D82>=1978,"L4",IF(D82>=1965,"L5","L6")))))) -> L1 | H82: =IFERROR(INDEX(Lanes!$C$2:$C$60,MATCH(LEFT(I82,FIND(" ",I82)-1),Lanes!$A$2:$A$60,0)),"?") -> Core | I82: C2 Barroom storytellers and deadpan songwriters | K82: Folk rock | L82: The West | M82: Oakland, CA | O82: close harmonies; lo-fi; storytelling; hushed; breezy | P82: Mildred's debut EP introduces the four-singer, four-songwriter format they'd expand on Fenceline. It is homemade and intimate, with trading lead vocals over living-room-scale guitar arrangements. | Q82: Precedes Fenceline as the band's first release. | R82: Documented | S82: Twinkle Lights; Laila; Green Car | T82: Deep cut | W82: Y | X82: https://mildredband.bandcamp.com/album/mild-2 | Y82: Medium
A83: A0082 | B83: Paper Castles | C83: I'm Sad as Hell and I'm Not Going to Fake It Anymore | D83: 2025 | E83: LP | F83: Sipsman | G83: =IF(LEFT(I83,3)="R1 ","L6",IF(D83>=2014,"L1",IF(D83>=1998,"L2",IF(D83>=1987,"L3",IF(D83>=1978,"L4",IF(D83>=1965,"L5","L6")))))) -> L1 | H83: =IFERROR(INDEX(Lanes!$C$2:$C$60,MATCH(LEFT(I83,FIND(" ",I83)-1),Lanes!$A$2:$A$60,0)),"?") -> Core | I83: C2 Barroom storytellers and deadpan songwriters | K83: Indie folk | L83: Burlington, Vermont | M83: Burlington, VT | N83: Burlington, Vermont | O83: jangle; funny-sad; storytelling; anthemic; heartbreak | P83: Janky, livewire guitars and winking humor meet surprisingly massive choruses, somewhere between Amen Dunes and a Lou Reed doing country. The title alone sets the funny-sad tone that carries through songs about content-creation anxiety and modern malaise. | Q83: Sounds close to the Northeast indie-twang of Greg Freeman and Lily Seabird; extends jokey, confessional indie-folk songwriting into anthemic rock territory. | R83: Inferred | S83: Content Creator; Name Changer; Hey Bobby | T83: Recommended | V83: https://www.noexpectations.fyi/p/the-40-best-albums-of-2025-so-far | X83: https://papercastles.bandcamp.com/album/im-sad-as-hell-and-im-not-going-to-fake-it-anymore https://www.noexpectations.fyi/p/the-40-best-albums-of-2025-so-far | Y83: High
A84: A0083 | B84: Ryan Davis & the Roadhouse Band | C84: New Threats from the Soul | D84: 2025 | E84: LP | F84: Sophomore Lounge | G84: =IF(LEFT(I84,3)="R1 ","L6",IF(D84>=2014,"L1",IF(D84>=1998,"L2",IF(D84>=1987,"L3",IF(D84>=1978,"L4",IF(D84>=1965,"L5","L6")))))) -> L1 | H84: =IFERROR(INDEX(Lanes!$C$2:$C$60,MATCH(LEFT(I84,FIND(" ",I84)-1),Lanes!$A$2:$A$60,0)),"?") -> Core | I84: C2 Barroom storytellers and deadpan songwriters | K84: Crossover | L84: The South | M84: Louisville, KY | N84: Louisville and Sophomore Lounge | O84: deadpan; funny-sad; storytelling; pedal steel; baritone | P84: A sprawling seven-song double LP of conversational barfly rock, Davis half-sings dense, punning verses over a loose Roadhouse Band arrangement that folds pedal steel and violin into synths and programmed beats. It is dark, funny and grand at once, with guest harmonies from Will Oldham, Catherine Irwin and Lou Turner deepening its Drag City-indebted, David Berman-adjacent lineage. For listeners who want the modern high-water mark of wordy, tragicomic songwriting. | Q84: Davis fronted the earlier Louisville band State Champion before going solo with the Roadhouse Band; the record extends the Silver Jews/David Berman line of deadpan storytelling into the 2020s. | R84: Documented | S84: New Threats from the Soul; Monte Carlo / No Limits; Better If You Make Me | T84: Essential | U84: Y | V84: https://www.noexpectations.fyi/p/no-expectations-116-be-here-now | W84: Y | X84: https://sophomorelounge.bandcamp.com/album/ryan-davis-the-roadhouse-band-new-threats-from-the-soul https://www.noexpectations.fyi/p/no-expectations-116-be-here-now | Y84: High
A85: A0084 | B85: The Bird Calls | C85: Take Leave | D85: 2026 | E85: LP | F85: Ruination Record Co. | G85: =IF(LEFT(I85,3)="R1 ","L6",IF(D85>=2014,"L1",IF(D85>=1998,"L2",IF(D85>=1987,"L3",IF(D85>=1978,"L4",IF(D85>=1965,"L5","L6")))))) -> L1 | H85: =IFERROR(INDEX(Lanes!$C$2:$C$60,MATCH(LEFT(I85,FIND(" ",I85)-1),Lanes!$A$2:$A$60,0)),"?") -> Core | I85: C2 Barroom storytellers and deadpan songwriters | K85: Country folk | L85: The Northeast | M85: Brooklyn, NY | O85: deadpan; funny-sad; storytelling; drawl; anthemic | P85: Sam Sodomsky's songwriting project sounds akin to David Berman, John Darnielle and Dan Bejar: clever, plainspoken songs balancing folksy earnestness against wry self-awareness. Gentle guitar arrangements leave room for the lyrics to do the work. It suits listeners who come to songs for the words. | Q85: Sounds indebted to the deadpan-songwriter lineage of Berman and Darnielle, within the small Brooklyn Ruination Record Co. circle. | R85: Inferred | S85: Glow Like Me; To Everything There Is A Ceiling; Take Leave | T85: Recommended | X85: https://ruinationrecordco.bandcamp.com/music https://thebirdcalls.bandcamp.com/album/take-leave | Y85: High
A86: A0085 | B86: Brad Goodall | C86: Hometown | D86: 2026 | E86: LP | F86: Self-released | G86: =IF(LEFT(I86,3)="R1 ","L6",IF(D86>=2014,"L1",IF(D86>=1998,"L2",IF(D86>=1987,"L3",IF(D86>=1978,"L4",IF(D86>=1965,"L5","L6")))))) -> L1 | H86: =IFERROR(INDEX(Lanes!$C$2:$C$60,MATCH(LEFT(I86,FIND(" ",I86)-1),Lanes!$A$2:$A$60,0)),"?") -> Core | I86: C2 Barroom storytellers and deadpan songwriters | K86: Country folk | L86: The South | M86: Huntington, WV | O86: piano; storytelling; funny-sad; small-town; hushed | P86: A piano-driven, introspective record about returning to his West Virginia hometown, with the sophisticated melodic sense of Made In America turned toward homesickness rather than jokes. It rounds out Goodall's small catalog of plainspoken, piano-led songwriting. | Q86: Follows Made In America and a Levon Helm Studios live set; continues his piano-based storytelling, which sounds indebted to Zevon and Newman. | R86: Both | S86: Hometown; River Water; Where I Come From | T86: Deep cut | V86: https://www.noexpectations.fyi/p/the-40-best-albums-of-2026-so-far | X86: https://bradgoodall.bandcamp.com/album/hometown https://www.noexpectations.fyi/p/the-40-best-albums-of-2026-so-far | Y86: High
A87: A0086 | B87: Daughn Gibson | C87: Lake Mary not mysterious | D87: 2026 | E87: LP | F87: Self-released | G87: =IF(LEFT(I87,3)="R1 ","L6",IF(D87>=2014,"L1",IF(D87>=1998,"L2",IF(D87>=1987,"L3",IF(D87>=1978,"L4",IF(D87>=1965,"L5","L6")))))) -> L1 | H87: =IFERROR(INDEX(Lanes!$C$2:$C$60,MATCH(LEFT(I87,FIND(" ",I87)-1),Lanes!$A$2:$A$60,0)),"?") -> Core | I87: C2 Barroom storytellers and deadpan songwriters | K87: Country folk | L87: The Northeast | M87: Carlisle, PA | O87: baritone; storytelling; bleak; Southern gothic; drawl | P87: Gibson's fourth full-length, a slow-building record of Florida noir vignettes that trades his earlier sample-collage approach for a more spacious, bar-at-closing-time mood. His deep, deadpan baritone carries Southern gothic storytelling over sparse arrangements. | Q87: Fourth Daughn Gibson LP, following Carnation (2015); continues his deadpan-narrator persona in a stripped-down mode. | R87: Documented | S87: So Good, I Was; Cocoa Beach; Last Night at Sugar's Bar | T87: Deep cut | W87: Y | X87: https://daughngibson.bandcamp.com/album/lake-mary-not-mysterious-2 | Y87: Medium
A88: A0087 | B88: Mildred | C88: Fenceline | D88: 2026 | E88: LP | F88: Memorials of Distinction / Dog Day Records | G88: =IF(LEFT(I88,3)="R1 ","L6",IF(D88>=2014,"L1",IF(D88>=1998,"L2",IF(D88>=1987,"L3",IF(D88>=1978,"L4",IF(D88>=1965,"L5","L6")))))) -> L1 | H88: =IFERROR(INDEX(Lanes!$C$2:$C$60,MATCH(LEFT(I88,FIND(" ",I88)-1),Lanes!$A$2:$A$60,0)),"?") -> Core | I88: C2 Barroom storytellers and deadpan songwriters | K88: Folk rock | L88: The West | M88: Oakland, CA | O88: close harmonies; storytelling; breezy; funny-sad; duets | P88: The Oakland quartet's breezy, affecting debut LP, with four singers and songwriters trading lead vocals from laconic to full-throated. Conversational lyrics and a living-room-session intimacy carry its funny-sad, plainspoken storytelling. | Q88: Sounds of a piece with the funny-sad, plainspoken songwriting in the barroom-storyteller lane. | R88: Inferred | S88: Fenceline; UPS Brown; Fleet Week | T88: Recommended | V88: https://www.noexpectations.fyi/p/mildred-brad-goodall-youbet-bruce-springsteen-pearla | W88: Y | X88: https://mildredband.bandcamp.com/album/fenceline https://www.noexpectations.fyi/p/mildred-brad-goodall-youbet-bruce-springsteen-pearla | Y88: High
A89: A0088 | B89: Styrofoam Winos | C89: Any River | D89: 2026 | E89: LP | F89: Self-released | G89: =IF(LEFT(I89,3)="R1 ","L6",IF(D89>=2014,"L1",IF(D89>=1998,"L2",IF(D89>=1987,"L3",IF(D89>=1978,"L4",IF(D89>=1965,"L5","L6")))))) -> L1 | H89: =IFERROR(INDEX(Lanes!$C$2:$C$60,MATCH(LEFT(I89,FIND(" ",I89)-1),Lanes!$A$2:$A$60,0)),"?") -> Core | I89: C2 Barroom storytellers and deadpan songwriters | K89: Country folk | L89: The South | M89: Nashville, TN | N89: Louisville and Sophomore Lounge | O89: harmonized guitars; storytelling; breezy; funny-sad; cosmic | P89: The trio's follow-up to Real Time leans further into playful genre-hopping, with lounge, B-52's pulse and Glen Campbell dust. It keeps the same trading-instruments, trading-verses songwriting method. | Q89: Sounds close to Ryan Davis & the Roadhouse Band and MJ Lenderman and the Wind. | R89: Inferred | S89: Pearls; BBQ; New Friend | T89: Recommended | V89: https://www.noexpectations.fyi/p/shabason-krgovich-styrofoam-winos-haylie-davis | X89: https://styrofoamwinos.bandcamp.com/album/any-river https://www.noexpectations.fyi/p/shabason-krgovich-styrofoam-winos-haylie-davis | Y89: High
A90: A0089 | B90: Symbol Soup | C90: Stepping on the Same Rakes | D90: 2026 | E90: LP | F90: Self-released | G90: =IF(LEFT(I90,3)="R1 ","L6",IF(D90>=2014,"L1",IF(D90>=1998,"L2",IF(D90>=1987,"L3",IF(D90>=1978,"L4",IF(D90>=1965,"L5","L6")))))) -> L1 | H90: =IFERROR(INDEX(Lanes!$C$2:$C$60,MATCH(LEFT(I90,FIND(" ",I90)-1),Lanes!$A$2:$A$60,0)),"?") -> Core | I90: C2 Barroom storytellers and deadpan songwriters | K90: Indie folk | L90: The UK, Ireland and Canada | M90: London, UK | O90: fingerpicked acoustic; storytelling; breezy; funny-sad; hushed | P90: London songwriter Michael Rea's charming, conversational folk-rock record moves at an ambling, unhurried pace, its plainspoken verses and breezy melodies squarely in the wordy funny-sad tradition despite its UK setting. | Q90: A non-US example of the Prine/Berman deadpan-storyteller mode, showing the style's reach beyond its American scenes. | R90: Inferred | S90: Peaks; Rakes; Wading | T90: Deep cut | V90: https://www.noexpectations.fyi/p/natalie-jane-hill-dagmar-zuniga-symbol-soup-doll-spirit-vessel | X90: https://symbolsoup.bandcamp.com/album/stepping-on-the-same-rakes https://www.noexpectations.fyi/p/natalie-jane-hill-dagmar-zuniga-symbol-soup-doll-spirit-vessel | Y90: High
A91: A0090 | B91: Buck Meek | C91: Buck Meek | D91: 2018 | E91: LP | F91: Keeled Scales | G91: =IF(LEFT(I91,3)="R1 ","L6",IF(D91>=2014,"L1",IF(D91>=1998,"L2",IF(D91>=1987,"L3",IF(D91>=1978,"L4",IF(D91>=1965,"L5","L6")))))) -> L1 | H91: =IFERROR(INDEX(Lanes!$C$2:$C$60,MATCH(LEFT(I91,FIND(" ",I91)-1),Lanes!$A$2:$A$60,0)),"?") -> Core | I91: C3 New alt-country and honky-tonk bands | K91: Alt-country | L91: The Northeast | M91: Brooklyn, NY | O91: Telecaster twang; drawl; fingerpicked acoustic; storytelling; breezy | P91: Meek's solo debut, looser and more overtly country than Big Thief. It is built on plain, warm Telecaster twang and easygoing melodies, with his reedy voice sitting relaxed in front of the band. | Q91: Establishes Meek's separate honky-tonk-adjacent solo identity outside Big Thief, rooted in his Texas upbringing. | R91: Documented | S91: Ruby; Joe By The Book | T91: Recommended | W91: Y | X91: https://en.wikipedia.org/wiki/Buck_Meek https://buckmeek.bandcamp.com/music https://buckmeek.bandcamp.com/album/buck-meek | Y91: High
A92: A0091 | B92: Ruston Kelly | C92: Dying Star | D92: 2018 | E92: LP | F92: Rounder Records | G92: =IF(LEFT(I92,3)="R1 ","L6",IF(D92>=2014,"L1",IF(D92>=1998,"L2",IF(D92>=1987,"L3",IF(D92>=1978,"L4",IF(D92>=1965,"L5","L6")))))) -> L1 | H92: =IFERROR(INDEX(Lanes!$C$2:$C$60,MATCH(LEFT(I92,FIND(" ",I92)-1),Lanes!$A$2:$A$60,0)),"?") -> Core | I92: C3 New alt-country and honky-tonk bands | K92: Alt-country | L92: The South | M92: Nashville, TN | O92: pedal steel; drawl; heartbreak; storytelling; bleak | P92: Ruston Kelly's debut is the sound he calls 'dirt emo': confessional, downcast lyrics about addiction and heartbreak set over pedal steel and plainspoken country-rock arrangements, closer in mood to emo than to Music Row polish. It moves between hushed acoustic laments and fuller, rootsy full-band tracks without losing its diary-like intimacy. It is a gateway record for listeners coming to alt-country from indie/emo rather than from classic country. | Q92: Draws on Nashville's neo-traditional and outlaw country vocabulary but bends it toward emo's confessional mode, a hybrid Kelly himself named 'dirt emo' and one that seems to echo across later indie-adjacent country songwriting. | R92: Both | S92: Dying Star; Mockingbird; Blackout | T92: Recommended | X92: https://en.wikipedia.org/wiki/Dying_Star_(album) https://www.discogs.com/search/?q=Ruston+Kelly+Dying+Star+Rounder&type=master | Y92: High
A93: A0092 | B93: Kacy & Clayton | C93: Plastic Bouquet | D93: 2020 | E93: Collab | F93: New West Records | G93: =IF(LEFT(I93,3)="R1 ","L6",IF(D93>=2014,"L1",IF(D93>=1998,"L2",IF(D93>=1987,"L3",IF(D93>=1978,"L4",IF(D93>=1965,"L5","L6")))))) -> L1 | H93: =IFERROR(INDEX(Lanes!$C$2:$C$60,MATCH(LEFT(I93,FIND(" ",I93)-1),Lanes!$A$2:$A$60,0)),"?") -> Core | I93: C3 New alt-country and honky-tonk bands | J93: C6 | K93: Country folk | L93: The UK, Ireland and Canada | M93: Saskatchewan, Canada | O93: pedal steel; close harmonies; duets; drawl; breezy | P93: A full-band collaboration with New Zealand's Marlon Williams, Plastic Bouquet brightens Kacy & Clayton's usual spare Canadian prairie folk into warmer, harmony-heavy country rock. Williams and Kacy Anderson's voices trade and blend across a set of plainspoken duets. | Q93: A one-off widening of Kacy & Clayton's traditional-leaning catalog through collaboration with Marlon Williams, closer to breezy country rock than their usual austere folk. | R93: Documented | S93: Plastic Bouquet; Isn't It | T93: Deep cut | X93: https://en.wikipedia.org/wiki/Kacy_%26_Clayton | Y93: Medium
A94: A0093 | B94: S.G. Goodman | C94: Old Time Feeling | D94: 2020 | E94: LP | F94: Verve Forecast Records | G94: =IF(LEFT(I94,3)="R1 ","L6",IF(D94>=2014,"L1",IF(D94>=1998,"L2",IF(D94>=1987,"L3",IF(D94>=1978,"L4",IF(D94>=1965,"L5","L6")))))) -> L1 | H94: =IFERROR(INDEX(Lanes!$C$2:$C$60,MATCH(LEFT(I94,FIND(" ",I94)-1),Lanes!$A$2:$A$60,0)),"?") -> Core | I94: C3 New alt-country and honky-tonk bands | K94: Country folk | L94: The South | M94: Hickman, KY | O94: drawl; storytelling; small-town; Southern gothic; spiritual or gospel | P94: Kentucky songwriter S.G. Goodman's debut is a rocking, rootsy country-folk record steeped in her rural western-Kentucky upbringing, produced by My Morning Jacket's Jim James. Her keening voice and reverb-heavy guitars make it a stark, plainspoken start to her catalog. | Q94: Sounds close to Tyler Childers and Ian Noe in the Kentucky storyteller wing of the new country scene. | R94: Inferred | S94: Space and Time; Old Time Feeling | T94: Recommended | X94: https://en.wikipedia.org/wiki/S.G._Goodman https://guitargirlmag.com/news/music-news/s-g-goodman-queer-indie-rocker-from-kentucky-releases-teeth-marks-powerful-sophomore-album-out-today-via-verve-forecast/ | Y94: High
A95: A0094 | B95: Waxahatchee | C95: Saint Cloud | D95: 2020 | E95: LP | F95: Merge | G95: =IF(LEFT(I95,3)="R1 ","L6",IF(D95>=2014,"L1",IF(D95>=1998,"L2",IF(D95>=1987,"L3",IF(D95>=1978,"L4",IF(D95>=1965,"L5","L6")))))) -> L1 | H95: =IFERROR(INDEX(Lanes!$C$2:$C$60,MATCH(LEFT(I95,FIND(" ",I95)-1),Lanes!$A$2:$A$60,0)),"?") -> Core | I95: C3 New alt-country and honky-tonk bands | K95: Crossover | L95: The South | M95: Birmingham, AL | O95: pedal steel; drawl; storytelling; small-town; heartbreak | P95: Katie Crutchfield's fifth Waxahatchee album traded her indie-rock guitars for a warmer, twangier palette of pedal steel and loping tempos, written in the wake of getting sober. The plainspoken lyrics about family, memory and the South made it one of the most acclaimed records of 2020. It is often cited as a turning point for indie musicians leaning into country. | Q95: Grows out of Crutchfield's earlier lo-fi indie-rock work into full country songwriting, leading directly to the Plains project with Jess Williamson and sitting at the front of a wider wave of indie musicians leaning into twang. | R95: Both | S95: Fire; Lilacs; Can't Do Much | T95: Essential | U95: Y | V95: https://www.noexpectations.fyi/p/new-music-sam-evian-villagerrr-rosali-sun-seeker | W95: Y | X95: https://en.wikipedia.org/wiki/Waxahatchee https://www.noexpectations.fyi/p/new-music-sam-evian-villagerrr-rosali-sun-seeker | Y95: High
A96: A0095 | B96: Buck Meek | C96: Two Saviors | D96: 2021 | E96: LP | F96: Keeled Scales | G96: =IF(LEFT(I96,3)="R1 ","L6",IF(D96>=2014,"L1",IF(D96>=1998,"L2",IF(D96>=1987,"L3",IF(D96>=1978,"L4",IF(D96>=1965,"L5","L6")))))) -> L1 | H96: =IFERROR(INDEX(Lanes!$C$2:$C$60,MATCH(LEFT(I96,FIND(" ",I96)-1),Lanes!$A$2:$A$60,0)),"?") -> Core | I96: C3 New alt-country and honky-tonk bands | K96: Alt-country | L96: The Northeast | M96: Brooklyn, NY | O96: Telecaster twang; drawl; storytelling; harmonized guitars; breezy | P96: A warmer, more full-band record than his debut, with ramshackle, patient country-rock songs and groove-locked guitar interplay. | Q96: Deepens Meek's alt-country songwriting voice ahead of his move to 4AD for Haunted Mountain. | R96: Documented | S96: Two Saviors; Second Sight | T96: Recommended | V96: https://www.noexpectations.fyi/p/new-albums-jeff-rosenstock-diners-buck-meek | W96: Y | X96: https://en.wikipedia.org/wiki/Buck_Meek https://buckmeek.bandcamp.com/music https://buckmeek.bandcamp.com/album/two-saviors | Y96: High
A97: A0096 | B97: Fust | C97: Evil Joy | D97: 2021 | E97: LP | F97: Self-released | G97: =IF(LEFT(I97,3)="R1 ","L6",IF(D97>=2014,"L1",IF(D97>=1998,"L2",IF(D97>=1987,"L3",IF(D97>=1978,"L4",IF(D97>=1965,"L5","L6")))))) -> L1 | H97: =IFERROR(INDEX(Lanes!$C$2:$C$60,MATCH(LEFT(I97,FIND(" ",I97)-1),Lanes!$A$2:$A$60,0)),"?") -> Core | I97: C3 New alt-country and honky-tonk bands | K97: Alt-country | L97: The Carolinas | M97: Durham, NC | O97: drawl; storytelling; small-town; lo-fi; heartbreak | P97: Aaron Dowdy's self-released full-length debut as Fust is a lo-fi, plainspoken alt-country record, its narrators drifting through small Southern towns and bad decisions. It set the template the band expanded on with a full lineup on Genevieve and Big Ugly. A quieter, more private-sounding entry point into the band's catalog. | Q97: Fust's founding document, before the fuller alt-country sound the band pursued once signed to Dear Life Records. | R97: Documented | S97: The Last Days; Where the Good Ones Go; Evil Joy | T97: Recommended | W97: Y | X97: https://fust.bandcamp.com/album/evil-joy https://en.wikipedia.org/wiki/Fust_(band) | Y97: High
A98: A0097 | B98: Florence Dore | C98: Highways & Rocketships | D98: 2022 | E98: LP | F98: Propeller Sound Recordings | G98: =IF(LEFT(I98,3)="R1 ","L6",IF(D98>=2014,"L1",IF(D98>=1998,"L2",IF(D98>=1987,"L3",IF(D98>=1978,"L4",IF(D98>=1965,"L5","L6")))))) -> L1 | H98: =IFERROR(INDEX(Lanes!$C$2:$C$60,MATCH(LEFT(I98,FIND(" ",I98)-1),Lanes!$A$2:$A$60,0)),"?") -> Core | I98: C3 New alt-country and honky-tonk bands | K98: Alt-country | L98: The Carolinas | M98: Chapel Hill, NC | O98: storytelling; close harmonies; drawl; heartbreak; small-town | P98: Chapel Hill songwriter and literature professor Florence Dore blends classic-rock hooks, Americana twang and 1980s college-radio jangle. Narrative-heavy lyrics and a lived-in, veteran band sound keep it far from Nashville polish. It is built for listeners who want literate, well-crafted country-rock steeped in the history of the genre's indie wing. | Q98: Sounds steeped in the 1980s-'90s college-rock and No Depression alt-country lineage that C3 grew from. | R98: Inferred | S98: Highways & Rocketships; Rebel Debutante; Thundercloud (Fucking With Your Heart) | T98: Deep cut | X98: https://florencedore.bandcamp.com/album/highways-rocketships https://www.florencedoremusic.com/welcome | Y98: High
A99: A0098 | B99: Plains | C99: I Walked with You a Ways | D99: 2022 | E99: Collab | F99: Anti- | G99: =IF(LEFT(I99,3)="R1 ","L6",IF(D99>=2014,"L1",IF(D99>=1998,"L2",IF(D99>=1987,"L3",IF(D99>=1978,"L4",IF(D99>=1965,"L5","L6")))))) -> L1 | H99: =IFERROR(INDEX(Lanes!$C$2:$C$60,MATCH(LEFT(I99,FIND(" ",I99)-1),Lanes!$A$2:$A$60,0)),"?") -> Core | I99: C3 New alt-country and honky-tonk bands | K99: Alt-country | L99: Texas and Oklahoma | M99: Austin, TX / Kansas City, MO | O99: pedal steel; close harmonies; duets; drawl; storytelling | P99: A duo album pairing Katie Crutchfield (Waxahatchee) with fellow songwriter Jess Williamson, built around plush '90s-country vocal harmonies and pedal steel over breakup-and-friendship songs. It plays like a loving homage to Lucinda Williams and Trisha Yearwood-style country radio filtered through two indie songwriters. A key document of the indie scene's 2020s country turn. | Q99: A direct collaborative offshoot of Waxahatchee's country pivot, pairing Crutchfield with Jess Williamson's own move from folk toward country songwriting. | R99: Documented | S99: Problem With It; Abilene; Hurricane | T99: Recommended | W99: Y | X99: https://en.wikipedia.org/wiki/Waxahatchee https://www.discogs.com/master/2824592-Plains-I-Walked-With-You-A-Ways | Y99: High
A100: A0099 | B100: S.G. Goodman | C100: Teeth Marks | D100: 2022 | E100: LP | F100: Verve Forecast Records | G100: =IF(LEFT(I100,3)="R1 ","L6",IF(D100>=2014,"L1",IF(D100>=1998,"L2",IF(D100>=1987,"L3",IF(D100>=1978,"L4",IF(D100>=1965,"L5","L6")))))) -> L1 | H100: =IFERROR(INDEX(Lanes!$C$2:$C$60,MATCH(LEFT(I100,FIND(" ",I100)-1),Lanes!$A$2:$A$60,0)),"?") -> Core | I100: C3 New alt-country and honky-tonk bands | K100: Country folk | L100: The South | M100: Hickman, KY | O100: drawl; storytelling; bleak; small-town; Southern gothic | P100: Goodman's second album sharpens her rural-Kentucky storytelling into a bleaker, more electric record about depression and rural isolation. The arrangements lean harder into fuzzy guitar than her debut without losing its plainspoken drawl. A more confident, harder-hitting follow-up. | Q100: Extends Old Time Feeling's western-Kentucky storytelling into darker territory; sounds close to Ian Noe and the post-Childers Kentucky scene. | R100: Both | S100: Space and Time; All My Love Is Coming Back to Me | T100: Recommended | X100: https://en.wikipedia.org/wiki/S.G._Goodman https://guitargirlmag.com/news/music-news/s-g-goodman-queer-indie-rocker-from-kentucky-releases-teeth-marks-powerful-sophomore-album-out-today-via-verve-forecast/ | Y100: High
...

Sheet Artists
A1: Artist | B1: Base | C1: Region | D1: Active years (in atlas) | E1: Primary lane | F1: Zone | G1: Key album IDs | H1: Albums in atlas | I1: Related artists | J1: Summary | K1: In field guide
A2: 16 Horsepower | B2: Denver, CO | C2: The West | D2: 1996–2000 | E2: V9 No Depression and insurgent country | F2: V | G2: A1479, A1485, A1512 | H2: =COUNTIF(Albums!$B$2:$B$2862,A2) -> 3 | I2: Wovenhand | J2: Denver band whose Chemnitzer-concertina, hellfire vocals and old-time Appalachian gospel over post-punk intensity founded the gothic-country subgenre.
A3: 20/20 | B3: Los Angeles, CA | C3: The West | D3: 1979 | E3: V17 Jangle and power pop, Big Star to GBV | F3: V | G3: A2035 | H3: =COUNTIF(Albums!$B$2:$B$2862,A3) -> 1 | I3: the Knack; the Records | J3: Tulsa-to-LA power-pop band whose tightly written, ringing-guitar debut sat with the Knack and the Records at the polished, new-wave end of the genre.
A4: 22º Halo | B4: Philadelphia, PA | C4: Philadelphia | D4: 2024 | E4: C8 Modern slowcore and hushed twang | F4: Core | G4: A0708 | H4: =COUNTIF(Albums!$B$2:$B$2862,A4) -> 1 | I4: Friendship; hemlock | J4: Philadelphia songwriter Will Kennedy's project blending folk, slacker rock and bedroom pop into hopeful, plainspoken songs written through hardship.
A5: 28th Day | B5: Chico, CA | C5: The West | D5: 1985 | E5: V15 Paisley Underground | F5: V | G5: A1900 | H5: =COUNTIF(Albums!$B$2:$B$2862,A5) -> 1 | I5: Barbara Manning; True West | J5: Short-lived Chico, California jangle-pop trio, with a young Barbara Manning on bass, whose lone ringing, melancholy EP was produced by True West's Russ Tolman.
A6: 2nd Grade | B6: Philadelphia, PA | C6: Philadelphia | D6: 2020–2026 | E6: C7 Slacker, jangle, and power-pop revival | F6: Core | G6: A0631, A0577, A0598, A0666 | H6: =COUNTIF(Albums!$B$2:$B$2862,A6) -> 4 | I6: Friendship; Hour; Hurry; Golden Apples; Lawn | J6: Peter Gill's Philadelphia project crams Guided by Voices- and Big Star-indebted hooks into prolific, miniature-song power-pop sprawls. | K6: Y
A7: The 3Ds | B7: Dunedin, New Zealand | C7: Australia and New Zealand | D7: 1992–1993 | E7: V18 Flying Nun and Antipodean indie | F7: V | G7: A2126, A2128 | H7: =COUNTIF(Albums!$B$2:$B$2862,A7) -> 2 | J7: Second-generation Dunedin band whose distorted, dual-vocalist guitar noise pushed the scene's jangle template toward American college-rock volume.
A8: 49 Winchester | B8: Castlewood, VA | C8: The South | D8: 2024 | E8: X2 Red Dirt, Texas country, and arena Americana | F8: Context | G8: A2723 | H8: =COUNTIF(Albums!$B$2:$B$2862,A8) -> 1 | I8: Tyler Childers; Zach Bryan; Chris Stapleton | J8: Southwest Virginia band whose plainspoken, Appalachian arena-Americana splits the difference between The Band's groove and Tyler Childers's directness.
A9: 764-HERO | B9: Seattle, WA | C9: The West | D9: 1998 | E9: V10 Slacker and '90s indie rock | F9: V | G9: A1594 | H9: =COUNTIF(Albums!$B$2:$B$2862,A9) -> 1 | I9: Modest Mouse; Built to Spill | J9: Seattle Up Records band whose ringing, unhurried guitar interplay and plainspoken vocals made them a quieter cousin of tourmates Modest Mouse.
A10: Abbey Blackwell | B10: Seattle, WA | C10: The West | D10: 2023–2026 | E10: C5 Twangy indie folk | F10: Core | G10: A0306, A0229, A0249 | H10: =COUNTIF(Albums!$B$2:$B$2862,A10) -> 3 | J10: Seattle bassist-turned-songwriter whose rich, lush-voiced, organically arranged folk records grew steadily more confident across a self-released run. | K10: Y
A11: Abel | B11: Columbus, OH | C11: Chicago and the Midwest | D11: 2025 | E11: C1 Indie twang / yallternative | F11: Core | G11: A0032 | H11: =COUNTIF(Albums!$B$2:$B$2862,A11) -> 1 | I11: Spencer Radcliffe | J11: Columbus songwriter whose self-lacerating, ramshackle country-jangle debut fits the small-label DIY twang network of Julia's War and Candlepin.
A12: The Able Tasmans | B12: Auckland, New Zealand | C12: Australia and New Zealand | D12: 1987–1990 | E12: V18 Flying Nun and Antipodean indie | F12: V | G12: A2100, A2112 | H12: =COUNTIF(Albums!$B$2:$B$2862,A12) -> 2 | J12: Auckland band built around Graeme Humphreys's tumbling piano rather than guitar, an odd, whimsical counterpoint to Flying Nun's guitar-heavy Dunedin sound.
A13: Acetone | B13: Los Angeles, CA | C13: The West | D13: 1993–1996 | E13: V12 Slowcore and sadcore | F13: V | G13: A1706, A1725 | H13: =COUNTIF(Albums!$B$2:$B$2862,A13) -> 2 | I13: Low | J13: Los Angeles trio whose slow, country-tinged, hushed-vocal drone shared Vernon Yard Records with early Low, working a hazy desert-highway strain of slowcore.
A14: Ada Lea | B14: Montreal, Quebec | C14: The UK, Ireland and Canada | D14: 2025 | E14: C6 Cosmic country and the '70s revival | F14: Core | G14: A0464 | H14: =COUNTIF(Albums!$B$2:$B$2862,A14) -> 1 | I14: Kate Bollinger; Courtney Marie Andrews | J14: Montreal songwriter Alexandra Levy who traded moody indie rock for breezy, Dylan-referencing '70s Laurel Canyon folk warmth.
A15: Adam Faucett | B15: Little Rock, AR | C15: The South | D15: 2007–2018 | E15: V3 Southern storytelling rock | F15: V | G15: A0924, A0956, A0968 | H15: =COUNTIF(Albums!$B$2:$B$2862,A15) -> 3 | I15: John Moreland; Two Cow Garage | J15: Little Rock songwriter whose weathered, cracked baritone and sparse arrangements deepened into fuller, bleaker band records on Last Chance Records.
A16: Adeline Hotel | B16: Brooklyn, NY | C16: The Northeast | D16: 2021 | E16: C5 Twangy indie folk | F16: Core | G16: A0194 | H16: =COUNTIF(Albums!$B$2:$B$2862,A16) -> 1 | I16: Frank Meadows; Jackie West; The Bird Calls | J16: Dan Knishkowy's gentle, fingerpicked indie-folk project of plainspoken, wry songs about memory, part of a close-knit Brooklyn songwriter circle.
A17: Adrianne Lenker | C17: The Northeast | D17: 2006–2024 | E17: C5 Twangy indie folk | F17: Core | G17: A0169, A0188, A0250, A0147 | H17: =COUNTIF(Albums!$B$2:$B$2862,A17) -> 7 | I17: Big Thief; Buck Meek; Gillian Welch | J17: Big Thief singer whose parallel solo catalog runs from embryonic teenage recordings to hushed, cabin-recorded confessionals and a Grammy-nominated late high point.
A18: Adrianne Lenker & Buck Meek | C18: The Northeast | D18: 2014 | E18: C5 Twangy indie folk | F18: Core | G18: A0148, A0149 | H18: =COUNTIF(Albums!$B$2:$B$2862,A18) -> 2 | I18: Big Thief; Adrianne Lenker; Buck Meek | J18: A pre-Big Thief duo release of stripped-back, harmony-driven folk documenting the songwriting chemistry between Lenker and Meek.
A19: Advance Base | B19: Chicago, IL | C19: Chicago and the Midwest | D19: 2015 | E19: C2 Barroom storytellers and deadpan songwriters | F19: Core | G19: A0051 | H19: =COUNTIF(Albums!$B$2:$B$2862,A19) -> 1 | I19: Casiotone for the Painfully Alone; Silver Jews | J19: Owen Ashworth's post-Casiotone project sets deadpan, plainly sung short stories over minimal drum machine and synth, continuing the Drag City deadpan school.
A20: Age of Peace | B20: Los Angeles, CA | C20: The West | D20: 2026 | E20: C6 Cosmic country and the '70s revival | F20: Core | G20: A0479 | H20: =COUNTIF(Albums!$B$2:$B$2862,A20) -> 1 | I20: Artificial Go; ROD | J20: Los Angeles duo Angie Willcutt and Micah Wu's spectral, folk-based Cosmic American Music, plucked strings and mallet pulse under playful, transcendental lyrics.
A21: Aïda Mekonnen Caby | B21: Brittany, France | C21: Elsewhere | D21: 2025 | E21: C5 Twangy indie folk | F21: Core | G21: A0274 | H21: =COUNTIF(Albums!$B$2:$B$2862,A21) -> 1 | I21: TOLEDO | J21: TOLEDO member's solo turn into pristine, dreamy folk-pop at a more intimate, personal scale than her main band.
A22: Alan Jackson | B22: Newnan, GA | C22: The South | D22: 1991 | E22: X1 Mainstream Nashville, countrypolitan to bro-country | F22: Context | G22: A2707 | H22: =COUNTIF(Albums!$B$2:$B$2862,A22) -> 1 | J22: Georgia neotraditionalist whose plain drawl and fiddle-and-steel arrangements defended honky-tonk country as Music Row turned pop.
A23: Alasdair Roberts | B23: Glasgow, Scotland | C23: The UK, Ireland and Canada | D23: 2003 | E23: V2 Drag City deadpan school | F23: V | G23: A0865 | H23: =COUNTIF(Albums!$B$2:$B$2862,A23) -> 1 | I23: Appendix Out | J23: Glasgow songwriter whose spare, fingerpicked solo work after Appendix Out steeps Scottish and Appalachian folk phrasing in the Drag City deadpan-folk lineage.
A24: Alejandro Escovedo | B24: Austin, TX | C24: Texas and Oklahoma | D24: 1992–2001 | E24: V13 Americana songwriters before the label | F24: V | G24: A1783, A1832, A1806, A1823 | H24: =COUNTIF(Albums!$B$2:$B$2862,A24) -> 4 | I24: the Nuns; Rank and File; True Believers | J24: Austin songwriter who moved from punk and cowpunk bands into orchestral, string-laden chamber-rock Americana about grief and Texas-Mexican family history.
A25: Alela Diane | B25: Nevada City, CA | C25: The West | D25: 2004–2018 | E25: V5 Rootsy indie folk | F25: V | G25: A1095, A1113, A1130, A1145 | H25: =COUNTIF(Albums!$B$2:$B$2862,A25) -> 4 | I25: Wild Divine; Tom Bevitori | J25: Nevada City folk singer whose clear, unadorned voice carries home-recorded, hymn-and-ballad-rooted songwriting into fuller, then quieter and more domestic, records.
A26: Alela Diane & Wild Divine | B26: Nevada City, CA | C26: The West | D26: 2011 | E26: V5 Rootsy indie folk | F26: V | G26: A1123 | H26: =COUNTIF(Albums!$B$2:$B$2862,A26) -> 1 | I26: Alela Diane; Tom Bevitori | J26: Alela Diane credited jointly with her touring band on a warmer, full-band folk-rock record built around her marriage to guitarist Tom Bevitori.
A27: Alex Chilton | B27: Memphis, TN | C27: The South | D27: 1979–1985 | E27: V17 Jangle and power pop, Big Star to GBV | F27: V | G27: A2036, A2052 | H27: =COUNTIF(Albums!$B$2:$B$2862,A27) -> 2 | I27: Big Star | J27: Post-Big Star Memphis songwriter who turned from polished jangle to deliberately wrecked, sloppy garage rock and loose, soul-inflected bar-band records.
A28: Alex G | B28: Philadelphia, PA | C28: Philadelphia | D28: 2011–2025 | E28: C7 Slacker, jangle, and power-pop revival | F28: Core | G28: A0517, A0546, A0573, A0599 | H28: =COUNTIF(Albums!$B$2:$B$2862,A28) -> 10 | J28: Philadelphia bedroom-pop songwriter whose warped, pitch-shifted vocals and plainspoken menace-and-gentleness grew from prolific Bandcamp lo-fi into major-label pop songcraft. | K28: Y
A29: Alison Krauss & Union Station | B29: Nashville, TN | C29: The South | D29: 2001 | E29: X4 Bluegrass, old-time, and newgrass | F29: Context | G29: A2736 | H29: =COUNTIF(Albums!$B$2:$B$2862,A29) -> 1 | J29: Crystalline-voiced, radio-ready bluegrass ensemble whose polished, vocal-forward picking made them the genre's mainstream-crossover face just before O Brother, Where Art Thou?.
A30: Allegra Krieger | B30: New York, NY | C30: The Northeast | D30: 2020–2023 | E30: C5 Twangy indie folk | F30: Core | G30: A0230, A0189 | H30: =COUNTIF(Albums!$B$2:$B$2862,A30) -> 2 | J30: New York songwriter whose plainspoken, mortality-fixated diaristic songwriting grew from spare Northern Spy records into a quietly contemplative career high point.
A31: The Allman Betts Band | B31: Sarasota, FL | C31: The South | D31: 2019–2020 | E31: X11 Modern Southern rock | F31: Context | G31: A2815, A2818 | H31: =COUNTIF(Albums!$B$2:$B$2862,A31) -> 2 | I31: The Allman Brothers Band | J31: Band formed by the sons of three founding Allman Brothers Band members, recreating their fathers' twin-lead-guitar, jam-friendly sound almost note for note.
A32: The Allman Brothers Band | B32: Macon, GA | C32: The South | D32: 1969–1973 | E32: V28 Southern rock and country soul | F32: V | G32: A2572, A2579, A2581, A2584 | H32: =COUNTIF(Albums!$B$2:$B$2862,A32) -> 5 | J32: Macon, Georgia band whose twin-guitar, twin-drummer blues-and-jazz jams set the template for the whole Capricorn Southern-rock roster across a run of studio and live landmarks.
A33: Amalgamated Sons of Rest | B33: Chicago, IL | C33: Chicago and the Midwest | D33: 2002 | E33: V1 Molina and the Magnolia circle | F33: V | G33: A0783 | H33: =COUNTIF(Albums!$B$2:$B$2862,A33) -> 1 | I33: Jason Molina; Will Oldham; Alasdair Roberts | J33: One-off unplugged folk-balladry side project pairing Jason Molina with Will Oldham and Alasdair Roberts in close, unpolished front-porch harmonies.
A34: Amanda Shires | B34: Nashville, TN | C34: The South | D34: 2011–2016 | E34: V6 2000s–2010s alt-country | F34: V | G34: A1230, A1245, A1264 | H34: =COUNTIF(Albums!$B$2:$B$2862,A34) -> 3 | I34: Jason Isbell; the Highwomen | J34: Nashville fiddle player turned literate singer-songwriter whose image-heavy Americana records grew darker and more personal across motherhood and marriage.
A35: Amen Dunes | B35: New York, NY | C35: The Northeast | D35: 2014–2018 | E35: C6 Cosmic country and the '70s revival | F35: Core | G35: A0343, A0374 | H35: =COUNTIF(Albums!$B$2:$B$2862,A35) -> 2 | J35: Damon McMahon's project moved from lo-fi murk into hazy, Dead-and-Parsons-adjacent guitar-folk and then a warmer, radio-scaled classic-rock-informed sound.
A36: American Aquarium | B36: Raleigh, NC | C36: The Carolinas | D36: 2009–2020 | E36: V3 Southern storytelling rock | F36: V | G36: A0944, A0961, A0969, A0971 | H36: =COUNTIF(Albums!$B$2:$B$2862,A36) -> 6 | I36: Drive-By Truckers; Lucero; Two Cow Garage | J36: BJ Barham's Raleigh band turned van-touring poverty and later sobriety into plainspoken, conversational Drive-By Truckers- and Lucero-indebted storytelling rock.
A37: American Football | B37: Urbana, IL | C37: Chicago and the Midwest | D37: 1999 | E37: X6 Emo and Midwest emo | F37: Context | G37: A2758 | H37: =COUNTIF(Albums!$B$2:$B$2862,A37) -> 1 | I37: Cap'n Jazz | J37: Mike Kinsella's post-Cap'n Jazz project distilled Midwest emo into gentle, jazzy guitar interplay and conversational vocals on its genre-defining lone original album.
A38: American Music Club | B38: San Francisco, CA | C38: The West | D38: 1988–1994 | E38: V12 Slowcore and sadcore | F38: V | G38: A1693, A1701, A1707, A1712 | H38: =COUNTIF(Albums!$B$2:$B$2862,A38) -> 5 | J38: San Francisco band led by Mark Eitzel's ragged, plainspoken baritone through slow, pedal-steel-streaked, theatrically bleak country-rock and sadcore songwriting.
A39: Andrew Combs | B39: Nashville, TN | C39: The South | D39: 2012–2017 | E39: V6 2000s–2010s alt-country | F39: V | G39: A1239, A1258, A1271 | H39: =COUNTIF(Albums!$B$2:$B$2862,A39) -> 3 | I39: Caitlin Rose; Elizabeth Cook | J39: Nashville songwriter whose warm, classic-leaning country-folk records, closer to 1970s countrypolitan than rock-inflected alt-country, grew more orchestrated over time.
A40: Angela Autumn | B40: Nashville, TN | C40: The South | D40: 2026 | E40: C6 Cosmic country and the '70s revival | F40: Core | G40: A0480 | H40: =COUNTIF(Albums!$B$2:$B$2862,A40) -> 1 | J40: Appalachian-raised clawhammer banjo player nicknamed 'The Rose of Appalachia' who folds old-time and bluegrass roots into an arena-sized, psychedelic gothic-country sound.
A41: Angel Olsen | B41: Asheville, NC | C41: Chicago and the Midwest | D41: 2010–2022 | E41: V5 Rootsy indie folk | F41: V | G41: A1133, A1138, A1146, A1128 | H41: =COUNTIF(Albums!$B$2:$B$2862,A41) -> 7 | I41: Bonnie 'Prince' Billy; the Cairo Gang | J41: Chicago-born-then-Asheville singer whose strange, old-time-adjacent vibrato grew from Bonnie 'Prince' Billy-mentored lo-fi folk into glammy pop-rock, orchestral art-pop and pedal-steel country.
A42: Angst | B42: San Francisco, CA | C42: The West | D42: 1985 | E42: V16 American underground and college rock | F42: V | G42: A1946 | H42: =COUNTIF(Albums!$B$2:$B$2862,A42) -> 1 | J42: San Francisco SST band whose clean, politically engaged folk-punk songwriting stood out as more melodic than the label's noisier hardcore roster.
A43: Anna St. Louis | B43: Los Angeles, CA | C43: The West | D43: 2023 | E43: C6 Cosmic country and the '70s revival | F43: Core | G43: A0432 | H43: =COUNTIF(Albums!$B$2:$B$2862,A43) -> 1 | I43: Jess Williamson; Kacey Johansing; Woods | J43: Los Angeles songwriter whose stark debut opened into brighter, orchestral arrangements on a record made within the overlapping Woodsist singer-songwriter circle.
A44: Anne Briggs | B44: Nottinghamshire, England | C44: The UK, Ireland and Canada | D44: 1971 | E44: V30 British folk rock (selective) | F44: V | G44: A2655 | H44: =COUNTIF(Albums!$B$2:$B$2862,A44) -> 1 | J44: Nottinghamshire folk singer whose plain, unornamented voice and sparse original songs sold poorly but became a hard-to-find cult record among British folk revivalists.
A45: Annie Williams | B45: Nashville, TN | C45: The South | D45: 2024 | E45: C5 Twangy indie folk | F45: Core | G45: A0252 | H45: =COUNTIF(Albums!$B$2:$B$2862,A45) -> 1 | J45: Nashville debut songwriter whose subtle pop melodies and conversational, funny writing favor wit and understatement, part of the Nashville indie-folk underground.
A46: The Anomoanon | B46: Louisville, KY | C46: The South | D46: 1998–1999 | E46: V2 Drag City deadpan school | F46: V | G46: A0844, A0850 | H46: =COUNTIF(Albums!$B$2:$B$2862,A46) -> 2 | I46: Will Oldham; Palace | J46: Louisville project led by Will Oldham's brother, setting Robert Louis Stevenson's public-domain poems to spare country-folk on Oldham's own record label.
A47: Appendix Out | B47: Glasgow, Scotland | C47: The UK, Ireland and Canada | D47: 1997 | E47: V2 Drag City deadpan school | F47: V | G47: A0840 | H47: =COUNTIF(Albums!$B$2:$B$2862,A47) -> 1 | I47: Alasdair Roberts; Will Oldham | J47: Alasdair Roberts's Glasgow band, signed to Drag City after Roberts gave Will Oldham a demo, plays hushed, fingerpicked Scottish folk-rock in the label's deadpan idiom.
A48: The Apples in Stereo | B48: Denver, CO | C48: Chicago and the Midwest | D48: 1995–1997 | E48: V11 Lo-fi and home taping | F48: V | G48: A1651, A1666 | H48: =COUNTIF(Albums!$B$2:$B$2862,A48) -> 2 | I48: Neutral Milk Hotel; The Olivia Tremor Control | J48: Robert Schneider's Denver band whose lo-fi, tape-saturated Beach Boys/British Invasion pop founded the whole Elephant 6 Recording Company aesthetic.
A49: Arbor Labor Union | B49: Athens, GA | C49: The South | D49: 2016–2025 | E49: C6 Cosmic country and the '70s revival | F49: Core | G49: A0353, A0396, A0433, A0465 | H49: =COUNTIF(Albums!$B$2:$B$2862,A49) -> 4 | J49: Athens, Georgia punks turned Dead-worshipping jammers whose fuzzed-out cosmic-country evolved from noisy riff-jamming into cleaner, Allman/Wilburys-style songcraft. | K49: Y
A50: Arbouretum | B50: Baltimore, MD | C50: The Northeast | D50: 2007–2020 | E50: V1 Molina and the Magnolia circle | F50: V | G50: A0804, A0797, A0801, A0808 | H50: =COUNTIF(Albums!$B$2:$B$2862,A50) -> 5 | J50: Baltimore band led by Dave Heumann's plainspoken baritone through slow, heavy, extended-jam guitar folk-rock in an explicitly Crazy Horse-scale mode.
A51: Archers of Loaf | B51: Chapel Hill, NC | C51: The Carolinas | D51: 1993–1998 | E51: V10 Slacker and '90s indie rock | F51: V | G51: A1532, A1560, A1570, A1595 | H51: =COUNTIF(Albums!$B$2:$B$2862,A51) -> 4 | J51: Eric Bachmann's Chapel Hill band whose tangled, feedback-streaked guitar interplay and yelped vocals made them instant peers of Pavement and a cornerstone of the scene. | K51: Y
A52: Arlo McKinley | B52: Cincinnati, OH | C52: Chicago and the Midwest | D52: 2020–2022 | E52: V7 Neo-traditional and 'new outlaw' country | F52: V | G52: A1339, A1357 | H52: =COUNTIF(Albums!$B$2:$B$2862,A52) -> 2 | I52: John Prine | J52: Cincinnati songwriter, personally signed by John Prine to Oh Boy Records, whose weathered voice carries bleak Midwestern country-folk about addiction and hometown decay.
A53: Arthur Alexander | B53: Muscle Shoals, AL | C53: The South | D53: 1972 | E53: V28 Southern rock and country soul | F53: V | G53: A2582 | H53: =COUNTIF(Albums!$B$2:$B$2862,A53) -> 1 | J53: Muscle Shoals soul singer whose early singles were covered by the Beatles, Stones and Dylan, returning here with a warm, country-soul comeback record.
A54: Astrachan | B54: Chicago, IL | C54: Chicago and the Midwest | D54: 2025 | E54: C7 Slacker, jangle, and power-pop revival | F54: Core | G54: A0645 | H54: =COUNTIF(Albums!$B$2:$B$2862,A54) -> 1 | I54: Smushie; Shoulderbird | J54: Chicago songwriter Ben Astrachan's maximalist solo debut packs '60s-and-'70s-indebted melodic twists into off-kilter, conceptual guitar-pop.
A55: Austin Lucas | B55: Bloomington, IN | C55: Chicago and the Midwest | D55: 2009–2013 | E55: V3 Southern storytelling rock | F55: V | G55: A0930, A0952 | H55: =COUNTIF(Albums!$B$2:$B$2862,A55) -> 2 | I55: Two Cow Garage | J55: Punk-rooted Bloomington, Indiana songwriter whose plainspoken alt-country grew fuller and more country-radio-adjacent as he moved from Suburban Home to New West Records.
A56: Avett Brothers | B56: Concord, NC | C56: The Carolinas | D56: 2009 | E56: X3 Big-tent Americana and stomp-clap folk | F56: Context | G56: A2726 | H56: =COUNTIF(Albums!$B$2:$B$2862,A56) -> 1 | J56: Rick Rubin-produced Concord, NC brothers band that smoothed its punk-folk roughness into string-and-piano Americana built for festival-crowd singalongs.
A57: Babehoven | B57: Hudson Valley, NY | C57: The Northeast | D57: 2026 | E57: C8 Modern slowcore and hushed twang | F57: Core | G57: A0732 | H57: =COUNTIF(Albums!$B$2:$B$2862,A57) -> 1 | I57: Bloomsday; Ryan Albert | J57: Maya Bon's Hudson Valley project moved from lo-fi duo beginnings into full-band indie folk-pop with country and Americana touches and soaring vocals.
A58: Bad Brains | B58: Washington, D.C. | C58: The Northeast | D58: 1982 | E58: X14 Punk and hardcore roots | F58: Context | G58: A2850 | H58: =COUNTIF(Albums!$B$2:$B$2862,A58) -> 1 | J58: Washington D.C. jazz-trained musicians who played hardcore at breakneck, technically dazzling speed with reggae interludes, setting the standard for early-80s American hardcore.
A59: Badfinger | B59: Swansea, Wales | C59: The UK, Ireland and Canada | D59: 1971 | E59: V17 Jangle and power pop, Big Star to GBV | F59: V | G59: A2024 | H59: =COUNTIF(Albums!$B$2:$B$2862,A59) -> 1 | J59: Swansea band on the Beatles' own Apple label whose crisp, chiming, unabashedly Beatlesque songwriting made the Beatles-to-power-pop lineage nearly literal.
A60: Bad Livers | B60: Austin, TX | C60: Texas and Oklahoma | D60: 1992–1997 | E60: V9 No Depression and insurgent country | F60: V | G60: A1453, A1486 | H60: =COUNTIF(Albums!$B$2:$B$2862,A60) -> 2 | J60: Austin trio, produced by Butthole Surfers' Paul Leary, who ran bluegrass instrumentation at punk speed and volume behind Danny Barnes's deadpan banjo songwriting.
A61: Bailter Space | B61: Christchurch, New Zealand | C61: Australia and New Zealand | D61: 1988 | E61: V18 Flying Nun and Antipodean indie | F61: V | G61: A2107 | H61: =COUNTIF(Albums!$B$2:$B$2862,A61) -> 1 | I61: the Gordons | J61: Christchurch band formed by two ex-members of the Gordons who traded the Dunedin sound's chime for churning, noise-caked, motorik guitar rock.
A62: The Band | B62: Toronto / Woodstock, NY | C62: The UK, Ireland and Canada | D62: 1968–1978 | E62: V22 Dylan and The Band | F62: V | G62: A2301, A2302, A2312, A2319 | H62: =COUNTIF(Albums!$B$2:$B$2862,A62) -> 9 | I62: Bob Dylan | J62: Dylan's former backing group whose warm, unhurried blend of country, gospel, R&B and rock reoriented a generation toward roots music.
A63: Band of Horses | B63: Charleston, SC | C63: The South | D63: 2006–2010 | E63: V4 Roots-inflected 2000s indie | F63: V | G63: A1016, A1022, A1050 | H63: =COUNTIF(Albums!$B$2:$B$2862,A63) -> 3 | I63: Carissa's Wierd | J63: Ben Bridwell's post-Carissa's Wierd band built big, reverb-soaked, Crazy-Horse-and-My-Morning-Jacket-indebted choruses that grew warmer, more Southern and more polished over time.
A64: The Bangles | B64: Los Angeles, CA | C64: The West | D64: 1984 | E64: V15 Paisley Underground | F64: V | G64: A1895 | H64: =COUNTIF(Albums!$B$2:$B$2862,A64) -> 1 | I64: The Three O'Clock; Rain Parade | J64: Los Angeles band whose tight, twelve-string power-pop debut preceded their mainstream pop years, made in the same early-'80s club scene as Paisley Underground peers.
A65: Baptist Generals | B65: Denton, TX | C65: Texas and Oklahoma | D65: 2003 | E65: V4 Roots-inflected 2000s indie | F65: V | G65: A0996 | H65: =COUNTIF(Albums!$B$2:$B$2862,A65) -> 1 | I65: Midlake; Centro-matic | J65: Chris Flemmons's Denton, Texas band made a scrappy, tape-worn Sub Pop debut of cracked-voice folk-rock within the North Texas DIY scene around Midlake.
A66: The Bats | B66: Christchurch, New Zealand | C66: Australia and New Zealand | D66: 1987–1993 | E66: V18 Flying Nun and Antipodean indie | F66: V | G66: A2101, A2113, A2121, A2129 | H66: =COUNTIF(Albums!$B$2:$B$2862,A66) -> 4 | I66: The Clean | J66: Christchurch band formed by a former Clean drummer, playing the gentlest, most purely melodic jangle-pop to come out of the Flying Nun catalog.
A67: Beach Bunny | B67: Chicago, IL | C67: Chicago and the Midwest | D67: 2018–2021 | E67: C7 Slacker, jangle, and power-pop revival | F67: Core | G67: A0557, A0586 | H67: =COUNTIF(Albums!$B$2:$B$2862,A67) -> 2 | I67: Dehd | J67: Lili Trifilio's Chicago project turned bright, hooky power-pop about body image and self-doubt from a viral bedroom EP into arena-ready choruses.
A68: Beachwood Sparks | B68: Los Angeles, CA | C68: The West | D68: 2000–2024 | E68: V4 Roots-inflected 2000s indie | F68: V | G68: A0984, A0989, A0334, A0449 | H68: =COUNTIF(Albums!$B$2:$B$2862,A68) -> 4 | J68: Los Angeles Paisley Underground pioneers whose pedal-steel-laced, Gram Parsons-descended cosmic country rock anticipated the 2000s revival before returning to it themselves.
A69: The Beat Farmers | B69: San Diego, CA | C69: The West | D69: 1985–1989 | E69: V14 Cowpunk and LA roots punk | F69: V | G69: A1864, A1872, A1885 | H69: =COUNTIF(Albums!$B$2:$B$2862,A69) -> 3 | I69: Los Lobos | J69: San Diego band splitting vocal duties between a booming novelty baritone and straighter roots-rock songwriting, produced by Los Lobos's Steve Berlin.
A70: Beat Happening | B70: Olympia, WA | C70: The West | D70: 1985–1992 | E70: V16 American underground and college rock | F70: V | G70: A1947, A1992, A1635 | H70: =COUNTIF(Albums!$B$2:$B$2862,A70) -> 3 | J70: Calvin Johnson, Heather Lewis and Bret Lunsford's deliberately amateurish, home-taped Olympia trio founded the whole lo-fi, twee-adjacent K Records aesthetic.
A71: Beck | B71: Los Angeles, CA | C71: The West | D71: 1994 | E71: V11 Lo-fi and home taping | F71: V | G71: A1641, A1642 | H71: =COUNTIF(Albums!$B$2:$B$2862,A71) -> 2 | I71: Calvin Johnson; Beat Happening | J71: Los Angeles songwriter whose home-taped acoustic-blues and tape-collage detours, made with and around Calvin Johnson, aligned him directly with the K Records lo-fi aesthetic. | K71: Y
A72: Bedhead | B72: Dallas, TX | C72: Texas and Oklahoma | D72: 1994–1998 | E72: V12 Slowcore and sadcore | F72: V | G72: A1713, A1738, A1726 | H72: =COUNTIF(Albums!$B$2:$B$2862,A72) -> 3 | I72: Codeine; the New Year | J72: Dallas twin-brother-led five-piece whose interlocking clean-toned guitars build slowly toward controlled swells over flat, whispered deadpan vocals, a touchstone of guitar-interplay slowcore.
A73: Beirut | B73: Santa Fe, NM | C73: The West | D73: 2006–2007 | E73: X5 Chamber, baroque, and freak folk | F73: Context | G73: A2747, A2750 | H73: =COUNTIF(Albums!$B$2:$B$2862,A73) -> 2 | J73: Zach Condon's teenage Balkan-brass project, built on ukulele, mandolin and rotating horns, set the template for chamber indie.
A74: The Belair Lip Bombs | B74: Melbourne, Australia | C74: Australia and New Zealand | D74: 2025 | E74: C7 Slacker, jangle, and power-pop revival | F74: Core | G74: A0646 | H74: =COUNTIF(Albums!$B$2:$B$2862,A74) -> 1 | I74: Rolling Blackouts Coastal Fever | J74: Melbourne band whose frenetic, interlocking power pop was produced by a member of Rolling Blackouts Coastal Fever.
A75: Bella White | B75: Calgary, Alberta | C75: The UK, Ireland and Canada | D75: 2023 | E75: C3 New alt-country and honky-tonk bands | F75: Core | G75: A0100 | H75: =COUNTIF(Albums!$B$2:$B$2862,A75) -> 1 | J75: Calgary-born, bluegrass-trained singer whose Appalachian-rooted picking widens into country, indie and classic-rock textures without losing its traditional core. | K75: Y
A76: Ben Seretan | B76: New York, NY | C76: The Northeast | D76: 2024 | E76: C5 Twangy indie folk | F76: Core | G76: A0253 | H76: =COUNTIF(Albums!$B$2:$B$2862,A76) -> 1 | J76: New York songwriter whose chaotic, ecstatic, hymnlike full-band record swings between grief and communal joy within a prolific DIY solo catalog.
A77: Bert Jansch | B77: London, England | C77: The UK, Ireland and Canada | D77: 1965–1974 | E77: V30 British folk rock (selective) | F77: V | G77: A2642, A2643, A2664 | H77: =COUNTIF(Albums!$B$2:$B$2862,A77) -> 3 | I77: John Renbourn; Pentangle | J77: London fingerstyle guitarist whose harder-edged folk-blues-jazz playing shaped a generation of British guitarists and directly seeded Pentangle.
A78: The Beths | B78: Auckland, New Zealand | C78: Australia and New Zealand | D78: 2022 | E78: C7 Slacker, jangle, and power-pop revival | F78: Core | G78: A0600 | H78: =COUNTIF(Albums!$B$2:$B$2862,A78) -> 1 | J78: Auckland band led by Elizabeth Stokes writing tight, guitar-heavy autobiographical power-pop that its own liner notes call a collision of pop and skuzz.
A79: Beulah | B79: San Francisco, CA | C79: The West | D79: 1997–1999 | E79: V10 Slacker and '90s indie rock | F79: V | G79: A1605, A1583 | H79: =COUNTIF(Albums!$B$2:$B$2862,A79) -> 2 | J79: Elephant 6-affiliated San Francisco band whose fuzzy guitar pop, stray horns and loose, sunny-then-bittersweet arrangements traded on scrappy, homemade psych-pop melody.
A80: Beyoncé | B80: Houston, TX | C80: The South | D80: 2024 | E80: X12 Pop and indie artists' country turns | F80: Context | G80: A2828 | H80: =COUNTIF(Albums!$B$2:$B$2862,A80) -> 1 | I80: Dolly Parton; Willie Nelson; Linda Martell | J80: Pop superstar whose sprawling, star-studded reckoning with country music's Black roots mixes pedal steel and banjo with hip-hop and R&B production.
A81: Big Black | B81: Chicago, IL | C81: Chicago and the Midwest | D81: 1986–1987 | E81: X10 Post-punk and noise rock | F81: Context | G81: A2798, A2799 | H81: =COUNTIF(Albums!$B$2:$B$2862,A81) -> 2 | J81: Steve Albini's Chicago project paired a programmed drum machine with clanging, treated guitars and confrontational lyrics to define mechanical, abrasive noise rock.
A82: Big Dipper | B82: Boston, MA | C82: The Northeast | D82: 1987–1988 | E82: V16 American underground and college rock | F82: V | G82: A1974, A1993 | H82: =COUNTIF(Albums!$B$2:$B$2862,A82) -> 2 | I82: Volcano Suns; Dumptruck | J82: Boston band assembled from Volcano Suns and Dumptruck whose hooky, deceptively simple power pop dressed odd lyrical subjects in equal parts jangle and crunch.
A83: Big Star | B83: Memphis, TN | C83: The South | D83: 1972–2005 | E83: V17 Jangle and power pop, Big Star to GBV | F83: V | G83: A2025, A2028, A2033, A2083 | H83: =COUNTIF(Albums!$B$2:$B$2862,A83) -> 4 | I83: Alex Chilton; Chris Bell | J83: Alex Chilton and Chris Bell's Memphis band stacked ringing twelve-string guitars and Beatlesque harmonies into the founding document of jangle and power pop.
A84: Big Thief | B84: Brooklyn, NY | C84: The Northeast | D84: 2016–2025 | E84: C5 Twangy indie folk | F84: Core | G84: A0158, A0162, A0175, A0176 | H84: =COUNTIF(Albums!$B$2:$B$2862,A84) -> 6 | I84: Adrianne Lenker | J84: Adrianne Lenker-led Brooklyn band whose raw, intimate, vividly storytelling indie folk deepened into sprawling double albums and cosmic, ambient-tinged textures. | K84: Y
A85: Big Vic | B85: Ann Arbor, MI | C85: The Northeast | D85: 2021 | E85: C4 Countrygaze and loud twang | F85: Core | G85: A0129 | H85: =COUNTIF(Albums!$B$2:$B$2862,A85) -> 1 | J85: Ann Arbor band led by Victoria Rinaldi whose fuzzed-out, noisy indie rock was only retroactively tagged countrygaze for its Wilco- and Silver Jews-tinged Americana touches.
A86: Bill Callahan | B86: Austin, TX | C86: Texas and Oklahoma | D86: 2007–2022 | E86: V2 Drag City deadpan school | F86: V | G86: A0885, A0887, A0876, A0879 | H86: =COUNTIF(Albums!$B$2:$B$2862,A86) -> 8 | I86: Smog | J86: Chicago-then-Austin songwriter whose deadpan, aphoristic delivery carried his post-Smog solo work from gospel-inflected looseness through folk austerity to warm, groove-based domestic songwriting. | K86: Y
A87: Bill Fox | B87: Cleveland, OH | C87: Chicago and the Midwest | D87: 1997–1998 | E87: V11 Lo-fi and home taping | F87: V | G87: A1667, A1673 | H87: =COUNTIF(Albums!$B$2:$B$2862,A87) -> 2 | I87: the Mice | J87: Cleveland songwriter who left garage-punk band the Mice for thin, close-mic'd, Beatles-echoing home-cassette solo records before a long disappearance from music.
A88: Billie Marten | B88: Ripon, North Yorkshire, UK | C88: The UK, Ireland and Canada | D88: 2016–2025 | E88: C5 Twangy indie folk | F88: Core | G88: A0276, A0195, A0231, A0159 | H88: =COUNTIF(Albums!$B$2:$B$2862,A88) -> 5 | J88: UK singer-songwriter, discovered via YouTube covers, whose hushed, breathy, fingerpicked folk grew fuller and more rhythmically alive across her RCA and Fiction Records albums. | K88: Y
A89: Bill Monroe | B89: Rosine, KY | C89: The South | D89: 1992 | E89: R1 Roots | F89: V | G89: A2695 | H89: =COUNTIF(Albums!$B$2:$B$2862,A89) -> 1 | J89: Rosine, Kentucky bandleader whose fast, hard-driven string-band music and keening high-lonesome tenor with the classic Blue Grass Boys lineup invented bluegrass as a genre.
A90: Bill Morrissey | B90: New Hampshire | C90: The Northeast | D90: 1992 | E90: V13 Americana songwriters before the label | F90: V | G90: A1784 | H90: =COUNTIF(Albums!$B$2:$B$2862,A90) -> 1 | J90: New Hampshire folksinger whose dry, novelistic character studies of blue-collar mill-town life were delivered in a warm, conversational baritone over spare acoustic guitar.
A91: Bill Orcutt | B91: San Francisco, CA | C91: The West | D91: 2011 | E91: V8 American Primitive and solo guitar | F91: V | G91: A1414 | H91: =COUNTIF(Albums!$B$2:$B$2862,A91) -> 1 | J91: Former Harry Pussy noise-guitarist whose battered four-string acoustic playing tears through blues and American song fragments with a violent, broken-string attack.
A92: Billy Joe Shaver | B92: Nashville, TN | C92: Texas and Oklahoma | D92: 1973–1977 | E92: V23 Outlaw country | F92: V | G92: A2341, A2359, A2368 | H92: =COUNTIF(Albums!$B$2:$B$2862,A92) -> 3 | I92: Waylon Jennings | J92: Nashville outlaw-country songwriter whose rough, talking-blues voice delivered his own working-class, hard-luck character songs as the definitive versions of tunes others made famous.
A93: Billy Strings | B93: Nashville, TN | C93: The Northeast | D93: 2019 | E93: X4 Bluegrass, old-time, and newgrass | F93: Context | G93: A2738 | H93: =COUNTIF(Albums!$B$2:$B$2862,A93) -> 1 | I93: Bob Weir | J93: Nashville flatpicker whose blistering guitar runs and jam-band-scaled improvisation over traditional bluegrass drew a younger, festival-jam-scene audience into the genre.
A94: The Bird Calls | B94: Brooklyn, NY | C94: The Northeast | D94: 2026 | E94: C2 Barroom storytellers and deadpan songwriters | F94: Core | G94: A0084 | H94: =COUNTIF(Albums!$B$2:$B$2862,A94) -> 1 | I94: David Berman; Silver Jews; John Darnielle; Mountain Goats; Destroyer | J94: Songwriting project drawing explicit comparison to David Berman, John Darnielle and Destroyer's Dan Bejar for its clever, plainspoken, folksy-yet-wry songs.
A95: Blackberry Smoke | B95: Atlanta, GA | C95: The South | D95: 2012–2021 | E95: X11 Modern Southern rock | F95: Context | G95: A2809, A2811, A2819 | H95: =COUNTIF(Albums!$B$2:$B$2862,A95) -> 3 | J95: Atlanta band whose triple-guitar boogie and pedal steel flourishes carried Southern rock's Skynyrd/Allman lineage into 2010s mainstream and country-radio crossover.
A96: Black Flag | B96: Hermosa Beach, CA | C96: The West | D96: 1981–1984 | E96: X14 Punk and hardcore roots | F96: Context | G96: A2849, A2851 | H96: =COUNTIF(Albums!$B$2:$B$2862,A96) -> 2 | J96: Hermosa Beach band whose Henry Rollins-fronted, self-released hardcore turned suburban California rage into lurching brutality, founding the SST/West Coast hardcore underground.
A97: Blackfoot | B97: Jacksonville, FL | C97: The South | D97: 1979 | E97: V28 Southern rock and country soul | F97: V | G97: A2611 | H97: =COUNTIF(Albums!$B$2:$B$2862,A97) -> 1 | J97: Jacksonville band whose raspy-voiced, harder-rocking take on Southern rock pushed the genre toward arena hard rock rather than the Allmans' jazzier jamming.
A98: The Black Swans | B98: Columbus, OH | C98: Chicago and the Midwest | D98: 2004–2007 | E98: V1 Molina and the Magnolia circle | F98: V | G98: A0788, A0798 | H98: =COUNTIF(Albums!$B$2:$B$2862,A98) -> 2 | I98: Songs: Ohia | J98: Columbus, Ohio band led by Jerry DeCicca building a spare, haunted folk-rock sound that shares Songs: Ohia's Midwestern gothic atmosphere.
A99: The Blasters | B99: Downey, CA | C99: The West | D99: 1980–1985 | E99: V14 Cowpunk and LA roots punk | F99: V | G99: A1839, A1841, A1851, A1865 | H99: =COUNTIF(Albums!$B$2:$B$2862,A99) -> 4 | I99: X; The Knitters | J99: Downey, California band (Dave and Phil Alvin) whose rockabilly-punk fusion became a cowpunk cornerstone and launchpad for the Knitters and X collaborations.
A100: Blaze Foley | B100: Austin, TX | C100: Texas and Oklahoma | D100: 1989–2010 | E100: V24 Texas songwriters and progressive country | F100: V | G100: A2422, A2428 | H100: =COUNTIF(Albums!$B$2:$B$2862,A100) -> 2 | I100: Townes Van Zandt | J100: Austin outlaw-folk songwriter whose rumbling baritone and wrecked-tender, dark-comic songs, caught on a rough club tape shortly before his death, built his posthumous legend.
...

Sheet Lanes
A1: ID | B1: Lane | C1: Zone | D1: Era span | E1: Definition | F1: Parent lanes | G1: Child lanes | H1: Key scenes | I1: Key labels | J1: Albums (primary) | K1: Essential | L1: Start here
A2: C1 | B2: Indie twang / yallternative | C2: Core | D2: 2014– | E2: Loud, loose guitar rock with pedal steel and country phrasing, made by punk- and indie-raised bands in the 2010s–2020s; Crazy Horse tone, small-town detail, deadpan or drawled vocals. | F2: V1, V3, V9, V20, V10, V2 | H2: Asheville; Burlington, Vermont; Philadelphia DIY | I2: Dear Life Records; Topshelf Records; ANTI-; Keeled Scales; Loose Music | J2: =COUNTIF(Albums!$I$2:$I$2862,A2&" *") -> 50 | K2: =COUNTIFS(Albums!$I$2:$I$2862,A2&" *",Albums!$T$2:$T$2862,"Essential") -> 13 | L2: =COUNTIFS(Albums!$I$2:$I$2862,A2&" *",Albums!$U$2:$U$2862,"Y") -> 2
A3: C2 | B3: Barroom storytellers and deadpan songwriters | C3: Core | D3: 2014– | E3: Wordy, funny-sad songwriting in the John Prine / David Berman line: half-spoken vocals, long verses, jokes that turn into grief, bar-band or home-studio backing. | F3: V2, V25, V13, V1 | H3: Louisville and Sophomore Lounge; Asheville; Chicago Drag City; Philadelphia DIY | I3: Sophomore Lounge; Orindal Records; Wharf Cat Records; Drag City; Oh Boy Records | J3: =COUNTIF(Albums!$I$2:$I$2862,A3&" *") -> 39 | K3: =COUNTIFS(Albums!$I$2:$I$2862,A3&" *",Albums!$T$2:$T$2862,"Essential") -> 4 | L3: =COUNTIFS(Albums!$I$2:$I$2862,A3&" *",Albums!$U$2:$U$2862,"Y") -> 1
A4: C3 | B4: New alt-country and honky-tonk bands | C4: Core | D4: 2014– | E4: 2010s–2020s bands and songwriters playing recognizable country (honky-tonk, '90s country, bluegrass-inflected) with indie-scene provenance, labels, and audiences. | F4: V9, V6, V26, V19, V7 | I4: Rounder Records; New West Records; Anti-; Keeled Scales; Verve Forecast Records | J4: =COUNTIF(Albums!$I$2:$I$2862,A4&" *") -> 35 | K4: =COUNTIFS(Albums!$I$2:$I$2862,A4&" *",Albums!$T$2:$T$2862,"Essential") -> 7 | L4: =COUNTIFS(Albums!$I$2:$I$2862,A4&" *",Albums!$U$2:$U$2862,"Y") -> 1
A5: C4 | B5: Countrygaze and loud twang | C5: Core | D5: 2018– | E5: Shoegaze- and noise-rock-scale guitar walls under pedal steel, twang, and country-song structures; the Wednesday template. | F5: V12, V16, X9, V20, V3 | H5: Asheville | I5: Orindal Records; Dead Oceans; Sub-Fi; Manic Static; Acrobat Unstable Records | J5: =COUNTIF(Albums!$I$2:$I$2862,A5&" *") -> 21 | K5: =COUNTIFS(Albums!$I$2:$I$2862,A5&" *",Albums!$T$2:$T$2862,"Essential") -> 5 | L5: =COUNTIFS(Albums!$I$2:$I$2862,A5&" *",Albums!$U$2:$U$2862,"Y") -> 2
A6: C5 | B6: Twangy indie folk | C6: Core | D6: 2014– | E6: Hushed or fervent acoustic-led songwriting with fiddle, pedal steel, and open tunings, from Big Thief's circle outward; folk lineage from Townes and Gillian Welch through the 2010s Bandcamp scene. | F6: V5, V8, V24, V25, V30, V11 | H6: Columbus; Chicago twang and DIY; Burlington, Vermont; Philadelphia DIY | I6: No Quarter; Keeled Scales; 4AD; Ruination Record Co.; Saddle Creek | J6: =COUNTIF(Albums!$I$2:$I$2862,A6&" *") -> 176 | K6: =COUNTIFS(Albums!$I$2:$I$2862,A6&" *",Albums!$T$2:$T$2862,"Essential") -> 32 | L6: =COUNTIFS(Albums!$I$2:$I$2862,A6&" *",Albums!$U$2:$U$2862,"Y") -> 2
A7: C6 | B7: Cosmic country and the '70s revival | C7: Core | D7: 2005– | E7: Grateful Dead-, Gram Parsons- and Laurel Canyon-indebted guitar bands and songwriters: buttery lead guitar, harmonies, breezy tempos, long instrumental passages. | F7: V21, V27, V20, V28, V8, V4 | H7: Woodsist and Brooklyn; Nashville; Durham and Chapel Hill; Laurel Canyon | I7: Woodsist; Dead Oceans; Secretly Canadian; Merge; Thrill Jockey | J7: =COUNTIF(Albums!$I$2:$I$2862,A7&" *") -> 170 | K7: =COUNTIFS(Albums!$I$2:$I$2862,A7&" *",Albums!$T$2:$T$2862,"Essential") -> 21 | L7: =COUNTIFS(Albums!$I$2:$I$2862,A7&" *",Albums!$U$2:$U$2862,"Y") -> 2
A8: C7 | B8: Slacker, jangle, and power-pop revival | C8: Core | D8: 2008– | E8: 2010s–2020s guitar pop descended from Pavement, GBV, Flying Nun and Big Star: jangle, fuzz, conversational lyrics, short songs, DIY release culture. | F8: V10, V11, V17, V18, V16 | H8: Philadelphia DIY; Chicago twang and DIY; Melbourne; Raleigh | I8: Matador Records; Lame-O Records; Sub Pop; Double Double Whammy; Salinas Records | J8: =COUNTIF(Albums!$I$2:$I$2862,A8&" *") -> 190 | K8: =COUNTIFS(Albums!$I$2:$I$2862,A8&" *",Albums!$T$2:$T$2862,"Essential") -> 37 | L8: =COUNTIFS(Albums!$I$2:$I$2862,A8&" *",Albums!$U$2:$U$2862,"Y") -> 2
A9: C8 | B9: Modern slowcore and hushed twang | C9: Core | D9: 2014– | E9: Slow tempos, quiet dynamics, sparse arrangements and country-tinged melodies; the 2010s–2020s descendants of Low, Red House Painters, Duster and Bedhead, often with pedal steel. | F9: V12, V5, V1, V2 | H9: Boston; Philadelphia DIY; Chicago twang and DIY; Durham and Chapel Hill | I9: Double Double Whammy; Captured Tracks; Run for Cover Records; Orindal Records; Dear Life Records | J9: =COUNTIF(Albums!$I$2:$I$2862,A9&" *") -> 58 | K9: =COUNTIFS(Albums!$I$2:$I$2862,A9&" *",Albums!$T$2:$T$2862,"Essential") -> 5 | L9: =COUNTIFS(Albums!$I$2:$I$2862,A9&" *",Albums!$U$2:$U$2862,"Y") -> 2
A10: C9 | B10: Emo-twang crossovers | C10: Core | D10: 2012– | E10: Bands from the emo and DIY punk circuit who folded country guitar, twang and Americana structures into emotional, anthemic rock. | F10: X6, V10, V9, V3 | H10: Asheville | I10: Lame-O Records; Saddle Creek; Tiny Engines; Rough Trade; ATO Records | J10: =COUNTIF(Albums!$I$2:$I$2862,A10&" *") -> 30 | K10: =COUNTIFS(Albums!$I$2:$I$2862,A10&" *",Albums!$T$2:$T$2862,"Essential") -> 8 | L10: =COUNTIFS(Albums!$I$2:$I$2862,A10&" *",Albums!$U$2:$U$2862,"Y") -> 2
A11: V1 | B11: Molina and the Magnolia circle | C11: V | D11: 1996–2013 | E11: Jason Molina's projects (Songs: Ohia, Magnolia Electric Co., solo) and the Secretly Canadian / Will Johnson orbit: haunted folk that grew into Crazy Horse-scale country rock. | F11: V20, V12, V2, V25 | G11: C1, C2, C8 | H11: Denton | I11: Secretly Canadian; Thrill Jockey; Keeled Scales; Idol/Munich; Misra/Munich | J11: =COUNTIF(Albums!$I$2:$I$2862,A11&" *") -> 46 | K11: =COUNTIFS(Albums!$I$2:$I$2862,A11&" *",Albums!$T$2:$T$2862,"Essential") -> 11 | L11: =COUNTIFS(Albums!$I$2:$I$2862,A11&" *",Albums!$U$2:$U$2862,"Y") -> 2
A12: V2 | B12: Drag City deadpan school | C12: V | D12: 1990– | E12: Silver Jews, Smog/Bill Callahan, Palace/Bonnie 'Prince' Billy and their Drag City kin: flat, wry, literary vocals over sparse or shambling country-tinged rock. | F12: V25, V29, V11, V22 | G12: C1, C2, C8, V1 | H12: Chicago Drag City; Louisville and Sophomore Lounge | I12: Drag City; Thrill Jockey; Raccoon/Warner Bros.; Sub Pop; Sing, Eunuchs! | J12: =COUNTIF(Albums!$I$2:$I$2862,A12&" *") -> 81 | K12: =COUNTIFS(Albums!$I$2:$I$2862,A12&" *",Albums!$T$2:$T$2862,"Essential") -> 19 | L12: =COUNTIFS(Albums!$I$2:$I$2862,A12&" *",Albums!$U$2:$U$2862,"Y") -> 2
A13: V3 | B13: Southern storytelling rock | C13: V | D13: 1996– | E13: Drive-By Truckers and the bands around them: three-guitar Southern rock carrying novelistic, unglamorous songs about the modern South. | F13: V28, V13, V9, V25 | G13: C1, C4, C9 | H13: Athens, Georgia; Memphis; Denton; Muscle Shoals | I13: New West Records; ATO Records; Last Chance Records; Liberty & Lament Records; Bloodshot Records | J13: =COUNTIF(Albums!$I$2:$I$2862,A13&" *") -> 85 | K13: =COUNTIFS(Albums!$I$2:$I$2862,A13&" *",Albums!$T$2:$T$2862,"Essential") -> 6 | L13: =COUNTIFS(Albums!$I$2:$I$2862,A13&" *",Albums!$U$2:$U$2862,"Y") -> 2
A14: V4 | B14: Roots-inflected 2000s indie | C14: V | D14: 1998–2013 | E14: 2000s indie rock that absorbed country, folk and Americana textures without becoming an alt-country band: Wilco after A.M., My Morning Jacket, Okkervil River, Calexico, Lambchop, Band of Horses. | F14: V9, V16, V20, V22, V27 | G14: C1, C5, C6 | H14: Omaha and Saddle Creek; Durham and Chapel Hill | I14: Sub Pop; Merge Records; dBpm Records; Dead Oceans; Jagjaguwar | J14: =COUNTIF(Albums!$I$2:$I$2862,A14&" *") -> 107 | K14: =COUNTIFS(Albums!$I$2:$I$2862,A14&" *",Albums!$T$2:$T$2862,"Essential") -> 25 | L14: =COUNTIFS(Albums!$I$2:$I$2862,A14&" *",Albums!$U$2:$U$2862,"Y") -> 2
A15: V5 | B15: Rootsy indie folk | C15: V | D15: 1996– | E15: Late-'90s to 2010s folk songwriters and duos with old-time, bluegrass and Appalachian roots rendered in indie terms: Gillian Welch, Iron & Wine, early Fleet Foxes, Bon Iver, Angel Olsen. | F15: V25, V24, R1, V30, V8 | G15: C5, C8, X3, X5 | H15: Philadelphia DIY | I15: Acony; Sub Pop; Jagjaguwar; Nonesuch; Paradise of Bachelors | J15: =COUNTIF(Albums!$I$2:$I$2862,A15&" *") -> 70 | K15: =COUNTIFS(Albums!$I$2:$I$2862,A15&" *",Albums!$T$2:$T$2862,"Essential") -> 26 | L15: =COUNTIFS(Albums!$I$2:$I$2862,A15&" *",Albums!$U$2:$U$2862,"Y") -> 2
A16: V6 | B16: 2000s–2010s alt-country | C16: V | D16: 1998– | E16: Alt-country after the No Depression boom: Bloodshot and Lost Highway-era songwriters and bands (Neko Case, Ryan Adams, Richmond Fontaine, Lydia Loveless, Hurray for the Riff Raff). | F16: V9, V13, V26, V6 | G16: C2, C3, V6, V7 | H16: New Orleans; Portland; Columbus; Durham and Chapel Hill | I16: Bloodshot Records; New West Records; Lost Highway Records; Yep Roc Records; Decor Records | J16: =COUNTIF(Albums!$I$2:$I$2862,A16&" *") -> 143 | K16: =COUNTIFS(Albums!$I$2:$I$2862,A16&" *",Albums!$T$2:$T$2862,"Essential") -> 32 | L16: =COUNTIFS(Albums!$I$2:$I$2862,A16&" *",Albums!$U$2:$U$2862,"Y") -> 2
A17: V7 | B17: Neo-traditional and 'new outlaw' country | C17: V | D17: 2012– | E17: Independent country of the 2010s–2020s that reached back to outlaw, Bakersfield and honky-tonk styles: Sturgill Simpson, Tyler Childers, Margo Price, Colter Wall, Charley Crockett. | F17: V23, V26, V24, V6 | G17: C3, X2 | I17: New West Records; Son of Davy; Southeastern; Hickman Holler Records / RCA; High Top Mountain Records | J17: =COUNTIF(Albums!$I$2:$I$2862,A17&" *") -> 95 | K17: =COUNTIFS(Albums!$I$2:$I$2862,A17&" *",Albums!$T$2:$T$2862,"Essential") -> 27 | L17: =COUNTIFS(Albums!$I$2:$I$2862,A17&" *",Albums!$U$2:$U$2862,"Y") -> 2
A18: V8 | B18: American Primitive and solo guitar | C18: V | D18: 1959– | E18: Fingerstyle steel-string guitar from John Fahey and Takoma through Jack Rose, William Tyler, Marisa Anderson and Hayden Pedigo; instrumental Americana with drone and raga. | F18: R1 | G18: C5, C6, V5 | H18: Takoma; Philly Free Folk | I18: Takoma; Tompkins Square; Three Lobed Recordings; Thrill Jockey; Vanguard | J18: =COUNTIF(Albums!$I$2:$I$2862,A18&" *") -> 52 | K18: =COUNTIFS(Albums!$I$2:$I$2862,A18&" *",Albums!$T$2:$T$2862,"Essential") -> 19 | L18: =COUNTIFS(Albums!$I$2:$I$2862,A18&" *",Albums!$U$2:$U$2862,"Y") -> 2
A19: V9 | B19: No Depression and insurgent country | C19: V | D19: 1987–1999 | E19: The 1987–1999 alt-country boom: Uncle Tupelo, the Jayhawks, Son Volt, early Wilco, Whiskeytown, Old 97's, Bloodshot's insurgent-country roster and the Gothic country wing. | F19: V14, V16, V21, V26, V23 | G19: C1, C3, C9, V3, V4, V6, X3 | H19: Chicago insurgent country; Belleville and St. Louis; Minneapolis; Durham and Chapel Hill | I19: Bloodshot Records; Carrot Top Records; Rough Trade Records; Thrill Jockey; American Recordings | J19: =COUNTIF(Albums!$I$2:$I$2862,A19&" *") -> 84 | K19: =COUNTIFS(Albums!$I$2:$I$2862,A19&" *",Albums!$T$2:$T$2862,"Essential") -> 24 | L19: =COUNTIFS(Albums!$I$2:$I$2862,A19&" *",Albums!$U$2:$U$2862,"Y") -> 2
A20: V10 | B20: Slacker and '90s indie rock | C20: V | D20: 1989–1999 | E20: Pavement, Archers of Loaf, Superchunk, Built to Spill, Silkworm, Polvo, early Modest Mouse: loose, off-kilter guitar rock with conversational vocals, Matador/Merge/Touch and Go culture. | F20: V16, V17, V18, V29 | G20: C1, C7, C9 | H20: Durham and Chapel Hill; Boise; Olympia and K Records; Elephant 6 | I20: Matador Records; Merge Records; Up Records; Touch and Go Records; Sub Pop | J20: =COUNTIF(Albums!$I$2:$I$2862,A20&" *") -> 101 | K20: =COUNTIFS(Albums!$I$2:$I$2862,A20&" *",Albums!$T$2:$T$2862,"Essential") -> 21 | L20: =COUNTIFS(Albums!$I$2:$I$2862,A20&" *",Albums!$U$2:$U$2862,"Y") -> 2
A21: V11 | B21: Lo-fi and home taping | C21: V | D21: 1985–2000 | E21: Four-track and cassette culture: Guided by Voices, Sebadoh, Daniel Johnston, Elephant 6, the Microphones, early Mountain Goats; home recording treated as an aesthetic. | F21: V16, V29, V17 | G21: C5, C7, V2, X5 | H21: Western Mass DIY; Elephant 6; Dayton lo-fi; Olympia and K Records | I21: K Records; Matador Records; Homestead Records; Sub Pop; Merge Records | J21: =COUNTIF(Albums!$I$2:$I$2862,A21&" *") -> 68 | K21: =COUNTIFS(Albums!$I$2:$I$2862,A21&" *",Albums!$T$2:$T$2862,"Essential") -> 24 | L21: =COUNTIFS(Albums!$I$2:$I$2862,A21&" *",Albums!$U$2:$U$2862,"Y") -> 2
A22: V12 | B22: Slowcore and sadcore | C22: V | D22: 1988–2000 | E22: Galaxie 500, Low, Red House Painters, Codeine, Bedhead, Duster, American Music Club, Mazzy Star: slow tempos, quiet dynamics, sadness as method. | F22: V29, V16, X9 | G22: C4, C8, V1 | H22: San Francisco; Minneapolis; Boston; Denton | I22: 4AD; Sub Pop; Vernon Yard; Rough Trade; Trance Syndicate | J22: =COUNTIF(Albums!$I$2:$I$2862,A22&" *") -> 73 | K22: =COUNTIFS(Albums!$I$2:$I$2862,A22&" *",Albums!$T$2:$T$2862,"Essential") -> 21 | L22: =COUNTIFS(Albums!$I$2:$I$2862,A22&" *",Albums!$U$2:$U$2862,"Y") -> 2
A23: V13 | B23: Americana songwriters before the label | C23: V | D23: 1986–1999 | E23: Songwriters who bridged country, folk and rock before 'Americana' was a format: Lucinda Williams, Steve Earle's '90s, Vic Chesnutt, Victoria Williams, Dave Alvin, Joe Henry. | F23: V24, V25, V19, V14 | G23: C2, V3, V6 | H23: Athens, Georgia; Austin; Laurel Canyon | I23: HighTone Records; Mammoth Records; E-Squared Records; Texas Hotel Records; Atlantic Records | J23: =COUNTIF(Albums!$I$2:$I$2862,A23&" *") -> 73 | K23: =COUNTIFS(Albums!$I$2:$I$2862,A23&" *",Albums!$T$2:$T$2862,"Essential") -> 31 | L23: =COUNTIFS(Albums!$I$2:$I$2862,A23&" *",Albums!$U$2:$U$2862,"Y") -> 2
A24: V14 | B24: Cowpunk and LA roots punk | C24: V | D24: 1978–1990 | E24: Punk bands who turned to country and rockabilly: X, the Blasters, the Gun Club, Rank and File, Lone Justice, Jason & the Scorchers, the Mekons' country turn. | F24: X14, V26, V21 | G24: C3, V13, V15, V19, V9 | H24: LA cowpunk; Leeds; Austin; Memphis | I24: Slash Records; Enigma Records; EMI America; Elektra Records; Slash/Warner Bros. Records | J24: =COUNTIF(Albums!$I$2:$I$2862,A24&" *") -> 49 | K24: =COUNTIFS(Albums!$I$2:$I$2862,A24&" *",Albums!$T$2:$T$2862,"Essential") -> 16 | L24: =COUNTIFS(Albums!$I$2:$I$2862,A24&" *",Albums!$U$2:$U$2862,"Y") -> 2
A25: V15 | B25: Paisley Underground | C25: V | D25: 1981–1989 | E25: Early-'80s LA neo-psychedelia and roots rock: the Dream Syndicate, Green on Red, the Long Ryders, Rain Parade, Opal; Velvets and Byrds revived with punk energy. | F25: V29, V21, V14 | G25: C6, V10, V9 | H25: Paisley Underground | I25: Frontier; Enigma; Island; PVC; A&M | J25: =COUNTIF(Albums!$I$2:$I$2862,A25&" *") -> 34 | K25: =COUNTIFS(Albums!$I$2:$I$2862,A25&" *",Albums!$T$2:$T$2862,"Essential") -> 9 | L25: =COUNTIFS(Albums!$I$2:$I$2862,A25&" *",Albums!$U$2:$U$2862,"Y") -> 2
A26: V16 | B26: American underground and college rock | C26: V | D26: 1979–1991 | E26: SST, Twin/Tone, Homestead and IRS-era bands: R.E.M., the Replacements, Hüsker Dü, Minutemen, Meat Puppets, Dinosaur Jr., Sonic Youth, Camper Van Beethoven, the Feelies. | F26: X14, V29, V17, V20 | G26: C4, C7, V10, V11, V12, V4, V9, X6, X8 | H26: SST and San Pedro; Minneapolis; Boston; Athens, Georgia | I26: SST Records; Homestead Records; Twin/Tone Records; I.R.S. Records; Sire Records | J26: =COUNTIF(Albums!$I$2:$I$2862,A26&" *") -> 102 | K26: =COUNTIFS(Albums!$I$2:$I$2862,A26&" *",Albums!$T$2:$T$2862,"Essential") -> 30 | L26: =COUNTIFS(Albums!$I$2:$I$2862,A26&" *",Albums!$U$2:$U$2862,"Y") -> 2
A27: V17 | B27: Jangle and power pop, Big Star to GBV | C27: V | D27: 1972–1995 | E27: Big Star, the dB's, Let's Active, Game Theory, Guadalcanal Diary, Teenage Fanclub, Velvet Crush: ringing guitars, harmonies, hooks in the Byrds/Beatles line. | F27: V21, V29 | G27: C7, V10, V11, V16, V18 | H27: Memphis; Durham and Chapel Hill; Glasgow; Athens, Georgia | I27: Enigma Records; Creation Records; Capitol Records; Epic Records; Elektra Records | J27: =COUNTIF(Albums!$I$2:$I$2862,A27&" *") -> 60 | K27: =COUNTIFS(Albums!$I$2:$I$2862,A27&" *",Albums!$T$2:$T$2862,"Essential") -> 20 | L27: =COUNTIFS(Albums!$I$2:$I$2862,A27&" *",Albums!$U$2:$U$2862,"Y") -> 2
A28: V18 | B28: Flying Nun and Antipodean indie | C28: V | D28: 1980–1995 | E28: Dunedin and Australian indie: the Clean, the Chills, the Verlaines, Tall Dwarfs, the Bats, the Go-Betweens, the Triffids; homemade jangle and drone. | F28: V29, V17 | G28: C7, V10 | H28: Dunedin; Brisbane | I28: Flying Nun; Beggars Banquet; Merge Records; Missing Link; Rough Trade | J28: =COUNTIF(Albums!$I$2:$I$2862,A28&" *") -> 53 | K28: =COUNTIFS(Albums!$I$2:$I$2862,A28&" *",Albums!$T$2:$T$2862,"Essential") -> 16 | L28: =COUNTIFS(Albums!$I$2:$I$2862,A28&" *",Albums!$U$2:$U$2862,"Y") -> 2
A29: V19 | B29: 1980s country rebels | C29: V | D29: 1980–1990 | E29: Mainstream-adjacent country that fought Nashville's gloss: Steve Earle's Guitar Town era, Dwight Yoakam, Lyle Lovett, k.d. lang, the Desert Rose Band, Rosanne Cash. | F29: V26, V23, V24, V14 | G29: C3, V13, V7, V9 | H29: Lubbock | I29: Warner Bros.; MCA; Columbia; Reprise; MCA/Curb | J29: =COUNTIF(Albums!$I$2:$I$2862,A29&" *") -> 40 | K29: =COUNTIFS(Albums!$I$2:$I$2862,A29&" *",Albums!$T$2:$T$2862,"Essential") -> 13 | L29: =COUNTIFS(Albums!$I$2:$I$2862,A29&" *",Albums!$U$2:$U$2862,"Y") -> 2
... A36: V26 | B36: Honky-tonk, Bakersfield, and hard country | C36: V | D36: 1960–1980 | E36: Merle Haggard, Buck Owens, George Jones, Loretta Lynn, Tammy Wynette, Dolly Parton, Johnny Cash, Gary Stewart, Wynn Stewart: the hard-country mainstream the V keeps returning to. | F36: R1 | G36: C3, V14, V19, V21, V23, V24, V28, V6, V7, V9, X1 | H36: Bakersfield | I36: Capitol; RCA Victor; Epic; Columbia; Decca | J36: =COUNTIF(Albums!$I$2:$I$2862,A36&" *") -> 72 | K36: =COUNTIFS(Albums!$I$2:$I$2862,A36&" *",Albums!$T$2:$T$2862,"Essential") -> 30 | L36: =COUNTIFS(Albums!$I$2:$I$2862,A36&" *",Albums!$U$2:$U$2862,"Y") -> 2
A37: V27 | B37: The Grateful Dead and California country-psych | C37: V | D37: 1969–1975 | E37: Workingman's Dead, American Beauty, Jerry Garcia's solo and bluegrass sides, New Riders of the Purple Sage: the Dead's country-folk turn and its jam offshoots. | F37: V21, R1, V22 | G37: C6, V4 | I37: Warner Bros.; Grateful Dead Records; Round Records; Columbia; Arista | J37: =COUNTIF(Albums!$I$2:$I$2862,A37&" *") -> 23 | K37: =COUNTIFS(Albums!$I$2:$I$2862,A37&" *",Albums!$T$2:$T$2862,"Essential") -> 10 | L37: =COUNTIFS(Albums!$I$2:$I$2862,A37&" *",Albums!$U$2:$U$2862,"Y") -> 2
A38: V28 | B38: Southern rock and country soul | C38: V | D38: 1969–1980 | E38: The Allman Brothers, Lynyrd Skynyrd, the Marshall Tucker Band, Little Feat, Tony Joe White, Dan Penn, Muscle Shoals: Southern guitar rock and swamp soul. | F38: V26, V22 | G38: C1, C6, V3, X11, X7 | H38: Capricorn and Jacksonville Southern rock; Muscle Shoals | I38: Capricorn Records; Warner Bros. Records; MCA Records; Atco Records; Monument Records | J38: =COUNTIF(Albums!$I$2:$I$2862,A38&" *") -> 40 | K38: =COUNTIFS(Albums!$I$2:$I$2862,A38&" *",Albums!$T$2:$T$2862,"Essential") -> 14 | L38: =COUNTIFS(Albums!$I$2:$I$2862,A38&" *",Albums!$U$2:$U$2862,"Y") -> 2
A39: V29 | B39: Velvet Underground and proto-indie | C39: V | D39: 1967–1976 | E39: The Velvet Underground, Lou Reed, Nico, the Modern Lovers/Jonathan Richman: drone, deadpan and amateurism as virtues. | G39: V10, V11, V12, V15, V16, V17, V18, V2, X10, X14, X9 | H39: New York proto-punk and CBGB; Boston | I39: RCA Records; Verve; Beserkley Records; Elektra Records; Reprise Records | J39: =COUNTIF(Albums!$I$2:$I$2862,A39&" *") -> 29 | K39: =COUNTIFS(Albums!$I$2:$I$2862,A39&" *",Albums!$T$2:$T$2862,"Essential") -> 12 | L39: =COUNTIFS(Albums!$I$2:$I$2862,A39&" *",Albums!$U$2:$U$2862,"Y") -> 2
A40: V30 | B40: British folk rock (selective) | C40: V | D40: 1968–1975 | E40: Fairport Convention, Sandy Denny, Richard & Linda Thompson, Nick Drake, Bert Jansch: the UK strand of folk rock that indie folk keeps citing. | F40: R1 | G40: C5, V5, X5 | H40: London folk clubs | I40: Island Records; Transatlantic Records; Decca Records; Dandelion Records; Harvest | J40: =COUNTIF(Albums!$I$2:$I$2862,A40&" *") -> 29 | K40: =COUNTIFS(Albums!$I$2:$I$2862,A40&" *",Albums!$T$2:$T$2862,"Essential") -> 15 | L40: =COUNTIFS(Albums!$I$2:$I$2862,A40&" *",Albums!$U$2:$U$2862,"Y") -> 2
A41: R1 | B41: Roots | C41: V | D41: before 1965 | E41: Pre-1965 country, folk and bluegrass foundations: Carter Family, Jimmie Rodgers, Hank Williams, Harry Smith's Anthology, Woody Guthrie, the Louvins, the Everlys, Lefty Frizzell, Bob Wills, Sun-era Cash, Patsy Cline, Stanley Brothers, Bill Monroe. | G41: V20, V21, V22, V23, V24, V25, V26, V27, V30, V5, V8, X1, X4 | H41: Memphis; Greenwich Village folk; Bakersfield | I41: Columbia; Decca; Capitol; Folkways Records; Sun Records | J41: =COUNTIF(Albums!$I$2:$I$2862,A41&" *") -> 33 | K41: =COUNTIFS(Albums!$I$2:$I$2862,A41&" *",Albums!$T$2:$T$2862,"Essential") -> 26 | L41: =COUNTIFS(Albums!$I$2:$I$2862,A41&" *",Albums!$U$2:$U$2862,"Y") -> 2
A42: X1 | B42: Mainstream Nashville, countrypolitan to bro-country | C42: Context | D42: 1960– | E42: The commercial country mainstream from the Nashville Sound to bro-country and Morgan Wallen. | F42: V26, R1 | G42: X12 | I42: Capitol; MCA Records; Warner Bros. Nashville; Capitol Nashville; Arista Nashville | J42: =COUNTIF(Albums!$I$2:$I$2862,A42&" *") -> 12 | K42: =COUNTIFS(Albums!$I$2:$I$2862,A42&" *",Albums!$T$2:$T$2862,"Essential") -> 9 | L42: =COUNTIFS(Albums!$I$2:$I$2862,A42&" *",Albums!$U$2:$U$2862,"Y") -> 1
A43: X2 | B43: Red Dirt, Texas country, and arena Americana | C43: Context | D43: 1995– | E43: Oklahoma/Texas scene country and the arena-scale Americana of Chris Stapleton and Zach Bryan. | F43: V24, V23, V7 | H43: Red Dirt | I43: Warner Records; Smith Music Group; Universal South; Universal/Republic; Bossier City Records | J43: =COUNTIF(Albums!$I$2:$I$2862,A43&" *") -> 10 | K43: =COUNTIFS(Albums!$I$2:$I$2862,A43&" *",Albums!$T$2:$T$2862,"Essential") -> 6 | L43: =COUNTIFS(Albums!$I$2:$I$2862,A43&" *",Albums!$U$2:$U$2862,"Y") -> 2
A44: X3 | B44: Big-tent Americana and stomp-clap folk | C44: Context | D44: 2000– | E44: Old Crow Medicine Show, the Avett Brothers, Mumford & Sons, the Lumineers, Brandi Carlile: the festival-scale Americana mainstream. | F44: V5, V9, X4 | I44: Nettwerk; American Recordings; Island Records/Glassnote Records; Sub Pop; Dualtone | J44: =COUNTIF(Albums!$I$2:$I$2862,A44&" *") -> 9 | K44: =COUNTIFS(Albums!$I$2:$I$2862,A44&" *",Albums!$T$2:$T$2862,"Essential") -> 5 | L44: =COUNTIFS(Albums!$I$2:$I$2862,A44&" *",Albums!$U$2:$U$2862,"Y") -> 1
A45: X4 | B45: Bluegrass, old-time, and newgrass | C45: Context | D45: 1965– | E45: Alison Krauss, Nickel Creek, Punch Brothers, Billy Strings, Molly Tuttle, Sierra Ferrell: the bluegrass line as its own tradition. | F45: R1 | G45: X3 | I45: Rounder; Nonesuch; Starday Records; Sugar Hill; ANTI- | J45: =COUNTIF(Albums!$I$2:$I$2862,A45&" *") -> 8 | K45: =COUNTIFS(Albums!$I$2:$I$2862,A45&" *",Albums!$T$2:$T$2862,"Essential") -> 6 | L45: =COUNTIFS(Albums!$I$2:$I$2862,A45&" *",Albums!$U$2:$U$2862,"Y") -> 1
A46: X5 | B46: Chamber, baroque, and freak folk | C46: Context | D46: 2000–2015 | E46: Sufjan Stevens, Joanna Newsom, Devendra Banhart, Beirut, the Decemberists: ornate indie folk that leads elsewhere. | F46: V5, V30, V11 | I46: Drag City; Asthmatic Kitty; Ba Da Bing; Young God; Kill Rock Stars | J46: =COUNTIF(Albums!$I$2:$I$2862,A46&" *") -> 12 | K46: =COUNTIFS(Albums!$I$2:$I$2862,A46&" *",Albums!$T$2:$T$2862,"Essential") -> 7 | L46: =COUNTIFS(Albums!$I$2:$I$2862,A46&" *",Albums!$U$2:$U$2862,"Y") -> 1
A47: X6 | B47: Emo and Midwest emo | C47: Context | D47: 1994– | E47: Cap'n Jazz, American Football, Modern Baseball: the emo line from which C9 borrows. | F47: V16, X14 | G47: C9 | I47: Sub Pop; Man With Gun; Crank!; Jade Tree; Polyvinyl | J47: =COUNTIF(Albums!$I$2:$I$2862,A47&" *") -> 8 | K47: =COUNTIFS(Albums!$I$2:$I$2862,A47&" *",Albums!$T$2:$T$2862,"Essential") -> 4 | L47: =COUNTIFS(Albums!$I$2:$I$2862,A47&" *",Albums!$U$2:$U$2862,"Y") -> 1
A48: X7 | B48: Heartland rock | C48: Context | D48: 1975–1995 | E48: Springsteen, Petty, Mellencamp, Seger: arena-scale American rock that occasionally feeds the V (Nebraska). | F48: V22, V28 | I48: Columbia; Capitol; Backstreet/MCA; Riva; MCA | J48: =COUNTIF(Albums!$I$2:$I$2862,A48&" *") -> 9 | K48: =COUNTIFS(Albums!$I$2:$I$2862,A48&" *",Albums!$T$2:$T$2862,"Essential") -> 5 | L48: =COUNTIFS(Albums!$I$2:$I$2862,A48&" *",Albums!$U$2:$U$2862,"Y") -> 1
A49: X8 | B49: Grunge and '90s alt radio | C49: Context | D49: 1988–1998 | E49: Nirvana, Pearl Jam, Soundgarden, Mudhoney, Screaming Trees: the Seattle line and its radio aftermath. | F49: V16, V20 | H49: Seattle | I49: Epic; Sub Pop; DGC Records; A&M | J49: =COUNTIF(Albums!$I$2:$I$2862,A49&" *") -> 9 | K49: =COUNTIFS(Albums!$I$2:$I$2862,A49&" *",Albums!$T$2:$T$2862,"Essential") -> 4 | L49: =COUNTIFS(Albums!$I$2:$I$2862,A49&" *",Albums!$U$2:$U$2862,"Y") -> 1
A50: X9 | B50: Classic shoegaze and dream pop | C50: Context | D50: 1988–1996 | E50: My Bloody Valentine, Slowdive, Ride, Cocteau Twins, Swirlies: the guitar-wall vocabulary countrygaze borrows. | F50: V29 | G50: C4, V12 | I50: Creation Records; 4AD; Dedicated Records; Taang! Records | J50: =COUNTIF(Albums!$I$2:$I$2862,A50&" *") -> 14 | K50: =COUNTIFS(Albums!$I$2:$I$2862,A50&" *",Albums!$T$2:$T$2862,"Essential") -> 4 | L50: =COUNTIFS(Albums!$I$2:$I$2862,A50&" *",Albums!$U$2:$U$2862,"Y") -> 1
A51: X10 | B51: Post-punk and noise rock | C51: Context | D51: 1977– | E51: Wire, Mission of Burma, Big Black, Fugazi, and modern post-punk like Robber Robber: the rhythmic, angular line adjacent to the scene. | F51: X14, V29 | H51: Asheville; Burlington, Vermont | I51: Harvest Records; Dischord Records; Ace of Hearts Records; Homestead Records; Touch and Go Records | J51: =COUNTIF(Albums!$I$2:$I$2862,A51&" *") -> 14 | K51: =COUNTIFS(Albums!$I$2:$I$2862,A51&" *",Albums!$T$2:$T$2862,"Essential") -> 4 | L51: =COUNTIFS(Albums!$I$2:$I$2862,A51&" *",Albums!$U$2:$U$2862,"Y") -> 1
A52: X11 | B52: Modern Southern rock | C52: Context | D52: 2005– | E52: Blackberry Smoke, Whiskey Myers: Southern rock's mainstream continuation. | F52: V28 | I52: Wiggy Thump Records; Thirty Tigers; Tricki-Woo Records; BMG; Southern Ground | J52: =COUNTIF(Albums!$I$2:$I$2862,A52&" *") -> 13 | K52: =COUNTIFS(Albums!$I$2:$I$2862,A52&" *",Albums!$T$2:$T$2862,"Essential") -> 4 | L52: =COUNTIFS(Albums!$I$2:$I$2862,A52&" *",Albums!$U$2:$U$2862,"Y") -> 1
A53: X12 | B53: Pop and indie artists' country turns | C53: Context | D53: 2010– | E53: Kacey Musgraves, Orville Peck, CMAT, Beyoncé's Cowboy Carter: country as a mode for pop and indie artists. | F53: X1, V21 | I53: CMATBaby/AWAL; Mercury Nashville; MCA Nashville; Sub Pop; Columbia | J53: =COUNTIF(Albums!$I$2:$I$2862,A53&" *") -> 10 | K53: =COUNTIFS(Albums!$I$2:$I$2862,A53&" *",Albums!$T$2:$T$2862,"Essential") -> 4 | L53: =COUNTIFS(Albums!$I$2:$I$2862,A53&" *",Albums!$U$2:$U$2862,"Y") -> 2
A54: X13 | B54: Laurel Canyon and '70s soft rock | C54: Context | D54: 1968–1980 | E54: Joni Mitchell, CSN, Jackson Browne, the Eagles, Linda Ronstadt, Harry Nilsson: the LA singer-songwriter mainstream next door to country rock. | F54: V21, V22 | G54: C6 | H54: Laurel Canyon | I54: Asylum; Atlantic Records; RCA; Reprise; Capitol Records | J54: =COUNTIF(Albums!$I$2:$I$2862,A54&" *") -> 12 | K54: =COUNTIFS(Albums!$I$2:$I$2862,A54&" *",Albums!$T$2:$T$2862,"Essential") -> 6 | L54: =COUNTIFS(Albums!$I$2:$I$2862,A54&" *",Albums!$U$2:$U$2862,"Y") -> 1
A55: X14 | B55: Punk and hardcore roots | C55: Context | D55: 1976–1985 | E55: Ramones, Black Flag, Minor Threat: the punk foundation under cowpunk, SST and the DIY network. | F55: V29 | G55: V14, V16, X10, X6 | H55: New York proto-punk and CBGB; SST and San Pedro | I55: Sire; SST; CBS/Epic; Frontier Records; Cherry Red Records | J55: =COUNTIF(Albums!$I$2:$I$2862,A55&" *") -> 10 | K55: =COUNTIFS(Albums!$I$2:$I$2862,A55&" *",Albums!$T$2:$T$2862,"Essential") -> 4 | L55: =COUNTIFS(Albums!$I$2:$I$2862,A55&" *",Albums!$U$2:$U$2862,"Y") -> 1

Sheet Scenes
A1: Scene | B1: Place | C1: Years | D1: Key labels | E1: Key artists | F1: Note | G1: Albums tagged
A2: Asheville | B2: Asheville, NC | C2: 2017– | D2: Dear Life Records, Drop of Sun (studio) | E2: Wednesday, MJ Lenderman, Karly Hartzman, Indigo De Souza, Florry-adjacent players | F2: The circle around Wednesday and Lenderman: shared members, the Drop of Sun studio, and a loud, pedal-steel-laced sound that became the template for indie twang. | G2: =COUNTIF(Albums!$N$2:$N$2862,A2) -> 29
A3: Durham and Chapel Hill | B3: Durham and Chapel Hill, NC | C3: 1989– | D3: Merge, Paradise of Bachelors, Dear Life | E3: Superchunk, Archers of Loaf, Hiss Golden Messenger, Mount Moriah, Fust, Sluice | F3: The Triangle's two eras: Merge-era '90s indie rock, then a roots-leaning scene around Paradise of Bachelors and Dear Life. | G3: =COUNTIF(Albums!$N$2:$N$2862,A3) -> 40
A4: Raleigh | B4: Raleigh, NC | C4: 1994– | D4: Mammoth, Bloodshot | E4: Whiskeytown, Tift Merritt, Caitlin Cary | F4: Home of Whiskeytown and the late-'90s alt-country boom in North Carolina. | G4: =COUNTIF(Albums!$N$2:$N$2862,A4) -> 8
A5: Burlington, Vermont | B5: Burlington, VT | C5: 2015– | D5: Fire Talk, Lame-O | E5: Greg Freeman, Lily Seabird, Robber Robber, Dari Bay, Lutalo | F5: A small, tight scene of loud, twangy guitar rock; one of the field guide's ten regions. | G5: =COUNTIF(Albums!$N$2:$N$2862,A5) -> 14
A6: Louisville and Sophomore Lounge | B6: Louisville, KY / Jeffersonville, IN | C6: 2006– | D6: Sophomore Lounge, Drag City, No Quarter | E6: Ryan Davis & the Roadhouse Band, State Champion, Styrofoam Winos, Grace Rogers, Joan Shelley, Palace, Slint | F6: From the Palace/Slint generation to Ryan Davis's Sophomore Lounge label and its barfly songwriters. | G6: =COUNTIF(Albums!$N$2:$N$2862,A6) -> 26
A7: Chicago insurgent country | B7: Chicago, IL | C7: 1993–2005 | D7: Bloodshot | E7: Waco Brothers, Robbie Fulks, Neko Case, Kelly Hogan, Freakwater, The Handsome Family | F7: Bloodshot's 'insurgent country': punks playing honky-tonk and Bakersfield in Chicago bars. | G7: =COUNTIF(Albums!$N$2:$N$2862,A7) -> 27
A8: Chicago twang and DIY | B8: Chicago, IL | C8: 2015– | D8: Sooper, Fire Talk, Run for Cover, Merge | E8: Tobacco City, Red PK, National Photo Committee, Case Oats, Horsegirl, Friko, Ratboys, Twin Peaks | F8: The current Chicago scene: a DIY alt-country cluster sharing pedal-steel players, beside a jangle and emo-twang circuit. | G8: =COUNTIF(Albums!$N$2:$N$2862,A8) -> 22
A9: Chicago folk revival | B9: Chicago, IL | C9: 1965–1980 | D9: Atlantic, Asylum, Flying Fish | E9: John Prine, Steve Goodman, Bonnie Koloc | F9: The Old Town School of Folk Music and North Side folk clubs that launched Prine and Goodman. | G9: =COUNTIF(Albums!$N$2:$N$2862,A9) -> 10
A10: Chicago Drag City | B10: Chicago, IL | C10: 1990– | D10: Drag City, Thrill Jockey | E10: Silver Jews, Smog, Palace, Royal Trux, Red Red Meat, Califone | F10: Drag City's deadpan, lo-fi songwriting culture and the Thrill Jockey post-rock scene next door. | G10: =COUNTIF(Albums!$N$2:$N$2862,A10) -> 25
A11: Philadelphia DIY | B11: Philadelphia, PA | C11: 2010– | D11: Lame-O, Salinas, Father/Daughter | E11: Waxahatchee, Swearin', Radiator Hospital, Hurry, Alex G, Golden Apples, 2nd Grade, Friendship, Sunday Mourners | F11: House-show power pop and indie rock; one of the field guide's regions. | G11: =COUNTIF(Albums!$N$2:$N$2862,A11) -> 38
A12: Philly Free Folk | B12: Philadelphia, PA | C12: 2000–2010 | D12: Drag City, Language of Stone | E12: Espers, Meg Baird, Fern Knight | F12: Psych-folk revival that fed the 2010s cosmic and folk revivals. | G12: =COUNTIF(Albums!$N$2:$N$2862,A12) -> 6
A13: Athens, Georgia | B13: Athens, GA | C13: 1980– | D13: DB, Elephant 6, Sub Pop | E13: R.E.M., Pylon, Love Tractor, Neutral Milk Hotel, Olivia Tremor Control, Drive-By Truckers, Arbor Labor Union | F13: College-town scene twice over: early-'80s jangle and new wave, then Elephant 6 and the Truckers. | G13: =COUNTIF(Albums!$N$2:$N$2862,A13) -> 39
... A18: Austin | B18: Austin, TX | C18: 1970– | D18: Armadillo World Headquarters (venue), Keeled Scales | E18: Willie Nelson, Jerry Jeff Walker, Townes Van Zandt, True Believers, Daniel Johnston, Lomelda (Silsbee), Hovvdy | F18: Cosmic cowboys and progressive country in the '70s; outsider tapes in the '80s; soft Texas indie today. | G18: =COUNTIF(Albums!$N$2:$N$2862,A18) -> 36
A19: Lubbock | B19: Lubbock, TX | C19: 1972– | E19: The Flatlanders, Joe Ely, Butch Hancock, Jimmie Dale Gilmore, Terry Allen | F19: West Texas songwriters who fed Austin and the Americana songwriter canon. | G19: =COUNTIF(Albums!$N$2:$N$2862,A19) -> 10
A20: Houston folk clubs | B20: Houston, TX | C20: 1965–1975 | E20: Townes Van Zandt, Guy Clark, Lightnin' Hopkins | F20: The coffeehouse circuit where the Texas songwriter tradition began. | G20: =COUNTIF(Albums!$N$2:$N$2862,A20) -> 9
A21: Bakersfield | B21: Bakersfield, CA | C21: 1958–1975 | D21: Capitol | E21: Buck Owens, Merle Haggard, Wynn Stewart | F21: Telecaster-driven honky-tonk that answered Nashville polish; a root of country rock and cowpunk. | G21: =COUNTIF(Albums!$N$2:$N$2862,A21) -> 24
A22: Nashville | B22: Nashville, TN | C22: 1950– | D22: RCA, Columbia, Hillbilly Central (studio) | E22: Waylon Jennings, Tompall Glaser, Margo Price, Caitlin Rose, Kelsey Waldon, Styrofoam Winos | F22: Music Row, the outlaw rebellion at Hillbilly Central, and today's East Nashville DIY country. | G22: =COUNTIF(Albums!$N$2:$N$2862,A22) -> 22
A23: LA cowpunk | B23: Los Angeles, CA | C23: 1978–1988 | D23: Slash, Enigma, Frontier | E23: X, The Blasters, The Gun Club, Lone Justice, The Knitters, Rank and File | F23: Punk bands discovering country, rockabilly and blues. | G23: =COUNTIF(Albums!$N$2:$N$2862,A23) -> 31
A24: Paisley Underground | B24: Los Angeles, CA | C24: 1981–1989 | D24: Slash, Enigma, Rough Trade | E24: The Dream Syndicate, Green on Red, The Long Ryders, Rain Parade, The Three O'Clock, Opal | F24: Neo-psychedelic '60s revival with a Byrds and Velvets bent. | G24: =COUNTIF(Albums!$N$2:$N$2862,A24) -> 34
A25: SST and San Pedro | B25: Southern California | C25: 1979–1990 | D25: SST | E25: Minutemen, Black Flag, Meat Puppets, Hüsker Dü, Dinosaur Jr. | F25: The label and van-tour network at the heart of the '80s underground. | G25: =COUNTIF(Albums!$N$2:$N$2862,A25) -> 27
A26: Laurel Canyon | B26: Los Angeles, CA | C26: 1966–1978 | D26: Asylum, A&M, Reprise | E26: The Byrds, Gram Parsons, Joni Mitchell, Crosby, Stills & Nash, Neil Young | F26: Country rock and the LA singer-songwriter scene; revisited by today's cosmic-country revival. | G26: =COUNTIF(Albums!$N$2:$N$2862,A26) -> 17
A27: Boston | B27: Boston, MA | C27: 1978– | D27: Taang!, Homestead, 4AD (US bands) | E27: Mission of Burma, Pixies, Galaxie 500, Buffalo Tom, Swirlies, Helium | F27: College-radio rock from post-punk to dream pop. | G27: =COUNTIF(Albums!$N$2:$N$2862,A27) -> 29
A28: Western Mass DIY | B28: Amherst and Northampton, MA | C28: 1985–2000 | D28: Homestead, Shrimper, Sub Pop | E28: Dinosaur Jr., Sebadoh, Scud Mountain Boys | F28: Home-taping and noisy college rock from the Pioneer Valley. | G28: =COUNTIF(Albums!$N$2:$N$2862,A28) -> 17
A29: Hoboken | B29: Hoboken, NJ | C29: 1978–1995 | D29: Coyote, Bar/None | E29: The Feelies, The dB's, Yo La Tengo, Speed the Plough | F29: Maxwell's and the jangle and guitar-drone bands around it. | G29: =COUNTIF(Albums!$N$2:$N$2862,A29) -> 7
A30: Dayton lo-fi | B30: Dayton, OH | C30: 1987– | D30: Scat, Matador | E30: Guided by Voices | F30: Basement four-track pop that defined lo-fi. | G30: =COUNTIF(Albums!$N$2:$N$2862,A30) -> 10
A31: Olympia and K Records | B31: Olympia and Anacortes, WA | C31: 1984–2005 | D31: K Records, Kill Rock Stars | E31: Beat Happening, The Microphones, Mount Eerie, early Modest Mouse (Issaquah) | F31: Anti-corporate DIY pop and home recording in the Pacific Northwest. | G31: =COUNTIF(Albums!$N$2:$N$2862,A31) -> 11
A32: Seattle | B32: Seattle, WA | C32: 1985– | D32: Sub Pop, Barsuk, Up | E32: Mudhoney, Screaming Trees, Built to Spill (Boise), Pedro the Lion, Death Cab for Cutie | F32: Grunge and its quieter indie aftermath. | G32: =COUNTIF(Albums!$N$2:$N$2862,A32) -> 12
... A50: Leeds | B50: Leeds, England | C50: 1977–1990 | D50: Fast Product, Sin, Twin/Tone (US) | E50: Mekons | F50: Post-punk art-school bands; the Mekons' turn to country fed insurgent country. | G50: =COUNTIF(Albums!$N$2:$N$2862,A50) -> 5
A51: Red Dirt | B51: Stillwater, OK | C51: 1990– | E51: Cross Canadian Ragweed, Jason Boland & the Stragglers, Turnpike Troubadours | F51: Oklahoma's bar-band country scene. | G51: =COUNTIF(Albums!$N$2:$N$2862,A51) -> 4
A52: Columbus | B52: Columbus, OH | C52: 1995– | D52: Anyway, Bloodshot | E52: Lydia Loveless, Saintseneca, Two Cow Garage, Times New Viking | F52: Ohio's DIY rock and alt-country bars. | G52: =COUNTIF(Albums!$N$2:$N$2862,A52) -> 16
A53: Woodsist and Brooklyn | B53: Brooklyn, NY | C53: 2006– | D53: Woodsist, Captured Tracks, Exploding in Sound | E53: Woods, Real Estate, Kurt Vile (Philadelphia), Speedy Ortiz | F53: Jeremy Earl's label and the Brooklyn DIY rock around it. | G53: =COUNTIF(Albums!$N$2:$N$2862,A53) -> 12

Sheet Labels
A1: Label | B1: Base | C1: Years active | D1: Zones and lanes | E1: Why it matters | F1: In field guide | G1: Albums in atlas
A2: Merge | B2: Durham, NC | C2: 1989– | D2: Core: C6, C7, C3 | E2: Superchunk's label. Home to Fust, Friendship, Hiss Golden Messenger (from 2014) and many Carolina acts. | F2: Y | G2: =COUNTIF(Albums!$F$2:$F$2862,A2&"*") -> 47
A3: Dear Life Records | B3: Asheville, NC | D3: Core: C1, C5, C8, C3, C2 | E3: Small label tied to the Wednesday and Lenderman circle; also Florry, Thomas Dollbaum, Natalie Jane Hill and Fust. | F3: Y | G3: =COUNTIF(Albums!$F$2:$F$2862,A3&"*") -> 19
A4: Anti- | B4: Los Angeles | C4: 1999– | D4: Context/Core/V: V6, C5, C1, C3, C6 | E4: Released Manning Fireworks, Waxahatchee's recent records and Snocaps. | F4: Y | G4: =COUNTIF(Albums!$F$2:$F$2862,A4&"*") -> 29
A5: Paradise of Bachelors | B5: Chapel Hill, NC | D5: Core/V: C6, V5, C5, V4, C7 | E5: Twangy folk and cosmic country. Hiss Golden Messenger's Poor Moon launched it; later Nap Eyes, Promised Land Sound, Mega Bog. | F5: Y | G5: =COUNTIF(Albums!$F$2:$F$2862,A5&"*") -> 14
A6: Sophomore Lounge | B6: Louisville, KY | D6: Core: C2, C6, C3 | E6: Ryan Davis's label: State Champion, Styrofoam Winos, Grace Rogers and Arbor Labor Union's later records. | F6: Y | G6: =COUNTIF(Albums!$F$2:$F$2862,A6&"*") -> 8
A7: Curation Records | B7: California | D7: Core: C6, C7 | E7: Dead-indebted guitar rock and jangle: Silver Synthetic, Sean Thompson's Weird Ears, Sunday Mourners, GospelbeacH, Beachwood Sparks. | F7: Y | G7: =COUNTIF(Albums!$F$2:$F$2862,A7&"*") -> 2
A8: Keeled Scales | B8: Austin | D8: Core/V: C5, V1, C6, C1, C3 | E8: Soft Texas indie and folk: Lomelda, Will Johnson's later records, twain, Why Bonnie, Renée Reed. | F8: Y | G8: =COUNTIF(Albums!$F$2:$F$2862,A8&"*") -> 23
A9: Exploding in Sound | B9: Brooklyn | E9: The best archive of noisy slacker rock (Speedy Ortiz, Pile, Ovlov). | F9: Y | G9: =COUNTIF(Albums!$F$2:$F$2862,A9&"*") -> 2
A10: Fire Talk | B10: Brooklyn | D10: Core: C1, C5, C6, C9 | E10: Adventurous indie rock, including Burlington's Robber Robber, Bnny and Wild Pink's Still Coming Down. | F10: Y | G10: =COUNTIF(Albums!$F$2:$F$2862,A10&"*") -> 10
A11: Lame-O Records | B11: Philadelphia | D11: Core: C7, C9, C5, C1 | E11: Philly's DIY indie and power pop: Hurry, 2nd Grade, Golden Apples, Lily Seabird, Saintseneca. | F11: Y | G11: =COUNTIF(Albums!$F$2:$F$2862,A11&"*") -> 18
A12: Drag City | B12: Chicago | C12: 1990– | D12: Context/Core/V: V2, C6, C2, V4, X5 | E12: Silver Jews, Palace, Smog and early Pavement. The home of the deadpan lyrical tradition; later Purple Mountains and Cory Hanson. | F12: Y | G12: =COUNTIF(Albums!$F$2:$F$2862,A12&"*") -> 74
A13: Bloodshot | B13: Chicago | C13: 1994– | E13: The '90s insurgent country label: Waco Brothers, Robbie Fulks, Neko Case, Ryan Adams, Lydia Loveless, Justin Townes Earle. | F13: Y | G13: =COUNTIF(Albums!$F$2:$F$2862,A13&"*") -> 47
A14: SST | B14: Southern California | C14: 1978– | D14: Context/V: X14, V15 | E14: '80s punk label for Minutemen, Hüsker Dü, Meat Puppets and Dinosaur Jr. The backbone of the punk-to-college-rock network. | F14: Y | G14: =COUNTIF(Albums!$F$2:$F$2862,A14&"*") -> 28
A15: Twin/Tone | B15: Minneapolis | C15: 1977– | E15: Early home of The Replacements; also Soul Asylum and the US Mekons. | F15: Y | G15: =COUNTIF(Albums!$F$2:$F$2862,A15&"*") -> 8
A16: Flying Nun | B16: New Zealand | C16: 1981– | D16: V: V18 | E16: The roots of jangly slacker rock: The Clean, The Chills, The Verlaines, The Bats. | F16: Y | G16: =COUNTIF(Albums!$F$2:$F$2862,A16&"*") -> 31
A17: Matador | B17: New York | C17: 1989– | D17: Core/V: C6, C7, V18 | E17: Pavement, Guided by Voices, Liz Phair, Yo La Tengo, Kurt Vile, Horsegirl: the slacker line from 1990 to now. | G17: =COUNTIF(Albums!$F$2:$F$2862,A17&"*") -> 55
A18: Sub Pop | B18: Seattle | C18: 1986– | D18: Context/Core/V: V4, V5, V12, C7, V10 | E18: Grunge first, then Iron & Wine, Fleet Foxes, Band of Horses, Arbor Labor Union, Scud Mountain Boys. | G18: =COUNTIF(Albums!$F$2:$F$2862,A18&"*") -> 59
A19: Secretly Canadian | B19: Bloomington, IN | C19: 1996– | D19: Core/V: V1, C6, C5, V5, V12 | E19: Songs: Ohia and Magnolia Electric Co.; the label behind the Molina circle. | G19: =COUNTIF(Albums!$F$2:$F$2862,A19&"*") -> 28
A20: Jagjaguwar | B20: Bloomington, IN | C20: 1996– | D20: Core/V: V5, V4, C6, C5, C7 | E20: Bon Iver, Angel Olsen and Okkervil River. | G20: =COUNTIF(Albums!$F$2:$F$2862,A20&"*") -> 20
A21: Dead Oceans | B21: Bloomington, IN | C21: 2007– | D21: Context/Core/V: C6, V4, C4, X12 | E21: Phosphorescent, Bright Eyes' later records and Kevin Morby. | G21: =COUNTIF(Albums!$F$2:$F$2862,A21&"*") -> 19
